Workbook

Sheet MRFx
B1: p
E2: Motorcycle Repair Form MRF
B3: CUSTOMER DETAILS: | G3: MRF #:
B4: Name: | E4: Address: | F4: Contact #: | G4: Email:
B5: Series: | D5: VIN: | F5: Dealer:
B6: VISUAL REFERENCE:
B9: MAJOR | C9: MINOR | D9: OPERATION | E9: WORKING | F9: REMARKS (IN) | G9: REMARKS (OUT)
B10: HANDLE BAR | C10: Handle bar | D10: Steering
D11: Side Mirror
C12: Switch / Buttons | D12: Head Light Button
D13: Signal Light Button
D14: Horn Button
D15: Reverse Button
D16: Hazard Button
D17: Gear Button (1,2,3)
D18: Park Button
D19: Front Brake
D20: Rear Brake
C21: Display Panel | D21: Battery (1 and 2)
D22: Battery Bar
D23: Range (Km)
D24: Speed (Km/H)
D25: Amps
D26: ODO
D27: Trip (Km)
D28: Settings
B29: FRONT | C29: Lights | D29: Head Lights
D30: Signal Lights
D31: Hazard Lights
C32: Shock Absorber | D32: Shock Absorber
D33: Reflectors
C34: Tire | D34: Front Tire
B35: BODY | C35: Frame | D35: Front Part
D36: Right Part
D37: Left Part
D38: Middle Part
D39: Rear Part
D40: Seat
C41: Battery | D41: Battery cable
D42: Airswitch
D43: Compartment part
C44: Ignition | D44: Keys
D45: Remote
C46: Stand | D46: Center Stand
D47: Side Stand
C48: Foot Rest | D48: Left and Right
B49: REAR | C49: Lights | D49: Signal Lights
D50: Hazard Lights
D51: Break Lights
D52: Tail Lights
D53: Plate Number Lights
C54: Shock Absorber | D54: Shock Absorber
D55: Reflectors
C56: Tire | D56: Rear Tire
B57: All Area | C57: Screw / Nut /Bolt | D57: Front / Rear / Side
B58: Performance | D58: Test Drive
B59: FINAL REMARKS:
B65: IN | C65: Customer: | E65: Cashier: | F65: Mechanic: | G65: Guard:
C66: Date: | E66: Date: | F66: Date: | G66: Date:
B68: OUT | C68: Customer: | E68: Cashier: | F68: Mechanic: | G68: Guard:
C69: Date: | E69: Date: | F69: Date: | G69: Date:

Sheet 2026 Transaction
A1: - | N1: Description | AH1: Appplicable for Batteries (Bundle with unit) | BB1: REMARKS Per Row | BV1: Return date (GRF) | BW1: Final Remarks
A2: STATUS | B2: Document | C2: No. | D2: GI No. | E2: GP No. | F2: GRF No. | G2: Req ID | H2: Date | I2: Requested by: / Dept | J2: Purpose | K2: Bill To (Name, Number & Email) : | L2: Pick Up | M2: Drop off / Address | N2: 1 | O2: 2 | P2: 3 | Q2: 4 | R2: 5 | S2: 6 | T2: 7 | U2: 8 | V2: 9 | W2: 10 | X2: 11 | Y2: =X2+1 -> 12 | Z2: =Y2+1 -> 13 | AA2: =Z2+1 -> 14 | AB2: =AA2+1 -> 15 | AC2: =AB2+1 -> 16 | AD2: =AC2+1 -> 17 | AE2: =AD2+1 -> 18 | AF2: =AE2+1 -> 19 | AG2: =AF2+1 -> 20 | AH2: 1 | AI2: 2 | AJ2: 3 | AK2: 4 | AL2: 5 | AM2: 6 | AN2: 7 | AO2: 8 | AP2: 9 | AQ2: 10 | AR2: =AQ2+1 -> 11 | AS2: =AR2+1 -> 12 | AT2: =AS2+1 -> 13 | AU2: =AT2+1 -> 14 | AV2: =AU2+1 -> 15 | AW2: =AV2+1 -> 16 | AX2: =AW2+1 -> 17 | AY2: =AX2+1 -> 18 | ... BA2: =AZ2+1 -> 20 | BB2: 1 | BC2: 2 | BD2: 3 | BE2: 4 | BF2: 5 | BG2: 6 | BH2: 7 | BI2: 8 | BJ2: 9 | BK2: 10 | BL2: =BK2+1 -> 11 | BM2: =BL2+1 -> 12 | BN2: =BM2+1 -> 13 | BO2: =BN2+1 -> 14 | BP2: =BO2+1 -> 15 | BQ2: =BP2+1 -> 16 | BR2: =BQ2+1 -> 17 | BS2: =BR2+1 -> 18 | ... BU2: =BT2+1 -> 20
A3: DONE | C3: 1 | F3: GR-2026000001 | H3: 46027 | I3: Wemove Makati | J3: Lease unit - 1 month | K3: GARY BORBOSO | M3: E88 Asgard Warehouse | N3: MC-D400 Blue / R5FBMX0B9RL000533 / N771WA | O3: RideBox Battery - Ampace / 519110002370AAXXXMJK0246 | P3: RideBox Battery - Ampace / 519110002370AAXXXMJK0411 | Q3: Regular Charger / OKL7208JH2024408300132 | AH3: 519110002370AAXXXMJK0338 519110002370AAXXXSNK0005 | BV3: 46027 | BW3: RETURN TO WAREHOUSE
A4: DONE | C4: =C3+1 -> 2 | D4: GI-2026000001 | E4: GP-2026000001 | G4: Requisition ID: 0000061 | H4: 46028 | I4: Ian Jimenez / Tech | J4: Deployment of Batteries - Powerfill Damong Maliit | K4: Ian Jimenez / 09062924124 / ijimenez@nrdev.ph | L4: E88 Asgard Warehouse | M4: Powerfill Damong Maliit Quezon City | N4: RideBox Battery - Ampace / 519110002370AAXXXNNK0116 | O4: RideBox Battery - Ampace / 519110002370AAXXXNNK0107 | P4: RideBox Battery - Ampace / 519110002370AAXXXMJK0407 | Q4: RideBox Battery - Ampace / 519110002370AAXXXJJK0200
A5: DONE | C5: =C4+1 -> 3 | D5: GI-2026000002 | E5: GP-2026000002 | G5: Requisition ID: 0000061 | H5: 46028 | I5: Ian Jimenez / Tech | J5: Deployment of Batteries - Powerfill Tandang Sora | K5: Ian Jimenez / 09062924124 / ijimenez@nrdev.ph | L5: E88 Asgard Warehouse | M5: Powerfill Tandang Sora Quezon City | N5: RideBox Battery - Ampace / 519110002370AAXXXMJK0523 | O5: RideBox Battery - Ampace / 519110002370AAXXXJJK0153 | P5: RideBox Battery - Ampace / 519110002370AAXXXJJK0201 | Q5: RideBox Battery - Ampace / 519110002370AAXXXNNK0040
A6: DONE | C6: =C5+1 -> 4 | D6: GI-2026000003 | E6: GP-2026000003 | G6: Requisition ID: 0000061 | H6: 46029 | I6: Ian Jimenez / Tech | J6: Deployment of Batteries - Powerfill Barangka | K6: Ian Jimenez / 09062924124 / ijimenez@nrdev.ph | L6: E88 Asgard Warehouse | M6: Powefill Barangka | N6: RideBox Battery - Ampace / 519110002370AAXXXMJK0185 | O6: RideBox Battery - Ampace / 519110002370AAXXXMJK0474 | P6: RideBox Battery - Ampace / 519110002370AAXXXNNK0057 | Q6: RideBox Battery - Ampace / 519110002370AAXXXMJK0157
A7: DONE | C7: =C6+1 -> 5 | D7: GI-2026-000004 | E7: GP-2026000004 | G7: Requisition ID: 0000061 | H7: 46030 | I7: Ian Jimenez / Tech | J7: Deployment of Batteries - Dasmarinas Makati | K7: Ian Jimenez / 09062924124 / ijimenez@nrdev.ph | L7: E88 Asgard Warehouse | M7: Dasmarinas Makati | N7: RideBox Locker - 9M0029 | AH7: RideBox Battery - Ampace: 519110002370AAXXXMJK0373 519110002370AAXXXJJK0103 519110002370AAXXXJJK0185 519110002370AAXXXNNK0101
A8: DONE | C8: =C7+1 -> 6 | F8: GR-2026000002 | H8: 46031 | I8: John Martin Ysaac / Tech | J8: Return to Warehouse - 2 Offline Batteries | K8: John Martin Ysaac / 0906 285 8290/ jysaac@nrdev.ph | L8: Tandang Sora/Damong Maliit | M8: E88 Asgard Warehouse | N8: RideBox Battery - Ampace / 519110002370AAXXXJJK0201 | O8: RideBox Battery - Ampace / 519110002370AAXXXMJK0407 | BV8: 46031 | BW8: RETURN TO WAREHOUSE
A9: DONE | C9: =C8+1 -> 7 | D9: GI-2026-000005 | E9: GP-2026000005 | G9: Requisition ID: 20260000006 | H9: 46031 | I9: John Martin Ysaac / Tech | J9: Replacement of 2 offline Batteries | K9: John Martin Ysaac / 0906 285 8290/ jysaac@nrdev.ph | L9: E88 Asgard Warehouse | M9: Tandang Sora/Damong Maliit | N9: RideBox Battery - Ampace / 519110002370AAXXXJJK0206 | O9: RideBox Battery - Ampace / 519110002370AAXXXJJK0225
A10: DONE | C10: =C9+1 -> 8 | D10: GI-2026-000006 | E10: GP-2026000006 | H10: 46034 | I10: Christopher Mendoza / PQM | J10: Inventory Transfer to Sta Rosa | K10: E88 Christopher Mendoza / +63 960 897 8870 / cmendoza@nrdev.ph | L10: E88 Asgard Warehouse | M10: Unit 8 and 9 Ground Floor One Sta. Rosa Prime (Caltex) Brgy Dila City of Sta Rosa Laguna | N10: ESP00065 / Front Tire 90/90-12 (R280/Sport) | O10: ESP00066 / Rear Tire 90/90-12 (R280/Sport | P10: ESP00137 / Rear Tire 110/80-14 (D400) | Q10: ESP00138 / Front Tire 110-80-16 (D400) | R10: ESP00077 / Head Light Guard (R280 Sport) | S10: ESP00212 / Controller Assembly (D400) | T10: ESP00224 / Speedometer (D400) | U10: Brake Cleaner
A11: DONE | C11: =C10+1 -> 9 | D11: GI-2026-000007 | G11: Requisition ID: 20260000007 | H11: 46034 | I11: Samuel Kniazeff / PQM | J11: Swapping of Parts (Seat) | K11: E88 Christopher Mendoza / +63 960 897 8870 / cmendoza@nrdev.ph | L11: E88 Asgard Warehouse | M11: E88 Asgard Warehouse | N11: ESP00281/ Seat v2 (R280/Sport)
A12: DONE | C12: =C11+1 -> 10 | D12: GI-2026-000008 | E12: GP-2026000007 | G12: Requisition ID-20260000004 | H12: 46034 | I12: Ron Dela Cruz / Sales | J12: Test/Demo Unit | K12: FlexRide Jerick Limuanco / 09177680944 | L12: E88 Asgard Warehouse | M12: Marikina | N12: MC-R280 2000W White / R5FBMGOC8RL000158 / N532WA | O12: MC-R280 2000W White / R5FBMGOC6RL000160 /N608WA | P12: MC-R280 2000W White / R5FBMGOC7RL000166 / N800WA | AH12: RideBox Battery - Ampace: 519110002370AAXXXJJK0187 519110002370AAXXXMJK0491 Regular Charger / OKL7208JH202408300056 | AI12: RideBox Battery - Ampace: 519110002370AAXXXJJK0093 519110002370AAXXXJJK0062 Regular Charger / OKL7208JH20240830133 | AJ12: RideBox Battery - Ampace: 519110002370AAXXXNNK0058 519110002370AAXXXMJK0094 Regular Charger / OKL7208JH20240830060 | BW12: FlexRide to handle warehouse pickup
A13: DONE | C13: =C12+1 -> 11 | F13: GR-2026000003 | G13: Requisition ID: 20260000007 | H13: 46034 | I13: Samuel Kniazeff / PQM | J13: Swapping of Parts (Seat) | K13: E88 Christopher Mendoza / +63 960 897 8870 / cmendoza@nrdev.ph | L13: E88 Asgard Warehouse | M13: E88 Asgard Warehouse | N13: ESP00113 / Seat (R280/Sport) | BB13: Replacement Seat RETURN TO WAREHOUSE | BV13: 46034 | BW13: Replacement Seat RETURN TO WAREHOUSE
A14: DONE | C14: =C13+1 -> 12 | D14: GI-2026-000009 | E14: GP-2026000008 | G14: Requisition ID: 20260000005 | H14: 46036 | I14: Ron Dela Cruz / Sales | J14: Lease Unit for Dasmarinas Village | K14: Dasmarinas Village / Orlando Bueno / 09177005363 | L14: E88 Asgard Warehouse | M14: Dasmarinas Makati | N14: MC-D400 4000W Blue / R5FBMX0B9RL000497 | O14: MC- D400 4000W Blue / R5FBMX0B5RL000495 | P14: MC- D400 4000W Blue / R5FBMX0B2RL000485 | Q14: MC- D400 4000W Blue / R5FBMX0B0RL000470 | R14: MC- D400 4000W Blue / R5FBMX0B8RL000507 | S14: MC- D400 4000W Blue / R5FBMX0B4RL000522 | T14: MC- D400 4000W Blue/ R5FBMX0B7RL000479 | U14: MC- D400 4000W Blue / R5FBMX0B5RL000514 | V14: MC- D400 4000W Blue / R5FBMX0B7RL000532 | W14: MC- D400 4000W Blue / R5FBMX0B0RL000498 | AH14: RideBox Battery - Ampace: 519110002370AAXXXNNK0098 519110002370AAXXXMJK0533 Regular Charger- OKL7208JH20240830280 | AI14: RideBox Battery - Ampace: 519110002370AAXXXMJK0263 519110002370AAXXXJJK0234 Regular Charger-OKL7208JH20240830134 | AJ14: RideBox Battery - Ampace: 519110002370AAXXXJJK0097 519110002370AAXXXMJK0233 Regular Charger- OKL7208JH20240830255 | AK14: RideBox Battery - Ampace: 519110002370AAXXXSNK0007 519110002370AAXXXMJK0112 Regular Charger- OKL7208JH20240830179 | AL14: RideBox Battery - Ampace: 519110002370AAXXXMJK0440 519110002370AAXXXMJK0329 Regular Charger- OKL7208JH20240830127 | AM14: RideBox Battery - Ampace: 519110002370AAXXXMJK0497 519110002370AAXXXJJK0168 Regular Charger- OKL7208JH20240830147 | AN14: RideBox Battery - Ampace: 519110002370AAXXXMJK0434 519110002370AAXXXMJK0141 Regular Charger-OKL7208JH20240830281 | AO14: RideBox Battery - Ampace: 519110002370AAXXXJJK0156 519110002370AAXXXNNK0011 Regular Charger- OKL7208JH20240830184 | AP14: RideBox Battery - Ampace: 519110002370AAXXXNNK0122 519110002370AAXXXMJK0433 Regular Battery- OKL7208JH20240830040 | AQ14: RideBox Battery - Ampace: 519110002370AAXXXMJK0501 519110002370AAXXXMJK0449 Regular Charger- OKL7208JH20240830310
A15: DONE | C15: =C14+1 -> 13 | D15: GI-2026-000010 | G15: Requisition ID: 20260000010 | H15: 46035 | I15: Christopher Mendoza / PQM | J15: Replacement Parts for D400 Dashboard | K15: E88 Christopher Mendoza / +63 960 897 8870 / cmendoza@nrdev.ph | L15: E88 Asgard Warehouse | M15: E88 Asgard Warehouse | N15: ESP00224 / Speedometer (D400) | BB15: Replacement Parts for D400 Speedometer for Dasma Village
A16: DONE | C16: =C15+1 -> 14 | D16: GI-2026-000011 | E16: GP-2026000009 | G16: Requisition ID: 0000061 | H16: 46036 | I16: Ian Jimenez / Tech | J16: Deployment of Batteries - BF Homes | K16: E88 Ian Jimenez / 09062924124 / ijimenez@nrdev.ph | L16: E88 Asgard Warehouse | M16: BF Homes Paranaque | N16: RideBox Locker- 9M0045 | AH16: RideBox Battery - Ampace: 519110002370AAXXXMJK0360 519110002370AAXXXJJK0047 519110002370AAXXXMJK0531 519110002370AAXXXJJK0050
A17: DONE | C17: =C16+1 -> 15 | D17: GI-2026-000012 | E17: GP-2026000010 | G17: Requisition ID: 20260000008 | H17: 46036 | I17: Samuel Kniazeff / PQM | J17: Sourcing of possible lockers location | K17: Jervy Soltura / +63 919 000 6311 / samuel@nrdev.ph | L17: E88 Asgard Warehouse | M17: Pasay City | N17: MC-D400 4000W Blue / R5FBMX0B9RL000533 | O17: EFS00009- Helmet | AH17: RideBox Battery - Ampace- 519110002370AAXXXMJK0338 519110002370AAXXXSNK0005 | BB17: Sourcing of possible lockers location
A18: DONE | C18: =C17+1 -> 16 | D18: GI-2026-000013 | E18: GP-2026000011 | G18: Requisition ID: 20260000011 | H18: 46037 | I18: Ron Dela Cruz / Sales | J18: Sale to Client | K18: Forest Hills Golf & Country Club / Martin Limgenco / 09173219779 | L18: E88 Asgard Warehouse | M18: Forest Hills Golf & Country Club - 1870 Marikina-Infanta Hwy, Antipolo | N18: MC-R280SPBLU2500 / R5FBMGOB1RL000154 | O18: EFS00009- Helmet | AH18: RideBox Battery - Ampace: 519110002370AAXXXMJK0411 519110002370AAXXXNNK0086 OKL7208JH20240830044
A19: DONE | C19: =C18+1 -> 17 | D19: GI-2026-000014 | E19: GP-2026000012 | G19: Requisition ID: 20260000012 | H19: 46037 | I19: Ron Dela Cruz / Sales | J19: Test/Demo Unit | K19: Forest Hills Golf & Country Club / Martin Limgenco / 09173219779 | L19: E88 Asgard Warehouse | M19: Forest Hills Golf & Country Club - 1870 Marikina-Infanta Hwy, Antipolo | N19: MC-D400 4000W Blue / R5FBMX0B9RL000533 | AH19: RideBox Battery - Ampace- 519110002370AAXXXMJK0338 519110002370AAXXXSNK0005 | BB19: Test/ Demo Unit | BV19: 46038
A20: DONE | C20: 18 | F20: GR-2026000004 | G20: Requisition ID: 20260000008 | H20: 46036 | I20: Samuel Kniazeff / PQM | J20: Sourcing of possible lockers location | K20: E88 Samuel Kniazeff / +63 919 000 6311 / samuel@nrdev.ph | L20: E88 Asgard Warehouse | M20: 174 acacia st | N20: MC-D400 4000W Blue / R5FBMX0B9RL000533 | O20: EFS00009- Helmet | AH20: RideBox Battery - Ampace- 519110002370AAXXXMJK0338 519110002370AAXXXSNK0005 | BB20: Returned by jervy / gerald | BV20: 46036
A21: DONE | C21: 19 | D21: GI-2026-000015 | E21: GP-2026000013 | G21: Requisition ID :20260000013 | H21: 46038 | I21: Samuel Kniazeff / PQM | J21: Install to sample unit in TCI | K21: E88 Samuel Kniazeff / +63 919 000 6311 / samuel@nrdev.ph | L21: E88 Asgard Warehouse | M21: TCI Pasig | N21: PARTS0111- LH front wing (White) | O21: PARTS0112- RH front wing (White) | BB21: install to sample unit in TCI | BC21: install to sample unit in TCI
A22: DONE | C22: 20 | E22: GP-2026000014 | H22: 46038 | I22: Greg Rivera | J22: Back up Battery for Forest Hills Event | K22: E88 Samuel Kniazeff / +63 919 000 6311 / samuel@nrdev.ph | L22: E88 Asgard Warehouse | M22: Forest Hills Golf & Country Club | N22: ESP00263 RideBox Battery (Ampace) / 519110002370AAXXXMJK0310 | BB22: Back up Battery for Forest Hills Event
A23: DONE | C23: 21 | F23: GR-2026000005 | G23: Requisition ID :20260000014 | H23: 46038 | I23: Greg Rivera | J23: Back up Battery for Forest Hills Event | K23: E88 Samuel Kniazeff / +63 919 000 6311 / samuel@nrdev.ph | L23: Forest Hills Golf & Country Club | M23: E88 Asgard Warehouse | N23: ESP00263 RideBox Battery (Ampace) / 519110002370AAXXXMJK0225 | BB23: Replacement Unit from San Antonio pasig | BV23: 46038
A24: DONE | C24: 22 | F24: GR-2026000006 | G24: Requisition ID: 20260000012 | H24: 46038 | I24: Ron Dela Cruz / Sales | J24: Test/Demo Unit | K24: Forest Hills Golf & Country Club / Martin Limgenco / 09173219779 | L24: Forest Hills Golf & Country Club | M24: E88 Asgard Warehouse | N24: MC-D400 4000W Blue / R5FBMX0B9RL000533 | AH24: RideBox Battery - Ampace- 519110002370AAXXXMJK0338 519110002370AAXXXSNK0005 | BB24: Test/ Demo Unit | BV24: 46038
A25: DONE | C25: 23 | F25: GR-2026000007 | G25: Requisition ID-20260000004 | H25: 46042 | I25: Ron Dela Cruz / Sales | J25: Test/Demo Unit | K25: FlexRide Jerick Limuanco / 09177680944 | L25: Marikina | M25: E88 Asgard Warehouse | N25: MC-R280 2000W White / R5FBMGOC8RL000158 / N532WA | O25: MC-R280 2000W White / R5FBMGOC7RL000166 / N800WA | AH25: RideBox Battery - Ampace- 519110002370AAXXXJJK0187 519110002370AAXXXMJK0491 | AI25: RideBox Battery - Ampace- 519110002370AAXXXMJK0094 519110002370AAXXXNNK0058 | BB25: Test/ Demo Unit-Odometer Reading- 347 KM | BC25: Test/ Demo Unit-Odometer Reading- 162 KM | BV25: 46042
A26: PENDING | C26: 24 | D26: GI-2026-000016 | E26: GP-2026000015 | G26: Requisition ID-20260000016 | H26: 46045 | I26: Judielle Guce / PM & Compliance | J26: For Lease / 1 Month | K26: Wemove Technology Inc. / JJ Cabral / 63 908 863 6620 | L26: E88 Asgard Warehouse | M26: UNIT 205, 1409 PABLO OCAMPO SR. EXT, MAKATI CITY, 1203 METRO MANILA | N26: MC-D400 Blue / R5FBMX0B9RL000533 / N771WA | O26: RideBox Battery - Ampace- 519110002370AAXXXNNK0067 | P26: RideBox Battery - Ampace- 519110002370AAXXXMJK0246 | AH26: RideBox Battery - Ampace- 519110002370AAXXXMJK0338 519110002370AAXXXSNK0005 OKL7208JH2024408300132
A27: DONE | C27: 25 | F27: GR-2026000008 | G27: Requisition ID-20260000004 | H27: 46045 | I27: Ron Dela Cruz / Sales | J27: Test/Demo Unit | K27: FlexRide Jerick Limuanco / 09177680944 | L27: Marikina | M27: E88 Asgard Warehouse | N27: MC-R280 2000W White / R5FBMGOC6RL000160 /N608WA | AH27: RideBox Battery - Ampace: 519110002370AAXXXJJK0093 519110002370AAXXXJJK0062 Regular Charger / OKL7208JH20240830133 | BB27: Test/ Demo Unit-Odometer Reading- 331 KM | BV27: 46045
A28: DONE | C28: 26 | E28: GP-2026000016 | G28: Requisition ID-20260000018 | H28: 46045 | I28: Judy Joy Rosare | J28: Replacement Unit | K28: E88 Samuel Kniazeff / +63 919 000 6311 / samuel@nrdev.ph | L28: E88 Asgard Warehouse | M28: E88 Asgard Warehouse | N28: ESP00217 Left Combination Switch (D400) | BB28: Replacement Parts for D400 Service Unit of RJ/Sales
A29: DONE | C29: 27 | D29: GI-2026-000017 | E29: GP-2026000017 | G29: Requisition ID: 0000061 | H29: 46046 | I29: Ian Jimenez / Tech | J29: Deployment of Batteries - Powerfill Punturin | K29: Ian Jimenez / 09062924124 / ijimenez@nrdev.ph | L29: E88 Asgard Warehouse | M29: Powerfill Punturin | N29: RideBox Battery - Ampace / 519110002370AAXXXNNK0130 | O29: RideBox Battery - Ampace / 519110002370AAXXXMJK0400 | P29: RideBox Battery - Ampace / 519110002370AAXXXMJK0499 | Q29: RideBox Battery - Ampace / 519110002370AAXXXNNK0094
A30: DONE | C30: 28 | E30: GP-2026000018 | G30: Requisition ID-20260000019 | H30: 46049 | I30: tmasiglat@nrdev.ph | J30: Test/Demo Unit / Phoenix Petroleum Philippines, Inc. | K30: Thea Masiglat / 09171022450 | L30: E88 Asgard Warehouse | M30: The Atrium at Enderun, 1100 Campus Avenue, McKinley Hill, Taguig | N30: MC-D400 4000W Blue / R5FBMX0B0RL000517 | O30: RideBox Battery - Ampace / 519110002370AAXXXMJK0548 | P30: Marketing Materials/ Booth | R30: Helmet | AH30: RideBox Battery - Ampace: 519110002370AAXXXMJK0376 519110002370AAXXXJJK0177
A31: DONE | C31: 29 | D31: GI-2026-000018 | E31: GP-2026000019 | G31: Requisition ID-20260000020 | H31: 46053 | I31: Christopher Mendoza / PQM | J31: Inventory Transfer to Sta Rosa | K31: E88 Christopher Mendoza / +63 960 897 8870 / cmendoza@nrdev.ph | L31: E88 Asgard Warehouse | M31: Unit 8 and 9 Ground Floor One Sta. Rosa Prime (Caltex) Brgy Dila City of Sta Rosa Laguna | N31: ESP00025-SWITCH LOCK ASSY W/KEY | O31: ESP00086- Controller Assembly 65A (R280 Sport) | P31: ESP00005-Speedomoter Panel (R280/Sport) | Q31: ESP00076-Cushion Seat Lock Cable (R280/Sport) | R31: ESP00083-Main Wiring (R280/Sport) | S31: ESP00224-Speedometer (D400) | T31: POWER TRAIN/MOTOR (Cris Inventory)
A32: DONE | C32: 30 | F32: GR-2026000009 | G32: Requisition ID-20260000019 | H32: 46049 | I32: tmasiglat@nrdev.ph | J32: Test/Demo Unit / Phoenix Petroleum Philippines, Inc. | K32: Thea Masiglat / 09171022450 | L32: The Atrium at Enderun, 1100 Campus Avenue, McKinley Hill, Taguig | M32: E88 Asgard Warehouse | N32: MC-D400 4000W Blue / R5FBMX0B0RL000517 | O32: RideBox Battery - Ampace / 519110002370AAXXXMJK0548 | P32: Marketing Materials/ Booth | Q32: RideBox Locker - 9M0021 | R32: Helmet | AH32: RideBox Battery - Ampace: 519110002370AAXXXMJK0376 519110002370AAXXXJJK0177 | BV32: 46049
C33: =C32+1 -> 31 | D33: GI-2026-000019 | E33: GP-2026000020 | G33: Requisition ID-20260000022 | H33: 46051 | I33: Haide Garcia / HR | J33: Assignment to Employee | K33: Ron Dela Cruz / (0917) 768 0944 / rdelacruz@nrdev.ph | L33: E88 Asgard Warehouse | M33: E88 Asgard Warehouse | N33: MC-D400 4000W Red / R5FBMX0B2RL000440 | AH33: RideBox Battery - Ampace: 519110002370AAXXXNNK0109 519110002370AAXXXMJK0133 OKL7208JH202408300048
C34: =C33+1 -> 32 | F34: GR-2026000010 | G34: Requisition ID-20260000044 | H34: 46051 | I34: Ron Dela Cruz / Sales | J34: Return To Warehouse/ Change of Assigned Unit | K34: Ron Dela Cruz / (0917) 768 0944 / rdelacruz@nrdev.ph | L34: E88 Asgard Warehouse | M34: E88 Asgard Warehouse | N34: MC- R280 Sport Blue / R5FBMGOB5RL000139 | AH34: RideBox Battery - Ampace: 519110002370AAXXXJJK0235 519110002370AAXXXJJK0190 OKL7208JH2024083000017 | BB34: Deffective Front Panel,Brake Lever / Odometer Reading- 1872 km | BV34: 46051
C35: =C34+1 -> 33 | D35: GI-2026-000020 | E35: GP-2026000021 | G35: Requisition ID-20260000023 | H35: 46054 | I35: Thea Masiglat / Marketing | J35: Test / Demo Unit | K35: Thea Masiglat / 09171022450 | L35: E88 Asgard Warehouse | M35: Premiere Southern Petroleum Corp. | N35: MC - D400 Red /
C36: =C35+1 -> 34 | D36: GI-2026-000021 | E36: GP-2026000022 | G36: Requisition ID-20260000024 | H36: 46053 | I36: Judielle Guce /PM & Compliance | J36: Test / Demo Unit | K36: Toni Nodalo / 09675019247 | L36: E88 Asgard Warehouse | M36: QuadX | N36: MC-D400 Blue / R5FBMX0B0RL000517 / N724WA | O36: MC-D400 Blue /R5FBMX0B7RL000501 | AH36: RideBox Battery - Ampace: 519110002370AAXXXJJK0177 519110002370AAXXXMJK0376 OKL7208JH202408300020 | AI36: RideBox Battery - Ampace: 519110002370AAXXXNNK0128 519110002370AAXXXJJK0203 OKL7208JH202408300050
C37: =C36+1 -> 35 | D37: GI-2026-000022 | E37: GP-2026000023 | G37: Requisition ID-20260000025 | H37: 46054 | I37: Judielle Guce /PM & Compliance | J37: Install and fit of Top Boxes | K37: Kim / +63 947 890 8545 | L37: E88 Asgard Warehouse | M37: 343 Poblete Compound (P7 warehouse) Sun Valley, Parañaque City | N37: MC-D400 Blue / R5FBMX0B0RL000503 / N730WA | O37: MC R280 Red / R5FBMGOB4RL000116 / N728WA | AH37: RideBox Battery - Ampace: 519110002370AAXXXNNK0097 519110002370AAXXXJJK0035 OKL7208JH202408300034 | AI37: RideBox Battery - Ampace: 519110002370AAXXXMJK0308 519110002370AAXXXJJK0115 OKL7208JH202408300018
C38: =C37+1 -> 36 | E38: GP-2026000024 | G38: Requisition ID-20260000026 | H38: 46055 | I38: Ron Dela Cruz / Sales | J38: Test / Demo Unit | K38: Ron Dela Cruz / (0917) 768 0944 / rdelacruz@nrdev.ph | L38: E88 Asgard Warehouse | M38: For testing c/o Ron | N38: MC- R280 Sport Blue / R5FBMGOB4RL000150 / N798WA | AH38: RideBox Battery - Ampace: 519110002370AAXXXNNK0067 519110002370AAXXXMJK0246 OKL7208JH202408300052
C39: =C38+1 -> 37 | F39: GR-2026000011 | G39: Requisition ID-20260000026 | H39: 46055 | I39: Ron Dela Cruz / Sales | J39: Test / Demo Unit | K39: Ron Dela Cruz / (0917) 768 0944 / rdelacruz@nrdev.ph | L39: For testing c/o Ron | M39: E88 Asgard Warehouse | N39: MC- R280 Sport Blue / R5FBMGOB4RL000150 / N798WA | AH39: RideBox Battery - Ampace: 519110002370AAXXXNNK0067 519110002370AAXXXMJK0246 OKL7208JH202408300052 | BV39: 46055
C40: 38 | E40: GP-2026000025 | G40: Requisition ID-20260000028 | H40: 46056 | I40: OKLA Team/ Visitors | J40: Replaced Parts | K40: E88 Samuel Kniazeff / +63 919 000 6311 / samuel@nrdev.ph | L40: E88 Asgard Warehouse | M40: OKLA Supplier China | N40: PARTS-ESP00086-Controller Assembly 65A (R280 Sport) | O40: PARTS- ESP00097 / Left Rear Fork Cover (R280 White) | P40: PARTS-ESP00025 / Switch Lock Assy with Key (R280/Sport) | Q40: PARTS- ESP00225 / Speedometer bracket (D400) | R40: PARTS- ESP00224 / Speedometer (D400) | BB40: 35 Units Coming from Cris Mendoza 6 Units taken from Spare Parts Warehouse Stocks | BC40: 1 Unit taken from Warehouse Stocks 1 Unit coming from replacement brought by OKLA Team | BD40: 2 units coming from replacement brought by OKLA Team | BE40: 2 Units coming replacement brought by OKLA Team | BF40: 1 Unit taken from Replaced unit by Cris
C41: 39 | D41: GI-2026-000023 | E41: GP-2026000026 | G41: Requisition ID-20260000023 | H41: 46056 | I41: Thea Masiglat / Marketing | J41: Test / Demo Unit | K41: Thea Masiglat / 09171022450 | L41: E88 Asgard Warehouse | M41: Premiere Southern Petroleum Corp. | N41: MC-D400 Red/ R5FBMX0B3RL000415 / N627WA | AH41: RideBox Battery - Ampace: 519110002370AAXXXNNK0067 519110002370AAXXXMJK0246 OKL7208JH202408300052
C42: 40 | D42: GI-2026-000024 | E42: GP-2026000027 | G42: Requisition ID-20260000027 | H42: 46057 | I42: John Martin Ysaac / Tech | J42: Replacement for offline batteries | K42: John Martin Ysaac / 09062858290 / jysaac@nrdev.ph | L42: E88 Asgard Warehouse | M42: Replacement for Offline Batteries | N42: RideBox Battery - Ampace / 519110002370AAXXXJJK0157 | O42: RideBox Battery - Ampace / 519110002370AAXXXJJK0074 | P42: RideBox Battery - Ampace / 519110002370AAXXXJJK0132 | Q42: RideBox Battery - Ampace / 519110002370AAXXXJJK0128
C43: 41 | D43: GI-2026-000025 | E43: GP-2026000028 | G43: Requisition ID-20260000028 | H43: 46058 | I43: Samuel Kniazeff / PQM | J43: Inventory Transfer to TCI / For Testing | K43: E88 Samuel Kniazeff / +63 919 000 6311 / samuel@nrdev.ph | L43: E88 Asgard Warehouse | M43: TCI Pasig | N43: RideBox Battery - Ampace 519110002370AAXXXNNK0126 | O43: RideBox Battery - Ampace / 519110002370AAXXXNNK0060 | P43: RideBox Battery - Ampace / 519110002370AAXXXNNK0088 | Q43: RideBox Battery - Ampace / 519110002370AAXXXMJK0313 | R43: RideBox Battery - Ampace / 519110002370AAXXXMJK0289
C44: 42 | D44: GI-2026-000026 | E44: GP-2026000029 | G44: Requisition ID-20260000029 | H44: 46060 | I44: John Martin Ysaac / Tech | J44: For Corner Stone | K44: John Martin Ysaac / 09062858290 / jysaac@nrdev.ph | L44: E88 Asgard Warehouse | M44: Cornerstone Building San Juan City | N44: RideBox Locker- 9M0021 | AH44: RideBox Battery - Ampace: 519110002370AAXXXJJK0131 519110002370AAXXXJJK0100 519110002370AAXXXJJK0256 519110002370AAXXXMJK0548
C45: 43 | D45: GI-2026-000027 | E45: GP-2026000030 | G45: Requisition ID-20260000030 | H45: 46060 | I45: John Martin Ysaac / Tech | J45: Corinthian Hills | K45: John Martin Ysaac / 09062858290 / jysaac@nrdev.ph | L45: E88 Asgard Warehouse | M45: Corinthian Hills Gate 1 | N45: RideBox Locker- 9M0035 | AH45: RideBox Battery - Ampace: 519110002370AAXXXJJK0069 519110002370AAXXXMJK0425 519110002370AAXXXNNK0023 519110002370AAXXXMJK0352
C46: 44 | D46: GI-2026-000028 | E46: GP-2026000032 | G46: Requisition ID-20260000033 | H46: 46065 | I46: John Martin Ysaac / Tech | J46: Deployment of Lockers and Batteries - Alfamart Ibayo Tipas Taguig | K46: Dagz Cabangisan / 0977 716 4472 | L46: E88 Asgard Warehouse | M46: Ibayo Tipas Taguig | N46: RideBox Locker- 9M0033 | AH46: RideBox Battery - Ampace: 519110002370AAXXXLJL0568 519110002370AAXXXLJL0501 519110002370AAXXXLJL0596 519110002370AAXXXLJL0338
C47: 45 | E47: GP-2026000033 | G47: Requisition ID-20260000034 | H47: 46062 | I47: Christopher Mendoza / PQM | J47: Replacement of Controller of Client Under Warranty | K47: E88 Christopher Mendoza / +63 960 897 8870 / cmendoza@nrdev.ph | L47: E88 Asgard Warehouse | M47: E88 Asgard Warehouse Service to Client under warranty | N47: Controller Assembly 50A (R280) | BB47: Change of Controller Under Warranty
C48: 46 | D48: GI-2026-000029 | E48: GP-2026000034 | G48: Requisition ID-20260000035 | H48: 46065 | I48: Emman Usi / Tech | J48: Replacement for Offline batteries | K48: Emman Usi / 0908 318 7665 / eusi@nrdev.ph | L48: E88 Asgard Warehouse | M48: Power Fill Barangka, 349 Barangka Dr., Mandaluyong City, 1550 Kalakhang Maynila | N48: RideBox Battery - Ampace / 519110002370AAXXXLJL0177 | O48: RideBox Battery - Ampace / 519110002370AAXXXLJL0589 | P48: RideBox Battery - Ampace / 519110002370AAXXXNJL0061
C49: 47 | F49: GR-2026000012 | G49: Requisition ID-20260000035 | H49: 46065 | I49: Emman Usi / Tech | J49: Offline batteries from Powerfill Barangka | K49: Emman Usi / 0908 318 7665 / eusi@nrdev.ph | L49: Power Fill Barangka, 349 Barangka Dr., Mandaluyong City, 1550 Kalakhang Maynila | M49: E88 Asgard Warehouse | N49: RideBox Battery - Ampace / 519110002370AAXXXMJK0157 | O49: RideBox Battery - Ampace / 519110002370AAXXXNNK0057 | P49: RideBox Battery - Ampace / 519110002370AAXXXMJK0185 | BV49: 46065
C50: 48 | D50: GI-2026-000030 | E50: GP-2026000035 | G50: Requisition ID-20260000036 | H50: 46066 | I50: Judielle Guce /PM & Compliance | J50: Test / Demo Unit | K50: JRS / Joprang / 09771975432 | L50: E88 Asgard Warehouse | M50: JRS / 19 Brixton St, Pasig, 1603 Metro Manila | N50: MC-D400 Blue / R5FBMX0B9RL000533 / N771WA | AH50: RideBox Battery - Ampace- 519110002370AAXXXMJK0338 519110002370AAXXXSNK0005 OKL7208JH2024408300132
C51: 49 | D51: GI-2026-000031 | E51: GP-2026000036 | G51: Requisition ID-20260000031 | H51: 46071 | I51: Judielle Guce /PM & Compliance | J51: Donation | K51: Raymond Lising / 09985840889 | L51: E88 Asgard Warehouse | M51: Barangay San Antonio / Gen. Malvar St., Barangay San Antonio, Pasig City | N51: MC-D400 Red / R5FBMX0B2RL000423 | O51: MC-R280 Sport Blue / R5FBMGOB7RL000157 | AH51: RideBox Battery - Ampace: 519110002370AAXXXMJK0151 519110002370AAXXXJJK0243 OKL7208JH2024408300110 | AI51: RideBox Battery - Ampace: 519110002370AAXXXMJK0323 519110002370AAXXXMJK0159 OKL7208JH2024408300083
C52: 50 | D52: GI-2026-000032 | E52: GP-2026000037 | G52: Requisition ID-20260000032 | H52: 46073 | I52: Judielle Guce /PM & Compliance | J52: Donation / Lease to Client | K52: Jeremy Marquez / Randy Buenaventura / 09985895636 | L52: E88 Asgard Warehouse | M52: BF Homes Paranaque | N52: MC D400 Red / R5FBMX0B4RL000438 | O52: MC D400 Red / R5FBMX0B5RL000464 | P52: MC D400 Red / R5FBMX0B7RL000417 | Q52: MC D400 Red / R5FBMX0B0RL000436 | R52: MC D400 Red / R5FBMX0B2RL000437 | S52: MC R280 Sport Blue / R5FBMGOB4RL000133 / N778WA | T52: MC R280 Sport Blue / R5FBMGOB8RL000135 / N776WA | U52: MC R280 Sport Blue / R5FBMGOB4RL000150 / N798WA | V52: MC R280 Sport Blue / R5FBMGOB1RL000137 | W52: MC R280 Sport Blue / R5FBMGOB5RL000156 / N799WA | AH52: RideBox Battery - Ampace: 519110002370AAXXXJJK0139 519110002370AAXXXLJL0380 OKL7208JH2024408300086 | AI52: RideBox Battery - Ampace: 519110002370AAXXXNNK0036 519110002370AAXXXLJL0497 OKL7208JH2024408300243 | AJ52: RideBox Battery - Ampace: 519110002370AAXXXLJL0202 519110002370AAXXXJJK0090 OKL7208JH2024408300077 | AK52: RideBox Battery - Ampace: 519110002370AAXXXMJK0405 519110002370AAXXXLJL0162 OKL7208JH2024408300046 | AL52: RideBox Battery - Ampace: 519110002370AAXXXLJL0549 519110002370AAXXXLJL0599 OKL7208JH2024408300090 | AM52: RideBox Battery - Ampace: 519110002370AAXXXMJK0250 519110002370AAXXXMJK0386 OKL7208JH2024408300088 | AN52: RideBox Battery - Ampace: 519110002370AAXXXJJK0052 519110002370AAXXXMJK0097 OKL7208JH2024408300084 | AO52: RideBox Battery - Ampace: 519110002370AAXXXLJL0385 519110002370AAXXXLJL0331 OKL7208JH2024408300082 | AP52: RideBox Battery - Ampace: 519110002370AAXXXMJK0197 519110002370AAXXXMJK0364 OKL7208JH2024408300032 | AQ52: RideBox Battery - Ampace: 519110002370AAXXXLJL0373 519110002370AAXXXLJL0372 OKL7208JH2024408300256
C53: 51 | D53: GI-2026-000033 | E53: GP-2026000038 | G53: Requisition ID-20260000037 | H53: 46069 | I53: Judielle Guce /PM & Compliance | J53: Donation | K53: Engr. Murphy / '09062191125 | L53: E88 Asgard Warehouse | M53: Corinthian Garden | N53: MC-R280 Sport Blue / R5FBMGOB5RL000142 | O53: MC-R280 Sport Blue / R5FBMGOB4RL000147 | P53: MC-R280 Sport Blue / R5FBMGOB6RL000151 | Q53: MC D400 Red / R5FBMX0B6RL000439 | R53: MC D400 Red / R5FBMX0B9RL000421 | AH53: RideBox Battery - Ampace: 519110002370AAXXXLJL0601 519110002370AAXXXLJL0344 OKL7208JH2024408300275 | AI53: RideBox Battery - Ampace: 519110002370AAXXXNNK0089 519110002370AAXXXJJK0201 OKL7208JH2024408300042 | AJ53: RideBox Battery - Ampace: 519110002370AAXXXLJL0272 519110002370AAXXXNJL0130 OKL7208JH2024408300238 | AK53: RideBox Battery - Ampace: 519110002370AAXXXLJL0547 519110002370AAXXXLJL0371 OKL7208JH2024408300066 | AL53: RideBox Battery - Ampace: 519110002370AAXXXLJL0326 519110002370AAXXXLJL0374 OKL7208JH2024408300202
A54: cancelled | C54: 52 | D54: GI-2026-000034 | E54: GP-2026000039 | G54: Requisition ID-20260000038 | H54: 46080 | I54: John Martin Ysaac / Tech | J54: Deployment of Lockers and Batteries - Jordan Plains | K54: Alfamart / Eduard Pranada / +63 917 954 9957 | L54: E88 Asgard Warehouse | M54: Jordan Plains Subdivision QC | N54: RideBox Locker- 9M0022 | AH54: RideBox Battery - Ampace: 519110002370AAXXXLJL0379 519110002370AAXXXNJL0067 519110002370AAXXXLJL0101 519110002370AAXXXLJL0340
C55: 53 | F55: GR-2026000013 | G55: Requisition ID-20260000025 | H55: 46069 | I55: Judielle Guce /PM & Compliance | J55: Install and fit of Top Boxes | K55: Kim / +63 947 890 8545 | L55: 343 Poblete Compound (P7 warehouse) Sun Valley, Parañaque City | M55: E88 Asgard Warehouse | N55: MC-D400 Blue / R5FBMX0B0RL000503 / N730WA | O55: MC R280 Red / R5FBMGOB4RL000116 / N728WA | AH55: RideBox Battery - Ampace: 519110002370AAXXXNNK0097 519110002370AAXXXJJK0035 OKL7208JH202408300034 | AI55: RideBox Battery - Ampace: 519110002370AAXXXMJK0308 519110002370AAXXXJJK0115 OKL7208JH202408300018 | BV55: 46069
C56: 54 | D56: GI-2026-000035 | E56: GP-2026000040 | G56: Requisition ID-20260000039 | H56: 46071 | I56: Judielle Guce /PM & Compliance | J56: Test / Demo Unit | K56: Pilipinas Messerve / Jaylord Duhaylungsod / +639392535263 | L56: E88 Asgard Warehouse | M56: 90 Congressional Ave., Brgy. Bahay Toro Project 8, Quezon City | N56: MC-D400 Red / R5FBMX0B1RL000462 | O56: MC-D400 Red / R5FBMX0BXRL000427 | AH56: RideBox Battery - Ampace: 519110002370AAXXXLJL0560 519110002370AAXXXLJL0518 OKL7208JH202408300154 | AI56: RideBox Battery - Ampace: 519110002370AAXXXLJL0036 519110002370AAXXXLJL0274 OKL7208JH202408300155
C57: 55 | D57: GI-2026-000036 | E57: GP-2026000041 | G57: Requisition ID-20260000041 | H57: 46070 | I57: Judielle Guce /PM & Compliance | J57: Test / Demo Unit | K57: Philpower | L57: E88 Asgard Warehouse | M57: Unit 2B, 120 K-6th St., Brgy. East Kamias, Quezon City, Metro Manila
C58: 56 | D58: GI-2026-000037 | E58: GP-2026000042 | G58: Requisition ID-20260000040 | H58: 46071 | I58: Judielle Guce /PM & Compliance | J58: Test / Demo Unit | K58: Angkas / Ron Dela Cruz / '09177680944 | L58: E88 Asgard Warehouse | M58: 2723 Sabio St., Chino Roces Ave., Bangkal, Makati City | N58: MC-D400 Blue / R5FBMX0B2RL000499 | O58: MC-D400 Blue / R5FBMX0BXRL000489 | AH58: RideBox Battery - Ampace: 519110002370AAXXXLJL0342 519110002370AAXXXLJL0499 OKL7208JH202408300269 | AI58: RideBox Battery - Ampace: 519110002370AAXXXLJL0381 519110002370AAXXXLJL0260 OKL7208JH202408300101
C59: 57 | D59: GI-2026-000038 | E59: GP-2026000043 | H59: 46073 | I59: Judielle Guce /PM & Compliance | J59: Lease to Client | K59: Angkas | L59: E88 Asgard Warehouse | M59: 73 Marymount St., Provident Village, Marikina City, Metro Manila | N59: MC-D400 Blue / R5FBMX0B8RL000510 | O59: MC-D400 Blue / R5FBMX0B1RL000526 | P59: MC-D400 Blue / R5FBMX0B1RL000512 | Q59: MC-D400 Blue / R5FBMX0B7RL000515 | R59: MC-D400 Blue / R5FBMX0B8RL000491 | S59: MC-D400 Blue / R5FBMX0BXRL000525 | T59: MC-D400 Blue / R5FBMX0B8RL000524 | U59: MC-D400 Blue / R5FBMX0B3RL000530 | V59: MC-D400 Blue / R5FBMX0B6RL000506 | W59: MC-D400 Blue / R5FBMX0B5RL000478 | AH59: RideBox Battery - Ampace: 519110002370AAXXXLJL0378 519110002370AAXXXLJL0367 OKL7208JH202408300294 | AI59: RideBox Battery - Ampace: 519110002370AAXXXLJL0388 519110002370AAXXXLJL0546 OKL7208JH202408300104 | AJ59: RideBox Battery - Ampace: 519110002370AAXXXNJL0099 519110002370AAXXXLJL0332 OKL7208JH202408300227 | AK59: RideBox Battery - Ampace: 519110002370AAXXXNJL0065 519110002370AAXXXLJL0270 OKL7208JH202408300173 | AL59: RideBox Battery - Ampace: 519110002370AAXXXLJL0545 519110002370AAXXXLJL0343 OKL7208JH202408300232 | AM59: RideBox Battery - Ampace: 519110002370AAXXXLJL0004 519110002370AAXXXLJL0520 OKL7208JH202408300230 | AN59: RideBox Battery - Ampace: 519110002370AAXXXLJL0225 519110002370AAXXXLJL0500 OKL7208JH202408300030 | AO59: RideBox Battery - Ampace: 519110002370AAXXXNJL0066 519110002370AAXXXLJL0517 OKL7208JH202408300114 | AP59: RideBox Battery - Ampace: 519110002370AAXXXNJL0102 519110002370AAXXXLJL0199 OKL7208JH202408300043 | AQ59: RideBox Battery - Ampace: 519110002370AAXXXLJL0334 519110002370AAXXXLJL0345 OKL7208JH202408300226
C60: 58 | F60: GR-2026000014 | G60: Requisition ID-20260000024 | H60: 46071 | I60: Judielle Guce /PM & Compliance | J60: Test / Demo Unit | K60: Toni Nodalo / 09675019247 | L60: QuadX | M60: E88 Asgard Warehouse | N60: MC-D400 Blue / R5FBMX0B0RL000517 / N724WA | O60: MC-D400 Blue /R5FBMX0B7RL000501 | AH60: RideBox Battery - Ampace: 519110002370AAXXXJJK0177 519110002370AAXXXMJK0376 OKL7208JH202408300020 | AI60: RideBox Battery - Ampace: 519110002370AAXXXNNK0128 519110002370AAXXXJJK0203 OKL7208JH202408300050 | BV60: 46071
C61: 59 | D61: GI-2026-000039 | E61: GP-2026000044 | G61: Requisition ID-20260000042 | H61: 46073 | I61: Judielle Guce /PM & Compliance | J61: Lease to Client | K61: Flexride / Jerrick Limoanco / '09175645545 | L61: E88 Asgard Warehouse | M61: 73 Marymount St., Provident Village, Marikina City, Metro Manila | N61: MC R280 White / R5FBMG0C6SL000214 | O61: MC R280 White / R5FBMG0C9SL000238 | P61: MC R280 White / R5FBMG0C8SL000215 | Q61: MC R280 White / R5FBMG0C0SL000225 | R61: MC R280 White / R5FBMG0C3SL000218 | S61: MC R280 White / R5FBMG0C9SL000224 | T61: MC R280 White / R5FBMG0C5SL000236 | U61: MC R280 White / R5FBMG0C2SL000226 | V61: MC R280 White / R5FBMG0C6SL000228 | W61: MC R280 White / R5FBMG0C6SL000231 | AH61: RideBox Battery - Ampace: 519110002370AAXXXLJL0368 519110002370AAXXXLJL0550 OKL7208JH202408300035 | AI61: RideBox Battery - Ampace: 519110002370AAXXXLJL0106 519110002370AAXXXLJL0148 OKL7208JH202408300038 | AJ61: RideBox Battery - Ampace: 519110002370AAXXXJJK0039 519110002370AAXXXLJL0543 OKL7208JH202408300094 | AK61: RideBox Battery - Ampace: 519110002370AAXXXLJL0329 519110002370AAXXXLJL0029 OKL7208JH202408300092 | AL61: RideBox Battery - Ampace: 519110002370AAXXXLJL0035 519110002370AAXXXLJL0335 OKL7208JH202408300089 | AM61: RideBox Battery - Ampace: 519110002370AAXXXLJL0366 519110002370AAXXXLJL0603 OKL7208JH202408300234 | AN61: RideBox Battery - Ampace: 519110002370AAXXXLJL0365 519110002370AAXXXLJL0197 OKL7208JH202408300211 | AO61: RideBox Battery - Ampace: 519110002370AAXXXLJL0502 519110002370AAXXXLJL0386 OKL7208JH202408300087 | AP61: RideBox Battery - Ampace: 519110002370AAXXXLJL0398 519110002370AAXXXLJL0207 OKL7208JH202408300091 | AQ61: RideBox Battery - Ampace: 519110002370AAXXXLJL0024 519110002370AAXXXLJL0552 OKL7208JH202408300100
C62: 60 | F62: GR-2026000015 | G62: Requisition ID-20260000022 | H62: 46072 | I62: Haide Garcia / HR | J62: Returned of Assigned Unit | K62: Ron Dela Cruz / (0917) 768 0944 / rdelacruz@nrdev.ph | L62: E88 Asgard Warehouse | M62: E88 Asgard Warehouse | N62: MC-D400 4000W Red / R5FBMX0B2RL000440 | BV62: 46072
C63: 61 | D63: GI-2026-000040 | E63: GP-2026000045 | G63: Requisition ID-20260000043 | H63: 46072 | I63: Haide Garcia / HR | J63: Assignment to Employee | K63: Ron Dela Cruz / (0917) 768 0944 / rdelacruz@nrdev.ph | L63: E88 Asgard Warehouse | M63: E88 Asgard Warehouse | N63: MC-D400 Black / R5FBMX0B9SL000554 | AH63: RideBox Battery - Ampace: 519110002370AAXXXLJL0518 519110002370AAXXXLJL0560 OKL7208JH202408300048 | BB63: Change of Unit Assignment Same Battery and Charger
C64: 62 | D64: GI-2026-000041 | E64: GP-2026000046 | G64: Requisition ID-20260000044 | H64: 46073 | I64: John Martin Ysaac / Tech | J64: Deployment of Lockers and Batteries - Alfamart Santolan Pasig | K64: Alfamart / Eduard Pranada / +63 917 954 9957 | L64: E88 Asgard Warehouse | M64: ATP EVANGELISTA ST SANTOLAN | N64: RideBox Locker- 9M0009 | AH64: RideBox Battery - Ampace: 519110002370AAXXXLJL0133 519110002370AAXXXLJL0215 519110002370AAXXXLJL0235 519110002370AAXXXLJL0135
C65: 63 | D65: GI-2026-000042 | E65: GP-2026000047 | G65: Requisition ID-20260000047 | H65: 46073 | I65: John Martin Ysaac / Tech | J65: Deployment of Lockers and Batteries - Alfamart 4th State Paranaque | K65: DAGZ CABANGISAN (ThingsPH) / 0977 716 4472 | L65: E88 Asgard Warehouse | M65: Alfamart 4th State Paranaque | N65: RideBox Locker- 9M0005 | AH65: RideBox Battery - Ampace: 519110002370AAXXXLJL0390 519110002370AAXXXLJL0094 519110002370AAXXXLJL0176 519110002370AAXXXNJL0116
C66: 64 | D66: GI-2026-000043 | E66: GP-2026000048 | G66: Requisition ID-20260000045 | I66: John Martin Ysaac / Tech | J66: Deployment of Lockers and Batteries - Alfamart Tanza Navotas | K66: Eduard Pranada / +63 917 954 9957 | L66: E88 Asgard Warehouse | M66: ATP CARVILLE SUBD TANZA NAVOTAS
C67: 65 | D67: GI-2026-000044 | E67: GP-2026000049 | G67: Requisition ID-20260000046 | H67: 46080 | I67: John Martin Ysaac / Tech | J67: Deployment of Lockers and Batteries - ATP Macanas St. – Panghulo, Malabon | K67: Eduard Pranada / +63 917 954 9957 | L67: E88 Asgard Warehouse | M67: ATP Macanas St. – Panghulo, Malabon | N67: RideBox Locker- 9M0047 | AH67: RideBox Battery - Ampace: 519110002370AAXXXLJL0290 519110002370AAXXXNJL0174 519110002370AAXXXLJL0258 519110002370AAXXXLJL0409
C68: 66 | E68: GP-2026000050 | G68: Requisition ID-20260000048 | H68: 46073 | I68: Christopher Mendoza / PQM | J68: Replacement of Parts for Flexride | K68: E88 Samuel Kniazeff / +63 919 000 6311 / samuel@nrdev.ph | L68: E88 Asgard Warehouse | M68: E88 Asgard Warehouse | N68: ESP00012 - Left Combination Switch (R280/Sport)
C69: 67 | D69: GI-2026-000045 | E69: GP-2026000051 | G69: Requisition ID-20260000049 | H69: 46076 | I69: Emman Usi / Tech | J69: Replacement of Offline Battery in Powerfill Sandoval Pasig | K69: E88 Ventures, Inc Emman Usi / 0908 318 7665 / eusi@nrdev.ph | L69: E88 Asgard Warehouse | M69: Powerfill Sandoval Pasig | N69: RideBox Battery - Ampace / 519110002370AAXXXLJL0506
C70: 68 | F70: GR-2026000016 | G70: Requisition ID-20260000049 | H70: 46077 | I70: Emman Usi / Tech | J70: Replacement of Offline Battery in Powerfill Sandoval Pasig | K70: E88 Ventures, Inc Emman Usi / 0908 318 7665 / eusi@nrdev.ph | L70: Powerfill Sandoval Pasig | M70: E88 Asgard Warehouse | N70: RideBox Battery - Ampace / 519110002370AAXXXMJK0221 | O70: RideBox Battery - Ampace / 519110002370AAXXXMJK0051 | P70: RideBox Battery - Ampace / 519110002370AAXXXMJK0495 | BV70: 46077
C71: 69 | D71: GI-2026-000046 | E71: GP-2026000052 | G71: Requisition ID-20260000051 | H71: 46077 | I71: Emman Usi / Tech | J71: Replacement of Battery | K71: E88 Ventures, Inc Emman Usi / 0908 318 7665 / eusi@nrdev.ph | L71: E88 Asgard Warehouse | M71: E88 Asgard Warehouse | N71: RideBox Battery - Ampace / 519110002370AAXXXJJK0128 | O71: RideBox Battery - Ampace / 519110002370AAXXXJJK0157
C72: 70 | D72: GI-2026-000047 | E72: GP-2026000053 | G72: Requisition ID-20260000050 | H72: 46078 | I72: Samuel Kniazeff / PQM | J72: Replacement of Offline Battery in Jamo Corp | K72: JAMO CORP | L72: E88 Asgard Warehouse | M72: 126 Simoun St., Sto. Domingo, QC | N72: RideBox Battery - Ampace / 519110002370AAXXXLJL0096 | O72: RideBox Battery - Ampace / 519110002370AAXXXNJL0083 | P72: RideBox Battery - Ampace / 519110002370AAXXXLJL0250 | Q72: RideBox Battery - Ampace / 519110002370AAXXXLJL0142 | R72: RideBox Battery - Ampace / 519110002370AAXXXLJL0220 | S72: RideBox Battery - Ampace / 519110002370AAXXXLJL0229 | T72: RideBox Battery - Ampace / 519110002370AAXXXNJL0107 | U72: RideBox Battery - Ampace / 519110002370AAXXXLJL0216 | V72: RideBox Battery - Ampace / 519110002370AAXXXLJL0387 | W72: RideBox Battery - Ampace / 519110002370AAXXXLJL0110 | X72: RideBox Battery - Ampace / 519110002370AAXXXLJL0092 | Y72: RideBox Battery - Ampace / 519110002370AAXXXNJL0078 | Z72: RideBox Battery - Ampace / 519110002370AAXXXNJL0075 | AA72: RideBox Battery - Ampace / 519110002370AAXXXNJL0098 | AB72: RideBox Battery - Ampace / 519110002370AAXXXLJL0537 | AC72: RideBox Battery - Ampace / 519110002370AAXXXMJK0454 | AD72: RideBox Battery - Ampace / 519110002370AAXXXLJL0164 | AE72: RideBox Battery - Ampace / 519110002370AAXXXLJL0238 | AF72: RideBox Battery - Ampace / 519110002370AAXXXLJL0346 | AG72: RideBox Battery - Ampace / 519110002370AAXXXLJL0600
C73: 71 | F73: GR-2026000017 | G73: Requisition ID-20260000050 | H73: 46078 | I73: Samuel Kniazeff / PQM | J73: Pull Out of Offline Battery | K73: JAMO CORP | L73: 126 Simoun St., Sto. Domingo, QC | M73: E88 Asgard Warehouse | N73: RideBox Battery - Ampace / 519110002370AAXXXJJK0135 | O73: RideBox Battery - Ampace / 519110002370AAXXXJJK0076 | P73: RideBox Battery - Ampace / 519110002370AAXXXMJK0354 | Q73: RideBox Battery - Ampace / 519110002370AAXXXJJK0241 | R73: RideBox Battery - Ampace / 519110002370AAXXXMJK0535 | S73: RideBox Battery - Ampace / 519110002370AAXXXMJK0327 | T73: RideBox Battery - Ampace / 519110002370AAXXXMJK0140 | U73: RideBox Battery - Ampace / 519110002370AAXXXJJK0146 | V73: RideBox Battery - Ampace / 519110002370AAXXXJJK0073 | W73: RideBox Battery - Ampace / 519110002370AAXXXMJK0350 | X73: RideBox Battery - Ampace / 519110002370AAXXXMJK0314 | Y73: RideBox Battery - Ampace / 519110002370AAXXXMJK0388 | Z73: RideBox Battery - Ampace / 519110002370AAXXXMJK0283 | AA73: RideBox Battery - Ampace / 519110002370AAXXXMJK0208 | AB73: RideBox Battery - Ampace / 519110002370AAXXXJJK0068 | AC73: RideBox Battery - Ampace / 519110002370AAXXXMJK0385 | AD73: RideBox Battery - Ampace / 519110002370AAXXXMJK0410 | AE73: RideBox Battery - Ampace / 519110002370AAXXXMJK0254 | AF73: RideBox Battery - Ampace / 519110002370AAXXXMJK0321 | AG73: RideBox Battery - Ampace / / 519110002370AAXXXMJK0040 | BV73: 46078
A74: Cancelled | C74: 72 | D74: GI-2026-000048 | E74: GP-2026000054 | G74: Requisition ID-20260000055 | H74: 46080 | I74: Christopher Mendoza / PQM | J74: PMS for Jamo | K74: JAMO CORP / ANN / +639665892036 | L74: E88 Asgard Warehouse | M74: 126 Simoun St., Sto. Domingo, QC | N74: ESP00224 - Speedometer (D400) | O74: ESP00224 - Front Left Signal Indicator Light (D400) | P74: ESP00222 - Right Passenger Foot Rest (D400)
C75: 73 | D75: GI-2026-000049 | E75: GP-2026000055 | G75: Requisition ID-20260000052 | H75: 46080 | I75: Ian Jimenez / Tech | J75: Inventory Transfer to TCI | K75: Ian Jimenez / 09062924124 / ijimenez@nrdev.ph | L75: E88 Asgard Warehouse | M75: 3rd Floor, TCI Building, West Capitol, Kapitolyo, Pasig | N75: RideBox Locker- 9M0013
C76: 74 | D76: GI-2026-000050 | E76: GP-2026000056 | G76: Requisition ID-20260000054 | H76: 46080 | I76: Ian Jimenez / Tech | J76: Inventory Transfer to TCI | K76: Ian Jimenez / 09062924124 / ijimenez@nrdev.ph | L76: E88 Asgard Warehouse | M76: 3rd Floor, TCI Building, West Capitol, Kapitolyo, Pasig | N76: RideBox Battery - Ampace / 519110002370AAXXXMJK0388 | BW76: With Crack in battery Connector base
C77: 75 | F77: GR-2026000018 | G77: Requisition ID-20260000050 | H77: 46078 | I77: Samuel Kniazeff / PQM | J77: Pull Out of Locker | K77: JAMO CORP / ANN / +639665892036 | L77: 126 Simoun St., Sto. Domingo, QC | M77: E88 Asgard Warehouse | N77: RideBox Locker- 9M0015 | AH77: RideBox Battery - Ampace / 519110002370AAXXXMJK0318 519110002370AAXXXJJK0116 519110002370AAXXXJJK0041 519110002370AAXXXMJK0350 | BV77: 46078
C78: 76 | D78: GI-2026-000051 | E78: GP-2026000057 | G78: Requisition ID-20260000056 | H78: 46081 | I78: Haide Garcia / HR | J78: Assignment to Employee | K78: Jomari Inhaynes / 0975 431 2241 / jinhaynes@nrdev.ph | L78: E88 Asgard Warehouse | M78: E88 Asgard Warehouse | N78: MC R280 Sport Blue / R5FBMGOB7RL000160 / N777WA | AH78: RideBox Battery - Ampace / 519110002370AAXXXMJK0445 519110002370AAXXXMJK0428 OKL7208JH202408300246
A79: DONE | C79: 77 | D79: GI-2026-000052 | E79: GP-2026000058 | G79: Requisition ID-20260000057 | H79: 46105 | I79: Judielle Guce /PM & Compliance | J79: Test / Demo Unit | K79: Teko Christopher Michael Teodoro / 09175440007 | L79: E88 Asgard Warehouse | M79: 7/F Common Goal Tower Suite 705 Finance, Cor Industry St, New Alabang Village, Muntinlupa, 1780 Metro Manila | N79: MC- R280 Sport-Red / R5FBMGOBXRL000105 / N619WA | AH79: RideBox Battery - Ampace / 519110002370AAXXXJJK0074 519110002370AAXXXLJL0376 OKL7208JH202408300105
A80: DONE | C80: 78 | D80: GI-2026-000053 | E80: GP-2026000059 | G80: Requisition ID-20260000058 | H80: 46108 | I80: Samuel Kniazeff / PQM | J80: Mobile BSS | K80: SAMUEL KNIAZEFF JR / '09171086482 | L80: E88 Asgard Warehouse | M80: 3rd Floor, TCI Building, West Capitol, Kapitolyo, Pasig | N80: MC- R280 Sport-Blue / R5FBMGOB6RL000148 / N606WA | O80: MC- R280 Sport-Blue / R5FBMGOBXRL000153 / N772WA | P80: EFS00009 - Helmet | AH80: RideBox Battery - Ampace / 519110002370AAXXXMJK0273 519110002370AAXXXMJK0255 | AI80: RideBox Battery - Ampace / 519110002370AAXXXJJK0022 519110002370AAXXXMJK0230
A81: DONE | C81: 79 | D81: GI-2026-000054 | E81: GP-2026000060 | G81: Requisition ID-20260000059 | H81: 46087 | I81: Judielle Guce /PM & Compliance | J81: Test / Demo Unit with Cage | K81: Phoenix Madrigal Vincent Leo B. Reyes / '09088697164 | L81: E88 Asgard Warehouse | M81: Alabang Zapote Road, Madrigal Business Park Ayala Alabang Muntinlupa City | N81: MC- D400 Blue / R5FBMX0B7RL000501 / N797WA | AH81: RideBox Battery - Ampace / 519110002370AAXXXNNK0128 519110002370AAXXXJJK0203 OKL7208JH202408300050
A82: DONE | C82: 80 | D82: GI-2026-000055 | E82: GP-2026000061 | G82: Requisition ID-20260000060 | H82: 46085 | I82: Christopher Mendoza / PQM | J82: Replacement Parts for Move It Unit | K82: Christopher C. Mendoza | L82: E88 Asgard Warehouse | M82: E88 Asgard Warehouse | N82: ESP00284 Left Front Protective Panel (D400 Black) | O82: ESP00165 Left Rear Protective Side Panel (D400)
A83: DONE | C83: 81 | D83: GI-2026-000056 | E83: GP-2026000062 | G83: Requisition ID-20260000064 | H83: 46086 | I83: Samuel Kniazeff / PQM | J83: Stock Transfer | K83: SAMUEL KNIAZEFF JR / '09171086482 | L83: E88 Asgard Warehouse | M83: 3rd Floor, TCI Building, West Capitol, Kapitolyo, Pasig | N83: ESP00224 / Speedometer (D400)
A84: DONE | C84: 82 | D84: GI-2026-000057 | E84: GP-2026000063 | G84: Requisition ID-20260000061 | H84: 46088 | I84: John Martin Ysaac / Tech | J84: Deployment of Locker and Batteries- ATP Gomez Mandaluyong | K84: STM Builders /ATP P GOMEZ POBLACION MANDALUYONG | L84: E88 Asgard Warehouse | M84: ATP P GOMEZ POBLACION MANDALUYONG | N84: RideBox Locker- 9M0027 | AH84: RideBox Battery - Ampace / 519110002370AAXXXNJL0199 519110002370AAXXXNJL0201 519110002370AAXXXLJL0303 519110002370AAXXXLJL0079
A85: PENDING | C85: 83 | D85: GI-2026-000058 | E85: GP-2026000064 | G85: Requisition ID-20260000062 | H85: 46088 | I85: John Martin Ysaac / Tech | J85: Deployment of Locker and Batteries- Robinsons Bluewave Marikina | K85: Creative Parking/ Robinsons Supermarket Blue Wave Marikina | L85: E88 Asgard Warehouse | M85: 2 Sumulong Highway cor. Gil Fernando St., Brgy. Sto. Niño,, Marikina | N85: RideBox Locker- 9M0031 | AH85: RideBox Battery - Ampace / 519110002370AAXXXLJL0246 519110002370AAXXXNJL0103 519110002370AAXXXNJL0167 519110002370AAXXXNJL0168
A86: PENDING | C86: 84 | D86: GI-2026-000059 | E86: GP-2026000065 | G86: Requisition ID-20260000063 | H86: 46088 | I86: John Martin Ysaac / Tech | J86: Deployment of Locker and Batteries- Creative Parking Pearl Drive CBP1 | K86: Creative Parking Pearl Drive CBP1 | L86: E88 Asgard Warehouse | M86: Creative Parking Pearl Drive CBP1 | N86: RideBox Locker- 9M0024 | AH86: RideBox Battery - Ampace / 519110002370AAXXXLJL0308 519110002370AAXXXNJL0140 519110002370AAXXXLJL0119 519110002370AAXXXLJL0249
A87: DONE | C87: 85 | F87: GR-2026000019 | G87: Requisition ID-20260000039 | H87: 46086 | I87: Judielle Guce /PM & Compliance | J87: Test / Demo Unit | K87: Pilipinas Messerve / Jaylord Duhaylungsod / +639392535263 | L87: 90 Congressional Ave., Brgy. Bahay Toro Project 8, Quezon City | M87: E88 Asgard Warehouse | N87: MC-D400 Red / R5FBMX0B1RL000462 | O87: MC-D400 Red / R5FBMX0BXRL000427 | AH87: RideBox Battery - Ampace: 519110002370AAXXXJJK0200 519110002370AAXXXJJK0050 OKL7208JH202408300154 | AI87: RideBox Battery - Ampace: 519110002370AAXXXNNK0107 519110002370AAXXXNNK0118 OKL7208JH202408300155 | BV87: 46086
A88: PENDING | C88: 86 | D88: GI-2026-000060 | E88: GP-2026000066 | G88: Requisition ID-20260000065 | H88: 46090 | I88: John Martin Ysaac / Tech | J88: Deployment of Lockers and Batteries- Energizer Battery Automotive Kalayaan Ave Makati | K88: John Digicore | L88: E88 Asgard Warehouse | M88: Energizer Battery Automotive Kalayaan Ave, Guadalupe Nuevo, Makati, 1212 Metro Manila | N88: RideBox Locker- 9M0031 | AH88: RideBox Battery - Ampace / 519110002370AAXXXLJL0246 519110002370AAXXXNJL0103 519110002370AAXXXNJL0167 519110002370AAXXXNJL0168
A89: DONE | C89: 87 | D89: GI-2026-000061 | E89: GP-2026000067 | G89: Requisition ID-20260000066 | H89: 46136 | I89: John Martin Ysaac / Tech | J89: Deployment of Lockers and Batteries- DIGICORE / Pateros Municipal Hall | K89: John Jerusalem / +6399 8560 7809 | L89: E88 Asgard Warehouse | M89: Pateros Municipal Hall G. de Borja Street 1620 Pateros National Capital Region | N89: RideBox Locker- 9M0024 | AH89: RideBox Battery - Ampace / 519110002370AAXXXLJL0308 519110002370AAXXXNJL0140 519110002370AAXXXLJL0119 519110002370AAXXXLJL0249
A90: DONE | C90: 88 | D90: GI-2026-000062 | E90: GP-2026000068 | G90: Requisition ID-20260000067 | H90: 46106 | I90: Judielle Guce /PM & Compliance | J90: Test / Demo Unit | K90: Ace Vergel Dela Cruz / '09190083175 | L90: E88 Asgard Warehouse | M90: Move It Training Facilities # 66 A Bonifacio Avenue Marikina | N90: RideBox Locker - 9M0019 | AH90: RideBox Battery - Ampace / 519110002370AAXXXLJL0459 519110002370AAXXXLJL0253 519110002370AAXXXLJL0358 519110002370AAXXXLJL0585
A91: DONE | C91: 89 | D91: GI-2026-000063 | E91: GP-2026000069 | G91: Requisition ID-20260000068 | H91: 46106 | I91: Judielle Guce /PM & Compliance | J91: Test / Demo Unit | K91: Move It / Ace Vergel Dela Cruz / '09190083175 | L91: E88 Asgard Warehouse | M91: Move It Training Facilities # 66 A Bonifacio Avenue Marikina | N91: MC-D400 Black / R5FBMX0B0SL000541 / N698WA | O91: MC-D400 Black / R5FBMX0B7SL000536 / N679WA | P91: MC-D400 Black / R5FBMX0B8SL000545 / N688WA | Q91: MC-D400 Black / R5FBMX0B6SL000544 / N685WA | R91: MC-D400 Black / R5FBMX0B8SL000562 / N696WA | S91: MC-D400 Black / R5FBMX0B5SL000552 / N691WA | T91: MC-D400 Black / MC-D400 Black / R5FBMX0B9SL000554 / N690WA | U91: MC-R280 2000W White / R5FBMGOC8RL000158 / N532WA | V91: MC-R280 2000W White / R5FBMGOC6RL000160 /N608WA | W91: MC-R280 2000W White / R5FBMGOC7RL000166 / N800WA | X91: MC-R280 Sport Red / R5FBMGOB2RL000132 / N609WA | Y91: MC-R280 Sport Red / R5FBMGOB4RL000116 / N728WA | AH91: RideBox Battery - Ampace / 519110002370AAXXXLJL0221 519110002370AAXXXLJL0382 Regular Charger / OKL7208JH202408300025 | AI91: RideBox Battery - Ampace / 519110002370AAXXXJJK0049 519110002370AAXXXLJL0384 Regular Charger / OKL7208JH202408300262 | AJ91: RideBox Battery - Ampace / 519110002370AAXXXMJK0414 519110002370AAXXXLJL0350 Regular Charger / OKL7208JH202408300229 | AK91: RideBox Battery - Ampace / 519110002370AAXXXLJL0542 519110002370AAXXXLJL0006 Regular Charger / OKL7208JH202408300114 | AL91: RideBox Battery - Ampace / 519110002370AAXXXNJL0105 519110002370AAXXXLJL0496 Regular Charger / OKL7208JH202408300029 | AM91: RideBox Battery - Ampace / 519110002370AAXXXLJL0100 519110002370AAXXXLJL0598 Regular Charger / OKL7208JH202408300160 | AN91: RideBox Battery - Ampace: 519110002370AAXXXLJL0010 519110002370AAXXXLJL0214 Regular Charger/ OKL7208JH202408300230 | AO91: RideBox Battery - Ampace: 519110002370AAXXXJJK0187 519110002370AAXXXMJK0491 Regular Charger / OKL7208JH202408300056 | AP91: RideBox Battery - Ampace: 519110002370AAXXXJJK0093 519110002370AAXXXJJK0062 Regular Charger / OKL7208JH20240830133 | AQ91: RideBox Battery - Ampace: 519110002370AAXXXNNK0058 519110002370AAXXXMJK0094 Regular Charger / OKL7208JH20240830060 | AR91: RideBox Battery - Ampace / 519110002370AAXXXLJL0339 519110002370AAXXXLJL0275 Regular Charger / OKL7208JH20240830258 | AS91: RideBox Battery - Ampace / 519110002370AAXXXLJL0359 519110002370AAXXXNJL0146 Regular Charger / OKL7208JH20240830018
A92: DONE | C92: 90 | F92: GR-2026000020 | G92: Requisition ID-20260000039 | H92: 46087 | I92: Judielle Guce /PM & Compliance | J92: Test / Demo Unit with Cage | K92: Vincent Leo B. Reyes / '09088697164 | L92: Alabang Zapote Road, Madrigal Business Park Ayala Alabang Muntinlupa City | M92: E88 Asgard Warehouse | N92: MC- D400 Blue / R5FBMX0B7RL000501 / N797WA | AH92: RideBox Battery - Ampace / 519110002370AAXXXNNK0128 519110002370AAXXXJJK0203 OKL7208JH202408300050 | BV92: 46087
A93: DONE | C93: 91 | D93: GI-2026-000064 | G93: Requisition ID-20260000069 | H93: 46108 | I93: Samuel Kniazeff / PQM | J93: Inventory Transfer | K93: SAMUEL KNIAZEFF JR / '09171086482 | L93: E88 Asgard Warehouse | M93: 3rd Floor, TCI Building, West Capitol, Kapitolyo, Pasig | N93: RideBox Battery - Ampace / 519110002370AAXXXLJL0227 | O93: RideBox Battery - Ampace / 519110002370AAXXXNJL0057 | P93: RideBox Battery - Ampace / 519110002370AAXXXLJL0185 | Q93: RideBox Battery - Ampace / 519110002370AAXXXLJL0223 | R93: RideBox Battery - Ampace / 519110002370AAXXXJJK0132 | S93: RideBox Battery - Ampace / 519110002370AAXXXLJL0136 | T93: RideBox Battery - Ampace / 519110002370AAXXXNJL0068 | U93: RideBox Battery - Ampace / 519110002370AAXXXLJL0566
A94: DONE | C94: 92 | D94: GI-2026-000065 | G94: Requisition ID-20260000070 | H94: 46094 | I94: Judielle Guce /PM & Compliance | J94: Donation | K94: Pateros Municipal Marko S. Pielago / 09283425636 | L94: E88 Asgard Warehouse | M94: 841 G. de Borja, Pateros, Metro Manila | N94: R280 Sport 2500W Blue / R5FBMGOB5RL000139 / N77WA | O94: MC- D400 Blue / R5FBMX0B1RL000512/N665WA | AH94: RideBox Battery - Ampace / 519110002370AAXXXNJL0206 519110002370AAXXXNJL0077 OKL7208JH202408300506 | AI94: RideBox Battery - Ampace / 519110002370AAXXXNJL0151 519110002370AAXXXNJL0113 OKL7208JH202408300173
A95: DONE | C95: 93 | D95: GI-2026-000066 | G95: Requisition ID-20260000041 | H95: 46093 | I95: Judielle Guce /PM & Compliance | J95: Test / Demo Unit | K95: Philpower / 09067425649 | L95: E88 Asgard Warehouse | M95: Unit 2B, 120 K-6th St., Brgy. East Kamias, Quezon City, Metro Manila | N95: MC-D400 Blue / R5FBMX0B8RL000491 | AH95: RideBox Battery - Ampace: 519110002370AAXXXLJL0545 519110002370AAXXXLJL0343 OKL7208JH202408300232
A96: DONE | C96: 94 | D96: GI-2026-000067 | G96: Requisition ID-20260000043 | H96: 46092 | I96: haide@nrdev.ph | J96: Assignment to Employee | K96: Ron Dela Cruz / (0917) 768 0944 / rdelacruz@nrdev.ph | L96: E88 Asgard Warehouse | M96: E88 Asgard Warehouse | N96: MC-D400 Black / R5FBMX0B3SL000551 | BW96: Change of Unit
A97: DONE | C97: 95 | D97: GI-2026-000068 | G97: Requisition ID-20260000071 | H97: 46097 | I97: Samuel Kniazeff / PQM | J97: Assignment to Employee | K97: SAMUEL KNIAZEFF JR / '09171086482 | L97: E88 Asgard Warehouse | M97: E88 Asgard Warehouse | N97: MC-D400 Blue / R5FBMX0B0RL000503 | AH97: RideBox Battery - Ampace- 519110002370AAXXXLJL0256 519110002370AAXXXNJL0132 SNMHC7215JH202412050026
A98: DONE | C98: 96 | F98: GR-2026000021 | G98: Requisition ID-20260000043 | H98: 46092 | I98: Haide Garcia / HR | J98: Assignment to Employee | K98: Ron Dela Cruz / (0917) 768 0944 / rdelacruz@nrdev.ph | L98: E88 Asgard Warehouse | M98: E88 Asgard Warehouse | N98: MC-D400 Black / R5FBMX0B9SL000554
A99: DONE | C99: 97 | D99: GI-2026-000069 | G99: Requisition ID-20260000073 | H99: 46093 | I99: Judielle Guce /PM & Compliance | J99: Test / Demo Unit | K99: Philpower / Arnel Ceriaco / 09563955610 | L99: E88 Asgard Warehouse | M99: 120 K-6th, East Kamias, Quezon City, Metro Manila, Philippines | N99: RideBox Battery - Ampace / 519110002370AAXXXLJL0251 | O99: RideBox Battery - Ampace / 519110002370AAXXXLJL0357 | P99: Charger / OKL7208JH202408300114 | Q99: Charger / OKL7208JH202408300226 | BW99: Additional Batteries and Chargers
A100: DONE | C100: 98 | F100: GR-2026000022 | H100: 46094 | I100: John Martin Ysaac / Tech | J100: Pull out RideBox Locker at Powerfill Tandang Sora QC | K100: John Martin Ysaac / 09062858290 / jysaac@nrdev.ph | L100: Powerfill Tandang Sora QC | M100: E88 Asgard Warehouse | N100: RideBox Locker- 9M0037 | BV100: 46094
...

Sheet GIS
B1: p
E2: Goods Issuance Slip | I2: =B6 -> JL Torno / 0967 257 4391
B3: Date: | C3: =VLOOKUP($G$3,'2026 Transaction'!$D$3:$BB$1013,5,FALSE()) -> 46237 | D3: Purpose: | E3: =VLOOKUP($G$3,'2026 Transaction'!$D$3:$BB$1013,7,FALSE()) -> Deployment of Locker & Batteries / Phoenix MOA | G3: GI-2026-000193
B4: Requested by: | C4: =VLOOKUP($G$3,'2026 Transaction'!$D$3:$BB$1013,6,FALSE()) -> Roy Patrick Nepomuceno / RBM
B5: Bill To (Name & Contact No.): | D5: Pick Up : Asgard Warehouse - E88 | E5: =VLOOKUP($G$3,'2026 Transaction'!$D$3:$BB$1013,9,FALSE()) -> E88 Asgard Warehouse
B6: =VLOOKUP($G$3,'2026 Transaction'!$D$3:$BB$1013,8,FALSE()) -> JL Torno / 0967 257 4391 | D6: Address: | E6: =VLOOKUP($G$3,'2026 Transaction'!$D$3:$BB$1013,10,FALSE()) -> Phoenix Petroleum, EDSA Ext, Pasay City, Metro Manila GPS Coordinates: 14.535568757681117, 120.98740685582172 | G6: =VLOOKUP($G$3,'2026 Transaction'!$D$3:$BB$1013,4,FALSE()) -> Requisition ID-20260000205
B8: No. | C8: Description | D8: Qty | E8: UoM | F8: Bundle | G8: REMARKS
B9: 1 | C9: =VLOOKUP($G$3,'2026 Transaction'!$D$3:$BB$1013,11,FALSE()) -> RideBox Locker- 9M0008 | D9: =IF(C9<>"",1,"") -> 1 | E9: =IF(C9<>"","Unit","") -> Unit | F9: =VLOOKUP($G$3,'2026 Transaction'!$D$3:$BWB$1013,31,FALSE()) -> RideBox Battery - Ampace / 519110002370AAXXXNJL0208 519110002370AAXXXLJL0210 519110002370AAXXXLJL0273 519110002370AAXXXLJL0237 | G9: =VLOOKUP($G$3,'2026 Transaction'!$D$3:$BW$1013,66,FALSE()) | H9: =VLOOKUP($G$3,'2026 Transaction'!$D$3:$BW$1013,66,FALSE())
B10: =B9+1 -> 2 | C10: =VLOOKUP($G$3,'2026 Transaction'!$D$3:$BB$1013,12,FALSE()) | D10: =IF(C10<>"",1,"") | E10: =IF(C10<>"","Unit","") | F10: =VLOOKUP($G$3,'2026 Transaction'!$D$3:$BW$1013,32,FALSE()) | G10: =VLOOKUP($G$3,'2026 Transaction'!$D$3:$BW$1013,66,FALSE()) | H10: =VLOOKUP($G$3,'2026 Transaction'!$D$3:$BW$1013,66,FALSE())
B11: =B10+1 -> 3 | C11: =VLOOKUP($G$3,'2026 Transaction'!$D$3:$BB$1013,13,FALSE()) | D11: =IF(C11<>"",1,"") | E11: =IF(C11<>"","Unit","") | F11: =VLOOKUP($G$3,'2026 Transaction'!$D$3:$BW$1013,33,FALSE()) | G11: =VLOOKUP($G$3,'2026 Transaction'!$D$3:$BW$1013,66,FALSE()) | H11: =VLOOKUP($G$3,'2026 Transaction'!$D$3:$BW$1013,66,FALSE())
B12: =B11+1 -> 4 | C12: =VLOOKUP($G$3,'2026 Transaction'!$D$3:$BB$1013,14,FALSE()) | D12: =IF(C12<>"",1,"") | E12: =IF(C12<>"","Unit","") | F12: =VLOOKUP($G$3,'2026 Transaction'!$D$3:$BW$1013,34,FALSE()) | G12: =VLOOKUP($G$3,'2026 Transaction'!$D$3:$BW$1013,66,FALSE()) | H12: =VLOOKUP($G$3,'2026 Transaction'!$D$3:$BW$1013,66,FALSE())
B13: =B12+1 -> 5 | C13: =VLOOKUP($G$3,'2026 Transaction'!$D$3:$BB$1013,15,FALSE()) | D13: =IF(C13<>"",1,"") | E13: =IF(C13<>"","Unit","") | F13: =VLOOKUP($G$3,'2026 Transaction'!$D$3:$BW$1013,35,FALSE()) | G13: =VLOOKUP($G$3,'2026 Transaction'!$D$3:$BW$1013,66,FALSE()) | H13: =VLOOKUP($G$3,'2026 Transaction'!$D$3:$BW$1013,66,FALSE())
B14: =B13+1 -> 6 | C14: =VLOOKUP($G$3,'2026 Transaction'!$D$3:$BB$1013,16,FALSE()) | D14: =IF(C14<>"",1,"") | E14: =IF(C14<>"","Unit","") | F14: =VLOOKUP($G$3,'2026 Transaction'!$D$3:$BW$1013,36,FALSE()) | G14: =VLOOKUP($G$3,'2026 Transaction'!$D$3:$BW$1013,66,FALSE()) | H14: =VLOOKUP($G$3,'2026 Transaction'!$D$3:$BW$1013,66,FALSE())
B15: =B14+1 -> 7 | C15: =VLOOKUP($G$3,'2026 Transaction'!$D$3:$BB$1013,17,FALSE()) | D15: =IF(C15<>"",1,"") | E15: =IF(C15<>"","Unit","") | F15: =VLOOKUP($G$3,'2026 Transaction'!$D$3:$BW$1013,37,FALSE()) | G15: =VLOOKUP($G$3,'2026 Transaction'!$D$3:$BW$1013,66,FALSE()) | H15: =VLOOKUP($G$3,'2026 Transaction'!$D$3:$BW$1013,66,FALSE())
B16: =B15+1 -> 8 | C16: =VLOOKUP($G$3,'2026 Transaction'!$D$3:$BB$1013,18,FALSE()) | D16: =IF(C16<>"",1,"") | E16: =IF(C16<>"","Unit","") | F16: =VLOOKUP($G$3,'2026 Transaction'!$D$3:$BW$1013,38,FALSE()) | G16: =VLOOKUP($G$3,'2026 Transaction'!$D$3:$BW$1013,66,FALSE()) | H16: =VLOOKUP($G$3,'2026 Transaction'!$D$3:$BW$1013,66,FALSE())
B17: =B16+1 -> 9 | C17: =VLOOKUP($G$3,'2026 Transaction'!$D$3:$BB$1013,19,FALSE()) | D17: =IF(C17<>"",1,"") | E17: =IF(C17<>"","Unit","") | F17: =VLOOKUP($G$3,'2026 Transaction'!$D$3:$BW$1013,39,FALSE()) | G17: =VLOOKUP($G$3,'2026 Transaction'!$D$3:$BW$1013,66,FALSE()) | H17: =VLOOKUP($G$3,'2026 Transaction'!$D$3:$BW$1013,66,FALSE())
B18: =B17+1 -> 10 | C18: =VLOOKUP($G$3,'2026 Transaction'!$D$3:$BB$1013,20,FALSE()) | D18: =IF(C18<>"",1,"") | E18: =IF(C18<>"","Unit","") | F18: =VLOOKUP($G$3,'2026 Transaction'!$D$3:$BW$1013,40,FALSE()) | G18: =VLOOKUP($G$3,'2026 Transaction'!$D$3:$BW$1013,66,FALSE()) | H18: =VLOOKUP($G$3,'2026 Transaction'!$D$3:$BW$1013,66,FALSE())
B19: =B18+1 -> 11 | C19: =VLOOKUP($G$3,'2026 Transaction'!$D$3:$BB$1013,21,FALSE()) | D19: =IF(C19<>"",1,"") | E19: =IF(C19<>"","Unit","") | F19: =VLOOKUP($G$3,'2026 Transaction'!$D$3:$BW$1013,41,FALSE()) | G19: =VLOOKUP($G$3,'2026 Transaction'!$D$3:$BW$1013,66,FALSE()) | H19: =VLOOKUP($G$3,'2026 Transaction'!$D$3:$BW$1013,66,FALSE())
B20: =B19+1 -> 12 | C20: =VLOOKUP($G$3,'2026 Transaction'!$D$3:$BB$1013,22,FALSE()) | D20: =IF(C20<>"",1,"") | E20: =IF(C20<>"","Unit","") | F20: =VLOOKUP($G$3,'2026 Transaction'!$D$3:$BW$1013,42,FALSE()) | G20: =VLOOKUP($G$3,'2026 Transaction'!$D$3:$BW$1013,66,FALSE()) | H20: =VLOOKUP($G$3,'2026 Transaction'!$D$3:$BW$1013,66,FALSE())
B21: =B20+1 -> 13 | C21: =VLOOKUP($G$3,'2026 Transaction'!$D$3:$BB$1013,23,FALSE()) | D21: =IF(C21<>"",1,"") | E21: =IF(C21<>"","Unit","") | F21: =VLOOKUP($G$3,'2026 Transaction'!$D$3:$BW$1013,43,FALSE()) | G21: =VLOOKUP($G$3,'2026 Transaction'!$D$3:$BW$1013,66,FALSE()) | H21: =VLOOKUP($G$3,'2026 Transaction'!$D$3:$BW$1013,66,FALSE())
B22: =B21+1 -> 14 | C22: =VLOOKUP($G$3,'2026 Transaction'!$D$3:$BB$1013,24,FALSE()) | D22: =IF(C22<>"",1,"") | E22: =IF(C22<>"","Unit","") | F22: =VLOOKUP($G$3,'2026 Transaction'!$D$3:$BW$1013,44,FALSE()) | G22: =VLOOKUP($G$3,'2026 Transaction'!$D$3:$BW$1013,66,FALSE()) | H22: =VLOOKUP($G$3,'2026 Transaction'!$D$3:$BW$1013,66,FALSE())
B23: =B22+1 -> 15 | C23: =VLOOKUP($G$3,'2026 Transaction'!$D$3:$BB$1013,25,FALSE()) | D23: =IF(C23<>"",1,"") | E23: =IF(C23<>"","Unit","") | F23: =VLOOKUP($G$3,'2026 Transaction'!$D$3:$BW$1013,45,FALSE()) | G23: =VLOOKUP($G$3,'2026 Transaction'!$D$3:$BW$1013,66,FALSE()) | H23: =VLOOKUP($G$3,'2026 Transaction'!$D$3:$BW$1013,66,FALSE())
B24: =B23+1 -> 16 | C24: =VLOOKUP($G$3,'2026 Transaction'!$D$3:$BB$1013,26,FALSE()) | D24: =IF(C24<>"",1,"") | E24: =IF(C24<>"","Unit","") | F24: =VLOOKUP($G$3,'2026 Transaction'!$D$3:$BW$1013,46,FALSE()) | G24: =VLOOKUP($G$3,'2026 Transaction'!$D$3:$BW$1013,66,FALSE()) | H24: =VLOOKUP($G$3,'2026 Transaction'!$D$3:$BW$1013,66,FALSE())
B25: =B24+1 -> 17 | C25: =VLOOKUP($G$3,'2026 Transaction'!$D$3:$BB$1013,27,FALSE()) | D25: =IF(C25<>"",1,"") | E25: =IF(C25<>"","Unit","") | F25: =VLOOKUP($G$3,'2026 Transaction'!$D$3:$BW$1013,47,FALSE()) | G25: =VLOOKUP($G$3,'2026 Transaction'!$D$3:$BW$1013,67,FALSE())
B26: =B25+1 -> 18 | C26: =VLOOKUP($G$3,'2026 Transaction'!$D$3:$BB$1013,28,FALSE()) | D26: =IF(C26<>"",1,"") | E26: =IF(C26<>"","Unit","") | F26: =VLOOKUP($G$3,'2026 Transaction'!$D$3:$BW$1013,48,FALSE()) | G26: =VLOOKUP($G$3,'2026 Transaction'!$D$3:$BW$1013,68,FALSE())
B27: =B26+1 -> 19 | C27: =VLOOKUP($G$3,'2026 Transaction'!$D$3:$BB$1013,29,FALSE()) | D27: =IF(C27<>"",1,"") | E27: =IF(C27<>"","Unit","") | F27: =VLOOKUP($G$3,'2026 Transaction'!$D$3:$BW$1013,49,FALSE()) | G27: =VLOOKUP($G$3,'2026 Transaction'!$D$3:$BW$1013,69,FALSE())
B28: =B27+1 -> 20 | C28: =VLOOKUP($G$3,'2026 Transaction'!$D$3:$BB$1013,30,FALSE()) | D28: =IF(C28<>"",1,"") | E28: =IF(C28<>"","Unit","") | F28: =VLOOKUP($G$3,'2026 Transaction'!$D$3:$BW$1013,50,FALSE()) | G28: =VLOOKUP($G$3,'2026 Transaction'!$D$3:$BW$1013,70,FALSE())
B29: FINAL REMARKS:
B31: =VLOOKUP($G$3,'2026 Transaction'!$D$3:$BW$1013,72,FALSE())
B35: Prepared by (SCM Admin) : Rowel Trazona | F35: Acknowledge by (Logistics Expert) : Judy Joy Rosare
B36: Date: | C36: =$C$3 -> 46237 | F36: Date: | G36: =$C$3 -> 46237
B38: Authorized by (Warehouse Expert) : Arby Mostrales | F38: Received & Delivered by (Delivery Driver) :
B39: Date: | C39: =$C$3 -> 46237 | F39: Date: | G39: =$C$3 -> 46237
B41: Approved by (Supply Chain) : Samuel Kniazeff Jr. | F41: Received by (Receiver) :
B42: Date: | C42: =$C$3 -> 46237 | F42: Date: | G42: =$C$3 -> 46237
B45: Inspected by (Guard On Duty) :
B46: Date: | C46: =$C$3 -> 46237

Sheet GRF
B1: p
F2: Goods Return Form (Site to Warehouse)
B3: Date | D3: =VLOOKUP($I$3,'2026 Transaction'!$F$3:$BW$1012,3,FALSE()) | F3: Purpose: | G3: =VLOOKUP($I$3,'2026 Transaction'!$F$3:$BW$1012,5,FALSE()) -> Test / Demo Unit | I3: GR-2026000055
B4: Return by: | D4: =VLOOKUP($I$3,'2026 Transaction'!$F$3:$BW$1012,4,FALSE()) -> Emmanuele Rapatan / Sales | F4: Return To: | G4: =VLOOKUP($I$3,'2026 Transaction'!$F$3:$BW$1012,8,FALSE()) -> E88 Asgard Warehouse | H4: Return Date: | I4: =VLOOKUP($I$3,'2026 Transaction'!$F$3:$BW$1012,3,FALSE())
B6: No. | C6: Description | E6: Qty | F6: UoM | G6: Bundle | H6: Remarks
B7: 1 | C7: =VLOOKUP($I$3,'2026 Transaction'!$F$3:$BW$1012,9,FALSE()) -> MC-D400 Black / R5FBMX0B6SL000561 / N225WC | E7: 1 | F7: Unit | G7: =VLOOKUP($I$3,'2026 Transaction'!$F$3:$BW$1012,29,FALSE()) -> RideBox Battery - Ampace / 519110002370AAXXXMJK0363 519110002370AAXXXMJK0149 Regular Charger: OKL7208JH202408300201 | H7: =VLOOKUP($I$3,'2026 Transaction'!$F$3:$BW$1012,49,FALSE())
B8: =B7+1 -> 2 | C8: =VLOOKUP($I$3,'2026 Transaction'!$F$3:$BW$1012,10,FALSE()) -> MC-D400 Red / R5FBMX0B2RL000440 | E8: 1 | F8: Unit | G8: =VLOOKUP($I$3,'2026 Transaction'!$F$3:$BW$1012,30,FALSE()) -> RideBox Battery - Ampace / 519110002370AAXXXJJK0157 519110002370AAXXXJJK0243 Regular Charger: OKL7208JH202408300140 | H8: =VLOOKUP($I$3,'2026 Transaction'!$F$3:$BW$1012,50,FALSE())
B9: =B8+1 -> 3 | C9: =VLOOKUP($I$3,'2026 Transaction'!$F$3:$BW$1012,11,FALSE()) -> MC-D400 Blue / R5FBMX0B7RL000501 | E9: 1 | F9: Unit | G9: =VLOOKUP($I$3,'2026 Transaction'!$F$3:$BW$1012,31,FALSE()) -> RideBox Battery - Ampace / 519110002370AAXXXLJL0140 519110002370AAXXXLJL0196 Regular Charger: OKL7208JH202408300050 | H9: =VLOOKUP($I$3,'2026 Transaction'!$F$3:$BW$1012,51,FALSE())
B10: =B9+1 -> 4 | C10: =VLOOKUP($I$3,'2026 Transaction'!$F$3:$BW$1012,12,FALSE()) | G10: =VLOOKUP($I$3,'2026 Transaction'!$F$3:$BW$1012,32,FALSE()) | H10: =VLOOKUP($I$3,'2026 Transaction'!$F$3:$BW$1012,52,FALSE())
B11: =B10+1 -> 5 | C11: =VLOOKUP($I$3,'2026 Transaction'!$F$3:$BW$1012,13,FALSE()) | G11: =VLOOKUP($I$3,'2026 Transaction'!$F$3:$BW$1012,33,FALSE()) | H11: =VLOOKUP($I$3,'2026 Transaction'!$F$3:$BW$1012,53,FALSE())
B12: =B11+1 -> 6 | C12: =VLOOKUP($I$3,'2026 Transaction'!$F$3:$BW$1012,14,FALSE()) | G12: =VLOOKUP($I$3,'2026 Transaction'!$F$3:$BW$1012,34,FALSE()) | H12: =VLOOKUP($I$3,'2026 Transaction'!$F$3:$BW$1012,54,FALSE())
B13: =B12+1 -> 7 | C13: =VLOOKUP($I$3,'2026 Transaction'!$F$3:$BW$1012,15,FALSE()) | G13: =VLOOKUP($I$3,'2026 Transaction'!$F$3:$BW$1012,35,FALSE()) | H13: =VLOOKUP($I$3,'2026 Transaction'!$F$3:$BW$1012,55,FALSE())
B14: =B13+1 -> 8 | C14: =VLOOKUP($I$3,'2026 Transaction'!$F$3:$BW$1012,16,FALSE()) | G14: =VLOOKUP($I$3,'2026 Transaction'!$F$3:$BW$1012,36,FALSE()) | H14: =VLOOKUP($I$3,'2026 Transaction'!$F$3:$BW$1012,56,FALSE())
B15: =B14+1 -> 9 | C15: =VLOOKUP($I$3,'2026 Transaction'!$F$3:$BW$1012,17,FALSE()) | G15: =VLOOKUP($I$3,'2026 Transaction'!$F$3:$BW$1012,37,FALSE()) | H15: =VLOOKUP($I$3,'2026 Transaction'!$F$3:$BW$1012,57,FALSE())
B16: =B15+1 -> 10 | C16: =VLOOKUP($I$3,'2026 Transaction'!$F$3:$BW$1012,18,FALSE()) | G16: =VLOOKUP($I$3,'2026 Transaction'!$F$3:$BW$1012,38,FALSE()) | H16: =VLOOKUP($I$3,'2026 Transaction'!$F$3:$BW$1012,58,FALSE())
B17: =B16+1 -> 11 | C17: =VLOOKUP($I$3,'2026 Transaction'!$F$3:$BW$1012,19,FALSE()) | H17: =VLOOKUP($I$3,'2026 Transaction'!$F$3:$BW$1012,59,FALSE())
B18: =B17+1 -> 12 | C18: =VLOOKUP($I$3,'2026 Transaction'!$F$3:$BW$1012,20,FALSE()) | H18: =VLOOKUP($I$3,'2026 Transaction'!$F$3:$BW$1012,60,FALSE())
B19: =B18+1 -> 13 | C19: =VLOOKUP($I$3,'2026 Transaction'!$F$3:$BW$1012,21,FALSE()) | H19: =VLOOKUP($I$3,'2026 Transaction'!$F$3:$BW$1012,61,FALSE())
B20: =B19+1 -> 14 | C20: =VLOOKUP($I$3,'2026 Transaction'!$F$3:$BW$1012,22,FALSE()) | H20: =VLOOKUP($I$3,'2026 Transaction'!$F$3:$BW$1012,62,FALSE())
B21: =B20+1 -> 15 | C21: =VLOOKUP($I$3,'2026 Transaction'!$F$3:$BW$1012,23,FALSE()) | H21: =VLOOKUP($I$3,'2026 Transaction'!$F$3:$BW$1012,63,FALSE())
B22: =B21+1 -> 16 | C22: =VLOOKUP($I$3,'2026 Transaction'!$F$3:$BW$1012,24,FALSE()) | H22: =VLOOKUP($I$3,'2026 Transaction'!$F$3:$BW$1012,64,FALSE())
B23: =B22+1 -> 17 | C23: =VLOOKUP($I$3,'2026 Transaction'!$F$3:$BW$1012,25,FALSE()) | G23: =VLOOKUP($I$3,'2026 Transaction'!$F$3:$BW$1012,45,FALSE()) | H23: =VLOOKUP($I$3,'2026 Transaction'!$F$3:$BW$1012,65,FALSE())
B24: =B23+1 -> 18 | C24: =VLOOKUP($I$3,'2026 Transaction'!$F$3:$BW$1012,26,FALSE()) | G24: =VLOOKUP($I$3,'2026 Transaction'!$F$3:$BW$1012,46,FALSE()) | H24: =VLOOKUP($I$3,'2026 Transaction'!$F$3:$BW$1012,66,FALSE())
B25: =B24+1 -> 19 | C25: =VLOOKUP($I$3,'2026 Transaction'!$F$3:$BW$1012,27,FALSE()) | G25: =VLOOKUP($I$3,'2026 Transaction'!$F$3:$BW$1012,47,FALSE()) | H25: =VLOOKUP($I$3,'2026 Transaction'!$F$3:$BW$1012,67,FALSE())
B26: =B25+1 -> 20 | C26: =VLOOKUP($I$3,'2026 Transaction'!$F$3:$BW$1012,28,FALSE()) | G26: =VLOOKUP($I$3,'2026 Transaction'!$F$3:$BW$1012,48,FALSE()) | H26: =VLOOKUP($I$3,'2026 Transaction'!$F$3:$BW$1012,68,FALSE())
B28: FINAL REMARKS:
B34: Requested by : | D34: Emmanuele Rapatan | G34: Inspected by (Guard on Duty) :
B35: Date: | D35: =VLOOKUP($I$3,'2026 Transaction'!$F$3:$BW$1012,3,FALSE()) | G35: Date: | H35: =VLOOKUP($I$3,'2026 Transaction'!$F$3:$BW$1012,3,FALSE())
B37: Prepared by : | D37: Rowel Trazona | G37: Verified by: | H37: Judy Joy Rosare
B38: Date: | D38: =VLOOKUP($I$3,'2026 Transaction'!$F$3:$BW$1012,3,FALSE()) | G38: Date: | H38: =VLOOKUP($I$3,'2026 Transaction'!$F$3:$BW$1012,3,FALSE())
B40: Approved by : | D40: Samuel Kniazeff Jr. | G40: Received by (Warehouse): | H40: Arby Mostrales
B41: Date: | D41: =VLOOKUP($I$3,'2026 Transaction'!$F$3:$BW$1012,3,FALSE()) | G41: Date: | H41: =VLOOKUP($I$3,'2026 Transaction'!$F$3:$BW$1012,3,FALSE())

Sheet GP
B1: p
E2: Gate Pass
B3: Date: | C3: =VLOOKUP($G$3,'2026 Transaction'!$E$3:$BW$1012,4,FALSE()) -> 46073 | D3: Purpose: | E3: =VLOOKUP($G$3,'2026 Transaction'!$E$3:$BW$1012,6,FALSE()) -> Replacement of Parts for Flexride | G3: GP-2026000050
B4: Requested by: | C4: =VLOOKUP($G$3,'2026 Transaction'!$E$3:$BW$1012,5,FALSE()) -> Christopher Mendoza / PQM
B5: Bill To (Name & Contact No.): | D5: Pick Up : Asgard Warehouse - E88 | E5: =VLOOKUP($G$3,'2026 Transaction'!$E$3:$BW$1012,8,FALSE()) -> E88 Asgard Warehouse
B6: =VLOOKUP($G$3,'2026 Transaction'!$E$3:$BW$1012,7,FALSE()) -> E88 Samuel Kniazeff / +63 919 000 6311 / samuel@nrdev.ph | D6: Address: | E6: =VLOOKUP($G$3,'2026 Transaction'!$E$3:$BW$1012,9,FALSE()) -> E88 Asgard Warehouse | G6: =VLOOKUP($G$3,'2026 Transaction'!$E$3:$BW$1012,3,FALSE()) -> Requisition ID-20260000048
B8: No. | C8: Description | D8: Qty | E8: UoM | F8: Bundle | G8: Remarks
B9: 1 | C9: =VLOOKUP($G$3,'2026 Transaction'!$E$3:$BW$1012,10,FALSE()) -> ESP00012 - Left Combination Switch (R280/Sport) | D9: 1 | E9: =IF(C9<>"","Unit","") -> Unit | F9: =VLOOKUP($G$3,'2026 Transaction'!$E$3:$BW$1012,30,FALSE()) | G9: =VLOOKUP($G$3,'2026 Transaction'!$E$3:$BW$1012,50,FALSE())
B10: =B9+1 -> 2 | C10: =VLOOKUP($G$3,'2026 Transaction'!$E$3:$BW$1012,11,FALSE()) | E10: =IF(C10<>"","Unit","") | F10: =VLOOKUP($G$3,'2026 Transaction'!$E$3:$BW$1012,31,FALSE()) | G10: =VLOOKUP($G$3,'2026 Transaction'!$E$3:$BW$1012,51,FALSE())
B11: =B10+1 -> 3 | C11: =VLOOKUP($G$3,'2026 Transaction'!$E$3:$BW$1012,12,FALSE()) | E11: =IF(C11<>"","Unit","") | F11: =VLOOKUP($G$3,'2026 Transaction'!$E$3:$BW$1012,32,FALSE()) | G11: =VLOOKUP($G$3,'2026 Transaction'!$E$3:$BW$1012,52,FALSE())
B12: =B11+1 -> 4 | C12: =VLOOKUP($G$3,'2026 Transaction'!$E$3:$BW$1012,13,FALSE()) | E12: =IF(C12<>"","Unit","") | F12: =VLOOKUP($G$3,'2026 Transaction'!$E$3:$BW$1012,33,FALSE()) | G12: =VLOOKUP($G$3,'2026 Transaction'!$E$3:$BW$1012,53,FALSE())
B13: =B12+1 -> 5 | C13: =VLOOKUP($G$3,'2026 Transaction'!$E$3:$BW$1012,14,FALSE()) | E13: =IF(C13<>"","Unit","") | F13: =VLOOKUP($G$3,'2026 Transaction'!$E$3:$BW$1012,34,FALSE()) | G13: =VLOOKUP($G$3,'2026 Transaction'!$E$3:$BW$1012,54,FALSE())
B14: =B13+1 -> 6 | C14: =VLOOKUP($G$3,'2026 Transaction'!$E$3:$BW$1012,15,FALSE()) | E14: =IF(C14<>"","Unit","") | F14: =VLOOKUP($G$3,'2026 Transaction'!$E$3:$BW$1012,35,FALSE()) | G14: =VLOOKUP($G$3,'2026 Transaction'!$E$3:$BW$1012,55,FALSE())
B15: =B14+1 -> 7 | C15: =VLOOKUP($G$3,'2026 Transaction'!$E$3:$BW$1012,16,FALSE()) | E15: =IF(C15<>"","Unit","") | F15: =VLOOKUP($G$3,'2026 Transaction'!$E$3:$BW$1012,36,FALSE()) | G15: =VLOOKUP($G$3,'2026 Transaction'!$E$3:$BW$1012,56,FALSE())
B16: =B15+1 -> 8 | C16: =VLOOKUP($G$3,'2026 Transaction'!$E$3:$BW$1012,17,FALSE()) | E16: =IF(C16<>"","Unit","") | F16: =VLOOKUP($G$3,'2026 Transaction'!$E$3:$BW$1012,37,FALSE()) | G16: =VLOOKUP($G$3,'2026 Transaction'!$E$3:$BW$1012,57,FALSE())
B17: =B16+1 -> 9 | C17: =VLOOKUP($G$3,'2026 Transaction'!$E$3:$BW$1012,18,FALSE()) | E17: =IF(C17<>"","Unit","") | F17: =VLOOKUP($G$3,'2026 Transaction'!$E$3:$BW$1012,38,FALSE()) | G17: =VLOOKUP($G$3,'2026 Transaction'!$E$3:$BW$1012,58,FALSE())
B18: =B17+1 -> 10 | C18: =VLOOKUP($G$3,'2026 Transaction'!$E$3:$BW$1012,19,FALSE()) | E18: =IF(C18<>"","Unit","") | F18: =VLOOKUP($G$3,'2026 Transaction'!$E$3:$BW$1012,39,FALSE()) | G18: =VLOOKUP($G$3,'2026 Transaction'!$E$3:$BW$1012,59,FALSE())
B19: =B18+1 -> 11 | C19: =VLOOKUP($G$3,'2026 Transaction'!$E$3:$BW$1012,20,FALSE()) | E19: =IF(C19<>"","Unit","") | F19: =VLOOKUP($G$3,'2026 Transaction'!$E$3:$BW$1012,40,FALSE()) | G19: =VLOOKUP($G$3,'2026 Transaction'!$E$3:$BW$1012,60,FALSE())
B20: =B19+1 -> 12 | C20: =VLOOKUP($G$3,'2026 Transaction'!$E$3:$BW$1012,21,FALSE()) | E20: =IF(C20<>"","Unit","") | F20: =VLOOKUP($G$3,'2026 Transaction'!$E$3:$BW$1012,41,FALSE()) | G20: =VLOOKUP($G$3,'2026 Transaction'!$E$3:$BW$1012,61,FALSE())
B21: =B20+1 -> 13 | C21: =VLOOKUP($G$3,'2026 Transaction'!$E$3:$BW$1012,22,FALSE()) | E21: =IF(C21<>"","Unit","") | F21: =VLOOKUP($G$3,'2026 Transaction'!$E$3:$BW$1012,42,FALSE()) | G21: =VLOOKUP($G$3,'2026 Transaction'!$E$3:$BW$1012,62,FALSE())
B22: =B21+1 -> 14 | C22: =VLOOKUP($G$3,'2026 Transaction'!$E$3:$BW$1012,23,FALSE()) | E22: =IF(C22<>"","Unit","") | F22: =VLOOKUP($G$3,'2026 Transaction'!$E$3:$BW$1012,43,FALSE()) | G22: =VLOOKUP($G$3,'2026 Transaction'!$E$3:$BW$1012,63,FALSE())
B23: =B22+1 -> 15 | C23: =VLOOKUP($G$3,'2026 Transaction'!$E$3:$BW$1012,24,FALSE()) | E23: =IF(C23<>"","Unit","") | F23: =VLOOKUP($G$3,'2026 Transaction'!$E$3:$BW$1012,44,FALSE()) | G23: =VLOOKUP($G$3,'2026 Transaction'!$E$3:$BW$1012,64,FALSE())
B24: =B23+1 -> 16 | C24: =VLOOKUP($G$3,'2026 Transaction'!$E$3:$BW$1012,25,FALSE()) | E24: =IF(C24<>"","Unit","") | F24: =VLOOKUP($G$3,'2026 Transaction'!$E$3:$BW$1012,45,FALSE()) | G24: =VLOOKUP($G$3,'2026 Transaction'!$E$3:$BW$1012,65,FALSE())
B25: =B24+1 -> 17 | C25: =VLOOKUP($G$3,'2026 Transaction'!$E$3:$BW$1012,26,FALSE()) | E25: =IF(C25<>"","Unit","") | F25: =VLOOKUP($G$3,'2026 Transaction'!$E$3:$BW$1012,46,FALSE()) | G25: =VLOOKUP($G$3,'2026 Transaction'!$E$3:$BW$1012,66,FALSE())
B26: =B25+1 -> 18 | C26: =VLOOKUP($G$3,'2026 Transaction'!$E$3:$BW$1012,27,FALSE()) | E26: =IF(C26<>"","Unit","") | F26: =VLOOKUP($G$3,'2026 Transaction'!$E$3:$BW$1012,47,FALSE()) | G26: =VLOOKUP($G$3,'2026 Transaction'!$E$3:$BW$1012,67,FALSE())
B27: =B26+1 -> 19 | C27: =VLOOKUP($G$3,'2026 Transaction'!$E$3:$BW$1012,28,FALSE()) | E27: =IF(C27<>"","Unit","") | F27: =VLOOKUP($G$3,'2026 Transaction'!$E$3:$BW$1012,48,FALSE()) | G27: =VLOOKUP($G$3,'2026 Transaction'!$E$3:$BW$1012,68,FALSE())
B28: =B27+1 -> 20 | C28: =VLOOKUP($G$3,'2026 Transaction'!$E$3:$BW$1012,29,FALSE()) | E28: =IF(C28<>"","Unit","") | F28: =VLOOKUP($G$3,'2026 Transaction'!$E$3:$BW$1012,49,FALSE()) | G28: =VLOOKUP($G$3,'2026 Transaction'!$E$3:$BW$1012,69,FALSE())
B30: FINAL REMARKS:
B32: =VLOOKUP($G$3,'2026 Transaction'!$E$3:$BW$1012,71,FALSE())
B36: Prepared by (Warehouse Personnel) : Reynan Llaneta | F36: Acknowledge by (Logistics Expert) : Judy Joy Rosare
B37: Date: | C37: =$C$3 -> 46073 | F37: Date: | G37: =$C$3 -> 46073
B39: Authorized by (Warehouse Expert) : Arby Mostrales | F39: Delivered by (Delivery Driver) :
B40: Date: | C40: =$C$3 -> 46073 | F40: Date: | G40: =$C$3 -> 46073
B42: Approved by (Supply Chain) : | F42: Inspected by (Guard On Duty) :
B43: Date: | C43: =$C$3 -> 46073 | F43: Date: | G43: =$C$3 -> 46073

Sheet STO
B1: p
F2: Stock Replacement
B4: REQUESTOR DETAILS: | J4: Replacement No. | K4: SR-0000004
B6: Date Requested: | D6: 45924
B7: Requesting Department: | D7: OPERATIONS
B8: Requestor Name: | D8: SAMUEL KNIAZEFF JR.
B9: Requestor Email: | D9: samuel@nrdev.ph
B10: Purpose: | D10: Test Unit Stock Replacement
B12: TRANSACTION DETAILS:
B14: Customer Name: | D14: UTITCO MOTOR CORPORATION | H14: Return Location: | J14: E88 VENTURES, INC. - ASGARD
B15: Address: | D15: Araneta Center, 6th Flr, Cyberpark Tower, 1 Gen. Aguinaldo Ave, Cubao, Quezon City, 1109 Metro Manila | H15: Address: | J15: 174 A. Acacia St. Dela Paz, Pasig City
B16: Contact Number | D16: 09173480505 / 09153869744 | H16: Contact Number | J16: Lyn Jhonson Greñas
B17: Person In Charge: | D17: MIC UTITCO | H17: Return To: | J17: Warehouse (Repair)
B19: RETURN ITEMS | H19: REPLACE ITEMS
B20: No. | C20: Description | D20: Serial / Vin No. | E20: Qty | F20: Remarks | H20: No. | I20: Description | J20: Serial / Vin No. | K20: Qty | L20: Remarks
B21: 1 | C21: D400 RED | D21: R5FBMX0B6RL000425 | E21: 1 | H21: 1 | I21: D400 RED | J21: R5FBMX0B9RL000452 | K21: 1
B22: =B21+1 -> 2 | C22: Ampace Battery | D22: 519110002370AAXXXJJK0175 | E22: 1 | H22: =H21+1 -> 2 | I22: Ampace Battery | J22: 519110002370AAXXXMJK0271 | K22: 1
B23: =B22+1 -> 3 | C23: Ampace Battery | D23: 519110002370AAXXXJJK0232 | E23: 1 | H23: =H22+1 -> 3 | I23: Ampace Battery | J23: 519110002370AAXXXMJK0430 | K23: 1
B24: =B23+1 -> 4 | C24: Regular Charger | D24: OKL7208JH202408300022 | E24: 1 | H24: =H23+1 -> 4 | I24: Regular Charger | J24: OKL7208JH202408300288 | K24: 1
B25: =B24+1 -> 5 | H25: =H24+1 -> 5
B26: =B25+1 -> 6 | H26: =H25+1 -> 6
B27: =B26+1 -> 7 | H27: =H26+1 -> 7
B28: =B27+1 -> 8 | H28: =H27+1 -> 8
B29: =B28+1 -> 9 | H29: =H28+1 -> 9
B30: =B29+1 -> 10 | H30: =H29+1 -> 10
B31: =B30+1 -> 11 | H31: =H30+1 -> 11
B32: =B31+1 -> 12 | H32: =H31+1 -> 12
B33: =B32+1 -> 13 | H33: =H32+1 -> 13
B34: =B33+1 -> 14 | H34: =H33+1 -> 14
B35: =B34+1 -> 15 | H35: =H34+1 -> 15
B36: =B35+1 -> 16 | H36: =H35+1 -> 16
... B60: =B59+1 -> 40 | H60: =H59+1 -> 40
B62: FINAL REMARKS:
B64: Units for replacement will be dispatched from the Sta. Rosa Retail Store, and return items will be sent to E88 Ventures – Asgard Warehouse in Pasig
C68: Requested by (Requestor) : Samuel Kniazeff Jr. | I68: Approved by (Operation) : Ervin Domingo
C69: Date: 09/25/25 | I69: Date: 09/25/25
C71: Verified by (Forwarder): | I71: Acknowledge by (Guard):
C72: Date: 09/25/25 | I72: Date: 09/25/25
C74: Received by (Location PIC) :
C75: Date: 09/25/25

Sheet IT
B1: p
E2: Inventory Transfer Form
B3: Date | C3: 45923 | E3: Asset Transfer | G3: IT-0000004
B4: Transfer By: Retail Store - Sta. Rosa | E4: Transfer To: | F4: Taal Vista Hotel | G4: Contact Person: MKTG: Angela Patricia De Luna
B6: No. | C6: Description | D6: Qty | E6: UoM | F6: REMARKS (From) | G6: REMARKS (Receiver)
B7: 1 | C7: R280 Sport Blue | D7: 1 | E7: Unit | F7: R5FBMGOB0RL000145
B8: 2 | C8: Ampace Battery | D8: 1 | E8: Unit | F8: 519110002370AAXXXMJK0179
B9: 3 | C9: Ampace Battery | D9: 1 | E9: Unit | F9: 519110002370AAXXXMJK0184
B10: 4 | C10: Regular Charger | D10: 1 | E10: Unit | F10: MHC7215JK202412050018
B11: 5 | C11: Helmet | D11: 1 | E11: PC
B12: 6
B13: 7
B14: 8
B15: 9
B16: 10
B17: 11
B18: 12
B19: 13
B20: 14
B21: 15
B22: 16
B23: 17
... B36: 30
B38: FINAL REMARKS:
C44: Prepared By : | F44: Released By (Releasing Site) :
C45: Date: | F45: Date:
C47: Confirmed By: | F47: Checked By (Guard on Duty):
C48: Date: | F48: Date:
C50: Approved By (Supply Chain) : | F50: Received By (Site Receiver):
C51: Date: | F51: Date:

Sheet PForm
B1: p
G2: Pullout Form
B3: Return Date: | G3: Purpose: RETURN OF 9 UNITS - JRS
B5: No. | C5: VIN | E5: PLATE NO. | F5: BATTERY A | G5: BATTERY B | H5: CHARGER | I5: REMARKS
B6: 1 | C6: MC-D400 Blue / R5FBMX0B9RL000533 | E6: N771WA | H6: OKL7208JH2024408300132
B7: =B6+1 -> 2 | C7: MC- D400 Blue / R5FBMX0B3RL000530 | E7: N673WA | H7: OKL7208JH202408300104
B8: =B7+1 -> 3 | C8: MC- D400 Blue / R5FBMX0B6RL000487 | E8: N708WA | H8: OKL7208JH202408300278
B9: =B8+1 -> 4 | C9: MC- D400 Blue / R5FBMX0B1RL000526 | E9: N669WA | H9: OKL7208JH202408300309
B10: =B9+1 -> 5 | C10: MC- D400 Blue / R5FBMX0B6RL000506 | E10: N705WA | H10: OKL7208JH202408300152
B11: =B10+1 -> 6 | C11: MC- D400 Blue / R5FBMX0B8RL000524 | E11: N712WA
B12: =B11+1 -> 7 | C12: MC- D400 Blue / R5FBMX0B7RL000515 | E12: N703WA | H12: OKL7208JH202408300227
B13: =B12+1 -> 8 | C13: MC- D400 Blue / R5FBMX0B8RL000510 | E13: N702WA | H13: OKL7208JH202408300294
B14: =B13+1 -> 9 | C14: MC- D400 Blue / R5FBMX0B9RL000483 | E14: N674WA | H14: OKL7208JH202408300093
B16: FINAL REMARKS:
B22: Prepared by :
B23: Date:
B25: Verified by :
B26: Date:
B28: Received by : | D28: Arby Mostrales
B29: Date:
