Workbook

Sheet ApprovedBudget
A1: Approved Budget - Monthly OPEX
A3: Department | B3: Cost Center | C3: Account / line | D3: CAPEX/OPEX | E3: Jan | F3: Feb | G3: Mar | H3: Apr | I3: May | J3: Jun | K3: Jul | L3: Aug | M3: Sep | N3: Oct | O3: Nov | P3: Dec | Q3: FY Total
A4: OPEX - Payroll
A5: Sales and Marketing | B5: Sales and Marketing | C5: Payroll | D5: OPEX | E5: 880387.75 | F5: 880387.75 | G5: 880387.75 | H5: 880387.75 | I5: 880387.75 | J5: 880387.75 | K5: 880387.75 | L5: 880387.75 | M5: 923100.26 | N5: 923100.26 | O5: 1179375.3 | P5: 1179375.3 | Q5: =SUM(E5:P5) -> 11248053
A6: Customer Success | B6: Customer Success | C6: Payroll | D6: OPEX | E6: 125860 | F6: 125860 | G6: 125860 | H6: 125860 | I6: 151032 | J6: 151032 | K6: 151032 | L6: 151032 | M6: 151032 | N6: 151032 | O6: 125860 | P6: 125860 | Q6: =SUM(E6:P6) -> 1661352
A7: Supply Chain | B7: Warehouse | C7: Payroll | D7: OPEX | E7: 250020 | F7: 250020 | G7: 250020 | H7: 250020 | I7: 250020 | J7: 250020 | K7: 250020 | L7: 250020 | M7: 277360 | N7: 277360 | O7: 523420 | P7: 523420 | Q7: =SUM(E7:P7) -> 3601720
A8: Aftersales | B8: Aftersales | C8: Payroll | D8: OPEX | E8: 40117.875 | F8: 40117.875 | G8: 40117.875 | H8: 40117.875 | I8: 40117.875 | J8: 40117.875 | K8: 40117.875 | L8: 40117.875 | M8: 53490.5 | N8: 53490.5 | O8: 93608.375 | P8: 93608.375 | Q8: =SUM(E8:P8) -> 615140.75
A9: Product | B9: Product | C9: Payroll | D9: OPEX | E9: 40117.875 | F9: 40117.875 | G9: 40117.875 | H9: 40117.875 | I9: 40117.875 | J9: 40117.875 | K9: 40117.875 | L9: 40117.875 | M9: 53490.5 | N9: 53490.5 | O9: 93608.375 | P9: 93608.375 | Q9: 615140.75
A10: RideBox | B10: RideBox | C10: Payroll | D10: OPEX | E10: 0 | F10: 0 | G10: 0 | H10: 0 | I10: 125860 | J10: 226548 | K10: 276892 | L10: 302064 | M10: 377580 | N10: 402752 | O10: 478268 | P10: 553784 | Q10: =SUM(E10:P10) -> 2743748
A11: Technology | B11: Technology | C11: Payroll | D11: OPEX | E11: 631987.45 | F11: 631987.45 | G11: 631987.45 | H11: 696587.45 | I11: 890387.45 | J11: 1277987.5 | K11: 1536387.5 | L11: 1794787.5 | M11: 1859387.5 | N11: 2053187.5 | O11: 2053187.5 | P11: 2053187.5 | Q11: =SUM(E11:P11) -> 16111049
A12: Finance and Accounting | B12: Finance and Accounting | C12: Payroll | D12: OPEX | E12: 633750 | F12: 633750 | G12: 974464.29 | H12: 340714.29 | I12: 390964.29 | J12: 390964.29 | K12: 390964.29 | L12: 390964.29 | M12: 390964.29 | N12: 441214.29 | O12: 441214.29 | P12: 441214.29 | Q12: =SUM(E12:P12) -> 5861142.9
A13: Admin | B13: Admin | C13: Payroll | D13: OPEX | E13: 57000 | F13: 57000 | G13: 57000 | H13: 57000 | I13: 61750 | J13: 61750 | K13: 61750 | L13: 61750 | M13: 61750 | N13: 61750 | O13: 61750 | P13: 61750 | Q13: =SUM(E13:P13) -> 722000
A14: HR | B14: HR | C14: Payroll | D14: OPEX | E14: 154375 | F14: 154375 | G14: 154375 | H14: 154375 | I14: 154375 | J14: 154375 | K14: 154375 | L14: 154375 | M14: 154375 | N14: 154375 | O14: 154375 | P14: 154375 | Q14: =SUM(E14:P14) -> 1852500
A15: Compliance and Risk | B15: Compliance and Risk | C15: Payroll | D15: OPEX | E15: 109326.4 | F15: 109326.4 | G15: 109326.4 | H15: 109326.4 | I15: 153993.07 | J15: 214659.73 | K15: 214659.73 | L15: 275326.4 | M15: 275326.4 | N15: 275326.4 | O15: 335993.07 | P15: 335993.07 | Q15: =SUM(E15:P15) -> 2518583.5
C16: TOTAL OPEX - Payroll | E16: =SUM(E5:E15) -> 2922942.4 | F16: =SUM(F5:F15) -> 2922942.4 | G16: =SUM(G5:G15) -> 3263656.6 | H16: =SUM(H5:H15) -> 2694506.6 | I16: =SUM(I5:I15) -> 3139005.3 | J16: =SUM(J5:J15) -> 3687960 | K16: =SUM(K5:K15) -> 3996704 | L16: =SUM(L5:L15) -> 4340942.6 | ... P16: =SUM(P5:P15) -> 5616175.8 | Q16: =SUM(E16:P16) -> 47550430
A18: OPEX - Non-payroll
A19: Sales and Marketing | B19: Sales | C19: CRM / sales pipeline tool | D19: OPEX | E19: 2000 | F19: 2000 | G19: 2000 | H19: 2000 | I19: 2000 | J19: 2000 | K19: 2000 | L19: 2000 | M19: 2000 | N19: 2000 | O19: 2000 | P19: 2000 | Q19: =SUM(E19:P19) -> 24000
A20: Sales and Marketing | B20: Sales | C20: Canva | D20: OPEX | E20: 1000 | F20: 1000 | G20: 1000 | H20: 1000 | I20: 1000 | J20: 1000 | K20: 1000 | L20: 1000 | M20: 1000 | N20: 1000 | O20: 1000 | P20: 1000 | Q20: =SUM(E20:P20) -> 12000
A21: Sales and Marketing | B21: Sales | C21: Lemlist | D21: OPEX | E21: 6000 | F21: 6000 | G21: 6000 | H21: 6000 | I21: 6000 | J21: 6000 | K21: 6000 | L21: 6000 | M21: 6000 | N21: 6000 | O21: 6000 | P21: 6000 | Q21: =SUM(E21:P21) -> 72000
A22: Sales and Marketing | B22: Sales | C22: Digital Ads | D22: OPEX | E22: 20000 | F22: 20000 | G22: 20000 | H22: 20000 | I22: 20000 | J22: 20000 | K22: 20000 | L22: 20000 | M22: 20000 | N22: 20000 | O22: 20000 | P22: 20000 | Q22: =SUM(E22:P22) -> 240000
A23: Sales and Marketing | B23: Marketing | C23: Marketing Collaterals | D23: OPEX | E23: 15000 | F23: 15000 | G23: 15000 | H23: 15000 | I23: 15000 | J23: 15000 | K23: 15000 | L23: 15000 | M23: 15000 | N23: 15000 | O23: 15000 | P23: 15000 | Q23: =SUM(E23:P23) -> 180000
A24: Sales and Marketing | B24: Marketing | C24: Media Subscriptions | D24: OPEX | E24: 5000 | F24: 5000 | G24: 5000 | H24: 5000 | I24: 25000 | J24: 5000 | K24: 5000 | L24: 5000 | M24: 5000 | N24: 5000 | O24: 5000 | P24: 5000 | Q24: =SUM(E24:P24) -> 80000
A25: Sales and Marketing | B25: Marketing | C25: Tools & Equipments | D25: OPEX | E25: - | F25: - | G25: - | H25: - | I25: 100000 | J25: - | K25: - | L25: - | M25: - | N25: - | O25: - | P25: - | Q25: =SUM(E25:P25) -> 100000
A26: Sales and Marketing | B26: Marketing | C26: Lead generation giveaways | D26: OPEX | E26: 26340 | F26: 26340 | G26: 26340 | H26: 26340 | I26: 26340 | J26: 26340 | K26: 26340 | L26: 26340 | M26: 26340 | N26: 26340 | O26: 26340 | P26: 26340 | Q26: =SUM(E26:P26) -> 316080
A27: Sales and Marketing | B27: Marketing | C27: Rider onboarding Kit | D27: OPEX | E27: 13800 | F27: 21000 | G27: 33000 | H27: 45000 | I27: 66000 | J27: 78000 | K27: 84000 | L27: 99000 | M27: 75000 | N27: 120000 | O27: 270000 | P27: 180000 | Q27: =SUM(E27:P27) -> 1084800
A28: Sales and Marketing | B28: Marketing | C28: Representation | D28: OPEX | E28: 30000 | F28: 30000 | G28: 30000 | H28: 30000 | I28: 30000 | J28: 30000 | K28: 30000 | L28: 30000 | M28: 30000 | N28: 30000 | O28: 30000 | P28: 30000 | Q28: =SUM(E28:P28) -> 360000
A29: Sales and Marketing | B29: Marketing | C29: Events Budget | E29: 100000 | F29: 100000 | G29: 100000 | H29: 100000 | I29: 100000 | J29: 100000 | K29: 100000 | L29: 100000 | M29: 100000 | N29: 100000 | O29: 100000 | P29: 100000 | Q29: =SUM(E29:P29) -> 1200000
A30: Sales and Marketing | B30: Marketing | C30: Helmet | E30: 50600 | F30: 77000 | G30: 121000 | H30: 165000 | I30: 242000 | J30: 286000 | K30: 308000 | L30: 363000 | M30: 275000 | N30: 440000 | O30: 990000 | P30: 660000 | Q30: =SUM(E30:P30) -> 3977600
A31: Sales and Marketing | B31: Marketing | C31: Longsleeves | D31: OPEX | E31: 25300 | F31: 38500 | G31: 60500 | H31: 82500 | I31: 121000 | J31: 143000 | K31: 154000 | L31: 181500 | M31: 137500 | N31: 220000 | O31: 495000 | P31: 330000 | Q31: =SUM(E31:P31) -> 1988800
A32: Sales and Marketing | B32: Marketing | C32: Miscellaneous | D32: OPEX | E32: 20000 | F32: 20000 | G32: 20000 | H32: 20000 | I32: 20000 | J32: 20000 | K32: 20000 | L32: 20000 | M32: 20000 | N32: 20000 | O32: 20000 | P32: 20000 | Q32: =SUM(E32:P32) -> 240000
C33: Subtotal - Sales and Marketing | E33: =SUM(E19:E32) -> 315040 | F33: =SUM(F19:F32) -> 361840 | G33: =SUM(G19:G32) -> 439840 | H33: =SUM(H19:H32) -> 517840 | I33: =SUM(I19:I32) -> 774340 | J33: =SUM(J19:J32) -> 732340 | K33: =SUM(K19:K32) -> 771340 | L33: =SUM(L19:L32) -> 868840 | ... P33: =SUM(P19:P32) -> 1395340 | Q33: =SUM(E33:P33) -> 9875280
A34: Customer Success | B34: Customer Success | C34: CRM | D34: OPEX | E34: - | F34: - | G34: - | H34: - | I34: - | J34: - | K34: - | L34: - | M34: 350000 | N34: - | O34: - | P34: - | Q34: =SUM(E34:P34) -> 350000
A35: Customer Success | B35: Customer Success | C35: AI Agent allowance | E35: 22500 | F35: 22500 | G35: 22500 | H35: 22500 | I35: 22500 | J35: 22500 | K35: 22500 | L35: 22500 | M35: 22500 | N35: 22500 | O35: 22500 | P35: 22500 | Q35: =SUM(E35:P35) -> 270000
A36: Customer Success | B36: Customer Success | C36: Manpower Agency | E36: 40000 | F36: 40000 | G36: 40000 | H36: 40000 | I36: 40000 | J36: 40000 | K36: 40000 | L36: 40000 | M36: 40000 | N36: 40000 | O36: 40000 | P36: 40000 | Q36: =SUM(E36:P36) -> 480000
A37: Customer Success | B37: Customer Success | C37: Miscellaneous | D37: OPEX | E37: 5000 | F37: 5000 | G37: 5000 | H37: 5000 | I37: 5000 | J37: 5000 | K37: 5000 | L37: 5000 | M37: 5000 | N37: 5000 | O37: 5000 | P37: 5000 | Q37: =SUM(E37:P37) -> 60000
C38: Subtotal - Customer Success | E38: =SUM(E34:E37) -> 67500 | F38: =SUM(F34:F37) -> 67500 | G38: =SUM(G34:G37) -> 67500 | H38: =SUM(H34:H37) -> 67500 | I38: =SUM(I34:I37) -> 67500 | J38: =SUM(J34:J37) -> 67500 | K38: =SUM(K34:K37) -> 67500 | L38: =SUM(L34:L37) -> 67500 | ... P38: =SUM(P34:P37) -> 67500 | Q38: =SUM(E38:P38) -> 1160000
A39: Supply Chain | B39: Procurement | C39: Electricity - battery charging | D39: OPEX | E39: 2579 | F39: 3967 | G39: 7340 | H39: 7411 | I39: 7855 | J39: 7983 | K39: 8238 | L39: 8338 | M39: 8448 | N39: 8820 | O39: 11167 | P39: 11332 | Q39: =SUM(E39:P39) -> 93478
A40: Supply Chain | B40: Warehouse | C40: Warehouse rent | D40: OPEX | E40: 240306 | F40: 228698 | G40: 228698 | H40: 228698 | I40: 686097 | J40: 686092 | K40: 686092 | L40: 686092 | M40: 686092 | N40: 686092 | O40: 686092 | P40: 686092 | Q40: =SUM(E40:P40) -> 6415141
A41: Supply Chain | B41: Warehouse | C41: Guard salary | D41: OPEX | E41: 134572 | F41: 128071 | G41: 128071 | H41: 128071 | I41: 384214 | J41: 384212 | K41: 384212 | L41: 384212 | M41: 384212 | N41: 384212 | O41: 384212 | P41: 384212 | Q41: =SUM(E41:P41) -> 3592483
A42: Supply Chain | B42: Warehouse | C42: Electricity / water / internet | D42: OPEX | E42: 48061 | F42: 45740 | G42: 45740 | H42: 45740 | I42: 137219 | J42: 137218 | K42: 137218 | L42: 137218 | M42: 137218 | N42: 137218 | O42: 137218 | P42: 137218 | Q42: =SUM(E42:P42) -> 1283026
A43: Supply Chain | B43: Warehouse | C43: Warehouse maintenance & supplies | D43: OPEX | E43: 24031 | F43: 22870 | G43: 22870 | H43: 22870 | I43: 68610 | J43: 68609 | K43: 68609 | L43: 68609 | M43: 68609 | N43: 68609 | O43: 68609 | P43: 68609 | Q43: =SUM(E43:P43) -> 641514
A44: Supply Chain | B44: Warehouse | C44: Miscellaneous | D44: OPEX | E44: 12016 | F44: 11433 | G44: 11433 | H44: 11433 | I44: 34306 | J44: 34305 | K44: 34305 | L44: 34305 | M44: 34305 | N44: 34305 | O44: 34305 | P44: 34305 | Q44: =SUM(E44:P44) -> 320756
A45: Supply Chain | B45: Warehouse | C45: BFP / barangay / permits | D45: OPEX | E45: 858 | F45: 817 | G45: 817 | H45: 817 | I45: 2450 | J45: 2450 | K45: 2450 | L45: 2450 | M45: 2450 | N45: 2450 | O45: 2450 | P45: 2450 | Q45: =SUM(E45:P45) -> 22909
A46: Supply Chain | B46: Retail | C46: Service Center / retail operating cost | D46: OPEX | E46: 125000 | F46: 125000 | G46: 125000 | H46: 125000 | I46: 125000 | J46: 125000 | K46: 125000 | L46: 125000 | M46: 125000 | N46: 125000 | O46: 125000 | P46: 125000 | Q46: =SUM(E46:P46) -> 1500000
A47: Supply Chain | B47: Logistics | C47: Hilux - maintenance + gas | D47: OPEX | E47: 14418 | F47: 13722 | G47: 13722 | H47: 13722 | I47: 41166 | J47: 41166 | K47: 41166 | L47: 41166 | M47: 41166 | N47: 41166 | O47: 41166 | P47: 41166 | Q47: =SUM(E47:P47) -> 384912
C48: Subtotal - Supply Chain | E48: =SUM(E39:E47) -> 601841 | F48: =SUM(F39:F47) -> 580318 | G48: =SUM(G39:G47) -> 583691 | H48: =SUM(H39:H47) -> 583762 | I48: =SUM(I39:I47) -> 1486917 | J48: =SUM(J39:J47) -> 1487035 | K48: =SUM(K39:K47) -> 1487290 | L48: =SUM(L39:L47) -> 1487390 | ... P48: =SUM(P39:P47) -> 1490384 | Q48: =SUM(E48:P48) -> 14254219
A49: Aftersales | B49: Aftersales | C49: Aftersales consumables | D49: OPEX | E49: 13800 | F49: 21000 | G49: 33000 | H49: 45000 | I49: 66000 | J49: 78000 | K49: 84000 | L49: 99000 | M49: 75000 | N49: 120000 | O49: 270000 | P49: 180000 | Q49: =SUM(E49:P49) -> 1084800
A50: Aftersales | B50: Aftersales | C50: Miscellaneous | D50: OPEX | E50: 15000 | F50: 15000 | G50: 15000 | H50: 15000 | I50: 15000 | J50: 15000 | K50: 15000 | L50: 15000 | M50: 15000 | N50: 15000 | O50: 15000 | P50: 15000 | Q50: =SUM(E50:P50) -> 180000
C51: Subtotal - Aftersales | E51: =SUM(E49:E50) -> 28800 | F51: =SUM(F49:F50) -> 36000 | G51: =SUM(G49:G50) -> 48000 | H51: =SUM(H49:H50) -> 60000 | I51: =SUM(I49:I50) -> 81000 | J51: =SUM(J49:J50) -> 93000 | K51: =SUM(K49:K50) -> 99000 | L51: =SUM(L49:L50) -> 114000 | ... P51: =SUM(P49:P50) -> 195000 | Q51: =SUM(E51:P51) -> 1264800
A52: Product | B52: R&D | C52: China Trip | D52: OPEX | E52: - | F52: - | G52: - | H52: - | I52: - | J52: - | K52: 500000 | L52: - | M52: - | N52: 500000 | O52: - | P52: - | Q52: =SUM(E52:P52) -> 1000000
A53: Product | B53: R&D | C53: R&D and V&V | D53: OPEX | E53: - | F53: - | G53: 100000 | H53: - | I53: - | J53: 100000 | K53: - | L53: - | M53: 100000 | N53: - | O53: - | P53: 100000 | Q53: =SUM(E53:P53) -> 400000
A54: Product | B54: R&D | C54: Miscellaneous | D54: OPEX | E54: 15000 | F54: 15000 | G54: 15000 | H54: 15000 | I54: 15000 | J54: 15000 | K54: 15000 | L54: 15000 | M54: 15000 | N54: 15000 | O54: 15000 | P54: 15000 | Q54: =SUM(E54:P54) -> 180000
C55: Subtotal - Product | E55: =sum(E52:E54) -> 15000 | F55: =sum(F52:F54) -> 15000 | G55: =sum(G52:G54) -> 115000 | H55: =sum(H52:H54) -> 15000 | I55: =sum(I52:I54) -> 15000 | J55: =sum(J52:J54) -> 115000 | K55: =sum(K52:K54) -> 515000 | L55: =sum(L52:L54) -> 15000 | ... P55: =sum(P52:P54) -> 115000 | Q55: =SUM(E55:P55) -> 1580000
A56: RideBox | B56: Monitoring & Field Ops | C56: Maintenance & repairs | D56: OPEX | H56: 37000 | I56: 68000 | J56: 85000 | K56: 138510 | L56: 153900 | M56: 171000 | N56: 284400 | O56: 316000 | P56: 347600 | Q56: =SUM(E56:P56) -> 1601410
A57: RideBox | B57: Network Rollout | C57: BSS site lease | D57: OPEX | H57: 185000 | I57: 340000 | J57: 425000 | K57: 692550 | L57: 769500 | M57: 855000 | N57: 1422000 | O57: 1580000 | P57: 1738000 | Q57: =SUM(E57:P57) -> 8007050
A58: RideBox | B58: Network Rollout | C58: Electricity — Battery Charging (COGS) | Q58: =SUM(E58:P58) -> 0
A59: RideBox | B59: RideBox | C59: Claude Standard licenses | D59: OPEX | H59: 2300 | I59: 7360 | J59: 9200 | K59: 14904 | L59: 16560 | M59: 18400 | N59: 26910 | O59: 29900 | P59: 32890 | Q59: =SUM(E59:P59) -> 158424
A60: RideBox | B60: RideBox | C60: Claude Max / Premium licenses | D60: OPEX | H60: - | I60: 9200 | J60: 11500 | K60: 13973 | L60: 15525 | M60: 17250 | N60: 20700 | O60: 23000 | P60: 25300 | Q60: =SUM(E60:P60) -> 136448
C61: Subtotal - RideBox | E61: =SUM(E56:E60) -> 0 | F61: =SUM(F56:F60) -> 0 | G61: =SUM(G56:G60) -> 0 | H61: =SUM(H56:H60) -> 224300 | I61: =SUM(I56:I60) -> 424560 | J61: =SUM(J56:J60) -> 530700 | K61: =SUM(K56:K60) -> 859937 | L61: =SUM(L56:L60) -> 955485 | ... P61: =SUM(P56:P60) -> 2143790 | Q61: =SUM(E61:P61) -> 9903332
A62: Technology | B62: IT | C62: Tool / Service | D62: OPEX | Q62: =SUM(E62:P62) -> 0
A63: Technology | B63: IT | C63: ── IT · Collaboration & Productivity ── | Q63: =SUM(E63:P63) -> 0
A64: Technology | B64: IT | C64: Slack (₱480/user/mo) | H64: 15360 | I64: 15360 | J64: 24000 | K64: 24000 | L64: 24000 | M64: 36000 | N64: 36000 | O64: 48480 | P64: 48480 | Q64: =SUM(E64:P64) -> 271680
A65: Technology | B65: IT | C65: Jira (₱1100/seat/mo — org FTE) | H65: 35200 | I65: 35200 | J65: 55000 | K65: 55000 | L65: 55000 | M65: 82500 | N65: 82500 | O65: 111100 | P65: 111100 | Q65: =SUM(E65:P65) -> 622600
A66: Technology | B66: IT | C66: Google Workspace (₱860/user/mo) | H66: 27520 | I66: 27520 | J66: 43000 | K66: 43000 | L66: 43000 | M66: 64500 | N66: 64500 | O66: 86860 | P66: 86860 | Q66: =SUM(E66:P66) -> 486760
A67: Technology | B67: IT | Q67: =SUM(E67:P67) -> 0
A68: Technology | B68: IT | C68: ERP Subscription (₱50k/mo) | H68: - | I68: - | J68: - | K68: - | L68: - | M68: 50000 | N68: 50000 | O68: 50000 | P68: 50000 | Q68: =SUM(E68:P68) -> 200000
A69: Technology | B69: IT | C69: ── IT · Cybersecurity & Devices ── | Q69: =SUM(E69:P69) -> 0
A70: Technology | B70: IT | C70: EDR / MDM / VPN (₱800/user/mo) | J70: 40000 | K70: 40000 | L70: 40000 | M70: 60000 | N70: 60000 | O70: 80800 | P70: 80800 | Q70: =SUM(E70:P70) -> 401600
A71: Technology | B71: IT | C71: Device Insurance (₱500/device/mo) | J71: 50000 | K71: 50000 | L71: 50000 | M71: 75000 | N71: 75000 | O71: 101000 | P71: 101000 | Q71: =SUM(E71:P71) -> 502000
A72: Technology | B72: IT | C72: Cloud Backup & DR (₱15k/mo) | J72: 15000 | K72: 15000 | L72: 15000 | M72: 15000 | N72: 15000 | O72: 15000 | P72: 15000 | Q72: =SUM(E72:P72) -> 105000
A73: Technology | B73: IT | C73: SIEM — Wazuh/GCP SCC (placeholder) | H73: - | I73: - | J73: - | K73: - | L73: - | M73: 20000 | N73: 20000 | O73: 20000 | P73: 20000 | Q73: =SUM(E73:P73) -> 80000
A74: Technology | B74: IT | C74: ── IT · Claude AI Licenses ── | Q74: =SUM(E74:P74) -> 0
A75: Technology | B75: IT | C75: Claude Standard ($20/user/mo) | H75: - | I75: - | J75: 60000 | K75: 60000 | L75: 60000 | M75: 90000 | N75: 90000 | O75: 121200 | P75: 121200
A76: Technology | B76: IT | C76: Claude Max / Premium ($100/user/mo · ~20% leads) | H76: - | I76: - | J76: 40000 | K76: 40000 | L76: 40000 | M76: 60000 | N76: 60000 | O76: 80800 | P76: 80800
A77: Technology | B77: IT | C77: ── OFFICE NETWORK --
A78: Technology | B78: IT | C78: ISP + Licenses | H78: 21000 | I78: 21000 | J78: 50000 | K78: 50000 | L78: 50000 | M78: 50000 | N78: 50000 | O78: 50000 | P78: 50000 | Q78: =SUM(E78:P78) -> 392000
A79: Technology | B79: Technology | C79: Tool / Service | D79: OPEX | Q79: =SUM(E79:P79) -> 0
A80: Technology | B80: Technology | C80: ── PE · Platform Engineering ── | H80: 120000 | I80: 120000 | J80: 180000 | K80: 180000 | L80: 180000 | M80: 280000 | N80: 280000 | O80: 420000 | P80: 420000 | Q80: =SUM(E80:P80) -> 2180000
A81: Technology | B81: Technology | C81: GCP (Firebase incl.) | H81: 5000 | I81: 5000 | J81: 5000 | K81: 5000 | L81: 5000 | M81: 12000 | N81: 12000 | O81: 28000 | P81: 28000 | Q81: =SUM(E81:P81) -> 105000
A82: Technology | B82: Technology | C82: Grafana / Prometheus (self-hosted) | H82: - | I82: - | J82: 8000 | K82: 8000 | L82: 8000 | M82: 8000 | N82: 8000 | O82: 8000 | P82: 8000 | Q82: =SUM(E82:P82) -> 56000
A83: Technology | B83: Technology | C83: PagerDuty | H83: - | I83: - | J83: 1508 | K83: 1508 | L83: 1508 | M83: 4640 | N83: 4640 | O83: 4640 | P83: 4640 | Q83: =SUM(E83:P83) -> 23084
A84: Technology | B84: Technology | C84: Sentry (error tracking) | H84: - | I84: - | J84: 460 | K84: 460 | L84: 460 | M84: 1840 | N84: 1840 | O84: 3220 | P84: 3220 | Q84: =SUM(E84:P84) -> 11500
A85: Technology | B85: Technology | C85: GitHub ($4/dev/mo) | Q85: =SUM(E85:P85) -> 0
A86: Technology | B86: Technology | C86: ── PDE+PE · Product & Platform ── | H86: - | I86: - | J86: 11500 | K86: 11500 | L86: 11500 | M86: 46000 | N86: 46000 | O86: 80500 | P86: 80500 | Q86: =SUM(E86:P86) -> 287500
A87: Technology | B87: Technology | C87: Claude Code Premium ($100/dev/mo) | H87: - | I87: - | J87: 862 | K87: 862 | L87: 862 | M87: 3450 | N87: 3450 | O87: 3450 | P87: 3450 | Q87: =SUM(E87:P87) -> 16386
A88: Technology | B88: Technology | C88: Figma ($15/seat/mo) | Q88: =SUM(E88:P88) -> 0
A89: Technology | B89: Technology | C89: ── ALL · All Teams ── | H89: 2588 | I89: 2588 | J89: 4312 | K89: 4312 | L89: 4312 | M89: 6900 | N89: 6900 | O89: 8625 | P89: 8625 | Q89: =SUM(E89:P89) -> 49162
A90: Technology | B90: Technology | C90: Lucidchart ($15/seat/mo · capped 10 seats) | Q90: =SUM(E90:P90) -> 0
A91: Technology | B91: Technology | C91: Confluence Premium ($10/user/mo) | H91: 2546 | I91: 2546 | J91: 10182 | K91: 10182 | L91: 10182 | M91: 15273 | N91: 15273 | O91: 20364 | P91: 20364 | Q91: =SUM(E91:P91) -> 106912
A92: Technology | B92: Technology | C92: Jira Service Management Premium ($44.27/seat/mo) | Q92: =SUM(E92:P92) -> 0
A93: Technology | B93: Technology | C93: ── ALL · Claude AI Licenses ── | H93: 6900 | I93: 6900 | J93: 12650 | K93: 12650 | L93: 12650 | M93: 21850 | N93: 21850 | O93: 37950 | P93: 37950 | Q93: =SUM(E93:P93) -> 171350
A94: Technology | B94: Technology | C94: Claude Standard ($20/user/mo) | H94: 5750 | I94: 5750 | J94: 11500 | K94: 11500 | L94: 11500 | M94: 23000 | N94: 23000 | O94: 40250 | P94: 40250 | Q94: =SUM(E94:P94) -> 172500
A95: Technology | B95: Technology | C95: Claude Max / Premium ($100/user/mo · ~20% leads) | Q95: =SUM(E95:P95) -> 0
A96: Technology | B96: Technology | C96: ── IoT · IoT Engineering ── | H96: 10000 | I96: 10000 | J96: 15000 | K96: 15000 | L96: 15000 | M96: 20000 | N96: 20000 | O96: 20000 | P96: 20000 | Q96: =SUM(E96:P96) -> 145000
A97: Technology | B97: Technology | C97: Hardware / Lab Consumables (placeholder) | Q97: =SUM(E97:P97) -> 0
A98: Technology | B98: Technology | C98: ── RN · Reliability & NOC ── | H98: - | I98: - | J98: 5000 | K98: 5000 | L98: 5000 | M98: 10000 | N98: 10000 | O98: 10000 | P98: 10000 | Q98: =SUM(E98:P98) -> 55000
A99: Technology | B99: Technology | C99: NOC Tools / Dashboards (placeholder) | D99: OPEX | Q99: =SUM(E99:P99) -> 0
A100: Technology | B100: Technology | C100: ── QE · Quality Engineering ── | D100: OPEX | H100: - | I100: - | J100: 3000 | K100: 3000 | L100: 3000 | M100: 5000 | N100: 5000 | O100: 8000 | P100: 8000 | Q100: =SUM(E100:P100) -> 35000
C101: QA Tools (placeholder) | E101: =SUM(E62:E100) -> 0 | F101: =SUM(F62:F100) -> 0 | G101: =SUM(G62:G100) -> 0 | H101: =SUM(H62:H100) -> 251864 | I101: =SUM(I62:I100) -> 251864 | J101: =SUM(J62:J100) -> 645974 | K101: =SUM(K62:K100) -> 645974 | L101: =SUM(L62:L100) -> 645974 | ... P101: =SUM(P62:P100) -> 1458239 | Q101: =SUM(E101:P101) -> 7480034
A102: Finance and Accounting | B102: Finance and Accounting | C102: Accounting software and Representation | D102: OPEX | E102: 0 | F102: 0 | G102: 0 | H102: 0 | I102: 50000 | J102: 50000 | K102: 50000 | L102: 50000 | M102: 50000 | N102: 50000 | O102: 50000 | P102: 50000 | Q102: =SUM(E102:P102) -> 400000
...

Sheet HC
A1: Department | E1: Jan-2026 | F1: Feb-2026 | G1: Mar-2026 | H1: Apr-2026 | I1: May-2026 | J1: Jun-2026 | K1: Jul-2026 | L1: Aug-2026 | M1: Sep-2026 | N1: Oct-2026 | O1: Nov-2026 | P1: Dec-2026
A2: Sales & Marketing | E2: 8 | F2: 8 | G2: 8 | H2: 8 | I2: 8 | J2: 8 | K2: 8 | L2: 8 | M2: 9 | N2: 9 | O2: 17 | P2: 17 | Q2: Adjust less 2 for Augmentation
A3: AfterSales Center | E3: 3 | F3: 3 | G3: 3 | H3: 3 | I3: 3 | J3: 3 | K3: 3 | L3: 3 | M3: 4 | N3: 4 | O3: 7 | P3: 7
A4: Supply Chain | E4: 3 | F4: 3 | G4: 3 | H4: 3 | I4: 3 | J4: 3 | K4: 3 | L4: 3 | M4: 4 | N4: 4 | O4: 13 | P4: 13 | Q4: Adjust less 2 for Augmentation
A5: Customer Support | E5: 5 | F5: 5 | G5: 5 | H5: 5 | I5: 6 | J5: 6 | K5: 6 | L5: 6 | M5: 6 | N5: 6 | O5: 5 | P5: 5
A7: Station Deployment Lead | B7: Ridebox tribe | C7: Rollout | D7: Now | I7: 1 | J7: 1 | K7: 1 | L7: 1 | M7: 1 | N7: 1 | O7: 1 | P7: 1
A8: RB Service Lead | B8: Ridebox tribe | C8: Service Center | D8: Now | I8: 1 | J8: 1 | K8: 1 | L8: 1 | M8: 1 | N8: 1 | O8: 1 | P8: 1
A9: Station Deployment Manager | B9: Ridebox tribe | C9: Rollout | D9: M2 | I9: 1 | J9: 1 | K9: 1 | L9: 1 | M9: 1 | N9: 1 | O9: 1 | P9: 1
A10: Commercial Ops Lead | B10: Ridebox tribe | C10: Billing & Admin | D10: M2 | I10: 1 | J10: 1 | K10: 1 | L10: 1 | M10: 1 | N10: 1 | O10: 1 | P10: 1
A11: Partners Squad Lead | B11: Ridebox tribe | C11: Billing & Admin | D11: M2 | I11: 1 | J11: 1 | K11: 1 | L11: 1 | M11: 1 | N11: 1 | O11: 1 | P11: 1
A12: RB Network Lead | B12: Ridebox tribe | C12: Monitoring & Field Ops | D12: M2 | J12: 1 | K12: 1 | L12: 1 | M12: 1 | N12: 1 | O12: 1 | P12: 1
A13: Site BD | B13: Ridebox tribe | C13: Rollout | D13: M2 | J13: 1 | K13: 1 | L13: 1 | M13: 1 | N13: 1 | O13: 1 | P13: 1
A14: Site Engineer | B14: Ridebox tribe | C14: Rollout | D14: M2 | J14: 1 | K14: 1 | L14: 1 | M14: 2 | N14: 2 | O14: 2 | P14: 2
A15: Ops Manager | B15: Ridebox tribe | C15: Monitoring & Field Ops | D15: M2 | J15: 1 | K15: 1 | L15: 1 | M15: 1 | N15: 1 | O15: 1 | P15: 1
A16: Network Ops | B16: Ridebox tribe | C16: Monitoring & Field Ops | D16: M3 | K16: 1 | L16: 1 | M16: 1 | N16: 1 | O16: 1 | P16: 1
A17: Field Technician | B17: Ridebox tribe | C17: Monitoring & Field Ops | D17: M3 | K17: 1 | L17: 1 | M17: 1 | N17: 2 | O17: 2 | P17: 2
A18: Battery Technician | B18: Ridebox tribe | C18: Service Center | D18: M3 | L18: 1 | M18: 1 | N18: 1 | O18: 2 | P18: 2
A19: Site Ops | B19: Ridebox tribe | C19: Monitoring & Field Ops | D19: M3 | M19: 1 | N19: 1 | O19: 1 | P19: 1
A20: Hardware Technician | B20: Ridebox tribe | C20: Service Center | D20: M3 | M20: 1 | N20: 1 | O20: 1 | P20: 1
A21: Parts & Inventory | B21: Ridebox tribe | C21: Service Center | D21: M4 | O21: 1 | P21: 1
A22: Billing Analyst | B22: Ridebox tribe | C22: Billing & Admin | D22: M4 | O22: 1 | P22: 1
A23: Site Admin | B23: Ridebox tribe | C23: Billing & Admin | D23: M4 | P23: 1
A24: Business Dev | B24: Ridebox tribe | C24: Billing & Admin | D24: M4 | P24: 1
A25: Partner Integrations | B25: Ridebox tribe | C25: Billing & Admin | D25: M4 | P25: 1
A32: Product Lead | B32: Tech chapter | C32: Tech Build | D32: M2 | I32: 1 | J32: 1 | K32: 1 | L32: 1 | M32: 1 | N32: 1 | O32: 1 | P32: 1
A33: App Lead | B33: Tech chapter | C33: Tech Build | D33: M2 | I33: 1 | J33: 1 | K33: 1 | L33: 1 | M33: 1 | N33: 1 | O33: 1 | P33: 1
A34: Technical Program Manager | B34: Tech chapter | C34: Tech Build | D34: M2 | I34: 1 | J34: 1 | K34: 1 | L34: 1 | M34: 1 | N34: 1 | O34: 1 | P34: 1
A35: Embedded & IoT Engineer | B35: Tech chapter | C35: Tech Build | D35: M2 | J35: 1 | K35: 2 | L35: 2 | M35: 2 | N35: 2 | O35: 2 | P35: 2
A36: Backend Engineer | B36: Tech chapter | C36: Tech Build | D36: M2 | J36: 1 | K36: 1 | L36: 2 | M36: 2 | N36: 2 | O36: 2 | P36: 2
A37: QA Lead | B37: Tech chapter | C37: Tech Build | D37: M3 | K37: 1 | L37: 1 | M37: 1 | N37: 1 | O37: 1 | P37: 1
A38: iOS Engineer | B38: Tech chapter | C38: Tech Build | D38: M3 | K38: 1 | L38: 1 | M38: 1 | N38: 1 | O38: 1 | P38: 1
A39: Android Engineer | B39: Tech chapter | C39: Tech Build | D39: M3 | K39: 1 | L39: 1 | M39: 1 | N39: 1 | O39: 1 | P39: 1
A40: Frontend Engineer | B40: Tech chapter | C40: Tech Build | D40: M3 | L40: 1 | M40: 1 | N40: 1 | O40: 1 | P40: 1
A41: QA Engineer | B41: Tech chapter | C41: Tech Build | D41: M4 | N41: 3 | O41: 3 | P41: 3
A42: Technical Support Eng. (L2) | B42: Tech chapter | C42: Tech Ops | D42: Now | H42: 1 | I42: 1 | J42: 1 | K42: 1 | L42: 1 | M42: 1 | N42: 1 | O42: 1 | P42: 1
A43: NOC Lead | B43: Tech chapter | C43: Tech Ops | D43: M2 | J43: 1 | K43: 1 | L43: 1 | M43: 1 | N43: 1 | O43: 1 | P43: 1
A44: DevOps / Cloud Engineer | B44: Tech chapter | C44: Tech Ops | D44: M2 | J44: 1 | K44: 1 | L44: 1 | M44: 1 | N44: 1 | O44: 1 | P44: 1
A45: Reliability Engineer | B45: Tech chapter | C45: Tech Ops | D45: M3 | L45: 1 | M45: 1 | N45: 1 | O45: 1 | P45: 1
A47: IT Manager | B47: IT Ops | C47: IT Ops | D47: M2 | J47: 1 | K47: 1 | L47: 1 | M47: 1 | N47: 1 | O47: 1 | P47: 1
A48: IT Support Specialist | B48: IT Ops | C48: IT Ops | D48: M2 | J48: 1 | K48: 1 | L48: 1 | M48: 1 | N48: 1 | O48: 1 | P48: 1
A49: Network Engineer | B49: IT Ops | C49: IT Ops | D49: M3 | L49: 1 | M49: 1 | N49: 1 | O49: 1 | P49: 1
A50: Cybersecurity Engineer | B50: IT Ops | C50: IT Ops | D50: M3 | M50: 1 | N50: 1 | O50: 1 | P50: 1
A52: Compliance | E52: 2 | F52: 2 | G52: 2 | H52: 2 | I52: 3 | J52: 4 | K52: 5 | L52: 5 | M52: 5 | N52: 5 | O52: 7 | P52: 7
A53: Admin | E53: 1 | F53: 1 | G53: 1 | H53: 1 | I53: 1 | J53: 1 | K53: 2 | L53: 2 | M53: 2 | N53: 2 | O53: 2 | P53: 2
A54: HR | E54: 1 | F54: 1 | G54: 1 | H54: 1 | I54: 2 | J54: 2 | K54: 2 | L54: 2 | M54: 2 | N54: 2 | O54: 5 | P54: 5
A55: Finance and Accounting | E55: 1 | F55: 1 | G55: 1 | H55: 1 | I55: 1 | J55: 2 | K55: 2 | L55: 2 | M55: 2 | N55: 2 | O55: 3 | P55: 3
A56: Total | E56: =SUM(E2:E55) -> 24 | F56: =SUM(F2:F55) -> 24 | G56: =SUM(G2:G55) -> 24 | H56: =SUM(H2:H55) -> 25 | I56: =SUM(I2:I55) -> 36 | J56: =SUM(J2:J55) -> 48 | K56: =SUM(K2:K55) -> 56 | L56: =SUM(L2:L55) -> 61 | ... P56: =SUM(P2:P55) -> 103
P57: 3 | Q57: Augmentation (current 5 hc with 650k)
B82: Billing Analyst

Sheet FX Variance (CAPEX USD)
A1: CAPEX FX Variance - USD imports (budget P60.00 vs actual ~P61.30)
E3: 61.7
A4: RFP No. | B4: Item | C4: USD | D4: Budget @60.00 (PHP) | E4: Actual @61.30 (PHP) | F4: FX Variance (PHP)
A5: RFP-OPS2026-0071 | B5: Taizhou Okla - CBU e-motorcycles | C5: 138124.8 | D5: =C5*60 -> 8287488 | E5: =C5*61.3 -> 8467050.2 | F5: =E5-D5 -> 179562.24
A6: RFP-OPS2026-0072 | B6: Guangzhou Yunku - battery-swap lockers | C6: 55200 | D6: =C6*60 -> 3312000 | E6: =C6*61.3 -> 3383760 | F6: =E6-D6 -> 71760
A7: RFP-OPS2026-0073 | B7: Taizhou Okla - spare parts | C7: 11076.63 | D7: =C7*60 -> 664597.8 | E7: =C7*61.3 -> 678997.42 | F7: =E7-D7 -> 14399.619
B8: TOTAL | C8: =SUM(C5:C7) -> 204401.43 | D8: =SUM(D5:D7) -> 12264086 | E8: =SUM(E5:E7) -> 12529808 | F8: =SUM(F5:F7) -> 265721.86

Sheet DP Monitoring
A1: Downpayment / Supplier Monitoring - balance to settle & completion tracking
A4: Vendor | B4: Item | C4: Project Location | D4: Receipt Date | E4: Date Paid | F4: Status | G4: % Paid | H4: Downpayment Paid (PHP) | I4: Balance to Settle (PHP) | J4: Total Contract (PHP) | K4: per site installation | L4: Remarks
A5: STM Builders and Trading Corp | B5: BSS install - 3 ATP sites (Alfamart) | C5: Malabon / Jordan Plaines / Santolan | D5: 4/24/2026 | E5: 5/29/2026 | F5: PAID | G5: 50% | H5: 31167 | I5: 31167 | J5: 62334 | K5: =J5/3 -> 20778 | L5: 40% + 10% milestones (=50%); acceptance/turnover
A6: STM Builders and Trading Corp | B6: BSS install - ATP Poblacion | C6: Poblacion, Mandaluyong | D6: 4/14/2026 | E6: 5/29/2026 | F6: PAID | G6: 50% | H6: 10389 | I6: 10389 | J6: 20778 | K6: =J6 -> 20778 | L6: 40% + 10% milestones (=50%); acceptance/turnover
A7: STM Builders and Trading Corp | B7: Feeder System Outdoor - 6 ATP sites | C7: 6 ATP sites | D7: 5/21/2026 | E7: 5/29/2026 | F7: PAID | G7: 50% | H7: 56334 | I7: 56334 | J7: 112668 | K7: =J7/6 -> 18778 | L7: 50% downpayment; balance on completion
A8: STM Builders and Trading Corp | B8: 4 RideBox lockers deployment | C8: Century City Mall, Makati | D8: 5/21/2026 | E8: 5/29/2026 | F8: PAID | G8: 50% | H8: 80917 | I8: 80917 | J8: 161834 | K8: =J8/4 -> 40458.5 | L8: 50% downpayment; balance on completion / turnover
A9: Digicore Integrated IT Solution | B9: BSS Pateros (service + electrical) | C9: Pateros | D9: 5/4/2026 | F9: PAID | G9: 100% | H9: 32949 | I9: 0 | J9: 32949 | L9: Full payment - no balance
A10: Taizhou Okla Automobile Co., Ltd | B10: OKLA CBU e-motorcycles (USD 138,124.80) | C10: Import - China (Taizhou) | D10: 6/18/2026 | F10: PAID | G10: 30% | H10: 8287488 | I10: 19337472 | J10: 27624960 | L10: Balance 70% on delivery; USD - FX applies at settlement
A11: Guangzhou Yunku Intelligent Co., Ltd | B11: Battery-swap lockers (USD 55,200) | C11: Import - China (Guangzhou) | D11: 6/18/2026 | F11: PAID | G11: 50% | H11: 3312000 | I11: 3312000 | J11: 6624000 | L11: Balance 50% on delivery; USD
A12: Taizhou Okla Automobile Co., Ltd | B12: OKLA spare parts (USD 11,076.63) | C12: Import - China (Taizhou) | D12: 6/22/2026 | F12: PAID | G12: 30% | H12: 664598 | I12: 1550729 | J12: 2215327 | L12: Balance 70% on delivery; USD
B13: TOTAL | H13: =SUM(H5:H12) -> 12475842 | I13: =SUM(I5:I12) -> 24379008 | J13: =SUM(J5:J12) -> 36854850

Sheet Purchase Orders (Approved)
A1: E88 Ventures - Purchase Orders Approved for Payment (Jan-Jun 2026)
A4: PO Number | B4: Date Issued | C4: Dept | D4: Vendor | E4: Orig. FX | F4: Amount (PHP) | G4: Activity / Purpose | H4: Status | I4: In RFP register?
A5: PO-202601-05 | B5: 01/29/2026 | D5: ThingsPh | F5: 61560 | G5: 10M requirement per site installation (70%DP) | H5: Issued to vendor | I5: NET-NEW (not in RFP)
A6: PO-202603-01 | C6: IT | D6: STM | F6: 20778 | G6: 10M requirement per site installation (70%DP) | H6: Issued to vendor | I6: NET-NEW (not in RFP)
A7: PO-TECH-202603-19 | C7: IT | D7: Digicore | F7: 42949 | G7: BSS Installations at Pateros Municipal Hall | H7: Issued to vendor | I7: NET-NEW (not in RFP)
A8: PO-TECH-202603-30 | C8: IT | D8: Claude AI | E8: US$ 150.00 | F8: 9000 | G8: Claude AI: Pro plan Individual (Monthly Subscription per Individual) | H8: Issued to vendor | I8: NET-NEW (not in RFP)
A9: PO - MKT2026-03-001 | C9: MARKETING | D9: WokzPh | F9: 4000 | G9: Battery Swap Updated Locker Stickers | H9: Issued to vendor | I9: Yes - already in RFP register
A10: PO-202601-01 | B10: 01/05/2026 | C10: MARKETING | D10: Wokz Ph | F10: 9550 | G10: A4 stickers for RideBox BSS ads promo, and pull-up banners for retail/events/dealerships. | H10: Issued to vendor | I10: Yes - already in RFP register
A11: PO-202601-02 | B11: 01/06/2025 | C11: IT | D11: TechnoClear | F11: 46704 | G11: for locker security and monitoring system to be integrated with NOC and CCTV integration to lockers (BSS Deployment) using brackets. Canopy Fabrication | H11: Issued to vendor | I11: Yes - already in RFP register
A12: PO-202601-03 | B12: 01/08/2025 | C12: MARKETING | D12: Wokz Ph | F12: 2000 | H12: Issued to vendor | I12: Yes - already in RFP register
A13: PO-202601-04 | B13: 01/12/2025 | C13: IT | D13: PC Central | F13: 20999 | G13: Video management system (vms), 24/7 monitoring systems for CCTVs | H13: Issued to vendor | I13: Yes - already in RFP register
A14: PO-HRA2026-0001 | C14: HRA | D14: EVANA BCBB ENTERPRISES | F14: 6524 | G14: Purchase of office uniform (HO, Warehouse, Retail) | H14: Issued to vendor | I14: Yes - already in RFP register
A15: PO-HRA2026-0002 | C15: HRA | D15: Microgenesis Business Systems | F15: 297000 | G15: Purchase of 5 13-inch MacBook Air: Apple M4 chip with 10-core CPU and 8-core GPU, 16GB Unified Memory, 256GB SSD | H15: Issued to vendor | I15: Yes - already in RFP register
A16: PO-HRA2026-0003 | C16: HRA | D16: Microgenesis Business Systems | F16: 12900 | G16: Purchase of 2 24-inch Samsung monitor | H16: Issued to vendor | I16: Yes - already in RFP register
A17: PO-MKTG2026-04-001 | C17: MARKETING | D17: Wokz Ph | F17: 3150 | G17: Pull up banner refills used during MoveIt event. | H17: Issued to vendor | I17: Yes - already in RFP register
A18: PO-MKTG2026-04-002 | C18: MARKETING | D18: Wokz Ph | F18: 525 | G18: Pull up banner for Flexride | H18: Issued to vendor | I18: Yes - already in RFP register
A19: PO-OPS2026-0001 | B19: 04/14/2026 | C19: OPERATIONS | D19: Guangzhou Yunku Intelligent Co., Ltd | E19: US$ 27600.00 | F19: 1656000 | G19: APRIL 2026 - YUNKU 5-DOOR LOCKERS (less 50% payment | H19: Issued to vendor | I19: Yes - already in RFP register
A20: PO-OPS2026-0002 | B20: 04/14/2026 | C20: OPERATIONS | D20: TAIZHOU OKLA AUTOMOBILE CO.,LTD | E20: US$ 33534.00 | F20: 2012040 | G20: APRIL 2026 - OKLA CBU (Less 70% Balance Payment); PAYMENT TERMS: T/T 30% IN ADVANCE PAYMENT 70% BEFORE SHIPPING ● DELIVERY TERMS: FOB NINGBO PORT, CHINA ● OTHER REMARKS: ○ All parts attached except rearview mirrors ○ OMIGO all longer seat version ○ Stencils of VIN and Motor numbers for each unit - 4 copies each motorcycle | H20: Issued to vendor | I20: Yes - already in RFP register
A21: PO-OPS2026-0003 | B21: 04/14/2026 | C21: OPERATIONS | D21: TAIZHOU OKLA AUTOMOBILE CO.,LTD | E21: US$ 4999.40 | F21: 299964 | G21: APRIL 2026 - OKLA SPARE PARTS (Less 70% Balance Payment);PAYMENT TERMS: T/T 30% IN ADVANCE PAYMENT 70% BEFORE SHIPPING ● DELIVERY TERMS: FOB NINGBO PORT, CHINA ● PACKAGING: BOXED SECURELY | H21: Issued to vendor | I21: Yes - already in RFP register
A22: PO-OPS2026-0006 | C22: OPERATIONS | D22: Guangzhou Yunku Intelligent Co., Ltd | E22: US$ 55200.00 | F22: 3312000 | G22: JUNE 2026 - YUNKU 5-DOOR LOCKERS | H22: Issued to vendor | I22: Yes - already in RFP register
A23: PO-OPS2026-0007 | C23: OPERATIONS | D23: TAIZHOU OKLA AUTOMOBILE CO.,LTD | E23: US$ 138124.80 | F23: 8287488 | G23: JUNE 2026 - OKLA CBU | H23: Issued to vendor | I23: Yes - already in RFP register
A24: PO-OPS2026-0009 | C24: OPERATIONS | D24: TAIZHOU OKLA AUTOMOBILE CO.,LTD | E24: US$ 11076.63 | F24: 664598 | G24: APRIL 2026 - OKLA SPARE PARTS | H24: Issued to vendor | I24: Yes - already in RFP register
E25: NET-NEW total (adds to actuals) | F25: =SUMIF(I5:I24,"NET*",F5:F24) -> 134287
E26: Already in RFP (do not add) | F26: =SUMIF(I5:I24,"Yes*",F5:F24) -> 16635442
E27: All approved POs | F27: =SUM(F5:F24) -> 16769729

Sheet Jan Budget vs Actual
A1: Jan Budget vs Actual - Non-payroll OPEX by Department / Cost Center (PHP)
A3: Department | B3: Cost Center | C3: Budget | D3: Actual | E3: Variance
A4: Sales and Marketing | B4: Sales | C4: =SUMIFS(ApprovedBudget!E19:E125,ApprovedBudget!$A$19:$A$125,"Sales and Marketing") -> 315040 | D4: =IF($A4<>"", SUMIFS('Detailed Receipts'!$K:$K, 'Detailed Receipts'!$A:$A, $A4, 'Detailed Receipts'!$B:$B, $B4, 'Detailed Receipts'!$D:$D, "Jan", 'Detailed Receipts'!$L:$L, "OPEX"), SUMIFS('Detailed Receipts'!$K:$K, 'Detailed Receipts'!$A:$A, MID($B4, 12, 100), 'Detailed Receipts'!$D:$D, "Jan", 'Detailed Receipts'!$L:$L, "OPEX")) -> 14534 | E4: =C4-D4 -> 300506
B5: Subtotal - Sales and Marketing | C5: =SUM(C4) -> 315040 | D5: =IF($A5<>"", SUMIFS('Detailed Receipts'!$K:$K, 'Detailed Receipts'!$A:$A, $A5, 'Detailed Receipts'!$B:$B, $B5, 'Detailed Receipts'!$D:$D, "Jan", 'Detailed Receipts'!$L:$L, "OPEX"), SUMIFS('Detailed Receipts'!$K:$K, 'Detailed Receipts'!$A:$A, MID($B5, 12, 100), 'Detailed Receipts'!$D:$D, "Jan", 'Detailed Receipts'!$L:$L, "OPEX")) -> 14534 | E5: =C5-D5 -> 300506
A6: Customer Success | B6: Customer Success | C6: =SUMIFS(ApprovedBudget!E19:E125,ApprovedBudget!$A$19:$A$125,"Customer Success",ApprovedBudget!$B$19:$B$125,"Customer Success") -> 67500 | D6: =IF($A6<>"", SUMIFS('Detailed Receipts'!$K:$K, 'Detailed Receipts'!$A:$A, $A6, 'Detailed Receipts'!$B:$B, $B6, 'Detailed Receipts'!$D:$D, "Jan", 'Detailed Receipts'!$L:$L, "OPEX"), SUMIFS('Detailed Receipts'!$K:$K, 'Detailed Receipts'!$A:$A, MID($B6, 12, 100), 'Detailed Receipts'!$D:$D, "Jan", 'Detailed Receipts'!$L:$L, "OPEX")) -> 0 | E6: =C6-D6 -> 67500
B7: Subtotal - Customer Success | C7: =SUM(C6) -> 67500 | D7: =IF($A7<>"", SUMIFS('Detailed Receipts'!$K:$K, 'Detailed Receipts'!$A:$A, $A7, 'Detailed Receipts'!$B:$B, $B7, 'Detailed Receipts'!$D:$D, "Jan", 'Detailed Receipts'!$L:$L, "OPEX"), SUMIFS('Detailed Receipts'!$K:$K, 'Detailed Receipts'!$A:$A, MID($B7, 12, 100), 'Detailed Receipts'!$D:$D, "Jan", 'Detailed Receipts'!$L:$L, "OPEX")) -> 0 | E7: =C7-D7 -> 67500
A8: Supply Chain | B8: Logistics | C8: =SUMIFS(ApprovedBudget!E19:E125,ApprovedBudget!$A$19:$A$125,"Supply Chain",ApprovedBudget!$B$19:$B$125,"Logistics") -> 14418 | D8: =IF($A8<>"", SUMIFS('Detailed Receipts'!$K:$K, 'Detailed Receipts'!$A:$A, $A8, 'Detailed Receipts'!$B:$B, $B8, 'Detailed Receipts'!$D:$D, "Jan", 'Detailed Receipts'!$L:$L, "OPEX"), SUMIFS('Detailed Receipts'!$K:$K, 'Detailed Receipts'!$A:$A, MID($B8, 12, 100), 'Detailed Receipts'!$D:$D, "Jan", 'Detailed Receipts'!$L:$L, "OPEX")) -> 0 | E8: =C8-D8 -> 14418
A9: Supply Chain | B9: Procurement | C9: =SUMIFS(ApprovedBudget!E19:E125,ApprovedBudget!$A$19:$A$125,"Supply Chain",ApprovedBudget!$B$19:$B$125,"Procurement") -> 2579 | D9: =IF($A9<>"", SUMIFS('Detailed Receipts'!$K:$K, 'Detailed Receipts'!$A:$A, $A9, 'Detailed Receipts'!$B:$B, $B9, 'Detailed Receipts'!$D:$D, "Jan", 'Detailed Receipts'!$L:$L, "OPEX"), SUMIFS('Detailed Receipts'!$K:$K, 'Detailed Receipts'!$A:$A, MID($B9, 12, 100), 'Detailed Receipts'!$D:$D, "Jan", 'Detailed Receipts'!$L:$L, "OPEX")) -> 13800 | E9: =C9-D9 -> -11221
A10: Supply Chain | B10: Retail | C10: =SUMIFS(ApprovedBudget!E19:E125,ApprovedBudget!$A$19:$A$125,"Supply Chain",ApprovedBudget!$B$19:$B$125,"Retail") -> 125000 | D10: =IF($A10<>"", SUMIFS('Detailed Receipts'!$K:$K, 'Detailed Receipts'!$A:$A, $A10, 'Detailed Receipts'!$B:$B, $B10, 'Detailed Receipts'!$D:$D, "Jan", 'Detailed Receipts'!$L:$L, "OPEX"), SUMIFS('Detailed Receipts'!$K:$K, 'Detailed Receipts'!$A:$A, MID($B10, 12, 100), 'Detailed Receipts'!$D:$D, "Jan", 'Detailed Receipts'!$L:$L, "OPEX")) -> 4275 | E10: =C10-D10 -> 120725
A11: Supply Chain | B11: Warehouse | C11: =SUMIFS(ApprovedBudget!E19:E125,ApprovedBudget!$A$19:$A$125,"Supply Chain",ApprovedBudget!$B$19:$B$125,"Warehouse") -> 459844 | D11: =IF($A11<>"", SUMIFS('Detailed Receipts'!$K:$K, 'Detailed Receipts'!$A:$A, $A11, 'Detailed Receipts'!$B:$B, $B11, 'Detailed Receipts'!$D:$D, "Jan", 'Detailed Receipts'!$L:$L, "OPEX"), SUMIFS('Detailed Receipts'!$K:$K, 'Detailed Receipts'!$A:$A, MID($B11, 12, 100), 'Detailed Receipts'!$D:$D, "Jan", 'Detailed Receipts'!$L:$L, "OPEX")) -> 265942 | E11: =C11-D11 -> 193902
B12: Subtotal - Supply Chain | C12: =SUM(C8:C11) -> 601841 | D12: =IF($A12<>"", SUMIFS('Detailed Receipts'!$K:$K, 'Detailed Receipts'!$A:$A, $A12, 'Detailed Receipts'!$B:$B, $B12, 'Detailed Receipts'!$D:$D, "Jan", 'Detailed Receipts'!$L:$L, "OPEX"), SUMIFS('Detailed Receipts'!$K:$K, 'Detailed Receipts'!$A:$A, MID($B12, 12, 100), 'Detailed Receipts'!$D:$D, "Jan", 'Detailed Receipts'!$L:$L, "OPEX")) -> 284017 | E12: =C12-D12 -> 317824
A13: Aftersales | B13: Aftersales | C13: =SUMIFS(ApprovedBudget!E19:E125,ApprovedBudget!$A$19:$A$125,"Aftersales",ApprovedBudget!$B$19:$B$125,"Aftersales") -> 28800 | D13: =IF($A13<>"", SUMIFS('Detailed Receipts'!$K:$K, 'Detailed Receipts'!$A:$A, $A13, 'Detailed Receipts'!$B:$B, $B13, 'Detailed Receipts'!$D:$D, "Jan", 'Detailed Receipts'!$L:$L, "OPEX"), SUMIFS('Detailed Receipts'!$K:$K, 'Detailed Receipts'!$A:$A, MID($B13, 12, 100), 'Detailed Receipts'!$D:$D, "Jan", 'Detailed Receipts'!$L:$L, "OPEX")) -> 0 | E13: =C13-D13 -> 28800
B14: Subtotal - Aftersales | C14: =SUM(C13) -> 28800 | D14: =IF($A14<>"", SUMIFS('Detailed Receipts'!$K:$K, 'Detailed Receipts'!$A:$A, $A14, 'Detailed Receipts'!$B:$B, $B14, 'Detailed Receipts'!$D:$D, "Jan", 'Detailed Receipts'!$L:$L, "OPEX"), SUMIFS('Detailed Receipts'!$K:$K, 'Detailed Receipts'!$A:$A, MID($B14, 12, 100), 'Detailed Receipts'!$D:$D, "Jan", 'Detailed Receipts'!$L:$L, "OPEX")) -> 0 | E14: =C14-D14 -> 28800
A15: Product | B15: Homologation & Registration | C15: =SUMIFS(ApprovedBudget!E19:E125,ApprovedBudget!$A$19:$A$125,"Product",ApprovedBudget!$B$19:$B$125,"Homologation & Registration") -> 0 | D15: =IF($A15<>"", SUMIFS('Detailed Receipts'!$K:$K, 'Detailed Receipts'!$A:$A, $A15, 'Detailed Receipts'!$B:$B, $B15, 'Detailed Receipts'!$D:$D, "Jan", 'Detailed Receipts'!$L:$L, "OPEX"), SUMIFS('Detailed Receipts'!$K:$K, 'Detailed Receipts'!$A:$A, MID($B15, 12, 100), 'Detailed Receipts'!$D:$D, "Jan", 'Detailed Receipts'!$L:$L, "OPEX")) -> 250555 | E15: =C15-D15 -> -250555
A16: Product | B16: R&D | C16: =SUMIFS(ApprovedBudget!E19:E125,ApprovedBudget!$A$19:$A$125,"Product",ApprovedBudget!$B$19:$B$125,"R&D") -> 15000 | D16: =IF($A16<>"", SUMIFS('Detailed Receipts'!$K:$K, 'Detailed Receipts'!$A:$A, $A16, 'Detailed Receipts'!$B:$B, $B16, 'Detailed Receipts'!$D:$D, "Jan", 'Detailed Receipts'!$L:$L, "OPEX"), SUMIFS('Detailed Receipts'!$K:$K, 'Detailed Receipts'!$A:$A, MID($B16, 12, 100), 'Detailed Receipts'!$D:$D, "Jan", 'Detailed Receipts'!$L:$L, "OPEX")) -> 0 | E16: =C16-D16 -> 15000
B17: Subtotal - Product | C17: =SUM(C15:C16) -> 15000 | D17: =IF($A17<>"", SUMIFS('Detailed Receipts'!$K:$K, 'Detailed Receipts'!$A:$A, $A17, 'Detailed Receipts'!$B:$B, $B17, 'Detailed Receipts'!$D:$D, "Jan", 'Detailed Receipts'!$L:$L, "OPEX"), SUMIFS('Detailed Receipts'!$K:$K, 'Detailed Receipts'!$A:$A, MID($B17, 12, 100), 'Detailed Receipts'!$D:$D, "Jan", 'Detailed Receipts'!$L:$L, "OPEX")) -> 250555 | E17: =C17-D17 -> -235555
A18: RideBox | B18: Billing & Admin | C18: =SUMIFS(ApprovedBudget!E19:E125,ApprovedBudget!$A$19:$A$125,"RideBox",ApprovedBudget!$B$19:$B$125,"RideBox") -> 0 | D18: =IF($A18<>"", SUMIFS('Detailed Receipts'!$K:$K, 'Detailed Receipts'!$A:$A, $A18, 'Detailed Receipts'!$B:$B, $B18, 'Detailed Receipts'!$D:$D, "Jan", 'Detailed Receipts'!$L:$L, "OPEX"), SUMIFS('Detailed Receipts'!$K:$K, 'Detailed Receipts'!$A:$A, MID($B18, 12, 100), 'Detailed Receipts'!$D:$D, "Jan", 'Detailed Receipts'!$L:$L, "OPEX")) -> 0 | E18: =C18-D18 -> 0
A19: RideBox | B19: Monitoring & Field Ops | C19: =SUMIFS(ApprovedBudget!E19:E125,ApprovedBudget!$A$19:$A$125,"RideBox",ApprovedBudget!$B$19:$B$125,"Monitoring & Field Ops") -> 0 | D19: =IF($A19<>"", SUMIFS('Detailed Receipts'!$K:$K, 'Detailed Receipts'!$A:$A, $A19, 'Detailed Receipts'!$B:$B, $B19, 'Detailed Receipts'!$D:$D, "Jan", 'Detailed Receipts'!$L:$L, "OPEX"), SUMIFS('Detailed Receipts'!$K:$K, 'Detailed Receipts'!$A:$A, MID($B19, 12, 100), 'Detailed Receipts'!$D:$D, "Jan", 'Detailed Receipts'!$L:$L, "OPEX")) -> 0 | E19: =C19-D19 -> 0
A20: RideBox | B20: Network Rollout | C20: =SUMIFS(ApprovedBudget!E19:E125,ApprovedBudget!$A$19:$A$125,"RideBox",ApprovedBudget!$B$19:$B$125,"Network Rollout") -> 0 | D20: =IF($A20<>"", SUMIFS('Detailed Receipts'!$K:$K, 'Detailed Receipts'!$A:$A, $A20, 'Detailed Receipts'!$B:$B, $B20, 'Detailed Receipts'!$D:$D, "Jan", 'Detailed Receipts'!$L:$L, "OPEX"), SUMIFS('Detailed Receipts'!$K:$K, 'Detailed Receipts'!$A:$A, MID($B20, 12, 100), 'Detailed Receipts'!$D:$D, "Jan", 'Detailed Receipts'!$L:$L, "OPEX")) -> 7922 | E20: =C20-D20 -> -7922
A21: RideBox | B21: Service Center | C21: =SUMIFS(ApprovedBudget!E19:E125,ApprovedBudget!$A$19:$A$125,"RideBox",ApprovedBudget!$B$19:$B$125,"Service Center") -> 0 | D21: =IF($A21<>"", SUMIFS('Detailed Receipts'!$K:$K, 'Detailed Receipts'!$A:$A, $A21, 'Detailed Receipts'!$B:$B, $B21, 'Detailed Receipts'!$D:$D, "Jan", 'Detailed Receipts'!$L:$L, "OPEX"), SUMIFS('Detailed Receipts'!$K:$K, 'Detailed Receipts'!$A:$A, MID($B21, 12, 100), 'Detailed Receipts'!$D:$D, "Jan", 'Detailed Receipts'!$L:$L, "OPEX")) -> 8308 | E21: =C21-D21 -> -8308
B22: Subtotal - RideBox | C22: =SUM(C18:C21) -> 0 | D22: =IF($A22<>"", SUMIFS('Detailed Receipts'!$K:$K, 'Detailed Receipts'!$A:$A, $A22, 'Detailed Receipts'!$B:$B, $B22, 'Detailed Receipts'!$D:$D, "Jan", 'Detailed Receipts'!$L:$L, "OPEX"), SUMIFS('Detailed Receipts'!$K:$K, 'Detailed Receipts'!$A:$A, MID($B22, 12, 100), 'Detailed Receipts'!$D:$D, "Jan", 'Detailed Receipts'!$L:$L, "OPEX")) -> 16230 | E22: =C22-D22 -> -16230
A23: Technology | B23: Technology | C23: =SUMIFS(ApprovedBudget!E19:E125,ApprovedBudget!$A$19:$A$125,"Technology") -> 0 | D23: =IF($A23<>"", SUMIFS('Detailed Receipts'!$K:$K, 'Detailed Receipts'!$A:$A, $A23, 'Detailed Receipts'!$B:$B, $B23, 'Detailed Receipts'!$D:$D, "Jan", 'Detailed Receipts'!$L:$L, "OPEX"), SUMIFS('Detailed Receipts'!$K:$K, 'Detailed Receipts'!$A:$A, MID($B23, 12, 100), 'Detailed Receipts'!$D:$D, "Jan", 'Detailed Receipts'!$L:$L, "OPEX")) -> 215926 | E23: =C23-D23 -> -215926
B24: Subtotal - Technology | C24: =SUM(C23) -> 0 | D24: =IF($A24<>"", SUMIFS('Detailed Receipts'!$K:$K, 'Detailed Receipts'!$A:$A, $A24, 'Detailed Receipts'!$B:$B, $B24, 'Detailed Receipts'!$D:$D, "Jan", 'Detailed Receipts'!$L:$L, "OPEX"), SUMIFS('Detailed Receipts'!$K:$K, 'Detailed Receipts'!$A:$A, MID($B24, 12, 100), 'Detailed Receipts'!$D:$D, "Jan", 'Detailed Receipts'!$L:$L, "OPEX")) -> 215926 | E24: =C24-D24 -> -215926
A25: Finance and Accounting | B25: Finance and Accounting | C25: =SUMIFS(ApprovedBudget!E19:E125,ApprovedBudget!$A$19:$A$125,"Finance and Accounting",ApprovedBudget!$B$19:$B$125,"Finance and Accounting") -> 46472 | D25: =IF($A25<>"", SUMIFS('Detailed Receipts'!$K:$K, 'Detailed Receipts'!$A:$A, $A25, 'Detailed Receipts'!$B:$B, $B25, 'Detailed Receipts'!$D:$D, "Jan", 'Detailed Receipts'!$L:$L, "OPEX"), SUMIFS('Detailed Receipts'!$K:$K, 'Detailed Receipts'!$A:$A, MID($B25, 12, 100), 'Detailed Receipts'!$D:$D, "Jan", 'Detailed Receipts'!$L:$L, "OPEX")) -> 367466 | E25: =C25-D25 -> -320994
B26: Subtotal - Finance and Accounting | C26: =SUM(C25) -> 46472 | D26: =IF($A26<>"", SUMIFS('Detailed Receipts'!$K:$K, 'Detailed Receipts'!$A:$A, $A26, 'Detailed Receipts'!$B:$B, $B26, 'Detailed Receipts'!$D:$D, "Jan", 'Detailed Receipts'!$L:$L, "OPEX"), SUMIFS('Detailed Receipts'!$K:$K, 'Detailed Receipts'!$A:$A, MID($B26, 12, 100), 'Detailed Receipts'!$D:$D, "Jan", 'Detailed Receipts'!$L:$L, "OPEX")) -> 367466 | E26: =C26-D26 -> -320994
A27: Admin | B27: Admin | C27: =SUMIFS(ApprovedBudget!E19:E125,ApprovedBudget!$A$19:$A$125,"Admin",ApprovedBudget!$B$19:$B$125,"Admin") -> 580893 | D27: =IF($A27<>"", SUMIFS('Detailed Receipts'!$K:$K, 'Detailed Receipts'!$A:$A, $A27, 'Detailed Receipts'!$B:$B, $B27, 'Detailed Receipts'!$D:$D, "Jan", 'Detailed Receipts'!$L:$L, "OPEX"), SUMIFS('Detailed Receipts'!$K:$K, 'Detailed Receipts'!$A:$A, MID($B27, 12, 100), 'Detailed Receipts'!$D:$D, "Jan", 'Detailed Receipts'!$L:$L, "OPEX")) -> 336277 | E27: =C27-D27 -> 244616
B28: Subtotal - Admin | C28: =SUM(C27) -> 580893 | D28: =IF($A28<>"", SUMIFS('Detailed Receipts'!$K:$K, 'Detailed Receipts'!$A:$A, $A28, 'Detailed Receipts'!$B:$B, $B28, 'Detailed Receipts'!$D:$D, "Jan", 'Detailed Receipts'!$L:$L, "OPEX"), SUMIFS('Detailed Receipts'!$K:$K, 'Detailed Receipts'!$A:$A, MID($B28, 12, 100), 'Detailed Receipts'!$D:$D, "Jan", 'Detailed Receipts'!$L:$L, "OPEX")) -> 336277 | E28: =C28-D28 -> 244616
A29: HR | B29: HR | C29: =SUMIFS(ApprovedBudget!E19:E125,ApprovedBudget!$A$19:$A$125,"HR",ApprovedBudget!$B$19:$B$125,"HR") -> 0 | D29: =IF($A29<>"", SUMIFS('Detailed Receipts'!$K:$K, 'Detailed Receipts'!$A:$A, $A29, 'Detailed Receipts'!$B:$B, $B29, 'Detailed Receipts'!$D:$D, "Jan", 'Detailed Receipts'!$L:$L, "OPEX"), SUMIFS('Detailed Receipts'!$K:$K, 'Detailed Receipts'!$A:$A, MID($B29, 12, 100), 'Detailed Receipts'!$D:$D, "Jan", 'Detailed Receipts'!$L:$L, "OPEX")) -> 12065 | E29: =C29-D29 -> -12065
B30: Subtotal - HR | C30: =SUM(C29) -> 0 | D30: =IF($A30<>"", SUMIFS('Detailed Receipts'!$K:$K, 'Detailed Receipts'!$A:$A, $A30, 'Detailed Receipts'!$B:$B, $B30, 'Detailed Receipts'!$D:$D, "Jan", 'Detailed Receipts'!$L:$L, "OPEX"), SUMIFS('Detailed Receipts'!$K:$K, 'Detailed Receipts'!$A:$A, MID($B30, 12, 100), 'Detailed Receipts'!$D:$D, "Jan", 'Detailed Receipts'!$L:$L, "OPEX")) -> 12065 | E30: =C30-D30 -> -12065
A31: Compliance and Risk | B31: Legal & notarial | C31: =SUMIFS(ApprovedBudget!E19:E125,ApprovedBudget!$A$19:$A$125,"Compliance and Risk",ApprovedBudget!$B$19:$B$125,"Legal & notarial") -> 60000 | D31: =IF($A31<>"", SUMIFS('Detailed Receipts'!$K:$K, 'Detailed Receipts'!$A:$A, $A31, 'Detailed Receipts'!$B:$B, $B31, 'Detailed Receipts'!$D:$D, "Jan", 'Detailed Receipts'!$L:$L, "OPEX"), SUMIFS('Detailed Receipts'!$K:$K, 'Detailed Receipts'!$A:$A, MID($B31, 12, 100), 'Detailed Receipts'!$D:$D, "Jan", 'Detailed Receipts'!$L:$L, "OPEX")) -> 103338 | E31: =C31-D31 -> -43338
A32: Compliance and Risk | B32: Permits & registration | C32: =SUMIFS(ApprovedBudget!E19:E125,ApprovedBudget!$A$19:$A$125,"Compliance and Risk",ApprovedBudget!$B$19:$B$125,"Permits & registration") -> 66800 | D32: =IF($A32<>"", SUMIFS('Detailed Receipts'!$K:$K, 'Detailed Receipts'!$A:$A, $A32, 'Detailed Receipts'!$B:$B, $B32, 'Detailed Receipts'!$D:$D, "Jan", 'Detailed Receipts'!$L:$L, "OPEX"), SUMIFS('Detailed Receipts'!$K:$K, 'Detailed Receipts'!$A:$A, MID($B32, 12, 100), 'Detailed Receipts'!$D:$D, "Jan", 'Detailed Receipts'!$L:$L, "OPEX")) -> 289718 | E32: =C32-D32 -> -222918
B33: Subtotal - Compliance and Risk | C33: =SUM(C31:C32) -> 126800 | D33: =IF($A33<>"", SUMIFS('Detailed Receipts'!$K:$K, 'Detailed Receipts'!$A:$A, $A33, 'Detailed Receipts'!$B:$B, $B33, 'Detailed Receipts'!$D:$D, "Jan", 'Detailed Receipts'!$L:$L, "OPEX"), SUMIFS('Detailed Receipts'!$K:$K, 'Detailed Receipts'!$A:$A, MID($B33, 12, 100), 'Detailed Receipts'!$D:$D, "Jan", 'Detailed Receipts'!$L:$L, "OPEX")) -> 393056 | E33: =C33-D33 -> -266256
B34: TOTAL OPEX | C34: =SUMIF($B4:$B33,"Subtotal*",C4:C33) -> 1782346 | D34: =SUMIF($B4:$B33,"Subtotal*",D4:D33) -> 1890126 | E34: =C34-D34 -> -107780

Sheet Feb Budget vs Actual
A1: Feb Budget vs Actual - Non-payroll OPEX by Department / Cost Center (PHP)
A3: Department | B3: Cost Center | C3: Budget | D3: Actual | E3: Variance
A4: Sales and Marketing | B4: Sales | C4: =SUMIFS(ApprovedBudget!F19:F125,ApprovedBudget!$A$19:$A$125,"Sales and Marketing") -> 361840 | D4: =IF($A4<>"", SUMIFS('Detailed Receipts'!$K:$K, 'Detailed Receipts'!$A:$A, $A4, 'Detailed Receipts'!$B:$B, $B4, 'Detailed Receipts'!$D:$D, "Feb", 'Detailed Receipts'!$L:$L, "OPEX"), SUMIFS('Detailed Receipts'!$K:$K, 'Detailed Receipts'!$A:$A, MID($B4, 12, 100), 'Detailed Receipts'!$D:$D, "Feb", 'Detailed Receipts'!$L:$L, "OPEX")) -> 11706 | E4: =C4-D4 -> 350134
B5: Subtotal - Sales and Marketing | C5: =SUM(C4) -> 361840 | D5: =IF($A5<>"", SUMIFS('Detailed Receipts'!$K:$K, 'Detailed Receipts'!$A:$A, $A5, 'Detailed Receipts'!$B:$B, $B5, 'Detailed Receipts'!$D:$D, "Feb", 'Detailed Receipts'!$L:$L, "OPEX"), SUMIFS('Detailed Receipts'!$K:$K, 'Detailed Receipts'!$A:$A, MID($B5, 12, 100), 'Detailed Receipts'!$D:$D, "Feb", 'Detailed Receipts'!$L:$L, "OPEX")) -> 11706 | E5: =C5-D5 -> 350134
A6: Customer Success | B6: Customer Success | C6: =SUMIFS(ApprovedBudget!F19:F125,ApprovedBudget!$A$19:$A$125,"Customer Success",ApprovedBudget!$B$19:$B$125,"Customer Success") -> 67500 | D6: =IF($A6<>"", SUMIFS('Detailed Receipts'!$K:$K, 'Detailed Receipts'!$A:$A, $A6, 'Detailed Receipts'!$B:$B, $B6, 'Detailed Receipts'!$D:$D, "Feb", 'Detailed Receipts'!$L:$L, "OPEX"), SUMIFS('Detailed Receipts'!$K:$K, 'Detailed Receipts'!$A:$A, MID($B6, 12, 100), 'Detailed Receipts'!$D:$D, "Feb", 'Detailed Receipts'!$L:$L, "OPEX")) -> 0 | E6: =C6-D6 -> 67500
B7: Subtotal - Customer Success | C7: =SUM(C6) -> 67500 | D7: =IF($A7<>"", SUMIFS('Detailed Receipts'!$K:$K, 'Detailed Receipts'!$A:$A, $A7, 'Detailed Receipts'!$B:$B, $B7, 'Detailed Receipts'!$D:$D, "Feb", 'Detailed Receipts'!$L:$L, "OPEX"), SUMIFS('Detailed Receipts'!$K:$K, 'Detailed Receipts'!$A:$A, MID($B7, 12, 100), 'Detailed Receipts'!$D:$D, "Feb", 'Detailed Receipts'!$L:$L, "OPEX")) -> 0 | E7: =C7-D7 -> 67500
A8: Supply Chain | B8: Logistics | C8: =SUMIFS(ApprovedBudget!F19:F125,ApprovedBudget!$A$19:$A$125,"Supply Chain",ApprovedBudget!$B$19:$B$125,"Logistics") -> 13722 | D8: =IF($A8<>"", SUMIFS('Detailed Receipts'!$K:$K, 'Detailed Receipts'!$A:$A, $A8, 'Detailed Receipts'!$B:$B, $B8, 'Detailed Receipts'!$D:$D, "Feb", 'Detailed Receipts'!$L:$L, "OPEX"), SUMIFS('Detailed Receipts'!$K:$K, 'Detailed Receipts'!$A:$A, MID($B8, 12, 100), 'Detailed Receipts'!$D:$D, "Feb", 'Detailed Receipts'!$L:$L, "OPEX")) -> 0 | E8: =C8-D8 -> 13722
A9: Supply Chain | B9: Procurement | C9: =SUMIFS(ApprovedBudget!F19:F125,ApprovedBudget!$A$19:$A$125,"Supply Chain",ApprovedBudget!$B$19:$B$125,"Procurement") -> 3967 | D9: =IF($A9<>"", SUMIFS('Detailed Receipts'!$K:$K, 'Detailed Receipts'!$A:$A, $A9, 'Detailed Receipts'!$B:$B, $B9, 'Detailed Receipts'!$D:$D, "Feb", 'Detailed Receipts'!$L:$L, "OPEX"), SUMIFS('Detailed Receipts'!$K:$K, 'Detailed Receipts'!$A:$A, MID($B9, 12, 100), 'Detailed Receipts'!$D:$D, "Feb", 'Detailed Receipts'!$L:$L, "OPEX")) -> 0 | E9: =C9-D9 -> 3967
A10: Supply Chain | B10: Retail | C10: =SUMIFS(ApprovedBudget!F19:F125,ApprovedBudget!$A$19:$A$125,"Supply Chain",ApprovedBudget!$B$19:$B$125,"Retail") -> 125000 | D10: =IF($A10<>"", SUMIFS('Detailed Receipts'!$K:$K, 'Detailed Receipts'!$A:$A, $A10, 'Detailed Receipts'!$B:$B, $B10, 'Detailed Receipts'!$D:$D, "Feb", 'Detailed Receipts'!$L:$L, "OPEX"), SUMIFS('Detailed Receipts'!$K:$K, 'Detailed Receipts'!$A:$A, MID($B10, 12, 100), 'Detailed Receipts'!$D:$D, "Feb", 'Detailed Receipts'!$L:$L, "OPEX")) -> 6932 | E10: =C10-D10 -> 118068
A11: Supply Chain | B11: Warehouse | C11: =SUMIFS(ApprovedBudget!F19:F125,ApprovedBudget!$A$19:$A$125,"Supply Chain",ApprovedBudget!$B$19:$B$125,"Warehouse") -> 437629 | D11: =IF($A11<>"", SUMIFS('Detailed Receipts'!$K:$K, 'Detailed Receipts'!$A:$A, $A11, 'Detailed Receipts'!$B:$B, $B11, 'Detailed Receipts'!$D:$D, "Feb", 'Detailed Receipts'!$L:$L, "OPEX"), SUMIFS('Detailed Receipts'!$K:$K, 'Detailed Receipts'!$A:$A, MID($B11, 12, 100), 'Detailed Receipts'!$D:$D, "Feb", 'Detailed Receipts'!$L:$L, "OPEX")) -> 665598 | E11: =C11-D11 -> -227969
B12: Subtotal - Supply Chain | C12: =SUM(C8:C11) -> 580318 | D12: =IF($A12<>"", SUMIFS('Detailed Receipts'!$K:$K, 'Detailed Receipts'!$A:$A, $A12, 'Detailed Receipts'!$B:$B, $B12, 'Detailed Receipts'!$D:$D, "Feb", 'Detailed Receipts'!$L:$L, "OPEX"), SUMIFS('Detailed Receipts'!$K:$K, 'Detailed Receipts'!$A:$A, MID($B12, 12, 100), 'Detailed Receipts'!$D:$D, "Feb", 'Detailed Receipts'!$L:$L, "OPEX")) -> 672530 | E12: =C12-D12 -> -92212
A13: Aftersales | B13: Aftersales | C13: =SUMIFS(ApprovedBudget!F19:F125,ApprovedBudget!$A$19:$A$125,"Aftersales",ApprovedBudget!$B$19:$B$125,"Aftersales") -> 36000 | D13: =IF($A13<>"", SUMIFS('Detailed Receipts'!$K:$K, 'Detailed Receipts'!$A:$A, $A13, 'Detailed Receipts'!$B:$B, $B13, 'Detailed Receipts'!$D:$D, "Feb", 'Detailed Receipts'!$L:$L, "OPEX"), SUMIFS('Detailed Receipts'!$K:$K, 'Detailed Receipts'!$A:$A, MID($B13, 12, 100), 'Detailed Receipts'!$D:$D, "Feb", 'Detailed Receipts'!$L:$L, "OPEX")) -> 1428 | E13: =C13-D13 -> 34572
B14: Subtotal - Aftersales | C14: =SUM(C13) -> 36000 | D14: =IF($A14<>"", SUMIFS('Detailed Receipts'!$K:$K, 'Detailed Receipts'!$A:$A, $A14, 'Detailed Receipts'!$B:$B, $B14, 'Detailed Receipts'!$D:$D, "Feb", 'Detailed Receipts'!$L:$L, "OPEX"), SUMIFS('Detailed Receipts'!$K:$K, 'Detailed Receipts'!$A:$A, MID($B14, 12, 100), 'Detailed Receipts'!$D:$D, "Feb", 'Detailed Receipts'!$L:$L, "OPEX")) -> 1428 | E14: =C14-D14 -> 34572
A15: Product | B15: Homologation & Registration | C15: =SUMIFS(ApprovedBudget!F19:F125,ApprovedBudget!$A$19:$A$125,"Product",ApprovedBudget!$B$19:$B$125,"Homologation & Registration") -> 0 | D15: =IF($A15<>"", SUMIFS('Detailed Receipts'!$K:$K, 'Detailed Receipts'!$A:$A, $A15, 'Detailed Receipts'!$B:$B, $B15, 'Detailed Receipts'!$D:$D, "Feb", 'Detailed Receipts'!$L:$L, "OPEX"), SUMIFS('Detailed Receipts'!$K:$K, 'Detailed Receipts'!$A:$A, MID($B15, 12, 100), 'Detailed Receipts'!$D:$D, "Feb", 'Detailed Receipts'!$L:$L, "OPEX")) -> 160346 | E15: =C15-D15 -> -160346
A16: Product | B16: R&D | C16: =SUMIFS(ApprovedBudget!F19:F125,ApprovedBudget!$A$19:$A$125,"Product",ApprovedBudget!$B$19:$B$125,"R&D") -> 15000 | D16: =IF($A16<>"", SUMIFS('Detailed Receipts'!$K:$K, 'Detailed Receipts'!$A:$A, $A16, 'Detailed Receipts'!$B:$B, $B16, 'Detailed Receipts'!$D:$D, "Feb", 'Detailed Receipts'!$L:$L, "OPEX"), SUMIFS('Detailed Receipts'!$K:$K, 'Detailed Receipts'!$A:$A, MID($B16, 12, 100), 'Detailed Receipts'!$D:$D, "Feb", 'Detailed Receipts'!$L:$L, "OPEX")) -> 0 | E16: =C16-D16 -> 15000
B17: Subtotal - Product | C17: =SUM(C15:C16) -> 15000 | D17: =IF($A17<>"", SUMIFS('Detailed Receipts'!$K:$K, 'Detailed Receipts'!$A:$A, $A17, 'Detailed Receipts'!$B:$B, $B17, 'Detailed Receipts'!$D:$D, "Feb", 'Detailed Receipts'!$L:$L, "OPEX"), SUMIFS('Detailed Receipts'!$K:$K, 'Detailed Receipts'!$A:$A, MID($B17, 12, 100), 'Detailed Receipts'!$D:$D, "Feb", 'Detailed Receipts'!$L:$L, "OPEX")) -> 160346 | E17: =C17-D17 -> -145346
A18: RideBox | B18: Billing & Admin | C18: =SUMIFS(ApprovedBudget!F19:F125,ApprovedBudget!$A$19:$A$125,"RideBox",ApprovedBudget!$B$19:$B$125,"RideBox") -> 0 | D18: =IF($A18<>"", SUMIFS('Detailed Receipts'!$K:$K, 'Detailed Receipts'!$A:$A, $A18, 'Detailed Receipts'!$B:$B, $B18, 'Detailed Receipts'!$D:$D, "Feb", 'Detailed Receipts'!$L:$L, "OPEX"), SUMIFS('Detailed Receipts'!$K:$K, 'Detailed Receipts'!$A:$A, MID($B18, 12, 100), 'Detailed Receipts'!$D:$D, "Feb", 'Detailed Receipts'!$L:$L, "OPEX")) -> 0 | E18: =C18-D18 -> 0
A19: RideBox | B19: Monitoring & Field Ops | C19: =SUMIFS(ApprovedBudget!F19:F125,ApprovedBudget!$A$19:$A$125,"RideBox",ApprovedBudget!$B$19:$B$125,"Monitoring & Field Ops") -> 0 | D19: =IF($A19<>"", SUMIFS('Detailed Receipts'!$K:$K, 'Detailed Receipts'!$A:$A, $A19, 'Detailed Receipts'!$B:$B, $B19, 'Detailed Receipts'!$D:$D, "Feb", 'Detailed Receipts'!$L:$L, "OPEX"), SUMIFS('Detailed Receipts'!$K:$K, 'Detailed Receipts'!$A:$A, MID($B19, 12, 100), 'Detailed Receipts'!$D:$D, "Feb", 'Detailed Receipts'!$L:$L, "OPEX")) -> 626590 | E19: =C19-D19 -> -626590
A20: RideBox | B20: Network Rollout | C20: =SUMIFS(ApprovedBudget!F19:F125,ApprovedBudget!$A$19:$A$125,"RideBox",ApprovedBudget!$B$19:$B$125,"Network Rollout") -> 0 | D20: =IF($A20<>"", SUMIFS('Detailed Receipts'!$K:$K, 'Detailed Receipts'!$A:$A, $A20, 'Detailed Receipts'!$B:$B, $B20, 'Detailed Receipts'!$D:$D, "Feb", 'Detailed Receipts'!$L:$L, "OPEX"), SUMIFS('Detailed Receipts'!$K:$K, 'Detailed Receipts'!$A:$A, MID($B20, 12, 100), 'Detailed Receipts'!$D:$D, "Feb", 'Detailed Receipts'!$L:$L, "OPEX")) -> 9075 | E20: =C20-D20 -> -9075
A21: RideBox | B21: Service Center | C21: =SUMIFS(ApprovedBudget!F19:F125,ApprovedBudget!$A$19:$A$125,"RideBox",ApprovedBudget!$B$19:$B$125,"Service Center") -> 0 | D21: =IF($A21<>"", SUMIFS('Detailed Receipts'!$K:$K, 'Detailed Receipts'!$A:$A, $A21, 'Detailed Receipts'!$B:$B, $B21, 'Detailed Receipts'!$D:$D, "Feb", 'Detailed Receipts'!$L:$L, "OPEX"), SUMIFS('Detailed Receipts'!$K:$K, 'Detailed Receipts'!$A:$A, MID($B21, 12, 100), 'Detailed Receipts'!$D:$D, "Feb", 'Detailed Receipts'!$L:$L, "OPEX")) -> 7172 | E21: =C21-D21 -> -7172
B22: Subtotal - RideBox | C22: =SUM(C18:C21) -> 0 | D22: =IF($A22<>"", SUMIFS('Detailed Receipts'!$K:$K, 'Detailed Receipts'!$A:$A, $A22, 'Detailed Receipts'!$B:$B, $B22, 'Detailed Receipts'!$D:$D, "Feb", 'Detailed Receipts'!$L:$L, "OPEX"), SUMIFS('Detailed Receipts'!$K:$K, 'Detailed Receipts'!$A:$A, MID($B22, 12, 100), 'Detailed Receipts'!$D:$D, "Feb", 'Detailed Receipts'!$L:$L, "OPEX")) -> 642837 | E22: =C22-D22 -> -642837
A23: Technology | B23: Technology | C23: =SUMIFS(ApprovedBudget!F19:F125,ApprovedBudget!$A$19:$A$125,"Technology") -> 0 | D23: =IF($A23<>"", SUMIFS('Detailed Receipts'!$K:$K, 'Detailed Receipts'!$A:$A, $A23, 'Detailed Receipts'!$B:$B, $B23, 'Detailed Receipts'!$D:$D, "Feb", 'Detailed Receipts'!$L:$L, "OPEX"), SUMIFS('Detailed Receipts'!$K:$K, 'Detailed Receipts'!$A:$A, MID($B23, 12, 100), 'Detailed Receipts'!$D:$D, "Feb", 'Detailed Receipts'!$L:$L, "OPEX")) -> 14314 | E23: =C23-D23 -> -14314
B24: Subtotal - Technology | C24: =SUM(C23) -> 0 | D24: =IF($A24<>"", SUMIFS('Detailed Receipts'!$K:$K, 'Detailed Receipts'!$A:$A, $A24, 'Detailed Receipts'!$B:$B, $B24, 'Detailed Receipts'!$D:$D, "Feb", 'Detailed Receipts'!$L:$L, "OPEX"), SUMIFS('Detailed Receipts'!$K:$K, 'Detailed Receipts'!$A:$A, MID($B24, 12, 100), 'Detailed Receipts'!$D:$D, "Feb", 'Detailed Receipts'!$L:$L, "OPEX")) -> 14314 | E24: =C24-D24 -> -14314
A25: Finance and Accounting | B25: Finance and Accounting | C25: =SUMIFS(ApprovedBudget!F19:F125,ApprovedBudget!$A$19:$A$125,"Finance and Accounting",ApprovedBudget!$B$19:$B$125,"Finance and Accounting") -> 46472 | D25: =IF($A25<>"", SUMIFS('Detailed Receipts'!$K:$K, 'Detailed Receipts'!$A:$A, $A25, 'Detailed Receipts'!$B:$B, $B25, 'Detailed Receipts'!$D:$D, "Feb", 'Detailed Receipts'!$L:$L, "OPEX"), SUMIFS('Detailed Receipts'!$K:$K, 'Detailed Receipts'!$A:$A, MID($B25, 12, 100), 'Detailed Receipts'!$D:$D, "Feb", 'Detailed Receipts'!$L:$L, "OPEX")) -> 33199 | E25: =C25-D25 -> 13273
B26: Subtotal - Finance and Accounting | C26: =SUM(C25) -> 46472 | D26: =IF($A26<>"", SUMIFS('Detailed Receipts'!$K:$K, 'Detailed Receipts'!$A:$A, $A26, 'Detailed Receipts'!$B:$B, $B26, 'Detailed Receipts'!$D:$D, "Feb", 'Detailed Receipts'!$L:$L, "OPEX"), SUMIFS('Detailed Receipts'!$K:$K, 'Detailed Receipts'!$A:$A, MID($B26, 12, 100), 'Detailed Receipts'!$D:$D, "Feb", 'Detailed Receipts'!$L:$L, "OPEX")) -> 33199 | E26: =C26-D26 -> 13273
A27: Admin | B27: Admin | C27: =SUMIFS(ApprovedBudget!F19:F125,ApprovedBudget!$A$19:$A$125,"Admin",ApprovedBudget!$B$19:$B$125,"Admin") -> 580893 | D27: =IF($A27<>"", SUMIFS('Detailed Receipts'!$K:$K, 'Detailed Receipts'!$A:$A, $A27, 'Detailed Receipts'!$B:$B, $B27, 'Detailed Receipts'!$D:$D, "Feb", 'Detailed Receipts'!$L:$L, "OPEX"), SUMIFS('Detailed Receipts'!$K:$K, 'Detailed Receipts'!$A:$A, MID($B27, 12, 100), 'Detailed Receipts'!$D:$D, "Feb", 'Detailed Receipts'!$L:$L, "OPEX")) -> 224889 | E27: =C27-D27 -> 356004
B28: Subtotal - Admin | C28: =SUM(C27) -> 580893 | D28: =IF($A28<>"", SUMIFS('Detailed Receipts'!$K:$K, 'Detailed Receipts'!$A:$A, $A28, 'Detailed Receipts'!$B:$B, $B28, 'Detailed Receipts'!$D:$D, "Feb", 'Detailed Receipts'!$L:$L, "OPEX"), SUMIFS('Detailed Receipts'!$K:$K, 'Detailed Receipts'!$A:$A, MID($B28, 12, 100), 'Detailed Receipts'!$D:$D, "Feb", 'Detailed Receipts'!$L:$L, "OPEX")) -> 224889 | E28: =C28-D28 -> 356004
A29: HR | B29: HR | C29: =SUMIFS(ApprovedBudget!F19:F125,ApprovedBudget!$A$19:$A$125,"HR",ApprovedBudget!$B$19:$B$125,"HR") -> 0 | D29: =IF($A29<>"", SUMIFS('Detailed Receipts'!$K:$K, 'Detailed Receipts'!$A:$A, $A29, 'Detailed Receipts'!$B:$B, $B29, 'Detailed Receipts'!$D:$D, "Feb", 'Detailed Receipts'!$L:$L, "OPEX"), SUMIFS('Detailed Receipts'!$K:$K, 'Detailed Receipts'!$A:$A, MID($B29, 12, 100), 'Detailed Receipts'!$D:$D, "Feb", 'Detailed Receipts'!$L:$L, "OPEX")) -> 72107 | E29: =C29-D29 -> -72107
B30: Subtotal - HR | C30: =SUM(C29) -> 0 | D30: =IF($A30<>"", SUMIFS('Detailed Receipts'!$K:$K, 'Detailed Receipts'!$A:$A, $A30, 'Detailed Receipts'!$B:$B, $B30, 'Detailed Receipts'!$D:$D, "Feb", 'Detailed Receipts'!$L:$L, "OPEX"), SUMIFS('Detailed Receipts'!$K:$K, 'Detailed Receipts'!$A:$A, MID($B30, 12, 100), 'Detailed Receipts'!$D:$D, "Feb", 'Detailed Receipts'!$L:$L, "OPEX")) -> 72107 | E30: =C30-D30 -> -72107
A31: Compliance and Risk | B31: Legal & notarial | C31: =SUMIFS(ApprovedBudget!F19:F125,ApprovedBudget!$A$19:$A$125,"Compliance and Risk",ApprovedBudget!$B$19:$B$125,"Legal & notarial") -> 60000 | D31: =IF($A31<>"", SUMIFS('Detailed Receipts'!$K:$K, 'Detailed Receipts'!$A:$A, $A31, 'Detailed Receipts'!$B:$B, $B31, 'Detailed Receipts'!$D:$D, "Feb", 'Detailed Receipts'!$L:$L, "OPEX"), SUMIFS('Detailed Receipts'!$K:$K, 'Detailed Receipts'!$A:$A, MID($B31, 12, 100), 'Detailed Receipts'!$D:$D, "Feb", 'Detailed Receipts'!$L:$L, "OPEX")) -> 136027 | E31: =C31-D31 -> -76027
A32: Compliance and Risk | B32: Permits & registration | C32: =SUMIFS(ApprovedBudget!F19:F125,ApprovedBudget!$A$19:$A$125,"Compliance and Risk",ApprovedBudget!$B$19:$B$125,"Permits & registration") -> 66800 | D32: =IF($A32<>"", SUMIFS('Detailed Receipts'!$K:$K, 'Detailed Receipts'!$A:$A, $A32, 'Detailed Receipts'!$B:$B, $B32, 'Detailed Receipts'!$D:$D, "Feb", 'Detailed Receipts'!$L:$L, "OPEX"), SUMIFS('Detailed Receipts'!$K:$K, 'Detailed Receipts'!$A:$A, MID($B32, 12, 100), 'Detailed Receipts'!$D:$D, "Feb", 'Detailed Receipts'!$L:$L, "OPEX")) -> 164030 | E32: =C32-D32 -> -97230
B33: Subtotal - Compliance and Risk | C33: =SUM(C31:C32) -> 126800 | D33: =IF($A33<>"", SUMIFS('Detailed Receipts'!$K:$K, 'Detailed Receipts'!$A:$A, $A33, 'Detailed Receipts'!$B:$B, $B33, 'Detailed Receipts'!$D:$D, "Feb", 'Detailed Receipts'!$L:$L, "OPEX"), SUMIFS('Detailed Receipts'!$K:$K, 'Detailed Receipts'!$A:$A, MID($B33, 12, 100), 'Detailed Receipts'!$D:$D, "Feb", 'Detailed Receipts'!$L:$L, "OPEX")) -> 300057 | E33: =C33-D33 -> -173257
B34: TOTAL OPEX | C34: =SUMIF($B4:$B33,"Subtotal*",C4:C33) -> 1814823 | D34: =SUMIF($B4:$B33,"Subtotal*",D4:D33) -> 2133413 | E34: =C34-D34 -> -318590

Sheet Mar Budget vs Actual
A1: Mar Budget vs Actual - Non-payroll OPEX by Department / Cost Center (PHP)
A3: Department | B3: Cost Center | C3: Budget | D3: Actual | E3: Variance
A4: Sales and Marketing | B4: Sales | C4: =SUMIFS(ApprovedBudget!G19:G125,ApprovedBudget!$A$19:$A$125,"Sales and Marketing") -> 439840 | D4: =IF($A4<>"", SUMIFS('Detailed Receipts'!$K:$K, 'Detailed Receipts'!$A:$A, $A4, 'Detailed Receipts'!$B:$B, $B4, 'Detailed Receipts'!$D:$D, "Mar", 'Detailed Receipts'!$L:$L, "OPEX"), SUMIFS('Detailed Receipts'!$K:$K, 'Detailed Receipts'!$A:$A, MID($B4, 12, 100), 'Detailed Receipts'!$D:$D, "Mar", 'Detailed Receipts'!$L:$L, "OPEX")) -> 10121 | E4: =C4-D4 -> 429719
B5: Subtotal - Sales and Marketing | C5: =SUM(C4) -> 439840 | D5: =IF($A5<>"", SUMIFS('Detailed Receipts'!$K:$K, 'Detailed Receipts'!$A:$A, $A5, 'Detailed Receipts'!$B:$B, $B5, 'Detailed Receipts'!$D:$D, "Mar", 'Detailed Receipts'!$L:$L, "OPEX"), SUMIFS('Detailed Receipts'!$K:$K, 'Detailed Receipts'!$A:$A, MID($B5, 12, 100), 'Detailed Receipts'!$D:$D, "Mar", 'Detailed Receipts'!$L:$L, "OPEX")) -> 10121 | E5: =C5-D5 -> 429719
A6: Customer Success | B6: Customer Success | C6: =SUMIFS(ApprovedBudget!G19:G125,ApprovedBudget!$A$19:$A$125,"Customer Success",ApprovedBudget!$B$19:$B$125,"Customer Success") -> 67500 | D6: =IF($A6<>"", SUMIFS('Detailed Receipts'!$K:$K, 'Detailed Receipts'!$A:$A, $A6, 'Detailed Receipts'!$B:$B, $B6, 'Detailed Receipts'!$D:$D, "Mar", 'Detailed Receipts'!$L:$L, "OPEX"), SUMIFS('Detailed Receipts'!$K:$K, 'Detailed Receipts'!$A:$A, MID($B6, 12, 100), 'Detailed Receipts'!$D:$D, "Mar", 'Detailed Receipts'!$L:$L, "OPEX")) -> 0 | E6: =C6-D6 -> 67500
B7: Subtotal - Customer Success | C7: =SUM(C6) -> 67500 | D7: =IF($A7<>"", SUMIFS('Detailed Receipts'!$K:$K, 'Detailed Receipts'!$A:$A, $A7, 'Detailed Receipts'!$B:$B, $B7, 'Detailed Receipts'!$D:$D, "Mar", 'Detailed Receipts'!$L:$L, "OPEX"), SUMIFS('Detailed Receipts'!$K:$K, 'Detailed Receipts'!$A:$A, MID($B7, 12, 100), 'Detailed Receipts'!$D:$D, "Mar", 'Detailed Receipts'!$L:$L, "OPEX")) -> 0 | E7: =C7-D7 -> 67500
A8: Supply Chain | B8: Logistics | C8: =SUMIFS(ApprovedBudget!G19:G125,ApprovedBudget!$A$19:$A$125,"Supply Chain",ApprovedBudget!$B$19:$B$125,"Logistics") -> 13722 | D8: =IF($A8<>"", SUMIFS('Detailed Receipts'!$K:$K, 'Detailed Receipts'!$A:$A, $A8, 'Detailed Receipts'!$B:$B, $B8, 'Detailed Receipts'!$D:$D, "Mar", 'Detailed Receipts'!$L:$L, "OPEX"), SUMIFS('Detailed Receipts'!$K:$K, 'Detailed Receipts'!$A:$A, MID($B8, 12, 100), 'Detailed Receipts'!$D:$D, "Mar", 'Detailed Receipts'!$L:$L, "OPEX")) -> 0 | E8: =C8-D8 -> 13722
A9: Supply Chain | B9: Procurement | C9: =SUMIFS(ApprovedBudget!G19:G125,ApprovedBudget!$A$19:$A$125,"Supply Chain",ApprovedBudget!$B$19:$B$125,"Procurement") -> 7340 | D9: =IF($A9<>"", SUMIFS('Detailed Receipts'!$K:$K, 'Detailed Receipts'!$A:$A, $A9, 'Detailed Receipts'!$B:$B, $B9, 'Detailed Receipts'!$D:$D, "Mar", 'Detailed Receipts'!$L:$L, "OPEX"), SUMIFS('Detailed Receipts'!$K:$K, 'Detailed Receipts'!$A:$A, MID($B9, 12, 100), 'Detailed Receipts'!$D:$D, "Mar", 'Detailed Receipts'!$L:$L, "OPEX")) -> 0 | E9: =C9-D9 -> 7340
A10: Supply Chain | B10: Retail | C10: =SUMIFS(ApprovedBudget!G19:G125,ApprovedBudget!$A$19:$A$125,"Supply Chain",ApprovedBudget!$B$19:$B$125,"Retail") -> 125000 | D10: =IF($A10<>"", SUMIFS('Detailed Receipts'!$K:$K, 'Detailed Receipts'!$A:$A, $A10, 'Detailed Receipts'!$B:$B, $B10, 'Detailed Receipts'!$D:$D, "Mar", 'Detailed Receipts'!$L:$L, "OPEX"), SUMIFS('Detailed Receipts'!$K:$K, 'Detailed Receipts'!$A:$A, MID($B10, 12, 100), 'Detailed Receipts'!$D:$D, "Mar", 'Detailed Receipts'!$L:$L, "OPEX")) -> 23074 | E10: =C10-D10 -> 101926
A11: Supply Chain | B11: Warehouse | C11: =SUMIFS(ApprovedBudget!G19:G125,ApprovedBudget!$A$19:$A$125,"Supply Chain",ApprovedBudget!$B$19:$B$125,"Warehouse") -> 437629 | D11: =IF($A11<>"", SUMIFS('Detailed Receipts'!$K:$K, 'Detailed Receipts'!$A:$A, $A11, 'Detailed Receipts'!$B:$B, $B11, 'Detailed Receipts'!$D:$D, "Mar", 'Detailed Receipts'!$L:$L, "OPEX"), SUMIFS('Detailed Receipts'!$K:$K, 'Detailed Receipts'!$A:$A, MID($B11, 12, 100), 'Detailed Receipts'!$D:$D, "Mar", 'Detailed Receipts'!$L:$L, "OPEX")) -> 389654 | E11: =C11-D11 -> 47975
B12: Subtotal - Supply Chain | C12: =SUM(C8:C11) -> 583691 | D12: =IF($A12<>"", SUMIFS('Detailed Receipts'!$K:$K, 'Detailed Receipts'!$A:$A, $A12, 'Detailed Receipts'!$B:$B, $B12, 'Detailed Receipts'!$D:$D, "Mar", 'Detailed Receipts'!$L:$L, "OPEX"), SUMIFS('Detailed Receipts'!$K:$K, 'Detailed Receipts'!$A:$A, MID($B12, 12, 100), 'Detailed Receipts'!$D:$D, "Mar", 'Detailed Receipts'!$L:$L, "OPEX")) -> 412728 | E12: =C12-D12 -> 170963
A13: Aftersales | B13: Aftersales | C13: =SUMIFS(ApprovedBudget!G19:G125,ApprovedBudget!$A$19:$A$125,"Aftersales",ApprovedBudget!$B$19:$B$125,"Aftersales") -> 48000 | D13: =IF($A13<>"", SUMIFS('Detailed Receipts'!$K:$K, 'Detailed Receipts'!$A:$A, $A13, 'Detailed Receipts'!$B:$B, $B13, 'Detailed Receipts'!$D:$D, "Mar", 'Detailed Receipts'!$L:$L, "OPEX"), SUMIFS('Detailed Receipts'!$K:$K, 'Detailed Receipts'!$A:$A, MID($B13, 12, 100), 'Detailed Receipts'!$D:$D, "Mar", 'Detailed Receipts'!$L:$L, "OPEX")) -> 0 | E13: =C13-D13 -> 48000
B14: Subtotal - Aftersales | C14: =SUM(C13) -> 48000 | D14: =IF($A14<>"", SUMIFS('Detailed Receipts'!$K:$K, 'Detailed Receipts'!$A:$A, $A14, 'Detailed Receipts'!$B:$B, $B14, 'Detailed Receipts'!$D:$D, "Mar", 'Detailed Receipts'!$L:$L, "OPEX"), SUMIFS('Detailed Receipts'!$K:$K, 'Detailed Receipts'!$A:$A, MID($B14, 12, 100), 'Detailed Receipts'!$D:$D, "Mar", 'Detailed Receipts'!$L:$L, "OPEX")) -> 0 | E14: =C14-D14 -> 48000
A15: Product | B15: Homologation & Registration | C15: =SUMIFS(ApprovedBudget!G19:G125,ApprovedBudget!$A$19:$A$125,"Product",ApprovedBudget!$B$19:$B$125,"Homologation & Registration") -> 0 | D15: =IF($A15<>"", SUMIFS('Detailed Receipts'!$K:$K, 'Detailed Receipts'!$A:$A, $A15, 'Detailed Receipts'!$B:$B, $B15, 'Detailed Receipts'!$D:$D, "Mar", 'Detailed Receipts'!$L:$L, "OPEX"), SUMIFS('Detailed Receipts'!$K:$K, 'Detailed Receipts'!$A:$A, MID($B15, 12, 100), 'Detailed Receipts'!$D:$D, "Mar", 'Detailed Receipts'!$L:$L, "OPEX")) -> 45474 | E15: =C15-D15 -> -45474
A16: Product | B16: R&D | C16: =SUMIFS(ApprovedBudget!G19:G125,ApprovedBudget!$A$19:$A$125,"Product",ApprovedBudget!$B$19:$B$125,"R&D") -> 115000 | D16: =IF($A16<>"", SUMIFS('Detailed Receipts'!$K:$K, 'Detailed Receipts'!$A:$A, $A16, 'Detailed Receipts'!$B:$B, $B16, 'Detailed Receipts'!$D:$D, "Mar", 'Detailed Receipts'!$L:$L, "OPEX"), SUMIFS('Detailed Receipts'!$K:$K, 'Detailed Receipts'!$A:$A, MID($B16, 12, 100), 'Detailed Receipts'!$D:$D, "Mar", 'Detailed Receipts'!$L:$L, "OPEX")) -> 0 | E16: =C16-D16 -> 115000
B17: Subtotal - Product | C17: =SUM(C15:C16) -> 115000 | D17: =IF($A17<>"", SUMIFS('Detailed Receipts'!$K:$K, 'Detailed Receipts'!$A:$A, $A17, 'Detailed Receipts'!$B:$B, $B17, 'Detailed Receipts'!$D:$D, "Mar", 'Detailed Receipts'!$L:$L, "OPEX"), SUMIFS('Detailed Receipts'!$K:$K, 'Detailed Receipts'!$A:$A, MID($B17, 12, 100), 'Detailed Receipts'!$D:$D, "Mar", 'Detailed Receipts'!$L:$L, "OPEX")) -> 45474 | E17: =C17-D17 -> 69526
A18: RideBox | B18: Billing & Admin | C18: =SUMIFS(ApprovedBudget!G19:G125,ApprovedBudget!$A$19:$A$125,"RideBox",ApprovedBudget!$B$19:$B$125,"RideBox") -> 0 | D18: =IF($A18<>"", SUMIFS('Detailed Receipts'!$K:$K, 'Detailed Receipts'!$A:$A, $A18, 'Detailed Receipts'!$B:$B, $B18, 'Detailed Receipts'!$D:$D, "Mar", 'Detailed Receipts'!$L:$L, "OPEX"), SUMIFS('Detailed Receipts'!$K:$K, 'Detailed Receipts'!$A:$A, MID($B18, 12, 100), 'Detailed Receipts'!$D:$D, "Mar", 'Detailed Receipts'!$L:$L, "OPEX")) -> 0 | E18: =C18-D18 -> 0
A19: RideBox | B19: Monitoring & Field Ops | C19: =SUMIFS(ApprovedBudget!G19:G125,ApprovedBudget!$A$19:$A$125,"RideBox",ApprovedBudget!$B$19:$B$125,"Monitoring & Field Ops") -> 0 | D19: =IF($A19<>"", SUMIFS('Detailed Receipts'!$K:$K, 'Detailed Receipts'!$A:$A, $A19, 'Detailed Receipts'!$B:$B, $B19, 'Detailed Receipts'!$D:$D, "Mar", 'Detailed Receipts'!$L:$L, "OPEX"), SUMIFS('Detailed Receipts'!$K:$K, 'Detailed Receipts'!$A:$A, MID($B19, 12, 100), 'Detailed Receipts'!$D:$D, "Mar", 'Detailed Receipts'!$L:$L, "OPEX")) -> 0 | E19: =C19-D19 -> 0
A20: RideBox | B20: Network Rollout | C20: =SUMIFS(ApprovedBudget!G19:G125,ApprovedBudget!$A$19:$A$125,"RideBox",ApprovedBudget!$B$19:$B$125,"Network Rollout") -> 0 | D20: =IF($A20<>"", SUMIFS('Detailed Receipts'!$K:$K, 'Detailed Receipts'!$A:$A, $A20, 'Detailed Receipts'!$B:$B, $B20, 'Detailed Receipts'!$D:$D, "Mar", 'Detailed Receipts'!$L:$L, "OPEX"), SUMIFS('Detailed Receipts'!$K:$K, 'Detailed Receipts'!$A:$A, MID($B20, 12, 100), 'Detailed Receipts'!$D:$D, "Mar", 'Detailed Receipts'!$L:$L, "OPEX")) -> 428 | E20: =C20-D20 -> -428
A21: RideBox | B21: Service Center | C21: =SUMIFS(ApprovedBudget!G19:G125,ApprovedBudget!$A$19:$A$125,"RideBox",ApprovedBudget!$B$19:$B$125,"Service Center") -> 0 | D21: =IF($A21<>"", SUMIFS('Detailed Receipts'!$K:$K, 'Detailed Receipts'!$A:$A, $A21, 'Detailed Receipts'!$B:$B, $B21, 'Detailed Receipts'!$D:$D, "Mar", 'Detailed Receipts'!$L:$L, "OPEX"), SUMIFS('Detailed Receipts'!$K:$K, 'Detailed Receipts'!$A:$A, MID($B21, 12, 100), 'Detailed Receipts'!$D:$D, "Mar", 'Detailed Receipts'!$L:$L, "OPEX")) -> 0 | E21: =C21-D21 -> 0
B22: Subtotal - RideBox | C22: =SUM(C18:C21) -> 0 | D22: =IF($A22<>"", SUMIFS('Detailed Receipts'!$K:$K, 'Detailed Receipts'!$A:$A, $A22, 'Detailed Receipts'!$B:$B, $B22, 'Detailed Receipts'!$D:$D, "Mar", 'Detailed Receipts'!$L:$L, "OPEX"), SUMIFS('Detailed Receipts'!$K:$K, 'Detailed Receipts'!$A:$A, MID($B22, 12, 100), 'Detailed Receipts'!$D:$D, "Mar", 'Detailed Receipts'!$L:$L, "OPEX")) -> 428 | E22: =C22-D22 -> -428
A23: Technology | B23: Technology | C23: =SUMIFS(ApprovedBudget!G19:G125,ApprovedBudget!$A$19:$A$125,"Technology") -> 0 | D23: =IF($A23<>"", SUMIFS('Detailed Receipts'!$K:$K, 'Detailed Receipts'!$A:$A, $A23, 'Detailed Receipts'!$B:$B, $B23, 'Detailed Receipts'!$D:$D, "Mar", 'Detailed Receipts'!$L:$L, "OPEX"), SUMIFS('Detailed Receipts'!$K:$K, 'Detailed Receipts'!$A:$A, MID($B23, 12, 100), 'Detailed Receipts'!$D:$D, "Mar", 'Detailed Receipts'!$L:$L, "OPEX")) -> 306279 | E23: =C23-D23 -> -306279
B24: Subtotal - Technology | C24: =SUM(C23) -> 0 | D24: =IF($A24<>"", SUMIFS('Detailed Receipts'!$K:$K, 'Detailed Receipts'!$A:$A, $A24, 'Detailed Receipts'!$B:$B, $B24, 'Detailed Receipts'!$D:$D, "Mar", 'Detailed Receipts'!$L:$L, "OPEX"), SUMIFS('Detailed Receipts'!$K:$K, 'Detailed Receipts'!$A:$A, MID($B24, 12, 100), 'Detailed Receipts'!$D:$D, "Mar", 'Detailed Receipts'!$L:$L, "OPEX")) -> 306279 | E24: =C24-D24 -> -306279
A25: Finance and Accounting | B25: Finance and Accounting | C25: =SUMIFS(ApprovedBudget!G19:G125,ApprovedBudget!$A$19:$A$125,"Finance and Accounting",ApprovedBudget!$B$19:$B$125,"Finance and Accounting") -> 46472 | D25: =IF($A25<>"", SUMIFS('Detailed Receipts'!$K:$K, 'Detailed Receipts'!$A:$A, $A25, 'Detailed Receipts'!$B:$B, $B25, 'Detailed Receipts'!$D:$D, "Mar", 'Detailed Receipts'!$L:$L, "OPEX"), SUMIFS('Detailed Receipts'!$K:$K, 'Detailed Receipts'!$A:$A, MID($B25, 12, 100), 'Detailed Receipts'!$D:$D, "Mar", 'Detailed Receipts'!$L:$L, "OPEX")) -> 208789 | E25: =C25-D25 -> -162317
B26: Subtotal - Finance and Accounting | C26: =SUM(C25) -> 46472 | D26: =IF($A26<>"", SUMIFS('Detailed Receipts'!$K:$K, 'Detailed Receipts'!$A:$A, $A26, 'Detailed Receipts'!$B:$B, $B26, 'Detailed Receipts'!$D:$D, "Mar", 'Detailed Receipts'!$L:$L, "OPEX"), SUMIFS('Detailed Receipts'!$K:$K, 'Detailed Receipts'!$A:$A, MID($B26, 12, 100), 'Detailed Receipts'!$D:$D, "Mar", 'Detailed Receipts'!$L:$L, "OPEX")) -> 208789 | E26: =C26-D26 -> -162317
A27: Admin | B27: Admin | C27: =SUMIFS(ApprovedBudget!G19:G125,ApprovedBudget!$A$19:$A$125,"Admin",ApprovedBudget!$B$19:$B$125,"Admin") -> 580893 | D27: =IF($A27<>"", SUMIFS('Detailed Receipts'!$K:$K, 'Detailed Receipts'!$A:$A, $A27, 'Detailed Receipts'!$B:$B, $B27, 'Detailed Receipts'!$D:$D, "Mar", 'Detailed Receipts'!$L:$L, "OPEX"), SUMIFS('Detailed Receipts'!$K:$K, 'Detailed Receipts'!$A:$A, MID($B27, 12, 100), 'Detailed Receipts'!$D:$D, "Mar", 'Detailed Receipts'!$L:$L, "OPEX")) -> 308755 | E27: =C27-D27 -> 272138
B28: Subtotal - Admin | C28: =SUM(C27) -> 580893 | D28: =IF($A28<>"", SUMIFS('Detailed Receipts'!$K:$K, 'Detailed Receipts'!$A:$A, $A28, 'Detailed Receipts'!$B:$B, $B28, 'Detailed Receipts'!$D:$D, "Mar", 'Detailed Receipts'!$L:$L, "OPEX"), SUMIFS('Detailed Receipts'!$K:$K, 'Detailed Receipts'!$A:$A, MID($B28, 12, 100), 'Detailed Receipts'!$D:$D, "Mar", 'Detailed Receipts'!$L:$L, "OPEX")) -> 308755 | E28: =C28-D28 -> 272138
A29: HR | B29: HR | C29: =SUMIFS(ApprovedBudget!G19:G125,ApprovedBudget!$A$19:$A$125,"HR",ApprovedBudget!$B$19:$B$125,"HR") -> 0 | D29: =IF($A29<>"", SUMIFS('Detailed Receipts'!$K:$K, 'Detailed Receipts'!$A:$A, $A29, 'Detailed Receipts'!$B:$B, $B29, 'Detailed Receipts'!$D:$D, "Mar", 'Detailed Receipts'!$L:$L, "OPEX"), SUMIFS('Detailed Receipts'!$K:$K, 'Detailed Receipts'!$A:$A, MID($B29, 12, 100), 'Detailed Receipts'!$D:$D, "Mar", 'Detailed Receipts'!$L:$L, "OPEX")) -> 166185 | E29: =C29-D29 -> -166185
B30: Subtotal - HR | C30: =SUM(C29) -> 0 | D30: =IF($A30<>"", SUMIFS('Detailed Receipts'!$K:$K, 'Detailed Receipts'!$A:$A, $A30, 'Detailed Receipts'!$B:$B, $B30, 'Detailed Receipts'!$D:$D, "Mar", 'Detailed Receipts'!$L:$L, "OPEX"), SUMIFS('Detailed Receipts'!$K:$K, 'Detailed Receipts'!$A:$A, MID($B30, 12, 100), 'Detailed Receipts'!$D:$D, "Mar", 'Detailed Receipts'!$L:$L, "OPEX")) -> 166185 | E30: =C30-D30 -> -166185
A31: Compliance and Risk | B31: Legal & notarial | C31: =SUMIFS(ApprovedBudget!G19:G125,ApprovedBudget!$A$19:$A$125,"Compliance and Risk",ApprovedBudget!$B$19:$B$125,"Legal & notarial") -> 60000 | D31: =IF($A31<>"", SUMIFS('Detailed Receipts'!$K:$K, 'Detailed Receipts'!$A:$A, $A31, 'Detailed Receipts'!$B:$B, $B31, 'Detailed Receipts'!$D:$D, "Mar", 'Detailed Receipts'!$L:$L, "OPEX"), SUMIFS('Detailed Receipts'!$K:$K, 'Detailed Receipts'!$A:$A, MID($B31, 12, 100), 'Detailed Receipts'!$D:$D, "Mar", 'Detailed Receipts'!$L:$L, "OPEX")) -> 0 | E31: =C31-D31 -> 60000
A32: Compliance and Risk | B32: Permits & registration | C32: =SUMIFS(ApprovedBudget!G19:G125,ApprovedBudget!$A$19:$A$125,"Compliance and Risk",ApprovedBudget!$B$19:$B$125,"Permits & registration") -> 66800 | D32: =IF($A32<>"", SUMIFS('Detailed Receipts'!$K:$K, 'Detailed Receipts'!$A:$A, $A32, 'Detailed Receipts'!$B:$B, $B32, 'Detailed Receipts'!$D:$D, "Mar", 'Detailed Receipts'!$L:$L, "OPEX"), SUMIFS('Detailed Receipts'!$K:$K, 'Detailed Receipts'!$A:$A, MID($B32, 12, 100), 'Detailed Receipts'!$D:$D, "Mar", 'Detailed Receipts'!$L:$L, "OPEX")) -> 0 | E32: =C32-D32 -> 66800
B33: Subtotal - Compliance and Risk | C33: =SUM(C31:C32) -> 126800 | D33: =IF($A33<>"", SUMIFS('Detailed Receipts'!$K:$K, 'Detailed Receipts'!$A:$A, $A33, 'Detailed Receipts'!$B:$B, $B33, 'Detailed Receipts'!$D:$D, "Mar", 'Detailed Receipts'!$L:$L, "OPEX"), SUMIFS('Detailed Receipts'!$K:$K, 'Detailed Receipts'!$A:$A, MID($B33, 12, 100), 'Detailed Receipts'!$D:$D, "Mar", 'Detailed Receipts'!$L:$L, "OPEX")) -> 0 | E33: =C33-D33 -> 126800
B34: TOTAL OPEX | C34: =SUMIF($B4:$B33,"Subtotal*",C4:C33) -> 2008196 | D34: =SUMIF($B4:$B33,"Subtotal*",D4:D33) -> 1458759 | E34: =C34-D34 -> 549437

Sheet Apr Budget vs Actual
A1: Apr Budget vs Actual - Non-payroll OPEX by Department / Cost Center (PHP)
A3: Department | B3: Cost Center | C3: Budget | D3: Actual | E3: Variance
A4: Sales and Marketing | B4: Sales | C4: =SUMIFS(ApprovedBudget!H19:H125,ApprovedBudget!$A$19:$A$125,"Sales and Marketing") -> 517840 | D4: =IF($A4<>"", SUMIFS('Detailed Receipts'!$K:$K, 'Detailed Receipts'!$A:$A, $A4, 'Detailed Receipts'!$B:$B, $B4, 'Detailed Receipts'!$D:$D, "Apr", 'Detailed Receipts'!$L:$L, "OPEX"), SUMIFS('Detailed Receipts'!$K:$K, 'Detailed Receipts'!$A:$A, MID($B4, 12, 100), 'Detailed Receipts'!$D:$D, "Apr", 'Detailed Receipts'!$L:$L, "OPEX")) -> 6332 | E4: =C4-D4 -> 511508
B5: Subtotal - Sales and Marketing | C5: =SUM(C4) -> 517840 | D5: =IF($A5<>"", SUMIFS('Detailed Receipts'!$K:$K, 'Detailed Receipts'!$A:$A, $A5, 'Detailed Receipts'!$B:$B, $B5, 'Detailed Receipts'!$D:$D, "Apr", 'Detailed Receipts'!$L:$L, "OPEX"), SUMIFS('Detailed Receipts'!$K:$K, 'Detailed Receipts'!$A:$A, MID($B5, 12, 100), 'Detailed Receipts'!$D:$D, "Apr", 'Detailed Receipts'!$L:$L, "OPEX")) -> 6332 | E5: =C5-D5 -> 511508
A6: Customer Success | B6: Customer Success | C6: =SUMIFS(ApprovedBudget!H19:H125,ApprovedBudget!$A$19:$A$125,"Customer Success",ApprovedBudget!$B$19:$B$125,"Customer Success") -> 67500 | D6: =IF($A6<>"", SUMIFS('Detailed Receipts'!$K:$K, 'Detailed Receipts'!$A:$A, $A6, 'Detailed Receipts'!$B:$B, $B6, 'Detailed Receipts'!$D:$D, "Apr", 'Detailed Receipts'!$L:$L, "OPEX"), SUMIFS('Detailed Receipts'!$K:$K, 'Detailed Receipts'!$A:$A, MID($B6, 12, 100), 'Detailed Receipts'!$D:$D, "Apr", 'Detailed Receipts'!$L:$L, "OPEX")) -> 0 | E6: =C6-D6 -> 67500
B7: Subtotal - Customer Success | C7: =SUM(C6) -> 67500 | D7: =IF($A7<>"", SUMIFS('Detailed Receipts'!$K:$K, 'Detailed Receipts'!$A:$A, $A7, 'Detailed Receipts'!$B:$B, $B7, 'Detailed Receipts'!$D:$D, "Apr", 'Detailed Receipts'!$L:$L, "OPEX"), SUMIFS('Detailed Receipts'!$K:$K, 'Detailed Receipts'!$A:$A, MID($B7, 12, 100), 'Detailed Receipts'!$D:$D, "Apr", 'Detailed Receipts'!$L:$L, "OPEX")) -> 0 | E7: =C7-D7 -> 67500
A8: Supply Chain | B8: Logistics | C8: =SUMIFS(ApprovedBudget!H19:H125,ApprovedBudget!$A$19:$A$125,"Supply Chain",ApprovedBudget!$B$19:$B$125,"Logistics") -> 13722 | D8: =IF($A8<>"", SUMIFS('Detailed Receipts'!$K:$K, 'Detailed Receipts'!$A:$A, $A8, 'Detailed Receipts'!$B:$B, $B8, 'Detailed Receipts'!$D:$D, "Apr", 'Detailed Receipts'!$L:$L, "OPEX"), SUMIFS('Detailed Receipts'!$K:$K, 'Detailed Receipts'!$A:$A, MID($B8, 12, 100), 'Detailed Receipts'!$D:$D, "Apr", 'Detailed Receipts'!$L:$L, "OPEX")) -> 52998 | E8: =C8-D8 -> -39276
A9: Supply Chain | B9: Procurement | C9: =SUMIFS(ApprovedBudget!H19:H125,ApprovedBudget!$A$19:$A$125,"Supply Chain",ApprovedBudget!$B$19:$B$125,"Procurement") -> 7411 | D9: =IF($A9<>"", SUMIFS('Detailed Receipts'!$K:$K, 'Detailed Receipts'!$A:$A, $A9, 'Detailed Receipts'!$B:$B, $B9, 'Detailed Receipts'!$D:$D, "Apr", 'Detailed Receipts'!$L:$L, "OPEX"), SUMIFS('Detailed Receipts'!$K:$K, 'Detailed Receipts'!$A:$A, MID($B9, 12, 100), 'Detailed Receipts'!$D:$D, "Apr", 'Detailed Receipts'!$L:$L, "OPEX")) -> 1000 | E9: =C9-D9 -> 6411
A10: Supply Chain | B10: Retail | C10: =SUMIFS(ApprovedBudget!H19:H125,ApprovedBudget!$A$19:$A$125,"Supply Chain",ApprovedBudget!$B$19:$B$125,"Retail") -> 125000 | D10: =IF($A10<>"", SUMIFS('Detailed Receipts'!$K:$K, 'Detailed Receipts'!$A:$A, $A10, 'Detailed Receipts'!$B:$B, $B10, 'Detailed Receipts'!$D:$D, "Apr", 'Detailed Receipts'!$L:$L, "OPEX"), SUMIFS('Detailed Receipts'!$K:$K, 'Detailed Receipts'!$A:$A, MID($B10, 12, 100), 'Detailed Receipts'!$D:$D, "Apr", 'Detailed Receipts'!$L:$L, "OPEX")) -> 1050 | E10: =C10-D10 -> 123950
A11: Supply Chain | B11: Warehouse | C11: =SUMIFS(ApprovedBudget!H19:H125,ApprovedBudget!$A$19:$A$125,"Supply Chain",ApprovedBudget!$B$19:$B$125,"Warehouse") -> 437629 | D11: =IF($A11<>"", SUMIFS('Detailed Receipts'!$K:$K, 'Detailed Receipts'!$A:$A, $A11, 'Detailed Receipts'!$B:$B, $B11, 'Detailed Receipts'!$D:$D, "Apr", 'Detailed Receipts'!$L:$L, "OPEX"), SUMIFS('Detailed Receipts'!$K:$K, 'Detailed Receipts'!$A:$A, MID($B11, 12, 100), 'Detailed Receipts'!$D:$D, "Apr", 'Detailed Receipts'!$L:$L, "OPEX")) -> 290878 | E11: =C11-D11 -> 146751
B12: Subtotal - Supply Chain | C12: =SUM(C8:C11) -> 583762 | D12: =IF($A12<>"", SUMIFS('Detailed Receipts'!$K:$K, 'Detailed Receipts'!$A:$A, $A12, 'Detailed Receipts'!$B:$B, $B12, 'Detailed Receipts'!$D:$D, "Apr", 'Detailed Receipts'!$L:$L, "OPEX"), SUMIFS('Detailed Receipts'!$K:$K, 'Detailed Receipts'!$A:$A, MID($B12, 12, 100), 'Detailed Receipts'!$D:$D, "Apr", 'Detailed Receipts'!$L:$L, "OPEX")) -> 345926 | E12: =C12-D12 -> 237836
A13: Aftersales | B13: Aftersales | C13: =SUMIFS(ApprovedBudget!H19:H125,ApprovedBudget!$A$19:$A$125,"Aftersales",ApprovedBudget!$B$19:$B$125,"Aftersales") -> 60000 | D13: =IF($A13<>"", SUMIFS('Detailed Receipts'!$K:$K, 'Detailed Receipts'!$A:$A, $A13, 'Detailed Receipts'!$B:$B, $B13, 'Detailed Receipts'!$D:$D, "Apr", 'Detailed Receipts'!$L:$L, "OPEX"), SUMIFS('Detailed Receipts'!$K:$K, 'Detailed Receipts'!$A:$A, MID($B13, 12, 100), 'Detailed Receipts'!$D:$D, "Apr", 'Detailed Receipts'!$L:$L, "OPEX")) -> 0 | E13: =C13-D13 -> 60000
B14: Subtotal - Aftersales | C14: =SUM(C13) -> 60000 | D14: =IF($A14<>"", SUMIFS('Detailed Receipts'!$K:$K, 'Detailed Receipts'!$A:$A, $A14, 'Detailed Receipts'!$B:$B, $B14, 'Detailed Receipts'!$D:$D, "Apr", 'Detailed Receipts'!$L:$L, "OPEX"), SUMIFS('Detailed Receipts'!$K:$K, 'Detailed Receipts'!$A:$A, MID($B14, 12, 100), 'Detailed Receipts'!$D:$D, "Apr", 'Detailed Receipts'!$L:$L, "OPEX")) -> 0 | E14: =C14-D14 -> 60000
A15: Product | B15: Homologation & Registration | C15: =SUMIFS(ApprovedBudget!H19:H125,ApprovedBudget!$A$19:$A$125,"Product",ApprovedBudget!$B$19:$B$125,"Homologation & Registration") -> 0 | D15: =IF($A15<>"", SUMIFS('Detailed Receipts'!$K:$K, 'Detailed Receipts'!$A:$A, $A15, 'Detailed Receipts'!$B:$B, $B15, 'Detailed Receipts'!$D:$D, "Apr", 'Detailed Receipts'!$L:$L, "OPEX"), SUMIFS('Detailed Receipts'!$K:$K, 'Detailed Receipts'!$A:$A, MID($B15, 12, 100), 'Detailed Receipts'!$D:$D, "Apr", 'Detailed Receipts'!$L:$L, "OPEX")) -> 0 | E15: =C15-D15 -> 0
A16: Product | B16: R&D | C16: =SUMIFS(ApprovedBudget!H19:H125,ApprovedBudget!$A$19:$A$125,"Product",ApprovedBudget!$B$19:$B$125,"R&D") -> 15000 | D16: =IF($A16<>"", SUMIFS('Detailed Receipts'!$K:$K, 'Detailed Receipts'!$A:$A, $A16, 'Detailed Receipts'!$B:$B, $B16, 'Detailed Receipts'!$D:$D, "Apr", 'Detailed Receipts'!$L:$L, "OPEX"), SUMIFS('Detailed Receipts'!$K:$K, 'Detailed Receipts'!$A:$A, MID($B16, 12, 100), 'Detailed Receipts'!$D:$D, "Apr", 'Detailed Receipts'!$L:$L, "OPEX")) -> 0 | E16: =C16-D16 -> 15000
B17: Subtotal - Product | C17: =SUM(C15:C16) -> 15000 | D17: =IF($A17<>"", SUMIFS('Detailed Receipts'!$K:$K, 'Detailed Receipts'!$A:$A, $A17, 'Detailed Receipts'!$B:$B, $B17, 'Detailed Receipts'!$D:$D, "Apr", 'Detailed Receipts'!$L:$L, "OPEX"), SUMIFS('Detailed Receipts'!$K:$K, 'Detailed Receipts'!$A:$A, MID($B17, 12, 100), 'Detailed Receipts'!$D:$D, "Apr", 'Detailed Receipts'!$L:$L, "OPEX")) -> 0 | E17: =C17-D17 -> 15000
A18: RideBox | B18: Billing & Admin | C18: =SUMIFS(ApprovedBudget!H19:H125,ApprovedBudget!$A$19:$A$125,"RideBox",ApprovedBudget!$B$19:$B$125,"RideBox") -> 2300 | D18: =IF($A18<>"", SUMIFS('Detailed Receipts'!$K:$K, 'Detailed Receipts'!$A:$A, $A18, 'Detailed Receipts'!$B:$B, $B18, 'Detailed Receipts'!$D:$D, "Apr", 'Detailed Receipts'!$L:$L, "OPEX"), SUMIFS('Detailed Receipts'!$K:$K, 'Detailed Receipts'!$A:$A, MID($B18, 12, 100), 'Detailed Receipts'!$D:$D, "Apr", 'Detailed Receipts'!$L:$L, "OPEX")) -> 0 | E18: =C18-D18 -> 2300
A19: RideBox | B19: Monitoring & Field Ops | C19: =SUMIFS(ApprovedBudget!H19:H125,ApprovedBudget!$A$19:$A$125,"RideBox",ApprovedBudget!$B$19:$B$125,"Monitoring & Field Ops") -> 37000 | D19: =IF($A19<>"", SUMIFS('Detailed Receipts'!$K:$K, 'Detailed Receipts'!$A:$A, $A19, 'Detailed Receipts'!$B:$B, $B19, 'Detailed Receipts'!$D:$D, "Apr", 'Detailed Receipts'!$L:$L, "OPEX"), SUMIFS('Detailed Receipts'!$K:$K, 'Detailed Receipts'!$A:$A, MID($B19, 12, 100), 'Detailed Receipts'!$D:$D, "Apr", 'Detailed Receipts'!$L:$L, "OPEX")) -> 0 | E19: =C19-D19 -> 37000
A20: RideBox | B20: Network Rollout | C20: =SUMIFS(ApprovedBudget!H19:H125,ApprovedBudget!$A$19:$A$125,"RideBox",ApprovedBudget!$B$19:$B$125,"Network Rollout") -> 185000 | D20: =IF($A20<>"", SUMIFS('Detailed Receipts'!$K:$K, 'Detailed Receipts'!$A:$A, $A20, 'Detailed Receipts'!$B:$B, $B20, 'Detailed Receipts'!$D:$D, "Apr", 'Detailed Receipts'!$L:$L, "OPEX"), SUMIFS('Detailed Receipts'!$K:$K, 'Detailed Receipts'!$A:$A, MID($B20, 12, 100), 'Detailed Receipts'!$D:$D, "Apr", 'Detailed Receipts'!$L:$L, "OPEX")) -> 148367 | E20: =C20-D20 -> 36633
A21: RideBox | B21: Service Center | C21: =SUMIFS(ApprovedBudget!H19:H125,ApprovedBudget!$A$19:$A$125,"RideBox",ApprovedBudget!$B$19:$B$125,"Service Center") -> 0 | D21: =IF($A21<>"", SUMIFS('Detailed Receipts'!$K:$K, 'Detailed Receipts'!$A:$A, $A21, 'Detailed Receipts'!$B:$B, $B21, 'Detailed Receipts'!$D:$D, "Apr", 'Detailed Receipts'!$L:$L, "OPEX"), SUMIFS('Detailed Receipts'!$K:$K, 'Detailed Receipts'!$A:$A, MID($B21, 12, 100), 'Detailed Receipts'!$D:$D, "Apr", 'Detailed Receipts'!$L:$L, "OPEX")) -> 0 | E21: =C21-D21 -> 0
B22: Subtotal - RideBox | C22: =SUM(C18:C21) -> 224300 | D22: =IF($A22<>"", SUMIFS('Detailed Receipts'!$K:$K, 'Detailed Receipts'!$A:$A, $A22, 'Detailed Receipts'!$B:$B, $B22, 'Detailed Receipts'!$D:$D, "Apr", 'Detailed Receipts'!$L:$L, "OPEX"), SUMIFS('Detailed Receipts'!$K:$K, 'Detailed Receipts'!$A:$A, MID($B22, 12, 100), 'Detailed Receipts'!$D:$D, "Apr", 'Detailed Receipts'!$L:$L, "OPEX")) -> 148367 | E22: =C22-D22 -> 75933
A23: Technology | B23: Technology | C23: =SUMIFS(ApprovedBudget!H19:H125,ApprovedBudget!$A$19:$A$125,"Technology") -> 251864 | D23: =IF($A23<>"", SUMIFS('Detailed Receipts'!$K:$K, 'Detailed Receipts'!$A:$A, $A23, 'Detailed Receipts'!$B:$B, $B23, 'Detailed Receipts'!$D:$D, "Apr", 'Detailed Receipts'!$L:$L, "OPEX"), SUMIFS('Detailed Receipts'!$K:$K, 'Detailed Receipts'!$A:$A, MID($B23, 12, 100), 'Detailed Receipts'!$D:$D, "Apr", 'Detailed Receipts'!$L:$L, "OPEX")) -> 3542 | E23: =C23-D23 -> 248322
B24: Subtotal - Technology | C24: =SUM(C23) -> 251864 | D24: =IF($A24<>"", SUMIFS('Detailed Receipts'!$K:$K, 'Detailed Receipts'!$A:$A, $A24, 'Detailed Receipts'!$B:$B, $B24, 'Detailed Receipts'!$D:$D, "Apr", 'Detailed Receipts'!$L:$L, "OPEX"), SUMIFS('Detailed Receipts'!$K:$K, 'Detailed Receipts'!$A:$A, MID($B24, 12, 100), 'Detailed Receipts'!$D:$D, "Apr", 'Detailed Receipts'!$L:$L, "OPEX")) -> 3542 | E24: =C24-D24 -> 248322
A25: Finance and Accounting | B25: Finance and Accounting | C25: =SUMIFS(ApprovedBudget!H19:H125,ApprovedBudget!$A$19:$A$125,"Finance and Accounting",ApprovedBudget!$B$19:$B$125,"Finance and Accounting") -> 42526 | D25: =IF($A25<>"", SUMIFS('Detailed Receipts'!$K:$K, 'Detailed Receipts'!$A:$A, $A25, 'Detailed Receipts'!$B:$B, $B25, 'Detailed Receipts'!$D:$D, "Apr", 'Detailed Receipts'!$L:$L, "OPEX"), SUMIFS('Detailed Receipts'!$K:$K, 'Detailed Receipts'!$A:$A, MID($B25, 12, 100), 'Detailed Receipts'!$D:$D, "Apr", 'Detailed Receipts'!$L:$L, "OPEX")) -> 57419 | E25: =C25-D25 -> -14893
B26: Subtotal - Finance and Accounting | C26: =SUM(C25) -> 42526 | D26: =IF($A26<>"", SUMIFS('Detailed Receipts'!$K:$K, 'Detailed Receipts'!$A:$A, $A26, 'Detailed Receipts'!$B:$B, $B26, 'Detailed Receipts'!$D:$D, "Apr", 'Detailed Receipts'!$L:$L, "OPEX"), SUMIFS('Detailed Receipts'!$K:$K, 'Detailed Receipts'!$A:$A, MID($B26, 12, 100), 'Detailed Receipts'!$D:$D, "Apr", 'Detailed Receipts'!$L:$L, "OPEX")) -> 57419 | E26: =C26-D26 -> -14893
A27: Admin | B27: Admin | C27: =SUMIFS(ApprovedBudget!H19:H125,ApprovedBudget!$A$19:$A$125,"Admin",ApprovedBudget!$B$19:$B$125,"Admin") -> 580893 | D27: =IF($A27<>"", SUMIFS('Detailed Receipts'!$K:$K, 'Detailed Receipts'!$A:$A, $A27, 'Detailed Receipts'!$B:$B, $B27, 'Detailed Receipts'!$D:$D, "Apr", 'Detailed Receipts'!$L:$L, "OPEX"), SUMIFS('Detailed Receipts'!$K:$K, 'Detailed Receipts'!$A:$A, MID($B27, 12, 100), 'Detailed Receipts'!$D:$D, "Apr", 'Detailed Receipts'!$L:$L, "OPEX")) -> 682822 | E27: =C27-D27 -> -101929
B28: Subtotal - Admin | C28: =SUM(C27) -> 580893 | D28: =IF($A28<>"", SUMIFS('Detailed Receipts'!$K:$K, 'Detailed Receipts'!$A:$A, $A28, 'Detailed Receipts'!$B:$B, $B28, 'Detailed Receipts'!$D:$D, "Apr", 'Detailed Receipts'!$L:$L, "OPEX"), SUMIFS('Detailed Receipts'!$K:$K, 'Detailed Receipts'!$A:$A, MID($B28, 12, 100), 'Detailed Receipts'!$D:$D, "Apr", 'Detailed Receipts'!$L:$L, "OPEX")) -> 682822 | E28: =C28-D28 -> -101929
A29: HR | B29: HR | C29: =SUMIFS(ApprovedBudget!H19:H125,ApprovedBudget!$A$19:$A$125,"HR",ApprovedBudget!$B$19:$B$125,"HR") -> 215000 | D29: =IF($A29<>"", SUMIFS('Detailed Receipts'!$K:$K, 'Detailed Receipts'!$A:$A, $A29, 'Detailed Receipts'!$B:$B, $B29, 'Detailed Receipts'!$D:$D, "Apr", 'Detailed Receipts'!$L:$L, "OPEX"), SUMIFS('Detailed Receipts'!$K:$K, 'Detailed Receipts'!$A:$A, MID($B29, 12, 100), 'Detailed Receipts'!$D:$D, "Apr", 'Detailed Receipts'!$L:$L, "OPEX")) -> 164621 | E29: =C29-D29 -> 50379
B30: Subtotal - HR | C30: =SUM(C29) -> 215000 | D30: =IF($A30<>"", SUMIFS('Detailed Receipts'!$K:$K, 'Detailed Receipts'!$A:$A, $A30, 'Detailed Receipts'!$B:$B, $B30, 'Detailed Receipts'!$D:$D, "Apr", 'Detailed Receipts'!$L:$L, "OPEX"), SUMIFS('Detailed Receipts'!$K:$K, 'Detailed Receipts'!$A:$A, MID($B30, 12, 100), 'Detailed Receipts'!$D:$D, "Apr", 'Detailed Receipts'!$L:$L, "OPEX")) -> 164621 | E30: =C30-D30 -> 50379
A31: Compliance and Risk | B31: Legal & notarial | C31: =SUMIFS(ApprovedBudget!H19:H125,ApprovedBudget!$A$19:$A$125,"Compliance and Risk",ApprovedBudget!$B$19:$B$125,"Legal & notarial") -> 60000 | D31: =IF($A31<>"", SUMIFS('Detailed Receipts'!$K:$K, 'Detailed Receipts'!$A:$A, $A31, 'Detailed Receipts'!$B:$B, $B31, 'Detailed Receipts'!$D:$D, "Apr", 'Detailed Receipts'!$L:$L, "OPEX"), SUMIFS('Detailed Receipts'!$K:$K, 'Detailed Receipts'!$A:$A, MID($B31, 12, 100), 'Detailed Receipts'!$D:$D, "Apr", 'Detailed Receipts'!$L:$L, "OPEX")) -> 47012 | E31: =C31-D31 -> 12988
A32: Compliance and Risk | B32: Permits & registration | C32: =SUMIFS(ApprovedBudget!H19:H125,ApprovedBudget!$A$19:$A$125,"Compliance and Risk",ApprovedBudget!$B$19:$B$125,"Permits & registration") -> 86800 | D32: =IF($A32<>"", SUMIFS('Detailed Receipts'!$K:$K, 'Detailed Receipts'!$A:$A, $A32, 'Detailed Receipts'!$B:$B, $B32, 'Detailed Receipts'!$D:$D, "Apr", 'Detailed Receipts'!$L:$L, "OPEX"), SUMIFS('Detailed Receipts'!$K:$K, 'Detailed Receipts'!$A:$A, MID($B32, 12, 100), 'Detailed Receipts'!$D:$D, "Apr", 'Detailed Receipts'!$L:$L, "OPEX")) -> 597 | E32: =C32-D32 -> 86203
B33: Subtotal - Compliance and Risk | C33: =SUM(C31:C32) -> 146800 | D33: =IF($A33<>"", SUMIFS('Detailed Receipts'!$K:$K, 'Detailed Receipts'!$A:$A, $A33, 'Detailed Receipts'!$B:$B, $B33, 'Detailed Receipts'!$D:$D, "Apr", 'Detailed Receipts'!$L:$L, "OPEX"), SUMIFS('Detailed Receipts'!$K:$K, 'Detailed Receipts'!$A:$A, MID($B33, 12, 100), 'Detailed Receipts'!$D:$D, "Apr", 'Detailed Receipts'!$L:$L, "OPEX")) -> 47609 | E33: =C33-D33 -> 99191
B34: TOTAL OPEX | C34: =SUMIF($B4:$B33,"Subtotal*",C4:C33) -> 2705485 | D34: =SUMIF($B4:$B33,"Subtotal*",D4:D33) -> 1456638 | E34: =C34-D34 -> 1248847

Sheet May Budget vs Actual
A1: May Budget vs Actual - Non-payroll OPEX by Department / Cost Center (PHP)
A3: Department | B3: Cost Center | C3: Budget | D3: Actual | E3: Variance
A4: Sales and Marketing | B4: Sales | C4: =SUMIFS(ApprovedBudget!I19:I125,ApprovedBudget!$A$19:$A$125,"Sales and Marketing") -> 774340 | D4: =IF($A4<>"", SUMIFS('Detailed Receipts'!$K:$K, 'Detailed Receipts'!$A:$A, $A4, 'Detailed Receipts'!$B:$B, $B4, 'Detailed Receipts'!$D:$D, "May", 'Detailed Receipts'!$L:$L, "OPEX"), SUMIFS('Detailed Receipts'!$K:$K, 'Detailed Receipts'!$A:$A, MID($B4, 12, 100), 'Detailed Receipts'!$D:$D, "May", 'Detailed Receipts'!$L:$L, "OPEX")) -> 7845 | E4: =C4-D4 -> 766495
B5: Subtotal - Sales and Marketing | C5: =SUM(C4) -> 774340 | D5: =IF($A5<>"", SUMIFS('Detailed Receipts'!$K:$K, 'Detailed Receipts'!$A:$A, $A5, 'Detailed Receipts'!$B:$B, $B5, 'Detailed Receipts'!$D:$D, "May", 'Detailed Receipts'!$L:$L, "OPEX"), SUMIFS('Detailed Receipts'!$K:$K, 'Detailed Receipts'!$A:$A, MID($B5, 12, 100), 'Detailed Receipts'!$D:$D, "May", 'Detailed Receipts'!$L:$L, "OPEX")) -> 7845 | E5: =C5-D5 -> 766495
A6: Customer Success | B6: Customer Success | C6: =SUMIFS(ApprovedBudget!I19:I125,ApprovedBudget!$A$19:$A$125,"Customer Success",ApprovedBudget!$B$19:$B$125,"Customer Success") -> 67500 | D6: =IF($A6<>"", SUMIFS('Detailed Receipts'!$K:$K, 'Detailed Receipts'!$A:$A, $A6, 'Detailed Receipts'!$B:$B, $B6, 'Detailed Receipts'!$D:$D, "May", 'Detailed Receipts'!$L:$L, "OPEX"), SUMIFS('Detailed Receipts'!$K:$K, 'Detailed Receipts'!$A:$A, MID($B6, 12, 100), 'Detailed Receipts'!$D:$D, "May", 'Detailed Receipts'!$L:$L, "OPEX")) -> 0 | E6: =C6-D6 -> 67500
B7: Subtotal - Customer Success | C7: =SUM(C6) -> 67500 | D7: =IF($A7<>"", SUMIFS('Detailed Receipts'!$K:$K, 'Detailed Receipts'!$A:$A, $A7, 'Detailed Receipts'!$B:$B, $B7, 'Detailed Receipts'!$D:$D, "May", 'Detailed Receipts'!$L:$L, "OPEX"), SUMIFS('Detailed Receipts'!$K:$K, 'Detailed Receipts'!$A:$A, MID($B7, 12, 100), 'Detailed Receipts'!$D:$D, "May", 'Detailed Receipts'!$L:$L, "OPEX")) -> 0 | E7: =C7-D7 -> 67500
A8: Supply Chain | B8: Logistics | C8: =SUMIFS(ApprovedBudget!I19:I125,ApprovedBudget!$A$19:$A$125,"Supply Chain",ApprovedBudget!$B$19:$B$125,"Logistics") -> 41166 | D8: =IF($A8<>"", SUMIFS('Detailed Receipts'!$K:$K, 'Detailed Receipts'!$A:$A, $A8, 'Detailed Receipts'!$B:$B, $B8, 'Detailed Receipts'!$D:$D, "May", 'Detailed Receipts'!$L:$L, "OPEX"), SUMIFS('Detailed Receipts'!$K:$K, 'Detailed Receipts'!$A:$A, MID($B8, 12, 100), 'Detailed Receipts'!$D:$D, "May", 'Detailed Receipts'!$L:$L, "OPEX")) -> 48244 | E8: =C8-D8 -> -7078
A9: Supply Chain | B9: Procurement | C9: =SUMIFS(ApprovedBudget!I19:I125,ApprovedBudget!$A$19:$A$125,"Supply Chain",ApprovedBudget!$B$19:$B$125,"Procurement") -> 7855 | D9: =IF($A9<>"", SUMIFS('Detailed Receipts'!$K:$K, 'Detailed Receipts'!$A:$A, $A9, 'Detailed Receipts'!$B:$B, $B9, 'Detailed Receipts'!$D:$D, "May", 'Detailed Receipts'!$L:$L, "OPEX"), SUMIFS('Detailed Receipts'!$K:$K, 'Detailed Receipts'!$A:$A, MID($B9, 12, 100), 'Detailed Receipts'!$D:$D, "May", 'Detailed Receipts'!$L:$L, "OPEX")) -> 0 | E9: =C9-D9 -> 7855
A10: Supply Chain | B10: Retail | C10: =SUMIFS(ApprovedBudget!I19:I125,ApprovedBudget!$A$19:$A$125,"Supply Chain",ApprovedBudget!$B$19:$B$125,"Retail") -> 125000 | D10: =IF($A10<>"", SUMIFS('Detailed Receipts'!$K:$K, 'Detailed Receipts'!$A:$A, $A10, 'Detailed Receipts'!$B:$B, $B10, 'Detailed Receipts'!$D:$D, "May", 'Detailed Receipts'!$L:$L, "OPEX"), SUMIFS('Detailed Receipts'!$K:$K, 'Detailed Receipts'!$A:$A, MID($B10, 12, 100), 'Detailed Receipts'!$D:$D, "May", 'Detailed Receipts'!$L:$L, "OPEX")) -> 0 | E10: =C10-D10 -> 125000
A11: Supply Chain | B11: Warehouse | C11: =SUMIFS(ApprovedBudget!I19:I125,ApprovedBudget!$A$19:$A$125,"Supply Chain",ApprovedBudget!$B$19:$B$125,"Warehouse") -> 1312896 | D11: =IF($A11<>"", SUMIFS('Detailed Receipts'!$K:$K, 'Detailed Receipts'!$A:$A, $A11, 'Detailed Receipts'!$B:$B, $B11, 'Detailed Receipts'!$D:$D, "May", 'Detailed Receipts'!$L:$L, "OPEX"), SUMIFS('Detailed Receipts'!$K:$K, 'Detailed Receipts'!$A:$A, MID($B11, 12, 100), 'Detailed Receipts'!$D:$D, "May", 'Detailed Receipts'!$L:$L, "OPEX")) -> 22586 | E11: =C11-D11 -> 1290310
B12: Subtotal - Supply Chain | C12: =SUM(C8:C11) -> 1486917 | D12: =IF($A12<>"", SUMIFS('Detailed Receipts'!$K:$K, 'Detailed Receipts'!$A:$A, $A12, 'Detailed Receipts'!$B:$B, $B12, 'Detailed Receipts'!$D:$D, "May", 'Detailed Receipts'!$L:$L, "OPEX"), SUMIFS('Detailed Receipts'!$K:$K, 'Detailed Receipts'!$A:$A, MID($B12, 12, 100), 'Detailed Receipts'!$D:$D, "May", 'Detailed Receipts'!$L:$L, "OPEX")) -> 70830 | E12: =C12-D12 -> 1416087
A13: Aftersales | B13: Aftersales | C13: =SUMIFS(ApprovedBudget!I19:I125,ApprovedBudget!$A$19:$A$125,"Aftersales",ApprovedBudget!$B$19:$B$125,"Aftersales") -> 81000 | D13: =IF($A13<>"", SUMIFS('Detailed Receipts'!$K:$K, 'Detailed Receipts'!$A:$A, $A13, 'Detailed Receipts'!$B:$B, $B13, 'Detailed Receipts'!$D:$D, "May", 'Detailed Receipts'!$L:$L, "OPEX"), SUMIFS('Detailed Receipts'!$K:$K, 'Detailed Receipts'!$A:$A, MID($B13, 12, 100), 'Detailed Receipts'!$D:$D, "May", 'Detailed Receipts'!$L:$L, "OPEX")) -> 0 | E13: =C13-D13 -> 81000
B14: Subtotal - Aftersales | C14: =SUM(C13) -> 81000 | D14: =IF($A14<>"", SUMIFS('Detailed Receipts'!$K:$K, 'Detailed Receipts'!$A:$A, $A14, 'Detailed Receipts'!$B:$B, $B14, 'Detailed Receipts'!$D:$D, "May", 'Detailed Receipts'!$L:$L, "OPEX"), SUMIFS('Detailed Receipts'!$K:$K, 'Detailed Receipts'!$A:$A, MID($B14, 12, 100), 'Detailed Receipts'!$D:$D, "May", 'Detailed Receipts'!$L:$L, "OPEX")) -> 0 | E14: =C14-D14 -> 81000
A15: Product | B15: Homologation & Registration | C15: =SUMIFS(ApprovedBudget!I19:I125,ApprovedBudget!$A$19:$A$125,"Product",ApprovedBudget!$B$19:$B$125,"Homologation & Registration") -> 0 | D15: =IF($A15<>"", SUMIFS('Detailed Receipts'!$K:$K, 'Detailed Receipts'!$A:$A, $A15, 'Detailed Receipts'!$B:$B, $B15, 'Detailed Receipts'!$D:$D, "May", 'Detailed Receipts'!$L:$L, "OPEX"), SUMIFS('Detailed Receipts'!$K:$K, 'Detailed Receipts'!$A:$A, MID($B15, 12, 100), 'Detailed Receipts'!$D:$D, "May", 'Detailed Receipts'!$L:$L, "OPEX")) -> 108959 | E15: =C15-D15 -> -108959
A16: Product | B16: R&D | C16: =SUMIFS(ApprovedBudget!I19:I125,ApprovedBudget!$A$19:$A$125,"Product",ApprovedBudget!$B$19:$B$125,"R&D") -> 15000 | D16: =IF($A16<>"", SUMIFS('Detailed Receipts'!$K:$K, 'Detailed Receipts'!$A:$A, $A16, 'Detailed Receipts'!$B:$B, $B16, 'Detailed Receipts'!$D:$D, "May", 'Detailed Receipts'!$L:$L, "OPEX"), SUMIFS('Detailed Receipts'!$K:$K, 'Detailed Receipts'!$A:$A, MID($B16, 12, 100), 'Detailed Receipts'!$D:$D, "May", 'Detailed Receipts'!$L:$L, "OPEX")) -> 0 | E16: =C16-D16 -> 15000
B17: Subtotal - Product | C17: =SUM(C15:C16) -> 15000 | D17: =IF($A17<>"", SUMIFS('Detailed Receipts'!$K:$K, 'Detailed Receipts'!$A:$A, $A17, 'Detailed Receipts'!$B:$B, $B17, 'Detailed Receipts'!$D:$D, "May", 'Detailed Receipts'!$L:$L, "OPEX"), SUMIFS('Detailed Receipts'!$K:$K, 'Detailed Receipts'!$A:$A, MID($B17, 12, 100), 'Detailed Receipts'!$D:$D, "May", 'Detailed Receipts'!$L:$L, "OPEX")) -> 108959 | E17: =C17-D17 -> -93959
A18: RideBox | B18: Billing & Admin | C18: =SUMIFS(ApprovedBudget!I19:I125,ApprovedBudget!$A$19:$A$125,"RideBox",ApprovedBudget!$B$19:$B$125,"RideBox") -> 16560 | D18: =IF($A18<>"", SUMIFS('Detailed Receipts'!$K:$K, 'Detailed Receipts'!$A:$A, $A18, 'Detailed Receipts'!$B:$B, $B18, 'Detailed Receipts'!$D:$D, "May", 'Detailed Receipts'!$L:$L, "OPEX"), SUMIFS('Detailed Receipts'!$K:$K, 'Detailed Receipts'!$A:$A, MID($B18, 12, 100), 'Detailed Receipts'!$D:$D, "May", 'Detailed Receipts'!$L:$L, "OPEX")) -> 0 | E18: =C18-D18 -> 16560
A19: RideBox | B19: Monitoring & Field Ops | C19: =SUMIFS(ApprovedBudget!I19:I125,ApprovedBudget!$A$19:$A$125,"RideBox",ApprovedBudget!$B$19:$B$125,"Monitoring & Field Ops") -> 68000 | D19: =IF($A19<>"", SUMIFS('Detailed Receipts'!$K:$K, 'Detailed Receipts'!$A:$A, $A19, 'Detailed Receipts'!$B:$B, $B19, 'Detailed Receipts'!$D:$D, "May", 'Detailed Receipts'!$L:$L, "OPEX"), SUMIFS('Detailed Receipts'!$K:$K, 'Detailed Receipts'!$A:$A, MID($B19, 12, 100), 'Detailed Receipts'!$D:$D, "May", 'Detailed Receipts'!$L:$L, "OPEX")) -> 120527 | E19: =C19-D19 -> -52527
A20: RideBox | B20: Network Rollout | C20: =SUMIFS(ApprovedBudget!I19:I125,ApprovedBudget!$A$19:$A$125,"RideBox",ApprovedBudget!$B$19:$B$125,"Network Rollout") -> 340000 | D20: =IF($A20<>"", SUMIFS('Detailed Receipts'!$K:$K, 'Detailed Receipts'!$A:$A, $A20, 'Detailed Receipts'!$B:$B, $B20, 'Detailed Receipts'!$D:$D, "May", 'Detailed Receipts'!$L:$L, "OPEX"), SUMIFS('Detailed Receipts'!$K:$K, 'Detailed Receipts'!$A:$A, MID($B20, 12, 100), 'Detailed Receipts'!$D:$D, "May", 'Detailed Receipts'!$L:$L, "OPEX")) -> 25157 | E20: =C20-D20 -> 314843
A21: RideBox | B21: Service Center | C21: =SUMIFS(ApprovedBudget!I19:I125,ApprovedBudget!$A$19:$A$125,"RideBox",ApprovedBudget!$B$19:$B$125,"Service Center") -> 0 | D21: =IF($A21<>"", SUMIFS('Detailed Receipts'!$K:$K, 'Detailed Receipts'!$A:$A, $A21, 'Detailed Receipts'!$B:$B, $B21, 'Detailed Receipts'!$D:$D, "May", 'Detailed Receipts'!$L:$L, "OPEX"), SUMIFS('Detailed Receipts'!$K:$K, 'Detailed Receipts'!$A:$A, MID($B21, 12, 100), 'Detailed Receipts'!$D:$D, "May", 'Detailed Receipts'!$L:$L, "OPEX")) -> 12964 | E21: =C21-D21 -> -12964
B22: Subtotal - RideBox | C22: =SUM(C18:C21) -> 424560 | D22: =IF($A22<>"", SUMIFS('Detailed Receipts'!$K:$K, 'Detailed Receipts'!$A:$A, $A22, 'Detailed Receipts'!$B:$B, $B22, 'Detailed Receipts'!$D:$D, "May", 'Detailed Receipts'!$L:$L, "OPEX"), SUMIFS('Detailed Receipts'!$K:$K, 'Detailed Receipts'!$A:$A, MID($B22, 12, 100), 'Detailed Receipts'!$D:$D, "May", 'Detailed Receipts'!$L:$L, "OPEX")) -> 158648 | E22: =C22-D22 -> 265912
A23: Technology | B23: Technology | C23: =SUMIFS(ApprovedBudget!I19:I125,ApprovedBudget!$A$19:$A$125,"Technology") -> 251864 | D23: =IF($A23<>"", SUMIFS('Detailed Receipts'!$K:$K, 'Detailed Receipts'!$A:$A, $A23, 'Detailed Receipts'!$B:$B, $B23, 'Detailed Receipts'!$D:$D, "May", 'Detailed Receipts'!$L:$L, "OPEX"), SUMIFS('Detailed Receipts'!$K:$K, 'Detailed Receipts'!$A:$A, MID($B23, 12, 100), 'Detailed Receipts'!$D:$D, "May", 'Detailed Receipts'!$L:$L, "OPEX")) -> 63674 | E23: =C23-D23 -> 188190
B24: Subtotal - Technology | C24: =SUM(C23) -> 251864 | D24: =IF($A24<>"", SUMIFS('Detailed Receipts'!$K:$K, 'Detailed Receipts'!$A:$A, $A24, 'Detailed Receipts'!$B:$B, $B24, 'Detailed Receipts'!$D:$D, "May", 'Detailed Receipts'!$L:$L, "OPEX"), SUMIFS('Detailed Receipts'!$K:$K, 'Detailed Receipts'!$A:$A, MID($B24, 12, 100), 'Detailed Receipts'!$D:$D, "May", 'Detailed Receipts'!$L:$L, "OPEX")) -> 63674 | E24: =C24-D24 -> 188190
A25: Finance and Accounting | B25: Finance and Accounting | C25: =SUMIFS(ApprovedBudget!I19:I125,ApprovedBudget!$A$19:$A$125,"Finance and Accounting",ApprovedBudget!$B$19:$B$125,"Finance and Accounting") -> 92526 | D25: =IF($A25<>"", SUMIFS('Detailed Receipts'!$K:$K, 'Detailed Receipts'!$A:$A, $A25, 'Detailed Receipts'!$B:$B, $B25, 'Detailed Receipts'!$D:$D, "May", 'Detailed Receipts'!$L:$L, "OPEX"), SUMIFS('Detailed Receipts'!$K:$K, 'Detailed Receipts'!$A:$A, MID($B25, 12, 100), 'Detailed Receipts'!$D:$D, "May", 'Detailed Receipts'!$L:$L, "OPEX")) -> 0 | E25: =C25-D25 -> 92526
B26: Subtotal - Finance and Accounting | C26: =SUM(C25) -> 92526 | D26: =IF($A26<>"", SUMIFS('Detailed Receipts'!$K:$K, 'Detailed Receipts'!$A:$A, $A26, 'Detailed Receipts'!$B:$B, $B26, 'Detailed Receipts'!$D:$D, "May", 'Detailed Receipts'!$L:$L, "OPEX"), SUMIFS('Detailed Receipts'!$K:$K, 'Detailed Receipts'!$A:$A, MID($B26, 12, 100), 'Detailed Receipts'!$D:$D, "May", 'Detailed Receipts'!$L:$L, "OPEX")) -> 0 | E26: =C26-D26 -> 92526
A27: Admin | B27: Admin | C27: =SUMIFS(ApprovedBudget!I19:I125,ApprovedBudget!$A$19:$A$125,"Admin",ApprovedBudget!$B$19:$B$125,"Admin") -> 588771 | D27: =IF($A27<>"", SUMIFS('Detailed Receipts'!$K:$K, 'Detailed Receipts'!$A:$A, $A27, 'Detailed Receipts'!$B:$B, $B27, 'Detailed Receipts'!$D:$D, "May", 'Detailed Receipts'!$L:$L, "OPEX"), SUMIFS('Detailed Receipts'!$K:$K, 'Detailed Receipts'!$A:$A, MID($B27, 12, 100), 'Detailed Receipts'!$D:$D, "May", 'Detailed Receipts'!$L:$L, "OPEX")) -> 48040 | E27: =C27-D27 -> 540731
B28: Subtotal - Admin | C28: =SUM(C27) -> 588771 | D28: =IF($A28<>"", SUMIFS('Detailed Receipts'!$K:$K, 'Detailed Receipts'!$A:$A, $A28, 'Detailed Receipts'!$B:$B, $B28, 'Detailed Receipts'!$D:$D, "May", 'Detailed Receipts'!$L:$L, "OPEX"), SUMIFS('Detailed Receipts'!$K:$K, 'Detailed Receipts'!$A:$A, MID($B28, 12, 100), 'Detailed Receipts'!$D:$D, "May", 'Detailed Receipts'!$L:$L, "OPEX")) -> 48040 | E28: =C28-D28 -> 540731
A29: HR | B29: HR | C29: =SUMIFS(ApprovedBudget!I19:I125,ApprovedBudget!$A$19:$A$125,"HR",ApprovedBudget!$B$19:$B$125,"HR") -> 235000 | D29: =IF($A29<>"", SUMIFS('Detailed Receipts'!$K:$K, 'Detailed Receipts'!$A:$A, $A29, 'Detailed Receipts'!$B:$B, $B29, 'Detailed Receipts'!$D:$D, "May", 'Detailed Receipts'!$L:$L, "OPEX"), SUMIFS('Detailed Receipts'!$K:$K, 'Detailed Receipts'!$A:$A, MID($B29, 12, 100), 'Detailed Receipts'!$D:$D, "May", 'Detailed Receipts'!$L:$L, "OPEX")) -> 233388 | E29: =C29-D29 -> 1612
B30: Subtotal - HR | C30: =SUM(C29) -> 235000 | D30: =IF($A30<>"", SUMIFS('Detailed Receipts'!$K:$K, 'Detailed Receipts'!$A:$A, $A30, 'Detailed Receipts'!$B:$B, $B30, 'Detailed Receipts'!$D:$D, "May", 'Detailed Receipts'!$L:$L, "OPEX"), SUMIFS('Detailed Receipts'!$K:$K, 'Detailed Receipts'!$A:$A, MID($B30, 12, 100), 'Detailed Receipts'!$D:$D, "May", 'Detailed Receipts'!$L:$L, "OPEX")) -> 233388 | E30: =C30-D30 -> 1612
A31: Compliance and Risk | B31: Legal & notarial | C31: =SUMIFS(ApprovedBudget!I19:I125,ApprovedBudget!$A$19:$A$125,"Compliance and Risk",ApprovedBudget!$B$19:$B$125,"Legal & notarial") -> 560000 | D31: =IF($A31<>"", SUMIFS('Detailed Receipts'!$K:$K, 'Detailed Receipts'!$A:$A, $A31, 'Detailed Receipts'!$B:$B, $B31, 'Detailed Receipts'!$D:$D, "May", 'Detailed Receipts'!$L:$L, "OPEX"), SUMIFS('Detailed Receipts'!$K:$K, 'Detailed Receipts'!$A:$A, MID($B31, 12, 100), 'Detailed Receipts'!$D:$D, "May", 'Detailed Receipts'!$L:$L, "OPEX")) -> 134395 | E31: =C31-D31 -> 425605
A32: Compliance and Risk | B32: Permits & registration | C32: =SUMIFS(ApprovedBudget!I19:I125,ApprovedBudget!$A$19:$A$125,"Compliance and Risk",ApprovedBudget!$B$19:$B$125,"Permits & registration") -> 86800 | D32: =IF($A32<>"", SUMIFS('Detailed Receipts'!$K:$K, 'Detailed Receipts'!$A:$A, $A32, 'Detailed Receipts'!$B:$B, $B32, 'Detailed Receipts'!$D:$D, "May", 'Detailed Receipts'!$L:$L, "OPEX"), SUMIFS('Detailed Receipts'!$K:$K, 'Detailed Receipts'!$A:$A, MID($B32, 12, 100), 'Detailed Receipts'!$D:$D, "May", 'Detailed Receipts'!$L:$L, "OPEX")) -> 107881 | E32: =C32-D32 -> -21081
B33: Subtotal - Compliance and Risk | C33: =SUM(C31:C32) -> 646800 | D33: =IF($A33<>"", SUMIFS('Detailed Receipts'!$K:$K, 'Detailed Receipts'!$A:$A, $A33, 'Detailed Receipts'!$B:$B, $B33, 'Detailed Receipts'!$D:$D, "May", 'Detailed Receipts'!$L:$L, "OPEX"), SUMIFS('Detailed Receipts'!$K:$K, 'Detailed Receipts'!$A:$A, MID($B33, 12, 100), 'Detailed Receipts'!$D:$D, "May", 'Detailed Receipts'!$L:$L, "OPEX")) -> 242276 | E33: =C33-D33 -> 404524
B34: TOTAL OPEX | C34: =SUMIF($B4:$B33,"Subtotal*",C4:C33) -> 4664278 | D34: =SUMIF($B4:$B33,"Subtotal*",D4:D33) -> 933660 | E34: =C34-D34 -> 3730618

Sheet June Budget vs Actual
A1: June Budget vs Actual - Non-payroll OPEX by Department / Cost Center (PHP)
A3: Department | B3: Cost Center | C3: Budget | D3: Actual | E3: Variance
A4: Sales and Marketing | B4: Sales | C4: =SUMIFS(ApprovedBudget!J19:J125,ApprovedBudget!$A$19:$A$125,"Sales and Marketing") -> 732340 | D4: =IF($A4<>"", SUMIFS('Detailed Receipts'!$K:$K, 'Detailed Receipts'!$A:$A, $A4, 'Detailed Receipts'!$B:$B, $B4, 'Detailed Receipts'!$D:$D, "Jun", 'Detailed Receipts'!$L:$L, "OPEX"), SUMIFS('Detailed Receipts'!$K:$K, 'Detailed Receipts'!$A:$A, MID($B4, 12, 100), 'Detailed Receipts'!$D:$D, "Jun", 'Detailed Receipts'!$L:$L, "OPEX")) -> 0 | E4: =C4-D4 -> 732340
B5: Subtotal - Sales and Marketing | C5: =SUM(C4) -> 732340 | D5: =IF($A5<>"", SUMIFS('Detailed Receipts'!$K:$K, 'Detailed Receipts'!$A:$A, $A5, 'Detailed Receipts'!$B:$B, $B5, 'Detailed Receipts'!$D:$D, "Jun", 'Detailed Receipts'!$L:$L, "OPEX"), SUMIFS('Detailed Receipts'!$K:$K, 'Detailed Receipts'!$A:$A, MID($B5, 12, 100), 'Detailed Receipts'!$D:$D, "Jun", 'Detailed Receipts'!$L:$L, "OPEX")) -> 0 | E5: =C5-D5 -> 732340
A6: Customer Success | B6: Customer Success | C6: =SUMIFS(ApprovedBudget!J19:J125,ApprovedBudget!$A$19:$A$125,"Customer Success",ApprovedBudget!$B$19:$B$125,"Customer Success") -> 67500 | D6: =IF($A6<>"", SUMIFS('Detailed Receipts'!$K:$K, 'Detailed Receipts'!$A:$A, $A6, 'Detailed Receipts'!$B:$B, $B6, 'Detailed Receipts'!$D:$D, "Jun", 'Detailed Receipts'!$L:$L, "OPEX"), SUMIFS('Detailed Receipts'!$K:$K, 'Detailed Receipts'!$A:$A, MID($B6, 12, 100), 'Detailed Receipts'!$D:$D, "Jun", 'Detailed Receipts'!$L:$L, "OPEX")) -> 0 | E6: =C6-D6 -> 67500
B7: Subtotal - Customer Success | C7: =SUM(C6) -> 67500 | D7: =IF($A7<>"", SUMIFS('Detailed Receipts'!$K:$K, 'Detailed Receipts'!$A:$A, $A7, 'Detailed Receipts'!$B:$B, $B7, 'Detailed Receipts'!$D:$D, "Jun", 'Detailed Receipts'!$L:$L, "OPEX"), SUMIFS('Detailed Receipts'!$K:$K, 'Detailed Receipts'!$A:$A, MID($B7, 12, 100), 'Detailed Receipts'!$D:$D, "Jun", 'Detailed Receipts'!$L:$L, "OPEX")) -> 0 | E7: =C7-D7 -> 67500
A8: Supply Chain | B8: Logistics | C8: =SUMIFS(ApprovedBudget!J19:J125,ApprovedBudget!$A$19:$A$125,"Supply Chain",ApprovedBudget!$B$19:$B$125,"Logistics") -> 41166 | D8: =IF($A8<>"", SUMIFS('Detailed Receipts'!$K:$K, 'Detailed Receipts'!$A:$A, $A8, 'Detailed Receipts'!$B:$B, $B8, 'Detailed Receipts'!$D:$D, "Jun", 'Detailed Receipts'!$L:$L, "OPEX"), SUMIFS('Detailed Receipts'!$K:$K, 'Detailed Receipts'!$A:$A, MID($B8, 12, 100), 'Detailed Receipts'!$D:$D, "Jun", 'Detailed Receipts'!$L:$L, "OPEX")) -> 0 | E8: =C8-D8 -> 41166
A9: Supply Chain | B9: Procurement | C9: =SUMIFS(ApprovedBudget!J19:J125,ApprovedBudget!$A$19:$A$125,"Supply Chain",ApprovedBudget!$B$19:$B$125,"Procurement") -> 7983 | D9: =IF($A9<>"", SUMIFS('Detailed Receipts'!$K:$K, 'Detailed Receipts'!$A:$A, $A9, 'Detailed Receipts'!$B:$B, $B9, 'Detailed Receipts'!$D:$D, "Jun", 'Detailed Receipts'!$L:$L, "OPEX"), SUMIFS('Detailed Receipts'!$K:$K, 'Detailed Receipts'!$A:$A, MID($B9, 12, 100), 'Detailed Receipts'!$D:$D, "Jun", 'Detailed Receipts'!$L:$L, "OPEX")) -> 0 | E9: =C9-D9 -> 7983
A10: Supply Chain | B10: Retail | C10: =SUMIFS(ApprovedBudget!J19:J125,ApprovedBudget!$A$19:$A$125,"Supply Chain",ApprovedBudget!$B$19:$B$125,"Retail") -> 125000 | D10: =IF($A10<>"", SUMIFS('Detailed Receipts'!$K:$K, 'Detailed Receipts'!$A:$A, $A10, 'Detailed Receipts'!$B:$B, $B10, 'Detailed Receipts'!$D:$D, "Jun", 'Detailed Receipts'!$L:$L, "OPEX"), SUMIFS('Detailed Receipts'!$K:$K, 'Detailed Receipts'!$A:$A, MID($B10, 12, 100), 'Detailed Receipts'!$D:$D, "Jun", 'Detailed Receipts'!$L:$L, "OPEX")) -> 0 | E10: =C10-D10 -> 125000
A11: Supply Chain | B11: Warehouse | C11: =SUMIFS(ApprovedBudget!J19:J125,ApprovedBudget!$A$19:$A$125,"Supply Chain",ApprovedBudget!$B$19:$B$125,"Warehouse") -> 1312886 | D11: =IF($A11<>"", SUMIFS('Detailed Receipts'!$K:$K, 'Detailed Receipts'!$A:$A, $A11, 'Detailed Receipts'!$B:$B, $B11, 'Detailed Receipts'!$D:$D, "Jun", 'Detailed Receipts'!$L:$L, "OPEX"), SUMIFS('Detailed Receipts'!$K:$K, 'Detailed Receipts'!$A:$A, MID($B11, 12, 100), 'Detailed Receipts'!$D:$D, "Jun", 'Detailed Receipts'!$L:$L, "OPEX")) -> 0 | E11: =C11-D11 -> 1312886
B12: Subtotal - Supply Chain | C12: =SUM(C8:C11) -> 1487035 | D12: =IF($A12<>"", SUMIFS('Detailed Receipts'!$K:$K, 'Detailed Receipts'!$A:$A, $A12, 'Detailed Receipts'!$B:$B, $B12, 'Detailed Receipts'!$D:$D, "Jun", 'Detailed Receipts'!$L:$L, "OPEX"), SUMIFS('Detailed Receipts'!$K:$K, 'Detailed Receipts'!$A:$A, MID($B12, 12, 100), 'Detailed Receipts'!$D:$D, "Jun", 'Detailed Receipts'!$L:$L, "OPEX")) -> 0 | E12: =C12-D12 -> 1487035
A13: Aftersales | B13: Aftersales | C13: =SUMIFS(ApprovedBudget!J19:J125,ApprovedBudget!$A$19:$A$125,"Aftersales",ApprovedBudget!$B$19:$B$125,"Aftersales") -> 93000 | D13: =IF($A13<>"", SUMIFS('Detailed Receipts'!$K:$K, 'Detailed Receipts'!$A:$A, $A13, 'Detailed Receipts'!$B:$B, $B13, 'Detailed Receipts'!$D:$D, "Jun", 'Detailed Receipts'!$L:$L, "OPEX"), SUMIFS('Detailed Receipts'!$K:$K, 'Detailed Receipts'!$A:$A, MID($B13, 12, 100), 'Detailed Receipts'!$D:$D, "Jun", 'Detailed Receipts'!$L:$L, "OPEX")) -> 0 | E13: =C13-D13 -> 93000
B14: Subtotal - Aftersales | C14: =SUM(C13) -> 93000 | D14: =IF($A14<>"", SUMIFS('Detailed Receipts'!$K:$K, 'Detailed Receipts'!$A:$A, $A14, 'Detailed Receipts'!$B:$B, $B14, 'Detailed Receipts'!$D:$D, "Jun", 'Detailed Receipts'!$L:$L, "OPEX"), SUMIFS('Detailed Receipts'!$K:$K, 'Detailed Receipts'!$A:$A, MID($B14, 12, 100), 'Detailed Receipts'!$D:$D, "Jun", 'Detailed Receipts'!$L:$L, "OPEX")) -> 0 | E14: =C14-D14 -> 93000
A15: Product | B15: Homologation & Registration | C15: =SUMIFS(ApprovedBudget!J19:J125,ApprovedBudget!$A$19:$A$125,"Product",ApprovedBudget!$B$19:$B$125,"Homologation & Registration") -> 0 | D15: =IF($A15<>"", SUMIFS('Detailed Receipts'!$K:$K, 'Detailed Receipts'!$A:$A, $A15, 'Detailed Receipts'!$B:$B, $B15, 'Detailed Receipts'!$D:$D, "Jun", 'Detailed Receipts'!$L:$L, "OPEX"), SUMIFS('Detailed Receipts'!$K:$K, 'Detailed Receipts'!$A:$A, MID($B15, 12, 100), 'Detailed Receipts'!$D:$D, "Jun", 'Detailed Receipts'!$L:$L, "OPEX")) -> 0 | E15: =C15-D15 -> 0
A16: Product | B16: R&D | C16: =SUMIFS(ApprovedBudget!J19:J125,ApprovedBudget!$A$19:$A$125,"Product",ApprovedBudget!$B$19:$B$125,"R&D") -> 115000 | D16: =IF($A16<>"", SUMIFS('Detailed Receipts'!$K:$K, 'Detailed Receipts'!$A:$A, $A16, 'Detailed Receipts'!$B:$B, $B16, 'Detailed Receipts'!$D:$D, "Jun", 'Detailed Receipts'!$L:$L, "OPEX"), SUMIFS('Detailed Receipts'!$K:$K, 'Detailed Receipts'!$A:$A, MID($B16, 12, 100), 'Detailed Receipts'!$D:$D, "Jun", 'Detailed Receipts'!$L:$L, "OPEX")) -> 0 | E16: =C16-D16 -> 115000
B17: Subtotal - Product | C17: =SUM(C15:C16) -> 115000 | D17: =IF($A17<>"", SUMIFS('Detailed Receipts'!$K:$K, 'Detailed Receipts'!$A:$A, $A17, 'Detailed Receipts'!$B:$B, $B17, 'Detailed Receipts'!$D:$D, "Jun", 'Detailed Receipts'!$L:$L, "OPEX"), SUMIFS('Detailed Receipts'!$K:$K, 'Detailed Receipts'!$A:$A, MID($B17, 12, 100), 'Detailed Receipts'!$D:$D, "Jun", 'Detailed Receipts'!$L:$L, "OPEX")) -> 0 | E17: =C17-D17 -> 115000
A18: RideBox | B18: Billing & Admin | C18: =SUMIFS(ApprovedBudget!J19:J125,ApprovedBudget!$A$19:$A$125,"RideBox",ApprovedBudget!$B$19:$B$125,"RideBox") -> 20700 | D18: =IF($A18<>"", SUMIFS('Detailed Receipts'!$K:$K, 'Detailed Receipts'!$A:$A, $A18, 'Detailed Receipts'!$B:$B, $B18, 'Detailed Receipts'!$D:$D, "Jun", 'Detailed Receipts'!$L:$L, "OPEX"), SUMIFS('Detailed Receipts'!$K:$K, 'Detailed Receipts'!$A:$A, MID($B18, 12, 100), 'Detailed Receipts'!$D:$D, "Jun", 'Detailed Receipts'!$L:$L, "OPEX")) -> 0 | E18: =C18-D18 -> 20700
A19: RideBox | B19: Monitoring & Field Ops | C19: =SUMIFS(ApprovedBudget!J19:J125,ApprovedBudget!$A$19:$A$125,"RideBox",ApprovedBudget!$B$19:$B$125,"Monitoring & Field Ops") -> 85000 | D19: =IF($A19<>"", SUMIFS('Detailed Receipts'!$K:$K, 'Detailed Receipts'!$A:$A, $A19, 'Detailed Receipts'!$B:$B, $B19, 'Detailed Receipts'!$D:$D, "Jun", 'Detailed Receipts'!$L:$L, "OPEX"), SUMIFS('Detailed Receipts'!$K:$K, 'Detailed Receipts'!$A:$A, MID($B19, 12, 100), 'Detailed Receipts'!$D:$D, "Jun", 'Detailed Receipts'!$L:$L, "OPEX")) -> 0 | E19: =C19-D19 -> 85000
A20: RideBox | B20: Network Rollout | C20: =SUMIFS(ApprovedBudget!J19:J125,ApprovedBudget!$A$19:$A$125,"RideBox",ApprovedBudget!$B$19:$B$125,"Network Rollout") -> 425000 | D20: =IF($A20<>"", SUMIFS('Detailed Receipts'!$K:$K, 'Detailed Receipts'!$A:$A, $A20, 'Detailed Receipts'!$B:$B, $B20, 'Detailed Receipts'!$D:$D, "Jun", 'Detailed Receipts'!$L:$L, "OPEX"), SUMIFS('Detailed Receipts'!$K:$K, 'Detailed Receipts'!$A:$A, MID($B20, 12, 100), 'Detailed Receipts'!$D:$D, "Jun", 'Detailed Receipts'!$L:$L, "OPEX")) -> 0 | E20: =C20-D20 -> 425000
A21: RideBox | B21: Service Center | C21: =SUMIFS(ApprovedBudget!J19:J125,ApprovedBudget!$A$19:$A$125,"RideBox",ApprovedBudget!$B$19:$B$125,"Service Center") -> 0 | D21: =IF($A21<>"", SUMIFS('Detailed Receipts'!$K:$K, 'Detailed Receipts'!$A:$A, $A21, 'Detailed Receipts'!$B:$B, $B21, 'Detailed Receipts'!$D:$D, "Jun", 'Detailed Receipts'!$L:$L, "OPEX"), SUMIFS('Detailed Receipts'!$K:$K, 'Detailed Receipts'!$A:$A, MID($B21, 12, 100), 'Detailed Receipts'!$D:$D, "Jun", 'Detailed Receipts'!$L:$L, "OPEX")) -> 0 | E21: =C21-D21 -> 0
B22: Subtotal - RideBox | C22: =SUM(C18:C21) -> 530700 | D22: =IF($A22<>"", SUMIFS('Detailed Receipts'!$K:$K, 'Detailed Receipts'!$A:$A, $A22, 'Detailed Receipts'!$B:$B, $B22, 'Detailed Receipts'!$D:$D, "Jun", 'Detailed Receipts'!$L:$L, "OPEX"), SUMIFS('Detailed Receipts'!$K:$K, 'Detailed Receipts'!$A:$A, MID($B22, 12, 100), 'Detailed Receipts'!$D:$D, "Jun", 'Detailed Receipts'!$L:$L, "OPEX")) -> 0 | E22: =C22-D22 -> 530700
A23: Technology | B23: Technology | C23: =SUMIFS(ApprovedBudget!J19:J125,ApprovedBudget!$A$19:$A$125,"Technology") -> 645974 | D23: =IF($A23<>"", SUMIFS('Detailed Receipts'!$K:$K, 'Detailed Receipts'!$A:$A, $A23, 'Detailed Receipts'!$B:$B, $B23, 'Detailed Receipts'!$D:$D, "Jun", 'Detailed Receipts'!$L:$L, "OPEX"), SUMIFS('Detailed Receipts'!$K:$K, 'Detailed Receipts'!$A:$A, MID($B23, 12, 100), 'Detailed Receipts'!$D:$D, "Jun", 'Detailed Receipts'!$L:$L, "OPEX")) -> 251493 | E23: =C23-D23 -> 394481
B24: Subtotal - Technology | C24: =SUM(C23) -> 645974 | D24: =IF($A24<>"", SUMIFS('Detailed Receipts'!$K:$K, 'Detailed Receipts'!$A:$A, $A24, 'Detailed Receipts'!$B:$B, $B24, 'Detailed Receipts'!$D:$D, "Jun", 'Detailed Receipts'!$L:$L, "OPEX"), SUMIFS('Detailed Receipts'!$K:$K, 'Detailed Receipts'!$A:$A, MID($B24, 12, 100), 'Detailed Receipts'!$D:$D, "Jun", 'Detailed Receipts'!$L:$L, "OPEX")) -> 251493 | E24: =C24-D24 -> 394481
A25: Finance and Accounting | B25: Finance and Accounting | C25: =SUMIFS(ApprovedBudget!J19:J125,ApprovedBudget!$A$19:$A$125,"Finance and Accounting",ApprovedBudget!$B$19:$B$125,"Finance and Accounting") -> 92526 | D25: =IF($A25<>"", SUMIFS('Detailed Receipts'!$K:$K, 'Detailed Receipts'!$A:$A, $A25, 'Detailed Receipts'!$B:$B, $B25, 'Detailed Receipts'!$D:$D, "Jun", 'Detailed Receipts'!$L:$L, "OPEX"), SUMIFS('Detailed Receipts'!$K:$K, 'Detailed Receipts'!$A:$A, MID($B25, 12, 100), 'Detailed Receipts'!$D:$D, "Jun", 'Detailed Receipts'!$L:$L, "OPEX")) -> 0 | E25: =C25-D25 -> 92526
B26: Subtotal - Finance and Accounting | C26: =SUM(C25) -> 92526 | D26: =IF($A26<>"", SUMIFS('Detailed Receipts'!$K:$K, 'Detailed Receipts'!$A:$A, $A26, 'Detailed Receipts'!$B:$B, $B26, 'Detailed Receipts'!$D:$D, "Jun", 'Detailed Receipts'!$L:$L, "OPEX"), SUMIFS('Detailed Receipts'!$K:$K, 'Detailed Receipts'!$A:$A, MID($B26, 12, 100), 'Detailed Receipts'!$D:$D, "Jun", 'Detailed Receipts'!$L:$L, "OPEX")) -> 0 | E26: =C26-D26 -> 92526
A27: Admin | B27: Admin | C27: =SUMIFS(ApprovedBudget!J19:J125,ApprovedBudget!$A$19:$A$125,"Admin",ApprovedBudget!$B$19:$B$125,"Admin") -> 633282 | D27: =IF($A27<>"", SUMIFS('Detailed Receipts'!$K:$K, 'Detailed Receipts'!$A:$A, $A27, 'Detailed Receipts'!$B:$B, $B27, 'Detailed Receipts'!$D:$D, "Jun", 'Detailed Receipts'!$L:$L, "OPEX"), SUMIFS('Detailed Receipts'!$K:$K, 'Detailed Receipts'!$A:$A, MID($B27, 12, 100), 'Detailed Receipts'!$D:$D, "Jun", 'Detailed Receipts'!$L:$L, "OPEX")) -> 799 | E27: =C27-D27 -> 632483
B28: Subtotal - Admin | C28: =SUM(C27) -> 633282 | D28: =IF($A28<>"", SUMIFS('Detailed Receipts'!$K:$K, 'Detailed Receipts'!$A:$A, $A28, 'Detailed Receipts'!$B:$B, $B28, 'Detailed Receipts'!$D:$D, "Jun", 'Detailed Receipts'!$L:$L, "OPEX"), SUMIFS('Detailed Receipts'!$K:$K, 'Detailed Receipts'!$A:$A, MID($B28, 12, 100), 'Detailed Receipts'!$D:$D, "Jun", 'Detailed Receipts'!$L:$L, "OPEX")) -> 799 | E28: =C28-D28 -> 632483
A29: HR | B29: HR | C29: =SUMIFS(ApprovedBudget!J19:J125,ApprovedBudget!$A$19:$A$125,"HR",ApprovedBudget!$B$19:$B$125,"HR") -> 233000 | D29: =IF($A29<>"", SUMIFS('Detailed Receipts'!$K:$K, 'Detailed Receipts'!$A:$A, $A29, 'Detailed Receipts'!$B:$B, $B29, 'Detailed Receipts'!$D:$D, "Jun", 'Detailed Receipts'!$L:$L, "OPEX"), SUMIFS('Detailed Receipts'!$K:$K, 'Detailed Receipts'!$A:$A, MID($B29, 12, 100), 'Detailed Receipts'!$D:$D, "Jun", 'Detailed Receipts'!$L:$L, "OPEX")) -> 17283 | E29: =C29-D29 -> 215717
B30: Subtotal - HR | C30: =SUM(C29) -> 233000 | D30: =IF($A30<>"", SUMIFS('Detailed Receipts'!$K:$K, 'Detailed Receipts'!$A:$A, $A30, 'Detailed Receipts'!$B:$B, $B30, 'Detailed Receipts'!$D:$D, "Jun", 'Detailed Receipts'!$L:$L, "OPEX"), SUMIFS('Detailed Receipts'!$K:$K, 'Detailed Receipts'!$A:$A, MID($B30, 12, 100), 'Detailed Receipts'!$D:$D, "Jun", 'Detailed Receipts'!$L:$L, "OPEX")) -> 17283 | E30: =C30-D30 -> 215717
A31: Compliance and Risk | B31: Legal & notarial | C31: =SUMIFS(ApprovedBudget!J19:J125,ApprovedBudget!$A$19:$A$125,"Compliance and Risk",ApprovedBudget!$B$19:$B$125,"Legal & notarial") -> 60000 | D31: =IF($A31<>"", SUMIFS('Detailed Receipts'!$K:$K, 'Detailed Receipts'!$A:$A, $A31, 'Detailed Receipts'!$B:$B, $B31, 'Detailed Receipts'!$D:$D, "Jun", 'Detailed Receipts'!$L:$L, "OPEX"), SUMIFS('Detailed Receipts'!$K:$K, 'Detailed Receipts'!$A:$A, MID($B31, 12, 100), 'Detailed Receipts'!$D:$D, "Jun", 'Detailed Receipts'!$L:$L, "OPEX")) -> 26548 | E31: =C31-D31 -> 33452
A32: Compliance and Risk | B32: Permits & registration | C32: =SUMIFS(ApprovedBudget!J19:J125,ApprovedBudget!$A$19:$A$125,"Compliance and Risk",ApprovedBudget!$B$19:$B$125,"Permits & registration") -> 86800 | D32: =IF($A32<>"", SUMIFS('Detailed Receipts'!$K:$K, 'Detailed Receipts'!$A:$A, $A32, 'Detailed Receipts'!$B:$B, $B32, 'Detailed Receipts'!$D:$D, "Jun", 'Detailed Receipts'!$L:$L, "OPEX"), SUMIFS('Detailed Receipts'!$K:$K, 'Detailed Receipts'!$A:$A, MID($B32, 12, 100), 'Detailed Receipts'!$D:$D, "Jun", 'Detailed Receipts'!$L:$L, "OPEX")) -> 0 | E32: =C32-D32 -> 86800
B33: Subtotal - Compliance and Risk | C33: =SUM(C31:C32) -> 146800 | D33: =IF($A33<>"", SUMIFS('Detailed Receipts'!$K:$K, 'Detailed Receipts'!$A:$A, $A33, 'Detailed Receipts'!$B:$B, $B33, 'Detailed Receipts'!$D:$D, "Jun", 'Detailed Receipts'!$L:$L, "OPEX"), SUMIFS('Detailed Receipts'!$K:$K, 'Detailed Receipts'!$A:$A, MID($B33, 12, 100), 'Detailed Receipts'!$D:$D, "Jun", 'Detailed Receipts'!$L:$L, "OPEX")) -> 26548 | E33: =C33-D33 -> 120252
B34: TOTAL OPEX | C34: =SUMIF($B4:$B33,"Subtotal*",C4:C33) -> 4777157 | D34: =SUMIF($B4:$B33,"Subtotal*",D4:D33) -> 296123 | E34: =C34-D34 -> 4481034

Sheet July Budget vs Actual
A1: July Budget vs Actual - Non-payroll OPEX by Department / Cost Center (PHP)
A3: Department | B3: Cost Center | C3: Budget | D3: Actual | E3: Variance
A4: Sales and Marketing | B4: Sales | C4: =SUMIFS(ApprovedBudget!K19:K125,ApprovedBudget!$A$19:$A$125,"Sales and Marketing") -> 771340 | D4: =IF($A4<>"", SUMIFS('Detailed Receipts'!$K:$K, 'Detailed Receipts'!$A:$A, $A4, 'Detailed Receipts'!$B:$B, $B4, 'Detailed Receipts'!$D:$D, "Jul", 'Detailed Receipts'!$L:$L, "OPEX"), SUMIFS('Detailed Receipts'!$K:$K, 'Detailed Receipts'!$A:$A, MID($B4, 12, 100), 'Detailed Receipts'!$D:$D, "Jul", 'Detailed Receipts'!$L:$L, "OPEX")) -> 1500 | E4: =C4-D4 -> 769840
B5: Subtotal - Sales and Marketing | C5: =SUM(C4) -> 771340 | D5: =IF($A5<>"", SUMIFS('Detailed Receipts'!$K:$K, 'Detailed Receipts'!$A:$A, $A5, 'Detailed Receipts'!$B:$B, $B5, 'Detailed Receipts'!$D:$D, "Jul", 'Detailed Receipts'!$L:$L, "OPEX"), SUMIFS('Detailed Receipts'!$K:$K, 'Detailed Receipts'!$A:$A, MID($B5, 12, 100), 'Detailed Receipts'!$D:$D, "Jul", 'Detailed Receipts'!$L:$L, "OPEX")) -> 1500 | E5: =C5-D5 -> 769840
A6: Customer Success | B6: Customer Success | C6: =SUMIFS(ApprovedBudget!K19:K125,ApprovedBudget!$A$19:$A$125,"Customer Success",ApprovedBudget!$B$19:$B$125,"Customer Success") -> 67500 | D6: =IF($A6<>"", SUMIFS('Detailed Receipts'!$K:$K, 'Detailed Receipts'!$A:$A, $A6, 'Detailed Receipts'!$B:$B, $B6, 'Detailed Receipts'!$D:$D, "Jul", 'Detailed Receipts'!$L:$L, "OPEX"), SUMIFS('Detailed Receipts'!$K:$K, 'Detailed Receipts'!$A:$A, MID($B6, 12, 100), 'Detailed Receipts'!$D:$D, "Jul", 'Detailed Receipts'!$L:$L, "OPEX")) -> 0 | E6: =C6-D6 -> 67500
B7: Subtotal - Customer Success | C7: =SUM(C6) -> 67500 | D7: =IF($A7<>"", SUMIFS('Detailed Receipts'!$K:$K, 'Detailed Receipts'!$A:$A, $A7, 'Detailed Receipts'!$B:$B, $B7, 'Detailed Receipts'!$D:$D, "Jul", 'Detailed Receipts'!$L:$L, "OPEX"), SUMIFS('Detailed Receipts'!$K:$K, 'Detailed Receipts'!$A:$A, MID($B7, 12, 100), 'Detailed Receipts'!$D:$D, "Jul", 'Detailed Receipts'!$L:$L, "OPEX")) -> 0 | E7: =C7-D7 -> 67500
A8: Supply Chain | B8: Logistics | C8: =SUMIFS(ApprovedBudget!K19:K125,ApprovedBudget!$A$19:$A$125,"Supply Chain",ApprovedBudget!$B$19:$B$125,"Logistics") -> 41166 | D8: =IF($A8<>"", SUMIFS('Detailed Receipts'!$K:$K, 'Detailed Receipts'!$A:$A, $A8, 'Detailed Receipts'!$B:$B, $B8, 'Detailed Receipts'!$D:$D, "Jul", 'Detailed Receipts'!$L:$L, "OPEX"), SUMIFS('Detailed Receipts'!$K:$K, 'Detailed Receipts'!$A:$A, MID($B8, 12, 100), 'Detailed Receipts'!$D:$D, "Jul", 'Detailed Receipts'!$L:$L, "OPEX")) -> 0 | E8: =C8-D8 -> 41166
A9: Supply Chain | B9: Procurement | C9: =SUMIFS(ApprovedBudget!K19:K125,ApprovedBudget!$A$19:$A$125,"Supply Chain",ApprovedBudget!$B$19:$B$125,"Procurement") -> 8238 | D9: =IF($A9<>"", SUMIFS('Detailed Receipts'!$K:$K, 'Detailed Receipts'!$A:$A, $A9, 'Detailed Receipts'!$B:$B, $B9, 'Detailed Receipts'!$D:$D, "Jul", 'Detailed Receipts'!$L:$L, "OPEX"), SUMIFS('Detailed Receipts'!$K:$K, 'Detailed Receipts'!$A:$A, MID($B9, 12, 100), 'Detailed Receipts'!$D:$D, "Jul", 'Detailed Receipts'!$L:$L, "OPEX")) -> 0 | E9: =C9-D9 -> 8238
A10: Supply Chain | B10: Retail | C10: =SUMIFS(ApprovedBudget!K19:K125,ApprovedBudget!$A$19:$A$125,"Supply Chain",ApprovedBudget!$B$19:$B$125,"Retail") -> 125000 | D10: =IF($A10<>"", SUMIFS('Detailed Receipts'!$K:$K, 'Detailed Receipts'!$A:$A, $A10, 'Detailed Receipts'!$B:$B, $B10, 'Detailed Receipts'!$D:$D, "Jul", 'Detailed Receipts'!$L:$L, "OPEX"), SUMIFS('Detailed Receipts'!$K:$K, 'Detailed Receipts'!$A:$A, MID($B10, 12, 100), 'Detailed Receipts'!$D:$D, "Jul", 'Detailed Receipts'!$L:$L, "OPEX")) -> 0 | E10: =C10-D10 -> 125000
A11: Supply Chain | B11: Warehouse | C11: =SUMIFS(ApprovedBudget!K19:K125,ApprovedBudget!$A$19:$A$125,"Supply Chain",ApprovedBudget!$B$19:$B$125,"Warehouse") -> 1312886 | D11: =IF($A11<>"", SUMIFS('Detailed Receipts'!$K:$K, 'Detailed Receipts'!$A:$A, $A11, 'Detailed Receipts'!$B:$B, $B11, 'Detailed Receipts'!$D:$D, "Jul", 'Detailed Receipts'!$L:$L, "OPEX"), SUMIFS('Detailed Receipts'!$K:$K, 'Detailed Receipts'!$A:$A, MID($B11, 12, 100), 'Detailed Receipts'!$D:$D, "Jul", 'Detailed Receipts'!$L:$L, "OPEX")) -> 0 | E11: =C11-D11 -> 1312886
B12: Subtotal - Supply Chain | C12: =SUM(C8:C11) -> 1487290 | D12: =IF($A12<>"", SUMIFS('Detailed Receipts'!$K:$K, 'Detailed Receipts'!$A:$A, $A12, 'Detailed Receipts'!$B:$B, $B12, 'Detailed Receipts'!$D:$D, "Jul", 'Detailed Receipts'!$L:$L, "OPEX"), SUMIFS('Detailed Receipts'!$K:$K, 'Detailed Receipts'!$A:$A, MID($B12, 12, 100), 'Detailed Receipts'!$D:$D, "Jul", 'Detailed Receipts'!$L:$L, "OPEX")) -> 0 | E12: =C12-D12 -> 1487290
A13: Aftersales | B13: Aftersales | C13: =SUMIFS(ApprovedBudget!K19:K125,ApprovedBudget!$A$19:$A$125,"Aftersales",ApprovedBudget!$B$19:$B$125,"Aftersales") -> 99000 | D13: =IF($A13<>"", SUMIFS('Detailed Receipts'!$K:$K, 'Detailed Receipts'!$A:$A, $A13, 'Detailed Receipts'!$B:$B, $B13, 'Detailed Receipts'!$D:$D, "Jul", 'Detailed Receipts'!$L:$L, "OPEX"), SUMIFS('Detailed Receipts'!$K:$K, 'Detailed Receipts'!$A:$A, MID($B13, 12, 100), 'Detailed Receipts'!$D:$D, "Jul", 'Detailed Receipts'!$L:$L, "OPEX")) -> 0 | E13: =C13-D13 -> 99000
B14: Subtotal - Aftersales | C14: =SUM(C13) -> 99000 | D14: =IF($A14<>"", SUMIFS('Detailed Receipts'!$K:$K, 'Detailed Receipts'!$A:$A, $A14, 'Detailed Receipts'!$B:$B, $B14, 'Detailed Receipts'!$D:$D, "Jul", 'Detailed Receipts'!$L:$L, "OPEX"), SUMIFS('Detailed Receipts'!$K:$K, 'Detailed Receipts'!$A:$A, MID($B14, 12, 100), 'Detailed Receipts'!$D:$D, "Jul", 'Detailed Receipts'!$L:$L, "OPEX")) -> 0 | E14: =C14-D14 -> 99000
A15: Product | B15: Homologation & Registration | C15: =SUMIFS(ApprovedBudget!K19:K125,ApprovedBudget!$A$19:$A$125,"Product",ApprovedBudget!$B$19:$B$125,"Homologation & Registration") -> 0 | D15: =IF($A15<>"", SUMIFS('Detailed Receipts'!$K:$K, 'Detailed Receipts'!$A:$A, $A15, 'Detailed Receipts'!$B:$B, $B15, 'Detailed Receipts'!$D:$D, "Jul", 'Detailed Receipts'!$L:$L, "OPEX"), SUMIFS('Detailed Receipts'!$K:$K, 'Detailed Receipts'!$A:$A, MID($B15, 12, 100), 'Detailed Receipts'!$D:$D, "Jul", 'Detailed Receipts'!$L:$L, "OPEX")) -> 0 | E15: =C15-D15 -> 0
A16: Product | B16: R&D | C16: =SUMIFS(ApprovedBudget!K19:K125,ApprovedBudget!$A$19:$A$125,"Product",ApprovedBudget!$B$19:$B$125,"R&D") -> 515000 | D16: =IF($A16<>"", SUMIFS('Detailed Receipts'!$K:$K, 'Detailed Receipts'!$A:$A, $A16, 'Detailed Receipts'!$B:$B, $B16, 'Detailed Receipts'!$D:$D, "Jul", 'Detailed Receipts'!$L:$L, "OPEX"), SUMIFS('Detailed Receipts'!$K:$K, 'Detailed Receipts'!$A:$A, MID($B16, 12, 100), 'Detailed Receipts'!$D:$D, "Jul", 'Detailed Receipts'!$L:$L, "OPEX")) -> 0 | E16: =C16-D16 -> 515000
B17: Subtotal - Product | C17: =SUM(C15:C16) -> 515000 | D17: =IF($A17<>"", SUMIFS('Detailed Receipts'!$K:$K, 'Detailed Receipts'!$A:$A, $A17, 'Detailed Receipts'!$B:$B, $B17, 'Detailed Receipts'!$D:$D, "Jul", 'Detailed Receipts'!$L:$L, "OPEX"), SUMIFS('Detailed Receipts'!$K:$K, 'Detailed Receipts'!$A:$A, MID($B17, 12, 100), 'Detailed Receipts'!$D:$D, "Jul", 'Detailed Receipts'!$L:$L, "OPEX")) -> 0 | E17: =C17-D17 -> 515000
A18: RideBox | B18: Billing & Admin | C18: =SUMIFS(ApprovedBudget!K19:K125,ApprovedBudget!$A$19:$A$125,"RideBox",ApprovedBudget!$B$19:$B$125,"RideBox") -> 28877 | D18: =IF($A18<>"", SUMIFS('Detailed Receipts'!$K:$K, 'Detailed Receipts'!$A:$A, $A18, 'Detailed Receipts'!$B:$B, $B18, 'Detailed Receipts'!$D:$D, "Jul", 'Detailed Receipts'!$L:$L, "OPEX"), SUMIFS('Detailed Receipts'!$K:$K, 'Detailed Receipts'!$A:$A, MID($B18, 12, 100), 'Detailed Receipts'!$D:$D, "Jul", 'Detailed Receipts'!$L:$L, "OPEX")) -> 0 | E18: =C18-D18 -> 28877
A19: RideBox | B19: Monitoring & Field Ops | C19: =SUMIFS(ApprovedBudget!K19:K125,ApprovedBudget!$A$19:$A$125,"RideBox",ApprovedBudget!$B$19:$B$125,"Monitoring & Field Ops") -> 138510 | D19: =IF($A19<>"", SUMIFS('Detailed Receipts'!$K:$K, 'Detailed Receipts'!$A:$A, $A19, 'Detailed Receipts'!$B:$B, $B19, 'Detailed Receipts'!$D:$D, "Jul", 'Detailed Receipts'!$L:$L, "OPEX"), SUMIFS('Detailed Receipts'!$K:$K, 'Detailed Receipts'!$A:$A, MID($B19, 12, 100), 'Detailed Receipts'!$D:$D, "Jul", 'Detailed Receipts'!$L:$L, "OPEX")) -> 1050 | E19: =C19-D19 -> 137460
A20: RideBox | B20: Network Rollout | C20: =SUMIFS(ApprovedBudget!K19:K125,ApprovedBudget!$A$19:$A$125,"RideBox",ApprovedBudget!$B$19:$B$125,"Network Rollout") -> 692550 | D20: =IF($A20<>"", SUMIFS('Detailed Receipts'!$K:$K, 'Detailed Receipts'!$A:$A, $A20, 'Detailed Receipts'!$B:$B, $B20, 'Detailed Receipts'!$D:$D, "Jul", 'Detailed Receipts'!$L:$L, "OPEX"), SUMIFS('Detailed Receipts'!$K:$K, 'Detailed Receipts'!$A:$A, MID($B20, 12, 100), 'Detailed Receipts'!$D:$D, "Jul", 'Detailed Receipts'!$L:$L, "OPEX")) -> 0 | E20: =C20-D20 -> 692550
A21: RideBox | B21: Service Center | C21: =SUMIFS(ApprovedBudget!K19:K125,ApprovedBudget!$A$19:$A$125,"RideBox",ApprovedBudget!$B$19:$B$125,"Service Center") -> 0 | D21: =IF($A21<>"", SUMIFS('Detailed Receipts'!$K:$K, 'Detailed Receipts'!$A:$A, $A21, 'Detailed Receipts'!$B:$B, $B21, 'Detailed Receipts'!$D:$D, "Jul", 'Detailed Receipts'!$L:$L, "OPEX"), SUMIFS('Detailed Receipts'!$K:$K, 'Detailed Receipts'!$A:$A, MID($B21, 12, 100), 'Detailed Receipts'!$D:$D, "Jul", 'Detailed Receipts'!$L:$L, "OPEX")) -> 0 | E21: =C21-D21 -> 0
B22: Subtotal - RideBox | C22: =SUM(C18:C21) -> 859937 | D22: =IF($A22<>"", SUMIFS('Detailed Receipts'!$K:$K, 'Detailed Receipts'!$A:$A, $A22, 'Detailed Receipts'!$B:$B, $B22, 'Detailed Receipts'!$D:$D, "Jul", 'Detailed Receipts'!$L:$L, "OPEX"), SUMIFS('Detailed Receipts'!$K:$K, 'Detailed Receipts'!$A:$A, MID($B22, 12, 100), 'Detailed Receipts'!$D:$D, "Jul", 'Detailed Receipts'!$L:$L, "OPEX")) -> 1050 | E22: =C22-D22 -> 858887
A23: Technology | B23: Technology | C23: =SUMIFS(ApprovedBudget!K19:K125,ApprovedBudget!$A$19:$A$125,"Technology") -> 645974 | D23: =IF($A23<>"", SUMIFS('Detailed Receipts'!$K:$K, 'Detailed Receipts'!$A:$A, $A23, 'Detailed Receipts'!$B:$B, $B23, 'Detailed Receipts'!$D:$D, "Jul", 'Detailed Receipts'!$L:$L, "OPEX"), SUMIFS('Detailed Receipts'!$K:$K, 'Detailed Receipts'!$A:$A, MID($B23, 12, 100), 'Detailed Receipts'!$D:$D, "Jul", 'Detailed Receipts'!$L:$L, "OPEX")) -> 0 | E23: =C23-D23 -> 645974
B24: Subtotal - Technology | C24: =SUM(C23) -> 645974 | D24: =IF($A24<>"", SUMIFS('Detailed Receipts'!$K:$K, 'Detailed Receipts'!$A:$A, $A24, 'Detailed Receipts'!$B:$B, $B24, 'Detailed Receipts'!$D:$D, "Jul", 'Detailed Receipts'!$L:$L, "OPEX"), SUMIFS('Detailed Receipts'!$K:$K, 'Detailed Receipts'!$A:$A, MID($B24, 12, 100), 'Detailed Receipts'!$D:$D, "Jul", 'Detailed Receipts'!$L:$L, "OPEX")) -> 0 | E24: =C24-D24 -> 645974
A25: Finance and Accounting | B25: Finance and Accounting | C25: =SUMIFS(ApprovedBudget!K19:K125,ApprovedBudget!$A$19:$A$125,"Finance and Accounting",ApprovedBudget!$B$19:$B$125,"Finance and Accounting") -> 92526 | D25: =IF($A25<>"", SUMIFS('Detailed Receipts'!$K:$K, 'Detailed Receipts'!$A:$A, $A25, 'Detailed Receipts'!$B:$B, $B25, 'Detailed Receipts'!$D:$D, "Jul", 'Detailed Receipts'!$L:$L, "OPEX"), SUMIFS('Detailed Receipts'!$K:$K, 'Detailed Receipts'!$A:$A, MID($B25, 12, 100), 'Detailed Receipts'!$D:$D, "Jul", 'Detailed Receipts'!$L:$L, "OPEX")) -> 0 | E25: =C25-D25 -> 92526
B26: Subtotal - Finance and Accounting | C26: =SUM(C25) -> 92526 | D26: =IF($A26<>"", SUMIFS('Detailed Receipts'!$K:$K, 'Detailed Receipts'!$A:$A, $A26, 'Detailed Receipts'!$B:$B, $B26, 'Detailed Receipts'!$D:$D, "Jul", 'Detailed Receipts'!$L:$L, "OPEX"), SUMIFS('Detailed Receipts'!$K:$K, 'Detailed Receipts'!$A:$A, MID($B26, 12, 100), 'Detailed Receipts'!$D:$D, "Jul", 'Detailed Receipts'!$L:$L, "OPEX")) -> 0 | E26: =C26-D26 -> 92526
A27: Admin | B27: Admin | C27: =SUMIFS(ApprovedBudget!K19:K125,ApprovedBudget!$A$19:$A$125,"Admin",ApprovedBudget!$B$19:$B$125,"Admin") -> 623434 | D27: =IF($A27<>"", SUMIFS('Detailed Receipts'!$K:$K, 'Detailed Receipts'!$A:$A, $A27, 'Detailed Receipts'!$B:$B, $B27, 'Detailed Receipts'!$D:$D, "Jul", 'Detailed Receipts'!$L:$L, "OPEX"), SUMIFS('Detailed Receipts'!$K:$K, 'Detailed Receipts'!$A:$A, MID($B27, 12, 100), 'Detailed Receipts'!$D:$D, "Jul", 'Detailed Receipts'!$L:$L, "OPEX")) -> 0 | E27: =C27-D27 -> 623434
B28: Subtotal - Admin | C28: =SUM(C27) -> 623434 | D28: =IF($A28<>"", SUMIFS('Detailed Receipts'!$K:$K, 'Detailed Receipts'!$A:$A, $A28, 'Detailed Receipts'!$B:$B, $B28, 'Detailed Receipts'!$D:$D, "Jul", 'Detailed Receipts'!$L:$L, "OPEX"), SUMIFS('Detailed Receipts'!$K:$K, 'Detailed Receipts'!$A:$A, MID($B28, 12, 100), 'Detailed Receipts'!$D:$D, "Jul", 'Detailed Receipts'!$L:$L, "OPEX")) -> 0 | E28: =C28-D28 -> 623434
A29: HR | B29: HR | C29: =SUMIFS(ApprovedBudget!K19:K125,ApprovedBudget!$A$19:$A$125,"HR",ApprovedBudget!$B$19:$B$125,"HR") -> 145000 | D29: =IF($A29<>"", SUMIFS('Detailed Receipts'!$K:$K, 'Detailed Receipts'!$A:$A, $A29, 'Detailed Receipts'!$B:$B, $B29, 'Detailed Receipts'!$D:$D, "Jul", 'Detailed Receipts'!$L:$L, "OPEX"), SUMIFS('Detailed Receipts'!$K:$K, 'Detailed Receipts'!$A:$A, MID($B29, 12, 100), 'Detailed Receipts'!$D:$D, "Jul", 'Detailed Receipts'!$L:$L, "OPEX")) -> 0 | E29: =C29-D29 -> 145000
B30: Subtotal - HR | C30: =SUM(C29) -> 145000 | D30: =IF($A30<>"", SUMIFS('Detailed Receipts'!$K:$K, 'Detailed Receipts'!$A:$A, $A30, 'Detailed Receipts'!$B:$B, $B30, 'Detailed Receipts'!$D:$D, "Jul", 'Detailed Receipts'!$L:$L, "OPEX"), SUMIFS('Detailed Receipts'!$K:$K, 'Detailed Receipts'!$A:$A, MID($B30, 12, 100), 'Detailed Receipts'!$D:$D, "Jul", 'Detailed Receipts'!$L:$L, "OPEX")) -> 0 | E30: =C30-D30 -> 145000
A31: Compliance and Risk | B31: Legal & notarial | C31: =SUMIFS(ApprovedBudget!K19:K125,ApprovedBudget!$A$19:$A$125,"Compliance and Risk",ApprovedBudget!$B$19:$B$125,"Legal & notarial") -> 310000 | D31: =IF($A31<>"", SUMIFS('Detailed Receipts'!$K:$K, 'Detailed Receipts'!$A:$A, $A31, 'Detailed Receipts'!$B:$B, $B31, 'Detailed Receipts'!$D:$D, "Jul", 'Detailed Receipts'!$L:$L, "OPEX"), SUMIFS('Detailed Receipts'!$K:$K, 'Detailed Receipts'!$A:$A, MID($B31, 12, 100), 'Detailed Receipts'!$D:$D, "Jul", 'Detailed Receipts'!$L:$L, "OPEX")) -> 0 | E31: =C31-D31 -> 310000
A32: Compliance and Risk | B32: Permits & registration | C32: =SUMIFS(ApprovedBudget!K19:K125,ApprovedBudget!$A$19:$A$125,"Compliance and Risk",ApprovedBudget!$B$19:$B$125,"Permits & registration") -> 86800 | D32: =IF($A32<>"", SUMIFS('Detailed Receipts'!$K:$K, 'Detailed Receipts'!$A:$A, $A32, 'Detailed Receipts'!$B:$B, $B32, 'Detailed Receipts'!$D:$D, "Jul", 'Detailed Receipts'!$L:$L, "OPEX"), SUMIFS('Detailed Receipts'!$K:$K, 'Detailed Receipts'!$A:$A, MID($B32, 12, 100), 'Detailed Receipts'!$D:$D, "Jul", 'Detailed Receipts'!$L:$L, "OPEX")) -> 0 | E32: =C32-D32 -> 86800
B33: Subtotal - Compliance and Risk | C33: =SUM(C31:C32) -> 396800 | D33: =IF($A33<>"", SUMIFS('Detailed Receipts'!$K:$K, 'Detailed Receipts'!$A:$A, $A33, 'Detailed Receipts'!$B:$B, $B33, 'Detailed Receipts'!$D:$D, "Jul", 'Detailed Receipts'!$L:$L, "OPEX"), SUMIFS('Detailed Receipts'!$K:$K, 'Detailed Receipts'!$A:$A, MID($B33, 12, 100), 'Detailed Receipts'!$D:$D, "Jul", 'Detailed Receipts'!$L:$L, "OPEX")) -> 0 | E33: =C33-D33 -> 396800
B34: TOTAL OPEX | C34: =SUMIF($B4:$B33,"Subtotal*",C4:C33) -> 5703801 | D34: =SUMIF($B4:$B33,"Subtotal*",D4:D33) -> 2550 | E34: =C34-D34 -> 5701251

Sheet Payroll (Confidential)
A1: PAYROLL - CONFIDENTIAL
A3: BUDGET
A4: Department | B4: Jan | C4: Feb | D4: Mar | E4: Apr | F4: May | G4: June | H4: July
A5: Sales and Marketing | B5: =SUMIFS(ApprovedBudget!E5:E15,ApprovedBudget!$A$5:$A$15,"Sales and Marketing") -> 880387.76 | C5: =SUMIFS(ApprovedBudget!F5:F15,ApprovedBudget!$A$5:$A$15,"Sales and Marketing") -> 880387.76 | D5: =SUMIFS(ApprovedBudget!G5:G15,ApprovedBudget!$A$5:$A$15,"Sales and Marketing") -> 880387.76 | E5: =SUMIFS(ApprovedBudget!H5:H15,ApprovedBudget!$A$5:$A$15,"Sales and Marketing") -> 880387.76 | F5: =SUMIFS(ApprovedBudget!I5:I15,ApprovedBudget!$A$5:$A$15,"Sales and Marketing") -> 880387.76 | G5: =SUMIFS(ApprovedBudget!J5:J15,ApprovedBudget!$A$5:$A$15,"Sales and Marketing") -> 880387.76 | H5: =SUMIFS(ApprovedBudget!K5:K15,ApprovedBudget!$A$5:$A$15,"Sales and Marketing") -> 880387.76
A6: Customer Success | B6: =SUMIFS(ApprovedBudget!E5:E15,ApprovedBudget!$A$5:$A$15,"Customer Success") -> 125860 | C6: =SUMIFS(ApprovedBudget!F5:F15,ApprovedBudget!$A$5:$A$15,"Customer Success") -> 125860 | D6: =SUMIFS(ApprovedBudget!G5:G15,ApprovedBudget!$A$5:$A$15,"Customer Success") -> 125860 | E6: =SUMIFS(ApprovedBudget!H5:H15,ApprovedBudget!$A$5:$A$15,"Customer Success") -> 125860 | F6: =SUMIFS(ApprovedBudget!I5:I15,ApprovedBudget!$A$5:$A$15,"Customer Success") -> 151032 | G6: =SUMIFS(ApprovedBudget!J5:J15,ApprovedBudget!$A$5:$A$15,"Customer Success") -> 151032 | H6: =SUMIFS(ApprovedBudget!K5:K15,ApprovedBudget!$A$5:$A$15,"Customer Success") -> 151032
A7: Supply Chain | B7: =SUMIFS(ApprovedBudget!E5:E15,ApprovedBudget!$A$5:$A$15,"Supply Chain") -> 250020 | C7: =SUMIFS(ApprovedBudget!F5:F15,ApprovedBudget!$A$5:$A$15,"Supply Chain") -> 250020 | D7: =SUMIFS(ApprovedBudget!G5:G15,ApprovedBudget!$A$5:$A$15,"Supply Chain") -> 250020 | E7: =SUMIFS(ApprovedBudget!H5:H15,ApprovedBudget!$A$5:$A$15,"Supply Chain") -> 250020 | F7: =SUMIFS(ApprovedBudget!I5:I15,ApprovedBudget!$A$5:$A$15,"Supply Chain") -> 250020 | G7: =SUMIFS(ApprovedBudget!J5:J15,ApprovedBudget!$A$5:$A$15,"Supply Chain") -> 250020 | H7: =SUMIFS(ApprovedBudget!K5:K15,ApprovedBudget!$A$5:$A$15,"Supply Chain") -> 250020
A8: Aftersales | B8: =SUMIFS(ApprovedBudget!E5:E15,ApprovedBudget!$A$5:$A$15,"Aftersales") -> 40117.875 | C8: =SUMIFS(ApprovedBudget!F5:F15,ApprovedBudget!$A$5:$A$15,"Aftersales") -> 40117.875 | D8: =SUMIFS(ApprovedBudget!G5:G15,ApprovedBudget!$A$5:$A$15,"Aftersales") -> 40117.875 | E8: =SUMIFS(ApprovedBudget!H5:H15,ApprovedBudget!$A$5:$A$15,"Aftersales") -> 40117.875 | F8: =SUMIFS(ApprovedBudget!I5:I15,ApprovedBudget!$A$5:$A$15,"Aftersales") -> 40117.875 | G8: =SUMIFS(ApprovedBudget!J5:J15,ApprovedBudget!$A$5:$A$15,"Aftersales") -> 40117.875 | H8: =SUMIFS(ApprovedBudget!K5:K15,ApprovedBudget!$A$5:$A$15,"Aftersales") -> 40117.875
A9: Product | B9: =SUMIFS(ApprovedBudget!E5:E15,ApprovedBudget!$A$5:$A$15,"Product") -> 40117.875 | C9: =SUMIFS(ApprovedBudget!F5:F15,ApprovedBudget!$A$5:$A$15,"Product") -> 40117.875 | D9: =SUMIFS(ApprovedBudget!G5:G15,ApprovedBudget!$A$5:$A$15,"Product") -> 40117.875 | E9: =SUMIFS(ApprovedBudget!H5:H15,ApprovedBudget!$A$5:$A$15,"Product") -> 40117.875 | F9: =SUMIFS(ApprovedBudget!I5:I15,ApprovedBudget!$A$5:$A$15,"Product") -> 40117.875 | G9: =SUMIFS(ApprovedBudget!J5:J15,ApprovedBudget!$A$5:$A$15,"Product") -> 40117.875 | H9: =SUMIFS(ApprovedBudget!K5:K15,ApprovedBudget!$A$5:$A$15,"Product") -> 40117.875
A10: RideBox | B10: =SUMIFS(ApprovedBudget!E5:E15,ApprovedBudget!$A$5:$A$15,"RideBox") -> 0 | C10: =SUMIFS(ApprovedBudget!F5:F15,ApprovedBudget!$A$5:$A$15,"RideBox") -> 0 | D10: =SUMIFS(ApprovedBudget!G5:G15,ApprovedBudget!$A$5:$A$15,"RideBox") -> 0 | E10: =SUMIFS(ApprovedBudget!H5:H15,ApprovedBudget!$A$5:$A$15,"RideBox") -> 0 | F10: =SUMIFS(ApprovedBudget!I5:I15,ApprovedBudget!$A$5:$A$15,"RideBox") -> 125860 | G10: =SUMIFS(ApprovedBudget!J5:J15,ApprovedBudget!$A$5:$A$15,"RideBox") -> 226548 | H10: =SUMIFS(ApprovedBudget!K5:K15,ApprovedBudget!$A$5:$A$15,"RideBox") -> 276892
A11: Technology | B11: =SUMIFS(ApprovedBudget!E5:E15,ApprovedBudget!$A$5:$A$15,"Technology") -> 631987.45 | C11: =SUMIFS(ApprovedBudget!F5:F15,ApprovedBudget!$A$5:$A$15,"Technology") -> 631987.45 | D11: =SUMIFS(ApprovedBudget!G5:G15,ApprovedBudget!$A$5:$A$15,"Technology") -> 631987.45 | E11: =SUMIFS(ApprovedBudget!H5:H15,ApprovedBudget!$A$5:$A$15,"Technology") -> 696587.45 | F11: =SUMIFS(ApprovedBudget!I5:I15,ApprovedBudget!$A$5:$A$15,"Technology") -> 890387.45 | G11: =SUMIFS(ApprovedBudget!J5:J15,ApprovedBudget!$A$5:$A$15,"Technology") -> 1277987.5 | H11: =SUMIFS(ApprovedBudget!K5:K15,ApprovedBudget!$A$5:$A$15,"Technology") -> 1536387.5
A12: Finance and Accounting | B12: =SUMIFS(ApprovedBudget!E5:E15,ApprovedBudget!$A$5:$A$15,"Finance and Accounting") -> 633750 | C12: =SUMIFS(ApprovedBudget!F5:F15,ApprovedBudget!$A$5:$A$15,"Finance and Accounting") -> 633750 | D12: =SUMIFS(ApprovedBudget!G5:G15,ApprovedBudget!$A$5:$A$15,"Finance and Accounting") -> 974464.29 | E12: =SUMIFS(ApprovedBudget!H5:H15,ApprovedBudget!$A$5:$A$15,"Finance and Accounting") -> 340714.29 | F12: =SUMIFS(ApprovedBudget!I5:I15,ApprovedBudget!$A$5:$A$15,"Finance and Accounting") -> 390964.29 | G12: =SUMIFS(ApprovedBudget!J5:J15,ApprovedBudget!$A$5:$A$15,"Finance and Accounting") -> 390964.29 | H12: =SUMIFS(ApprovedBudget!K5:K15,ApprovedBudget!$A$5:$A$15,"Finance and Accounting") -> 390964.29
A13: Admin | B13: =SUMIFS(ApprovedBudget!E5:E15,ApprovedBudget!$A$5:$A$15,"Admin") -> 57000 | C13: =SUMIFS(ApprovedBudget!F5:F15,ApprovedBudget!$A$5:$A$15,"Admin") -> 57000 | D13: =SUMIFS(ApprovedBudget!G5:G15,ApprovedBudget!$A$5:$A$15,"Admin") -> 57000 | E13: =SUMIFS(ApprovedBudget!H5:H15,ApprovedBudget!$A$5:$A$15,"Admin") -> 57000 | F13: =SUMIFS(ApprovedBudget!I5:I15,ApprovedBudget!$A$5:$A$15,"Admin") -> 61750 | G13: =SUMIFS(ApprovedBudget!J5:J15,ApprovedBudget!$A$5:$A$15,"Admin") -> 61750 | H13: =SUMIFS(ApprovedBudget!K5:K15,ApprovedBudget!$A$5:$A$15,"Admin") -> 61750
A14: HR | B14: =SUMIFS(ApprovedBudget!E5:E15,ApprovedBudget!$A$5:$A$15,"HR") -> 154375 | C14: =SUMIFS(ApprovedBudget!F5:F15,ApprovedBudget!$A$5:$A$15,"HR") -> 154375 | D14: =SUMIFS(ApprovedBudget!G5:G15,ApprovedBudget!$A$5:$A$15,"HR") -> 154375 | E14: =SUMIFS(ApprovedBudget!H5:H15,ApprovedBudget!$A$5:$A$15,"HR") -> 154375 | F14: =SUMIFS(ApprovedBudget!I5:I15,ApprovedBudget!$A$5:$A$15,"HR") -> 154375 | G14: =SUMIFS(ApprovedBudget!J5:J15,ApprovedBudget!$A$5:$A$15,"HR") -> 154375 | H14: =SUMIFS(ApprovedBudget!K5:K15,ApprovedBudget!$A$5:$A$15,"HR") -> 154375
A15: Compliance and Risk | B15: =SUMIFS(ApprovedBudget!E5:E15,ApprovedBudget!$A$5:$A$15,"Compliance and Risk") -> 109326.4 | C15: =SUMIFS(ApprovedBudget!F5:F15,ApprovedBudget!$A$5:$A$15,"Compliance and Risk") -> 109326.4 | D15: =SUMIFS(ApprovedBudget!G5:G15,ApprovedBudget!$A$5:$A$15,"Compliance and Risk") -> 109326.4 | E15: =SUMIFS(ApprovedBudget!H5:H15,ApprovedBudget!$A$5:$A$15,"Compliance and Risk") -> 109326.4 | F15: =SUMIFS(ApprovedBudget!I5:I15,ApprovedBudget!$A$5:$A$15,"Compliance and Risk") -> 153993.07 | G15: =SUMIFS(ApprovedBudget!J5:J15,ApprovedBudget!$A$5:$A$15,"Compliance and Risk") -> 214659.73 | H15: =SUMIFS(ApprovedBudget!K5:K15,ApprovedBudget!$A$5:$A$15,"Compliance and Risk") -> 214659.73
A16: TOTAL | B16: =SUM(B5:B15) -> 2922942.4 | C16: =SUM(C5:C15) -> 2922942.4 | D16: =SUM(D5:D15) -> 3263656.6 | E16: =SUM(E5:E15) -> 2694506.6 | F16: =SUM(F5:F15) -> 3139005.3 | G16: =SUM(G5:G15) -> 3687960 | H16: =SUM(H5:H15) -> 3996704
A18: ACTUAL
A19: Department | B19: Jan | C19: Feb | D19: Mar | E19: Apr | F19: May | G19: June | H19: July
A20: Sales and Marketing
A21: Customer Success
A22: Supply Chain
A23: Aftersales
A24: Product
A25: RideBox
A26: Technology
A27: Finance and Accounting
A28: Admin
A29: HR
A30: Compliance and Risk
A31: TOTAL | B31: =SUM(B20:B30) -> 0 | C31: =SUM(C20:C30) -> 0 | D31: =SUM(D20:D30) -> 0 | E31: =SUM(E20:E30) -> 0 | F31: =SUM(F20:F30) -> 0 | G31: =SUM(G20:G30) -> 0 | H31: =SUM(H20:H30) -> 0

Sheet CAPEX (Confidential)
A1: CAPEX - CONFIDENTIAL
A3: BUDGET
A4: Department | B4: Cost Center | C4: Jan | D4: Feb | E4: Mar | F4: Apr | G4: May | H4: June | I4: July
A5: Supply Chain | B5: Procurement | C5: =SUMIFS(ApprovedBudget!E130:E166,ApprovedBudget!$A$130:$A$166,"Supply Chain",ApprovedBudget!$B$130:$B$166,"Procurement") -> 6128626.4 | D5: =SUMIFS(ApprovedBudget!F130:F166,ApprovedBudget!$A$130:$A$166,"Supply Chain",ApprovedBudget!$B$130:$B$166,"Procurement") -> 9151827.9 | E5: =SUMIFS(ApprovedBudget!G130:G166,ApprovedBudget!$A$130:$A$166,"Supply Chain",ApprovedBudget!$B$130:$B$166,"Procurement") -> 14164546 | F5: =SUMIFS(ApprovedBudget!H130:H166,ApprovedBudget!$A$130:$A$166,"Supply Chain",ApprovedBudget!$B$130:$B$166,"Procurement") -> 19279747 | G5: =SUMIFS(ApprovedBudget!I130:I166,ApprovedBudget!$A$130:$A$166,"Supply Chain",ApprovedBudget!$B$130:$B$166,"Procurement") -> 30619821 | H5: =SUMIFS(ApprovedBudget!J130:J166,ApprovedBudget!$A$130:$A$166,"Supply Chain",ApprovedBudget!$B$130:$B$166,"Procurement") -> 33328596 | I5: =SUMIFS(ApprovedBudget!K130:K166,ApprovedBudget!$A$130:$A$166,"Supply Chain",ApprovedBudget!$B$130:$B$166,"Procurement") -> 35935908
A6: Supply Chain | B6: Warehouse | C6: =SUMIFS(ApprovedBudget!E130:E166,ApprovedBudget!$A$130:$A$166,"Supply Chain",ApprovedBudget!$B$130:$B$166,"Warehouse") -> 0 | D6: =SUMIFS(ApprovedBudget!F130:F166,ApprovedBudget!$A$130:$A$166,"Supply Chain",ApprovedBudget!$B$130:$B$166,"Warehouse") -> 0 | E6: =SUMIFS(ApprovedBudget!G130:G166,ApprovedBudget!$A$130:$A$166,"Supply Chain",ApprovedBudget!$B$130:$B$166,"Warehouse") -> 0 | F6: =SUMIFS(ApprovedBudget!H130:H166,ApprovedBudget!$A$130:$A$166,"Supply Chain",ApprovedBudget!$B$130:$B$166,"Warehouse") -> 0 | G6: =SUMIFS(ApprovedBudget!I130:I166,ApprovedBudget!$A$130:$A$166,"Supply Chain",ApprovedBudget!$B$130:$B$166,"Warehouse") -> 0 | H6: =SUMIFS(ApprovedBudget!J130:J166,ApprovedBudget!$A$130:$A$166,"Supply Chain",ApprovedBudget!$B$130:$B$166,"Warehouse") -> 0 | I6: =SUMIFS(ApprovedBudget!K130:K166,ApprovedBudget!$A$130:$A$166,"Supply Chain",ApprovedBudget!$B$130:$B$166,"Warehouse") -> 5132129.4
A7: Supply Chain | B7: Logistics | C7: =SUMIFS(ApprovedBudget!E130:E166,ApprovedBudget!$A$130:$A$166,"Supply Chain",ApprovedBudget!$B$130:$B$166,"Logistics") -> 286803 | D7: =SUMIFS(ApprovedBudget!F130:F166,ApprovedBudget!$A$130:$A$166,"Supply Chain",ApprovedBudget!$B$130:$B$166,"Logistics") -> 413358 | E7: =SUMIFS(ApprovedBudget!G130:G166,ApprovedBudget!$A$130:$A$166,"Supply Chain",ApprovedBudget!$B$130:$B$166,"Logistics") -> 639475 | F7: =SUMIFS(ApprovedBudget!H130:H166,ApprovedBudget!$A$130:$A$166,"Supply Chain",ApprovedBudget!$B$130:$B$166,"Logistics") -> 865591 | G7: =SUMIFS(ApprovedBudget!I130:I166,ApprovedBudget!$A$130:$A$166,"Supply Chain",ApprovedBudget!$B$130:$B$166,"Logistics") -> 1261296 | H7: =SUMIFS(ApprovedBudget!J130:J166,ApprovedBudget!$A$130:$A$166,"Supply Chain",ApprovedBudget!$B$130:$B$166,"Logistics") -> 1487413 | I7: =SUMIFS(ApprovedBudget!K130:K166,ApprovedBudget!$A$130:$A$166,"Supply Chain",ApprovedBudget!$B$130:$B$166,"Logistics") -> 1600472
A8: Product | B8: Homologation & Registration | C8: =SUMIFS(ApprovedBudget!E130:E166,ApprovedBudget!$A$130:$A$166,"Product",ApprovedBudget!$B$130:$B$166,"Homologation & Registration") -> 0 | D8: =SUMIFS(ApprovedBudget!F130:F166,ApprovedBudget!$A$130:$A$166,"Product",ApprovedBudget!$B$130:$B$166,"Homologation & Registration") -> 0 | E8: =SUMIFS(ApprovedBudget!G130:G166,ApprovedBudget!$A$130:$A$166,"Product",ApprovedBudget!$B$130:$B$166,"Homologation & Registration") -> 0 | F8: =SUMIFS(ApprovedBudget!H130:H166,ApprovedBudget!$A$130:$A$166,"Product",ApprovedBudget!$B$130:$B$166,"Homologation & Registration") -> 0 | G8: =SUMIFS(ApprovedBudget!I130:I166,ApprovedBudget!$A$130:$A$166,"Product",ApprovedBudget!$B$130:$B$166,"Homologation & Registration") -> 0 | H8: =SUMIFS(ApprovedBudget!J130:J166,ApprovedBudget!$A$130:$A$166,"Product",ApprovedBudget!$B$130:$B$166,"Homologation & Registration") -> 0 | I8: =SUMIFS(ApprovedBudget!K130:K166,ApprovedBudget!$A$130:$A$166,"Product",ApprovedBudget!$B$130:$B$166,"Homologation & Registration") -> 0
A9: Product | B9: R&D | C9: =SUMIFS(ApprovedBudget!E130:E166,ApprovedBudget!$A$130:$A$166,"Product",ApprovedBudget!$B$130:$B$166,"R&D") -> 259777.55 | D9: =SUMIFS(ApprovedBudget!F130:F166,ApprovedBudget!$A$130:$A$166,"Product",ApprovedBudget!$B$130:$B$166,"R&D") -> 392135.84 | E9: =SUMIFS(ApprovedBudget!G130:G166,ApprovedBudget!$A$130:$A$166,"Product",ApprovedBudget!$B$130:$B$166,"R&D") -> 611108.58 | F9: =SUMIFS(ApprovedBudget!H130:H166,ApprovedBudget!$A$130:$A$166,"Product",ApprovedBudget!$B$130:$B$166,"R&D") -> 832680.81 | G9: =SUMIFS(ApprovedBudget!I130:I166,ApprovedBudget!$A$130:$A$166,"Product",ApprovedBudget!$B$130:$B$166,"R&D") -> 1377768.1 | H9: =SUMIFS(ApprovedBudget!J130:J166,ApprovedBudget!$A$130:$A$166,"Product",ApprovedBudget!$B$130:$B$166,"R&D") -> 1441680.6 | I9: =SUMIFS(ApprovedBudget!K130:K166,ApprovedBudget!$A$130:$A$166,"Product",ApprovedBudget!$B$130:$B$166,"R&D") -> 1553372.3
A10: RideBox | B10: Network Rollout | C10: =SUMIFS(ApprovedBudget!E130:E166,ApprovedBudget!$A$130:$A$166,"RideBox") -> 12965.679 | D10: =SUMIFS(ApprovedBudget!F130:F166,ApprovedBudget!$A$130:$A$166,"RideBox") -> 18964.578 | E10: =SUMIFS(ApprovedBudget!G130:G166,ApprovedBudget!$A$130:$A$166,"RideBox") -> 29414.501 | F10: =SUMIFS(ApprovedBudget!H130:H166,ApprovedBudget!$A$130:$A$166,"RideBox") -> 39953.374 | G10: =SUMIFS(ApprovedBudget!I130:I166,ApprovedBudget!$A$130:$A$166,"RideBox") -> 58230.235 | H10: =SUMIFS(ApprovedBudget!J130:J166,ApprovedBudget!$A$130:$A$166,"RideBox") -> 68857.083 | I10: =SUMIFS(ApprovedBudget!K130:K166,ApprovedBudget!$A$130:$A$166,"RideBox") -> 74346.449
A11: Technology | B11: Technology | C11: =SUMIFS(ApprovedBudget!E130:E166,ApprovedBudget!$A$130:$A$166,"Technology") -> 28380 | D11: =SUMIFS(ApprovedBudget!F130:F166,ApprovedBudget!$A$130:$A$166,"Technology") -> 28380 | E11: =SUMIFS(ApprovedBudget!G130:G166,ApprovedBudget!$A$130:$A$166,"Technology") -> 28380 | F11: =SUMIFS(ApprovedBudget!H130:H166,ApprovedBudget!$A$130:$A$166,"Technology") -> 1338380 | G11: =SUMIFS(ApprovedBudget!I130:I166,ApprovedBudget!$A$130:$A$166,"Technology") -> 1338380 | H11: =SUMIFS(ApprovedBudget!J130:J166,ApprovedBudget!$A$130:$A$166,"Technology") -> 1038380 | I11: =SUMIFS(ApprovedBudget!K130:K166,ApprovedBudget!$A$130:$A$166,"Technology") -> 1038380
A12: Finance and Accounting | B12: Finance and Accounting | C12: =SUMIFS(ApprovedBudget!E130:E166,ApprovedBudget!$A$130:$A$166,"Finance") -> 0 | D12: =SUMIFS(ApprovedBudget!F130:F166,ApprovedBudget!$A$130:$A$166,"Finance") -> 0 | E12: =SUMIFS(ApprovedBudget!G130:G166,ApprovedBudget!$A$130:$A$166,"Finance") -> 0 | F12: =SUMIFS(ApprovedBudget!H130:H166,ApprovedBudget!$A$130:$A$166,"Finance") -> 0 | G12: =SUMIFS(ApprovedBudget!I130:I166,ApprovedBudget!$A$130:$A$166,"Finance") -> 0 | H12: =SUMIFS(ApprovedBudget!J130:J166,ApprovedBudget!$A$130:$A$166,"Finance") -> 500000 | I12: =SUMIFS(ApprovedBudget!K130:K166,ApprovedBudget!$A$130:$A$166,"Finance") -> 500000
A13: Admin | B13: Admin | C13: =SUMIFS(ApprovedBudget!E130:E166,ApprovedBudget!$A$130:$A$166,"Admin",ApprovedBudget!$B$130:$B$166,"Admin") -> 0 | D13: =SUMIFS(ApprovedBudget!F130:F166,ApprovedBudget!$A$130:$A$166,"Admin",ApprovedBudget!$B$130:$B$166,"Admin") -> 0 | E13: =SUMIFS(ApprovedBudget!G130:G166,ApprovedBudget!$A$130:$A$166,"Admin",ApprovedBudget!$B$130:$B$166,"Admin") -> 0 | F13: =SUMIFS(ApprovedBudget!H130:H166,ApprovedBudget!$A$130:$A$166,"Admin",ApprovedBudget!$B$130:$B$166,"Admin") -> 0 | G13: =SUMIFS(ApprovedBudget!I130:I166,ApprovedBudget!$A$130:$A$166,"Admin",ApprovedBudget!$B$130:$B$166,"Admin") -> 0 | H13: =SUMIFS(ApprovedBudget!J130:J166,ApprovedBudget!$A$130:$A$166,"Admin",ApprovedBudget!$B$130:$B$166,"Admin") -> 0 | I13: =SUMIFS(ApprovedBudget!K130:K166,ApprovedBudget!$A$130:$A$166,"Admin",ApprovedBudget!$B$130:$B$166,"Admin") -> 0
B14: TOTAL | C14: =SUM(C5:C13) -> 6716552.6 | D14: =SUM(D5:D13) -> 10004666 | E14: =SUM(E5:E13) -> 15472924 | F14: =SUM(F5:F13) -> 22356352 | G14: =SUM(G5:G13) -> 34655495 | H14: =SUM(H5:H13) -> 37864927 | I14: =SUM(I5:I13) -> 45834608
A16: ACTUAL
A17: Department | B17: Cost Center | C17: Jan | D17: Feb | E17: Mar | F17: Apr | G17: May | H17: June | I17: July
A18: Supply Chain | B18: Procurement | C18: =SUMIFS('Detailed Receipts'!$K:$K, 'Detailed Receipts'!$A:$A, $A18, 'Detailed Receipts'!$B:$B, $B18, 'Detailed Receipts'!$D:$D, C$17, 'Detailed Receipts'!$L:$L, "CAPEX") -> 3431 | D18: =SUMIFS('Detailed Receipts'!$K:$K, 'Detailed Receipts'!$A:$A, $A18, 'Detailed Receipts'!$B:$B, $B18, 'Detailed Receipts'!$D:$D, D$17, 'Detailed Receipts'!$L:$L, "CAPEX") -> 13204 | E18: =SUMIFS('Detailed Receipts'!$K:$K, 'Detailed Receipts'!$A:$A, $A18, 'Detailed Receipts'!$B:$B, $B18, 'Detailed Receipts'!$D:$D, E$17, 'Detailed Receipts'!$L:$L, "CAPEX") -> 140 | F18: =SUMIFS('Detailed Receipts'!$K:$K, 'Detailed Receipts'!$A:$A, $A18, 'Detailed Receipts'!$B:$B, $B18, 'Detailed Receipts'!$D:$D, F$17, 'Detailed Receipts'!$L:$L, "CAPEX") -> 2312004 | G18: =SUMIFS('Detailed Receipts'!$K:$K, 'Detailed Receipts'!$A:$A, $A18, 'Detailed Receipts'!$B:$B, $B18, 'Detailed Receipts'!$D:$D, G$17, 'Detailed Receipts'!$L:$L, "CAPEX") -> 0 | H18: =SUMIFS('Detailed Receipts'!$K:$K, 'Detailed Receipts'!$A:$A, $A18, 'Detailed Receipts'!$B:$B, $B18, 'Detailed Receipts'!$D:$D, H$17, 'Detailed Receipts'!$L:$L, "CAPEX") -> 0 | I18: =SUMIFS('Detailed Receipts'!$K:$K, 'Detailed Receipts'!$A:$A, $A18, 'Detailed Receipts'!$B:$B, $B18, 'Detailed Receipts'!$D:$D, I$17, 'Detailed Receipts'!$L:$L, "CAPEX") -> 0
A19: Supply Chain | B19: Warehouse | C19: =SUMIFS('Detailed Receipts'!$K:$K, 'Detailed Receipts'!$A:$A, $A19, 'Detailed Receipts'!$B:$B, $B19, 'Detailed Receipts'!$D:$D, C$17, 'Detailed Receipts'!$L:$L, "CAPEX") -> 0 | D19: =SUMIFS('Detailed Receipts'!$K:$K, 'Detailed Receipts'!$A:$A, $A19, 'Detailed Receipts'!$B:$B, $B19, 'Detailed Receipts'!$D:$D, D$17, 'Detailed Receipts'!$L:$L, "CAPEX") -> 6773 | E19: =SUMIFS('Detailed Receipts'!$K:$K, 'Detailed Receipts'!$A:$A, $A19, 'Detailed Receipts'!$B:$B, $B19, 'Detailed Receipts'!$D:$D, E$17, 'Detailed Receipts'!$L:$L, "CAPEX") -> 1331 | F19: =SUMIFS('Detailed Receipts'!$K:$K, 'Detailed Receipts'!$A:$A, $A19, 'Detailed Receipts'!$B:$B, $B19, 'Detailed Receipts'!$D:$D, F$17, 'Detailed Receipts'!$L:$L, "CAPEX") -> 0 | G19: =SUMIFS('Detailed Receipts'!$K:$K, 'Detailed Receipts'!$A:$A, $A19, 'Detailed Receipts'!$B:$B, $B19, 'Detailed Receipts'!$D:$D, G$17, 'Detailed Receipts'!$L:$L, "CAPEX") -> 0 | H19: =SUMIFS('Detailed Receipts'!$K:$K, 'Detailed Receipts'!$A:$A, $A19, 'Detailed Receipts'!$B:$B, $B19, 'Detailed Receipts'!$D:$D, H$17, 'Detailed Receipts'!$L:$L, "CAPEX") -> 0 | I19: =SUMIFS('Detailed Receipts'!$K:$K, 'Detailed Receipts'!$A:$A, $A19, 'Detailed Receipts'!$B:$B, $B19, 'Detailed Receipts'!$D:$D, I$17, 'Detailed Receipts'!$L:$L, "CAPEX") -> 0
A20: Supply Chain | B20: Logistics | C20: =SUMIFS('Detailed Receipts'!$K:$K, 'Detailed Receipts'!$A:$A, $A20, 'Detailed Receipts'!$B:$B, $B20, 'Detailed Receipts'!$D:$D, C$17, 'Detailed Receipts'!$L:$L, "CAPEX") -> 0 | D20: =SUMIFS('Detailed Receipts'!$K:$K, 'Detailed Receipts'!$A:$A, $A20, 'Detailed Receipts'!$B:$B, $B20, 'Detailed Receipts'!$D:$D, D$17, 'Detailed Receipts'!$L:$L, "CAPEX") -> 0 | E20: =SUMIFS('Detailed Receipts'!$K:$K, 'Detailed Receipts'!$A:$A, $A20, 'Detailed Receipts'!$B:$B, $B20, 'Detailed Receipts'!$D:$D, E$17, 'Detailed Receipts'!$L:$L, "CAPEX") -> 0 | F20: =SUMIFS('Detailed Receipts'!$K:$K, 'Detailed Receipts'!$A:$A, $A20, 'Detailed Receipts'!$B:$B, $B20, 'Detailed Receipts'!$D:$D, F$17, 'Detailed Receipts'!$L:$L, "CAPEX") -> 0 | G20: =SUMIFS('Detailed Receipts'!$K:$K, 'Detailed Receipts'!$A:$A, $A20, 'Detailed Receipts'!$B:$B, $B20, 'Detailed Receipts'!$D:$D, G$17, 'Detailed Receipts'!$L:$L, "CAPEX") -> 0 | H20: =SUMIFS('Detailed Receipts'!$K:$K, 'Detailed Receipts'!$A:$A, $A20, 'Detailed Receipts'!$B:$B, $B20, 'Detailed Receipts'!$D:$D, H$17, 'Detailed Receipts'!$L:$L, "CAPEX") -> 0 | I20: =SUMIFS('Detailed Receipts'!$K:$K, 'Detailed Receipts'!$A:$A, $A20, 'Detailed Receipts'!$B:$B, $B20, 'Detailed Receipts'!$D:$D, I$17, 'Detailed Receipts'!$L:$L, "CAPEX") -> 0
A21: Product | B21: Homologation & Registration | C21: =SUMIFS('Detailed Receipts'!$K:$K, 'Detailed Receipts'!$A:$A, $A21, 'Detailed Receipts'!$B:$B, $B21, 'Detailed Receipts'!$D:$D, C$17, 'Detailed Receipts'!$L:$L, "CAPEX") -> 0 | D21: =SUMIFS('Detailed Receipts'!$K:$K, 'Detailed Receipts'!$A:$A, $A21, 'Detailed Receipts'!$B:$B, $B21, 'Detailed Receipts'!$D:$D, D$17, 'Detailed Receipts'!$L:$L, "CAPEX") -> 0 | E21: =SUMIFS('Detailed Receipts'!$K:$K, 'Detailed Receipts'!$A:$A, $A21, 'Detailed Receipts'!$B:$B, $B21, 'Detailed Receipts'!$D:$D, E$17, 'Detailed Receipts'!$L:$L, "CAPEX") -> 0 | F21: =SUMIFS('Detailed Receipts'!$K:$K, 'Detailed Receipts'!$A:$A, $A21, 'Detailed Receipts'!$B:$B, $B21, 'Detailed Receipts'!$D:$D, F$17, 'Detailed Receipts'!$L:$L, "CAPEX") -> 0 | G21: =SUMIFS('Detailed Receipts'!$K:$K, 'Detailed Receipts'!$A:$A, $A21, 'Detailed Receipts'!$B:$B, $B21, 'Detailed Receipts'!$D:$D, G$17, 'Detailed Receipts'!$L:$L, "CAPEX") -> 0 | H21: =SUMIFS('Detailed Receipts'!$K:$K, 'Detailed Receipts'!$A:$A, $A21, 'Detailed Receipts'!$B:$B, $B21, 'Detailed Receipts'!$D:$D, H$17, 'Detailed Receipts'!$L:$L, "CAPEX") -> 0 | I21: =SUMIFS('Detailed Receipts'!$K:$K, 'Detailed Receipts'!$A:$A, $A21, 'Detailed Receipts'!$B:$B, $B21, 'Detailed Receipts'!$D:$D, I$17, 'Detailed Receipts'!$L:$L, "CAPEX") -> 0
A22: Product | B22: R&D | C22: =SUMIFS('Detailed Receipts'!$K:$K, 'Detailed Receipts'!$A:$A, $A22, 'Detailed Receipts'!$B:$B, $B22, 'Detailed Receipts'!$D:$D, C$17, 'Detailed Receipts'!$L:$L, "CAPEX") -> 4500 | D22: =SUMIFS('Detailed Receipts'!$K:$K, 'Detailed Receipts'!$A:$A, $A22, 'Detailed Receipts'!$B:$B, $B22, 'Detailed Receipts'!$D:$D, D$17, 'Detailed Receipts'!$L:$L, "CAPEX") -> 0 | E22: =SUMIFS('Detailed Receipts'!$K:$K, 'Detailed Receipts'!$A:$A, $A22, 'Detailed Receipts'!$B:$B, $B22, 'Detailed Receipts'!$D:$D, E$17, 'Detailed Receipts'!$L:$L, "CAPEX") -> 0 | F22: =SUMIFS('Detailed Receipts'!$K:$K, 'Detailed Receipts'!$A:$A, $A22, 'Detailed Receipts'!$B:$B, $B22, 'Detailed Receipts'!$D:$D, F$17, 'Detailed Receipts'!$L:$L, "CAPEX") -> 0 | G22: =SUMIFS('Detailed Receipts'!$K:$K, 'Detailed Receipts'!$A:$A, $A22, 'Detailed Receipts'!$B:$B, $B22, 'Detailed Receipts'!$D:$D, G$17, 'Detailed Receipts'!$L:$L, "CAPEX") -> 0 | H22: =SUMIFS('Detailed Receipts'!$K:$K, 'Detailed Receipts'!$A:$A, $A22, 'Detailed Receipts'!$B:$B, $B22, 'Detailed Receipts'!$D:$D, H$17, 'Detailed Receipts'!$L:$L, "CAPEX") -> 0 | I22: =SUMIFS('Detailed Receipts'!$K:$K, 'Detailed Receipts'!$A:$A, $A22, 'Detailed Receipts'!$B:$B, $B22, 'Detailed Receipts'!$D:$D, I$17, 'Detailed Receipts'!$L:$L, "CAPEX") -> 0
A23: RideBox | B23: Network Rollout | C23: =SUMIFS('Detailed Receipts'!$K:$K, 'Detailed Receipts'!$A:$A, $A23, 'Detailed Receipts'!$B:$B, $B23, 'Detailed Receipts'!$D:$D, C$17, 'Detailed Receipts'!$L:$L, "CAPEX") -> 184518 | D23: =SUMIFS('Detailed Receipts'!$K:$K, 'Detailed Receipts'!$A:$A, $A23, 'Detailed Receipts'!$B:$B, $B23, 'Detailed Receipts'!$D:$D, D$17, 'Detailed Receipts'!$L:$L, "CAPEX") -> 190322 | E23: =SUMIFS('Detailed Receipts'!$K:$K, 'Detailed Receipts'!$A:$A, $A23, 'Detailed Receipts'!$B:$B, $B23, 'Detailed Receipts'!$D:$D, E$17, 'Detailed Receipts'!$L:$L, "CAPEX") -> 520857 | F23: =SUMIFS('Detailed Receipts'!$K:$K, 'Detailed Receipts'!$A:$A, $A23, 'Detailed Receipts'!$B:$B, $B23, 'Detailed Receipts'!$D:$D, F$17, 'Detailed Receipts'!$L:$L, "CAPEX") -> 0 | G23: =SUMIFS('Detailed Receipts'!$K:$K, 'Detailed Receipts'!$A:$A, $A23, 'Detailed Receipts'!$B:$B, $B23, 'Detailed Receipts'!$D:$D, G$17, 'Detailed Receipts'!$L:$L, "CAPEX") -> 191599 | H23: =SUMIFS('Detailed Receipts'!$K:$K, 'Detailed Receipts'!$A:$A, $A23, 'Detailed Receipts'!$B:$B, $B23, 'Detailed Receipts'!$D:$D, H$17, 'Detailed Receipts'!$L:$L, "CAPEX") -> 0 | I23: =SUMIFS('Detailed Receipts'!$K:$K, 'Detailed Receipts'!$A:$A, $A23, 'Detailed Receipts'!$B:$B, $B23, 'Detailed Receipts'!$D:$D, I$17, 'Detailed Receipts'!$L:$L, "CAPEX") -> 0
A24: Technology | B24: Technology | C24: =SUMIFS('Detailed Receipts'!$K:$K, 'Detailed Receipts'!$A:$A, $A24, 'Detailed Receipts'!$B:$B, $B24, 'Detailed Receipts'!$D:$D, C$17, 'Detailed Receipts'!$L:$L, "CAPEX") -> 619920 | D24: =SUMIFS('Detailed Receipts'!$K:$K, 'Detailed Receipts'!$A:$A, $A24, 'Detailed Receipts'!$B:$B, $B24, 'Detailed Receipts'!$D:$D, D$17, 'Detailed Receipts'!$L:$L, "CAPEX") -> 0 | E24: =SUMIFS('Detailed Receipts'!$K:$K, 'Detailed Receipts'!$A:$A, $A24, 'Detailed Receipts'!$B:$B, $B24, 'Detailed Receipts'!$D:$D, E$17, 'Detailed Receipts'!$L:$L, "CAPEX") -> 1239840 | F24: =SUMIFS('Detailed Receipts'!$K:$K, 'Detailed Receipts'!$A:$A, $A24, 'Detailed Receipts'!$B:$B, $B24, 'Detailed Receipts'!$D:$D, F$17, 'Detailed Receipts'!$L:$L, "CAPEX") -> 0 | G24: =SUMIFS('Detailed Receipts'!$K:$K, 'Detailed Receipts'!$A:$A, $A24, 'Detailed Receipts'!$B:$B, $B24, 'Detailed Receipts'!$D:$D, G$17, 'Detailed Receipts'!$L:$L, "CAPEX") -> 0 | H24: =SUMIFS('Detailed Receipts'!$K:$K, 'Detailed Receipts'!$A:$A, $A24, 'Detailed Receipts'!$B:$B, $B24, 'Detailed Receipts'!$D:$D, H$17, 'Detailed Receipts'!$L:$L, "CAPEX") -> 0 | I24: =SUMIFS('Detailed Receipts'!$K:$K, 'Detailed Receipts'!$A:$A, $A24, 'Detailed Receipts'!$B:$B, $B24, 'Detailed Receipts'!$D:$D, I$17, 'Detailed Receipts'!$L:$L, "CAPEX") -> 0
A25: Finance and Accounting | B25: Finance and Accounting | C25: =SUMIFS('Detailed Receipts'!$K:$K, 'Detailed Receipts'!$A:$A, $A25, 'Detailed Receipts'!$B:$B, $B25, 'Detailed Receipts'!$D:$D, C$17, 'Detailed Receipts'!$L:$L, "CAPEX") -> 0 | D25: =SUMIFS('Detailed Receipts'!$K:$K, 'Detailed Receipts'!$A:$A, $A25, 'Detailed Receipts'!$B:$B, $B25, 'Detailed Receipts'!$D:$D, D$17, 'Detailed Receipts'!$L:$L, "CAPEX") -> 0 | E25: =SUMIFS('Detailed Receipts'!$K:$K, 'Detailed Receipts'!$A:$A, $A25, 'Detailed Receipts'!$B:$B, $B25, 'Detailed Receipts'!$D:$D, E$17, 'Detailed Receipts'!$L:$L, "CAPEX") -> 0 | F25: =SUMIFS('Detailed Receipts'!$K:$K, 'Detailed Receipts'!$A:$A, $A25, 'Detailed Receipts'!$B:$B, $B25, 'Detailed Receipts'!$D:$D, F$17, 'Detailed Receipts'!$L:$L, "CAPEX") -> 0 | G25: =SUMIFS('Detailed Receipts'!$K:$K, 'Detailed Receipts'!$A:$A, $A25, 'Detailed Receipts'!$B:$B, $B25, 'Detailed Receipts'!$D:$D, G$17, 'Detailed Receipts'!$L:$L, "CAPEX") -> 0 | H25: =SUMIFS('Detailed Receipts'!$K:$K, 'Detailed Receipts'!$A:$A, $A25, 'Detailed Receipts'!$B:$B, $B25, 'Detailed Receipts'!$D:$D, H$17, 'Detailed Receipts'!$L:$L, "CAPEX") -> 0 | I25: =SUMIFS('Detailed Receipts'!$K:$K, 'Detailed Receipts'!$A:$A, $A25, 'Detailed Receipts'!$B:$B, $B25, 'Detailed Receipts'!$D:$D, I$17, 'Detailed Receipts'!$L:$L, "CAPEX") -> 0
A26: Admin | B26: Admin | C26: =SUMIFS('Detailed Receipts'!$K:$K, 'Detailed Receipts'!$A:$A, $A26, 'Detailed Receipts'!$B:$B, $B26, 'Detailed Receipts'!$D:$D, C$17, 'Detailed Receipts'!$L:$L, "CAPEX") -> 0 | D26: =SUMIFS('Detailed Receipts'!$K:$K, 'Detailed Receipts'!$A:$A, $A26, 'Detailed Receipts'!$B:$B, $B26, 'Detailed Receipts'!$D:$D, D$17, 'Detailed Receipts'!$L:$L, "CAPEX") -> 0 | E26: =SUMIFS('Detailed Receipts'!$K:$K, 'Detailed Receipts'!$A:$A, $A26, 'Detailed Receipts'!$B:$B, $B26, 'Detailed Receipts'!$D:$D, E$17, 'Detailed Receipts'!$L:$L, "CAPEX") -> 0 | F26: =SUMIFS('Detailed Receipts'!$K:$K, 'Detailed Receipts'!$A:$A, $A26, 'Detailed Receipts'!$B:$B, $B26, 'Detailed Receipts'!$D:$D, F$17, 'Detailed Receipts'!$L:$L, "CAPEX") -> 0 | G26: =SUMIFS('Detailed Receipts'!$K:$K, 'Detailed Receipts'!$A:$A, $A26, 'Detailed Receipts'!$B:$B, $B26, 'Detailed Receipts'!$D:$D, G$17, 'Detailed Receipts'!$L:$L, "CAPEX") -> 0 | H26: =SUMIFS('Detailed Receipts'!$K:$K, 'Detailed Receipts'!$A:$A, $A26, 'Detailed Receipts'!$B:$B, $B26, 'Detailed Receipts'!$D:$D, H$17, 'Detailed Receipts'!$L:$L, "CAPEX") -> 0 | I26: =SUMIFS('Detailed Receipts'!$K:$K, 'Detailed Receipts'!$A:$A, $A26, 'Detailed Receipts'!$B:$B, $B26, 'Detailed Receipts'!$D:$D, I$17, 'Detailed Receipts'!$L:$L, "CAPEX") -> 0
B27: TOTAL | C27: =SUM(C18:C26) -> 812369 | D27: =SUM(D18:D26) -> 210299 | E27: =SUM(E18:E26) -> 1762168 | F27: =SUM(F18:F26) -> 2312004 | G27: =SUM(G18:G26) -> 191599 | H27: =SUM(H18:H26) -> 0 | I27: =SUM(I18:I26) -> 0

Sheet Detailed Receipts
A1: E88 Ventures - Detailed Receipts Jan-Jul 2026 (itemized per receipt; reimbursements split)
A4: Department | B4: Cost Center | C4: Accounting Title | D4: Month | E4: RFP / LIQ No. | F4: RFP Date | G4: Receipt Date | H4: Requestor / Payee | I4: Vendor / Office | J4: Description | K4: Amount | L4: CAPEX/OPEX
A5: Sales and Marketing | B5: Sales | C5: Advertising/promotions | D5: Jan | E5: RFP-MKTG2026-0002 | F5: 01/06/2026 | G5: 01/06/2026 | H5: THEA GRACE MASIGLAT | I5: wokz/printer (tarpaulin) | J5: Tarpaulin (3 pcs) | K5: 538 | L5: OPEX
A6: Sales and Marketing | B6: Sales | C6: Freight/delivery | D6: Jan | E6: RFP-MKTG2026-0002 | F6: 01/06/2026 | G6: 01/06/2026 | H6: THEA GRACE MASIGLAT | I6: delivery | J6: Tarpaulin delivery fee | K6: 250 | L6: OPEX
A7: Sales and Marketing | B7: Sales | C7: Freight/delivery | D7: Jan | E7: RFP-MKTG2026-0002 | F7: 01/06/2026 | G7: 01/06/2026 | H7: THEA GRACE MASIGLAT | I7: delivery | J7: Trifold sampling delivery fee | K7: 183 | L7: OPEX
A8: Sales and Marketing | B8: Sales | C8: Utilities (Electricity) | D8: Jan | E8: RFP-MKTG2026-0001 | F8: 01/08/2026 | G8: 01/08/2026 | H8: WOKZPH | I8: wokz.ph | J8: A4 Waterproof Sticker (80 pcs) | K8: 6400 | L8: OPEX
A9: Sales and Marketing | B9: Sales | C9: Advertising/promotions | D9: Jan | E9: RFP-MKTG2026-0001 | F9: 01/08/2026 | G9: 01/08/2026 | H9: WOKZPH | I9: wokz.ph | J9: Pull up banner (6 pcs) | K9: 3150 | L9: OPEX
A10: Sales and Marketing | B10: Sales | C10: Other operating expense (manpower/contracted) | D10: Jan | E10: RFP-MKTG2026-0003 | F10: 01/08/2026 | G10: 01/07/2026 | H10: WOKZPH | I10: wokz.ph | J10: B2B Trifold Brochure (100 pcs) | K10: 2000 | L10: OPEX
A11: Sales and Marketing | B11: Sales | C11: Office supplies | D11: Jan | E11: RFP-SALES2026-0047 | F11: 01/09/2026 | G11: 01/05/2026 | H11: Anne Margot Estadilla | I11: Pantry supplier | J11: Pantry Supply | K11: 720 | L11: OPEX
A12: Sales and Marketing | B12: Sales | C12: Office supplies | D12: Jan | E12: RFP-SALES2026-0047 | F12: 01/09/2026 | G12: 01/05/2026 | H12: Anne Margot Estadilla | I12: Pantry supplier | J12: Pantry Supply | K12: 188 | L12: OPEX
A13: Sales and Marketing | B13: Sales | C13: Utilities (Electricity) | D13: Jan | E13: RFP-SALES2026-0047 | F13: 01/09/2026 | G13: 01/08/2026 | H13: Anne Margot Estadilla | I13: Laguna Water | J13: Laguna Water | K13: 1055 | L13: OPEX
A14: Sales and Marketing | B14: Sales | C14: Other operating expense (manpower/contracted) | D14: Jan | E14: RFP-SALES2026-0048 | F14: 01/19/2026 | G14: 01/09/2026 | H14: Anne Margot Estadilla | I14: Locksmith | J14: Key duplicate (Restroom for NRD customer) | K14: 50 | L14: OPEX
A15: HR | B15: HR | C15: Utilities (Telecom) | D15: Jan | E15: RFP-SALES2026-0048 | F15: 01/19/2026 | G15: 01/12/2026 | H15: Anne Margot Estadilla | I15: Royal Cable | J15: Royal Cable Internet | K15: 2196 | L15: OPEX
A16: HR | B16: HR | C16: Utilities (Telecom) | D16: Jan | E16: RFP-SALES2026-0048 | F16: 01/19/2026 | G16: 01/17/2026 | H16: Anne Margot Estadilla | I16: Globe/Telco | J16: Monthly Load Allowance (Gerald Kalaw) | K16: 299 | L16: OPEX
... A455: Supply Chain | B455: Retail | C455: Travel/transportation/meals | D455: Mar | E455: RFP-OPS2026-0021 | F455: 03/03/2026 | G455: 2/27/2026 | H455: Erwin Javillonar | I455: Bus | J455: Transpo Sta Rosa Bus Terminal to BBL Terminal Taft | K455: 102 | L455: OPEX
A456: Supply Chain | B456: Retail | C456: Taxes/licenses/permits | D456: Mar | E456: RFP-EXC2026-0020 | F456: 03/04/2026 | H456: GREGORY B. RIVERA | I456: Sta Rosa LGU | J456: Business permit renewal - Retail Store | K456: 16649 | L456: OPEX
A457: Supply Chain | B457: Retail | C457: Taxes/licenses/permits | D457: Mar | E457: RFP-COMP2026-0042 | F457: 03/05/2026 | G457: 3/3/2026 | H457: Sheila Vinuya | I457: Per Diem | J457: Per Diem (Sta Rosa LGU permit processing) | K457: 1050 | L457: OPEX
A458: Supply Chain | B458: Retail | C458: Travel/transportation/meals | D458: Mar | E458: RFP-COMP2026-0042 | F458: 03/05/2026 | G458: 3/3/2026 | H458: Sheila Vinuya | I458: Grab/Transport | J458: Transpo Sta Rosa Balibago to Retail Store | K458: 50 | L458: OPEX
A459: Supply Chain | B459: Retail | C459: Travel/transportation/meals | D459: Mar | E459: RFP-COMP2026-0042 | F459: 03/05/2026 | G459: 3/3/2026 | H459: Sheila Vinuya | I459: Grab/Transport | J459: Transpo Retail Store to Sta Rosa Cityhall | K459: 57 | L459: OPEX
A460: Supply Chain | B460: Retail | C460: Travel/transportation/meals | D460: Mar | E460: RFP-COMP2026-0042 | F460: 03/05/2026 | G460: 3/3/2026 | H460: Sheila Vinuya | I460: Grab/Transport | J460: Transpo Sta Rosa Cityhall to Sta Rosa Balibago | K460: 57 | L460: OPEX
A461: Supply Chain | B461: Retail | C461: Utilities (Electricity) | D461: Mar | E461: RFP-COMP2026-0042 | F461: 03/05/2026 | G461: 3/3/2026 | H461: Sheila Vinuya | I461: Bus | J461: Bus Fare Ayala to Sta Rosa Laguna | K461: 102 | L461: OPEX
A462: Supply Chain | B462: Retail | C462: Utilities (Electricity) | D462: Mar | E462: RFP-COMP2026-0042 | F462: 03/05/2026 | G462: 3/3/2026 | H462: Sheila Vinuya | I462: Bus | J462: Bus Fare Sta Rosa Laguna to One Ayala Terminal | K462: 102 | L462: OPEX
A463: Supply Chain | B463: Retail | C463: Travel/transportation/meals | D463: Mar | E463: RFP-OPS2026-0030 | F463: 03/18/2026 | G463: March 17, 2026 | H463: SAMUEL U KNIAZEFF JR. | I463: Christopher Mendoza (SR Mechanic) | J463: Sta Rosa Service Center Visit per diem 3 days @1050 | K463: 3150 | L463: OPEX
A464: Supply Chain | B464: Retail | C464: Travel/transportation/meals | D464: Mar | E464: RFP-IT2026-0176 | F464: 03/27/2026 | G464: 2026-03-24 | H464: Ian Gabrielle Jimenez | I464: (Hotel Sta. Rosa) | J464: Hotel Accommodation at Sta. Rosa | K464: 1490 | L464: OPEX
A465: Supply Chain | B465: Warehouse | C465: Utilities (Electricity) | D465: Mar | E465: RFP-HR2026-0181 | F465: 03/02/2026 | G465: 3/2/2026 | H465: SPACEPRO CORPORATION | I465: Spacepro Corporation | J465: Meralco bill (Electricity) Jan 22-Feb 20, 2026 | K465: 13973 | L465: OPEX
A466: Supply Chain | B466: Warehouse | C466: Travel/transportation/meals | D466: Mar | E466: RFP-OPS2026-0021 | F466: 03/03/2026 | G466: 2/27/2026 | H466: Erwin Javillonar | I466: Grab/Transport | J466: Transpo Rosario Pasig to One Ayala Bus Terminal | K466: 148 | L466: OPEX
A467: Supply Chain | B467: Warehouse | C467: Travel/transportation/meals | D467: Mar | E467: RFP-OPS2026-0021 | F467: 03/03/2026 | G467: 2/27/2026 | H467: Erwin Javillonar | I467: Grab/Transport | J467: Asgard to Jamo (Client Onboarding) | K467: 613 | L467: OPEX
A468: Supply Chain | B468: Warehouse | C468: Travel/transportation/meals | D468: Mar | E468: RFP-OPS2026-0021 | F468: 03/03/2026 | G468: 2/27/2026 | H468: Erwin Javillonar | I468: Grab/Transport | J468: Jamo to Asgard | K468: 609 | L468: OPEX
... A625: HR | B625: HR | C625: Travel/transportation/meals | D625: Mar | E625: RFP-COMP2026-0042 | F625: 03/05/2026 | G625: 3/3/2026 | H625: Sheila Vinuya | I625: Grab/Transport | J625: Transpo Ayala to Pasig | K625: 123 | L625: OPEX
A626: HR | B626: HR | C626: Taxes/licenses/permits | D626: Mar | E626: RFP-COMP2026-0042 | F626: 03/05/2026 | H626: Sheila Vinuya | I626: LGU | J626: Community Tax Certificate | K626: 513 | L626: OPEX
A627: HR | B627: HR | C627: Other operating expense (manpower/contracted) | D627: Mar | E627: RFP-COMP2026-0042 | F627: 03/05/2026 | H627: Sheila Vinuya | I627: Notary | J627: Notary documents (Dealer agreement) | K627: 1000 | L627: OPEX
A628: HR | B628: HR | C628: Employee benefits | D628: Mar | E628: RFP-COMP2026-0044 | F628: 03/13/2026 | G628: 03/09/2026 | H628: Pioneer Insurance and Surety Corporation | I628: Pioneer Insurance and Surety Corp. | J628: Payment of CTPL Insurance | K628: 33550 | L628: OPEX
A629: HR | B629: HR | C629: Taxes/licenses/permits | D629: Mar | E629: RFP-EXC2026-0019 | F629: 03/02/2026 | G629: 1/21/2026 | H629: GREGORY B. RIVERA | I629: DOE | J629: DOE Registration | K629: 3025 | L629: OPEX
A630: HR | B630: HR | C630: Taxes/licenses/permits | D630: Mar | E630: LIQ-COMP2026-0003 | F630: 03/04/2026 | G630: 2/23/2026 | H630: Sheila Vinuya | I630: Barangay | J630: Barangay clearance business closure | K630: 30 | L630: OPEX
A631: HR | B631: HR | C631: Taxes/licenses/permits | D631: Mar | E631: LIQ-COMP2026-0003 | F631: 03/04/2026 | G631: 2/23/2026 | H631: Sheila Vinuya | I631: LGU Malusak | J631: Business permit closure (Malusak) | K631: 9862 | L631: OPEX
A632: HR | B632: HR | C632: Taxes/licenses/permits | D632: Mar | E632: RFP-EXC2026-0020 | F632: 03/04/2026 | H632: GREGORY B. RIVERA | I632: Malusak LGU | J632: Business permit termination - Malusak | K632: 2000 | L632: OPEX
A633: HR | B633: HR | C633: Taxes/licenses/permits | D633: Mar | E633: RFP-COMP2026-0042 | F633: 03/05/2026 | G633: 2/27/2026 | H633: Sheila Vinuya | I633: Grab/Transport | J633: Transpo Office to Pasig LGU (Brixton permit) | K633: 50 | L633: OPEX
A634: HR | B634: HR | C634: Taxes/licenses/permits | D634: Mar | E634: RFP-COMP2026-0042 | F634: 03/05/2026 | H634: Sheila Vinuya | I634: Pasig LGU | J634: Business permit-Brixton CTC | K634: 100 | L634: OPEX
A635: HR | B635: HR | C635: Taxes/licenses/permits | D635: Mar | E635: LIQ-EXC2026-0001 | F635: 03/13/2026 | G635: 3/12/2026 | H635: GREGORY B. RIVERA | I635: Land Transportation Office | J635: MAIRDOE Renewal | K635: 2117 | L635: OPEX
A636: HR | B636: HR | C636: Advertising/promotions | D636: Apr | E636: RFP-MKTG2026-0015 | F636: 04/06/2026 | G636: 2026-03-24 | H636: WOKZPH | I636: wokz.ph | J636: MoveIt Banners x6 | K636: 3150 | L636: OPEX
A637: HR | B637: HR | C637: Travel/transportation/meals | D637: Apr | E637: RFP-MKTG2026-0018 | F637: 04/10/2026 | G637: 2026-03-26 | H637: THEA GRACE MASIGLAT | I637: (Transport) | J637: To TCI | K637: 236 | L637: OPEX
A638: HR | B638: HR | C638: Travel/transportation/meals | D638: Apr | E638: RFP-MKTG2026-0018 | F638: 04/10/2026 | G638: 2026-03-25 | H638: THEA GRACE MASIGLAT | I638: (Transport) | J638: To Asgard | K638: 160 | L638: OPEX
A639: HR | B639: HR | C639: Travel/transportation/meals | D639: Apr | E639: RFP-MKTG2026-0018 | F639: 04/10/2026 | G639: 2026-03-25 | H639: THEA GRACE MASIGLAT | I639: (Transport) | J639: To MoveIt | K639: 144 | L639: OPEX
A640: HR | B640: HR | C640: Travel/transportation/meals | D640: Apr | E640: RFP-MKTG2026-0018 | F640: 04/10/2026 | G640: 2026-03-26 | H640: THEA GRACE MASIGLAT | I640: (Transport) | J640: To Asgard | K640: 81 | L640: OPEX
A641: HR | B641: HR | C641: Travel/transportation/meals | D641: Apr | E641: RFP-MKTG2026-0018 | F641: 04/10/2026 | G641: 2026-03-25 | H641: THEA GRACE MASIGLAT | I641: (Transport) | J641: To Asgard | K641: 146 | L641: OPEX
A642: HR | B642: HR | C642: Travel/transportation/meals | D642: Apr | E642: RFP-MKTG2026-0018 | F642: 04/10/2026 | G642: 2026-03-26 | H642: THEA GRACE MASIGLAT | I642: (Transport) | J642: To MoveIt | K642: 50 | L642: OPEX
A643: HR | B643: HR | C643: Travel/transportation/meals | D643: Apr | E643: RFP-MKTG2026-0018 | F643: 04/10/2026 | G643: 2026-03-30 | H643: THEA GRACE MASIGLAT | I643: (Transport) | J643: To Minerva | K643: 416 | L643: OPEX
A644: Sales and Marketing | B644: Sales | C644: Advertising/promotions | D644: Apr | E644: RFP-MKTG2026-0016 | F644: 04/10/2026 | G644: 2026-04-10 | H644: WOKZPH | I644: wokz.ph | J644: Pull up banner refills for Flexride | K644: 525 | L644: OPEX
A645: Sales and Marketing | B645: Sales | C645: Utilities (Electricity) | D645: Apr | E645: RFP-SALES2026-0055 | F645: 04/13/2026 | G645: 2026-03-31 | H645: ANNE Margot Estadilla | I645: Laguna Water | J645: Laguna Water | K645: 257 | L645: OPEX
A646: Sales and Marketing | B646: Sales | C646: Utilities (Telecom) | D646: Apr | E646: RFP-SALES2026-0055 | F646: 04/13/2026 | G646: 2026-04-10 | H646: ANNE Margot Estadilla | I646: Royal Cable | J646: Royal Cable Internet | K646: 2200 | L646: OPEX
... A919: Admin | B919: Admin | C919: PPE - Machinery & equipment | D919: Jun | E919: RFP-IT2026-0193 | F919: 6/10/2026 | G919: 6/5/2026 | H919: Makerlab Electronics | I919: Makerlab Electronics | J919: Tools and Equipments | K919: 13421 | L919: CAPEX
A920: Sales and Marketing | B920: Sales | C920: Travel/transportation/meals | D920: Jul | E920: RFP-SALES2026-0062 | F920: 46206 | G920: 46206 | H920: Samson K. Lim Jr. | I920: Per diem | J920: Per Diem - Lim, Samson K. (no receipt attached) | K920: 1500 | L920: OPEX
A921: RideBox | B921: Monitoring & Field Ops | C921: Travel/transportation/meals | D921: Jul | E921: RFP-OPS2026-0080 | F921: 46204 | G921: 46208 | H921: Erwin Javillonar | I921: Per diem | J921: Per Diem - Sy, Jezalyn (no receipt attached) | K921: 1050 | L921: OPEX
A922: Compliance and Risk | B922: Legal & notarial | C922: Professional fees (Legal and notarial) | D922: Jun | E922: RFP-COMP2026-0052 | F922: 6/8/2026 | G922: 6/8/2026 | H922: Irene S. Preyra | I922: Irene S. Preyra | J922: Retainer fee - bookkeeping + BIR report submission | K922: 26548 | L922: OPEX
J923: TOTAL | K923: =SUM(K5:K922) -> 29463545
A926: MONTHLY SUMMARY
A927: Month | B927: OPEX | C927: CAPEX | D927: Total
A928: Jan | B928: =SUMIFS($K$5:$K$922,$D$5:$D$922,A928,$L$5:$L$922,"OPEX") -> 1890126 | C928: =SUMIFS($K$5:$K$922,$D$5:$D$922,A928,$L$5:$L$922,"CAPEX") -> 831769 | D928: =B928+C928 -> 2721895
A929: Feb | B929: =SUMIFS($K$5:$K$922,$D$5:$D$922,A929,$L$5:$L$922,"OPEX") -> 2133413 | C929: =SUMIFS($K$5:$K$922,$D$5:$D$922,A929,$L$5:$L$922,"CAPEX") -> 251381 | D929: =B929+C929 -> 2384794
A930: Mar | B930: =SUMIFS($K$5:$K$922,$D$5:$D$922,A930,$L$5:$L$922,"OPEX") -> 1458759 | C930: =SUMIFS($K$5:$K$922,$D$5:$D$922,A930,$L$5:$L$922,"CAPEX") -> 1795168 | D930: =B930+C930 -> 3253927
A931: Apr | B931: =SUMIFS($K$5:$K$922,$D$5:$D$922,A931,$L$5:$L$922,"OPEX") -> 1456638 | C931: =SUMIFS($K$5:$K$922,$D$5:$D$922,A931,$L$5:$L$922,"CAPEX") -> 4643020 | D931: =B931+C931 -> 6099658
A932: May | B932: =SUMIFS($K$5:$K$922,$D$5:$D$922,A932,$L$5:$L$922,"OPEX") -> 933660 | C932: =SUMIFS($K$5:$K$922,$D$5:$D$922,A932,$L$5:$L$922,"CAPEX") -> 842515 | D932: =B932+C932 -> 1776175
A933: Jun | B933: =SUMIFS($K$5:$K$922,$D$5:$D$922,A933,$L$5:$L$922,"OPEX") -> 296123 | C933: =SUMIFS($K$5:$K$922,$D$5:$D$922,A933,$L$5:$L$922,"CAPEX") -> 12928423 | D933: =B933+C933 -> 13224546
A934: Jul | B934: =SUMIFS($K$5:$K$922,$D$5:$D$922,A934,$L$5:$L$922,"OPEX") -> 2550 | C934: =SUMIFS($K$5:$K$922,$D$5:$D$922,A934,$L$5:$L$922,"CAPEX") -> 0 | D934: =B934+C934 -> 2550
A935: TOTAL | B935: =SUM(B928:B934) -> 8171269 | C935: =SUM(C928:C934) -> 21292276 | D935: =SUM(D928:D934) -> 29463545
