Workbook

Sheet Cover
C18: FINANCIAL MODEL

Sheet Unit Econ
B2: UNIT ECONOMICS 2026
C4: R280 MC | D4: D400 MC | E4: 1 Swap Station (Energy)
B5: STATION COMPOSITION
B6: Motorcycles served / station | E6: =10 -> 10
B7: Batteries / station (2 per MC) | E7: =E6*2 -> 20
B10: DAILY REVENUE
B11: Lease revenue / day (net of battery) | C11: =('MC Drivers (NRD)'!D30*30-'Energy Drivers (RideBox)'!D11)*12/365 -> 113.0137 | D11: =('MC Drivers (NRD)'!D31*30-'Energy Drivers (RideBox)'!D11)*12/365 -> 161.44814 | E11: =E6*'MC Drivers (NRD)'!D35*12/365 -> 1614.4814
B12: Battery subscription / day | C12: ='Energy Drivers (RideBox)'!D11*12/365 -> 80.72407 | D12: ='Energy Drivers (RideBox)'!D11*12/365 -> 80.72407 | E12: =E7*'Energy Drivers (RideBox)'!D11*12/365 -> 1614.4814
B13: Total Daily Revenue | C13: =C11+C12 -> 193.73777 | D13: =D11+D12 -> 242.17221 | E13: =E11+E12 -> 3228.9628
B15: DAILY COST
B16: Asset depreciation / day | C16: =('MC Drivers (NRD)'!D45+2*'MC Drivers (NRD)'!D63)/'MC Drivers (NRD)'!D185/365 -> 25.994066 | D16: =('MC Drivers (NRD)'!D52+2*'MC Drivers (NRD)'!D63)/'MC Drivers (NRD)'!D185/365 -> 36.309266 | E16: =(E6*(('MC Drivers (NRD)'!D32*'MC Drivers (NRD)'!D45+'MC Drivers (NRD)'!D33*'MC Drivers (NRD)'!D52)+2*'MC Drivers (NRD)'!D63)/'MC Drivers (NRD)'!D185+'Energy Drivers (RideBox)'!D100/'Energy Drivers (RideBox)'!D103)/365 -> 373.49178
B17: Insurance / day | C17: =4500/365 -> 12.328767 | D17: =6500/365 -> 17.808219 | E17: =('Energy Drivers (RideBox)'!D100*'Energy Drivers (RideBox)'!D104+E7*'MC Drivers (NRD)'!D63*'MC Drivers (NRD)'!D64)/365 -> 33.269587
B18: Registration / day | C18: ='MC Drivers (NRD)'!D79/365 -> 0.79908676 | D18: ='MC Drivers (NRD)'!D79/365 -> 0.79908676
B19: Site rent / day | E19: ='Energy Drivers (RideBox)'!D29*12/365 -> 146.77104
B20: Connectivity / day | E20: =('Energy Drivers (RideBox)'!D30+E7*'Energy Drivers (RideBox)'!D14)*12/365 -> 61.643836
B21: Maintenance / day | E21: ='Energy Drivers (RideBox)'!D31*12/365 -> 5.8708415
B22: Electricity / day | E22: ='Energy Drivers (RideBox)'!D26*'Energy Drivers (RideBox)'!D19*1.1 -> 107.72885
B23: Payment gateway / day | C23: =C11*'MC Drivers (NRD)'!D80 -> 3.390411 | D23: =D11*'MC Drivers (NRD)'!D80 -> 4.8434442 | E23: =E12*'Energy Drivers (RideBox)'!D13 -> 48.434442
B24: Total Daily Cost | C24: =SUM(C16:C23) -> 42.512331 | D24: =SUM(D16:D23) -> 59.760016 | E24: =SUM(E16:E23) -> 777.21037
B26: DAILY PROFITABILITY
B27: Daily Gross Profit | C27: =C13-C24 -> 151.22544 | D27: =D13-D24 -> 182.4122 | E27: =E13-E24 -> 2451.7524
B28: Daily Gross Margin | C28: =IFERROR(C27/C13,0) -> 0.78056767 | D28: =IFERROR(D27/D13,0) -> 0.75323339 | E28: =IFERROR(E27/E13,0) -> 0.7593003
B29: Daily Cash Profit (pre-dep) | C29: =C27+C16 -> 177.2195 | D29: =D27+D16 -> 218.72146 | E29: =E27+E16 -> 2825.2442
B31: ANNUALIZED P&L (per unit) NIAT
B32: Annual Revenue | C32: =C13*365 -> 70714.286 | D32: =D13*365 -> 88392.857 | E32: =E13*365 -> 1178571.4
B33: Annual Cash Operating Cost | C33: =(C24-C16)*365 -> 6029.1667 | D33: =(D24-D16)*365 -> 8559.5238 | E33: =(E24-E16)*365 -> 147357.29
B34: EBITDA | C34: =C32-C33 -> 64685.119 | D34: =D32-D33 -> 79833.333 | E34: =E32-E33 -> 1031214.1
B35: Depreciation | C35: =C16*365 -> 9487.834 | D35: =D16*365 -> 13252.882 | E35: =E16*365 -> 136324.5
B36: EBIT (Operating Profit) | C36: =C34-C35 -> 55197.285 | D36: =D34-D35 -> 66580.451 | E36: =E34-E35 -> 894889.64
B37: Tax @ 25% | C37: =MAX(C36,0)*'MC Drivers (NRD)'!D315 -> 13799.321 | D37: =MAX(D36,0)*'MC Drivers (NRD)'!D315 -> 16645.113 | E37: =MAX(E36,0)*'MC Drivers (NRD)'!D315 -> 223722.41
B38: NIAT (Net Income After Tax) | C38: =C36-C37 -> 41397.964 | D38: =D36-D37 -> 49935.338 | E38: =E36-E37 -> 671167.23
B39: Net Margin (NIAT / Revenue) | C39: =IFERROR(C38/C32,0) -> 0.58542575 | D39: =IFERROR(D38/D32,0) -> 0.56492504 | E39: =IFERROR(E38/E32,0) -> 0.56947523
B41: PAYBACK & RETURNS
B42: Asset base (capex) | C42: ='MC Drivers (NRD)'!D45+2*'MC Drivers (NRD)'!D63 -> 94878.34 | D42: ='MC Drivers (NRD)'!D52+2*'MC Drivers (NRD)'!D63 -> 132528.82 | E42: ='Energy Drivers (RideBox)'!D100+E6*(('MC Drivers (NRD)'!D32*'MC Drivers (NRD)'!D45+'MC Drivers (NRD)'!D33*'MC Drivers (NRD)'!D52)+2*'MC Drivers (NRD)'!D63) -> 1363245
B43: Payback (years, on cash profit) | C43: =IFERROR(C42/C29/365,0) -> 1.4667723 | D43: =IFERROR(D42/D29/365,0) -> 1.6600687 | E43: =IFERROR(E42/E29/365,0) -> 1.3219805
B44: 10-yr Asset IRR | C44: =IFERROR(RATE(10,C32-C33-C37,-C42),0) -> 0.52862823 | D44: =IFERROR(RATE(10,D32-D33-D37,-D42),0) -> 0.46641936 | E44: =IFERROR(RATE(10,E32-E33-E37,-E42),0) -> 0.58646574

Sheet MC Drivers (NRD)
B2: NRD MOTORCYCLE - DRIVERS & INPUTS
B3: PHP (unless noted)
C4: Note / rate | D4: 2026 | E4: 2027 | F4: 2028 | G4: 2029 | H4: 2030 | I4: 2031 | J4: 2032 | K4: 2033 | L4: 2034 | M4: 2035 | N4: 2036
B5: OPERATING METRICS
B6: Growth Assumptions
B7: New Units Leased | E7: 0.5 | F7: 0.45 | G7: 0.31 | H7: 0.17 | I7: 0.18 | J7: 0.25 | K7: 0.182 | L7: 0.094 | M7: 0.086 | N7: 0.079
B8: Units Sold Outright | E8: 0.6 | F8: 0.6 | G8: 0.4 | H8: 0.25 | I8: 0.2 | J8: 0.25 | K8: 0.2 | L8: 0.111 | M8: 0.1 | N8: 0.0909
B9: Lease-to-Own units | E9: 0.4 | F9: 0.3 | G9: 0.3 | H9: 0.3 | I9: 0.3 | J9: 0.3 | K9: 0.3 | L9: 0.3 | M9: 0.3 | N9: 0.3
B10: Lease Churn % | C10: p.a. | D10: 0 | E10: =0.03 -> 0.03 | F10: =E10 -> 0.03 | G10: =F10 -> 0.03 | H10: =G10 -> 0.03 | I10: =H10 -> 0.03 | J10: =I10 -> 0.03 | K10: =J10 -> 0.03 | L10: =K10 -> 0.03 | M10: =L10 -> 0.03 | N10: =M10 -> 0.03
B12: Beginning Leased Fleet | C12: units | D12: =D349+D350 -> 0 | E12: =E349+E350 -> 2216 | F12: =F349+F350 -> 5374 | G12: =G349+G350 -> 9888 | H12: =H349+H350 -> 15717 | I12: =I349+I350 -> 22412 | J12: =J349+J350 -> 30197 | K12: =K349+K350 -> 39863 | ... N12: =N349+N350 -> 76246
B13: (+) New Units Leased | C13: units | D13: =D351+D352 -> 2216 | E13: =E351+E352 -> 3325 | F13: =F351+F352 -> 4821 | G13: =G351+G352 -> 6316 | H13: =H351+H352 -> 7390 | I13: =I351+I352 -> 8720 | J13: =J351+J352 -> 10900 | K13: =K351+K352 -> 12883 | ... N13: =N351+N352 -> 16516
B14: (-) Lease Churn | C14: units | D14: =D353+D354 -> 0 | E14: =E353+E354 -> -167 | F14: =F353+F354 -> -307 | G14: =G353+G354 -> -487 | H14: =H353+H354 -> -695 | I14: =I353+I354 -> -935 | J14: =J353+J354 -> -1234 | K14: =K353+K354 -> -1583 | ... N14: =N353+N354 -> -2784
B15: Ending Leased Fleet (stock) | C15: units | D15: =D355+D356 -> 2216 | E15: =E355+E356 -> 5374 | F15: =F355+F356 -> 9888 | G15: =G355+G356 -> 15717 | H15: =H355+H356 -> 22412 | I15: =I355+I356 -> 30197 | J15: =J355+J356 -> 39863 | K15: =K355+K356 -> 51163 | ... N15: =N355+N356 -> 89978
B16: Avg Leased Fleet | C16: units | D16: =D357+D358 -> 1108 | E16: =E357+E358 -> 3795 | F16: =F357+F358 -> 7631 | G16: =G357+G358 -> 12802.5 | H16: =H357+H358 -> 19064.5 | I16: =I357+I358 -> 26304.5 | J16: =J357+J358 -> 35030 | K16: =K357+K358 -> 45513 | ... N16: =N357+N358 -> 83112
B17: (+) Units Sold Outright | C17: units | D17: =D359+D360 -> 1200 | E17: =E359+E360 -> 1920 | F17: =F359+F360 -> 3072 | G17: =G359+G360 -> 4301 | H17: =H359+H360 -> 5376 | I17: =I359+I360 -> 6451 | J17: =J359+J360 -> 8064 | K17: =K359+K360 -> 9677 | ... N17: =N359+N360 -> 12901
B18: Cumulative Sold Units (owner base) | C18: units | D18: =D361+D362 -> 1200 | E18: =E361+E362 -> 3120 | F18: =F361+F362 -> 6192 | G18: =G361+G362 -> 10493 | H18: =H361+H362 -> 15869 | I18: =I361+I362 -> 22320 | J18: =J361+J362 -> 30384 | K18: =K361+K362 -> 40061 | ... N18: =N361+N362 -> 75539
B20: Lease-to-Own (L2O)
B21: L2O Term | C21: months | D21: 36 | E21: =D21 -> 36 | F21: =E21 -> 36 | G21: =F21 -> 36 | H21: =G21 -> 36 | I21: =H21 -> 36 | J21: =I21 -> 36 | K21: =J21 -> 36 | L21: =K21 -> 36 | ... N21: =M21 -> 36
B22: L2O R280 Mix % | C22: % | D22: 0.2 | E22: =$D22 -> 0.2 | F22: 0.2 | G22: 0.2 | H22: 0.2 | I22: 0.2 | J22: 0.2 | K22: 0.2 | L22: 0.2 | M22: 0.2 | N22: 0.2
B23: L2O-R280 Monthly Installment | C23: 6500/1.12 | D23: =6500/1.12 -> 5803.5714 | E23: =D23 -> 5803.5714 | F23: =E23 -> 5803.5714 | G23: =F23 -> 5803.5714 | H23: =G23 -> 5803.5714 | I23: =H23 -> 5803.5714 | J23: =I23 -> 5803.5714 | K23: =J23 -> 5803.5714 | L23: =K23 -> 5803.5714 | ... N23: =M23 -> 5803.5714
B24: L2O-D400 Monthly Installment | C24: 9000/1.12 | D24: =9000/1.12 -> 8035.7143 | E24: =D24 -> 8035.7143 | F24: =E24 -> 8035.7143 | G24: =F24 -> 8035.7143 | H24: =G24 -> 8035.7143 | I24: =H24 -> 8035.7143 | J24: =I24 -> 8035.7143 | K24: =J24 -> 8035.7143 | L24: =K24 -> 8035.7143 | ... N24: =M24 -> 8035.7143
B25: (+) New L2O Units [growth-driven] | C25: units | D25: =D363+D364 -> 200 | E25: =E363+E364 -> 280 | F25: =F363+F364 -> 364 | G25: =G363+G364 -> 473 | H25: =H363+H364 -> 615 | I25: =I363+I364 -> 799 | J25: =J363+J364 -> 1038 | K25: =K363+K364 -> 1350 | ... N25: =N363+N364 -> 2965
B26: Cumulative L2O Units placed | C26: units | D26: =D365+D366 -> 200 | E26: =E365+E366 -> 480 | F26: =F365+F366 -> 844 | G26: =G365+G366 -> 1317 | H26: =H365+H366 -> 1932 | I26: =I365+I366 -> 2731 | J26: =J365+J366 -> 3769 | K26: =K365+K366 -> 5119 | ... N26: =N365+N366 -> 12120
B27: Active L2O Contracts (within term) | C27: units | D27: =D367+D368 -> 200 | E27: =E367+E368 -> 480 | F27: =F367+F368 -> 844 | G27: =G367+G368 -> 1117 | H27: =H367+H368 -> 1452 | I27: =I367+I368 -> 1887 | J27: =J367+J368 -> 2452 | K27: =K367+K368 -> 3187 | ... N27: =N367+N368 -> 7001
B29: Lease Rates (D400 & R280)
B30: R280 - Daily Lease Rate (VAT-ex) | C30: 200/1.12 | D30: =220/1.12 -> 196.42857 | E30: =220/1.12 -> 196.42857 | F30: =220/1.12 -> 196.42857 | G30: =220/1.12 -> 196.42857 | H30: =220/1.12 -> 196.42857 | I30: =220/1.12 -> 196.42857 | J30: =220/1.12 -> 196.42857 | K30: =220/1.12 -> 196.42857 | ... N30: =220/1.12 -> 196.42857
B31: D400 - Daily Lease Rate (VAT-ex) | C31: 250/1.12 | D31: =275/1.12 -> 245.53571 | E31: =275/1.12 -> 245.53571 | F31: =275/1.12 -> 245.53571 | G31: =275/1.12 -> 245.53571 | H31: =275/1.12 -> 245.53571 | I31: =275/1.12 -> 245.53571 | J31: =275/1.12 -> 245.53571 | K31: =275/1.12 -> 245.53571 | ... N31: =275/1.12 -> 245.53571
B32: R280 - Lease Mix | C32: % | D32: 0.2 | E32: =D32 -> 0.2 | F32: =E32 -> 0.2 | G32: =F32 -> 0.2 | H32: =G32 -> 0.2 | I32: =H32 -> 0.2 | J32: =I32 -> 0.2 | K32: =J32 -> 0.2 | L32: =K32 -> 0.2 | ... N32: =M32 -> 0.2
B33: D400 - Lease Mix | C33: 1-R280 | D33: =1-D32 -> 0.8 | E33: =1-E32 -> 0.8 | F33: =1-F32 -> 0.8 | G33: =1-G32 -> 0.8 | H33: =1-H32 -> 0.8 | I33: =1-I32 -> 0.8 | J33: =1-J32 -> 0.8 | K33: =1-K32 -> 0.8 | ... N33: =1-N32 -> 0.8
B34: LSE Monthly Lease Rate - R280 (net of battery) | D34: =D381 -> 3437.5 | E34: =E381 -> 3437.5 | F34: =F381 -> 3437.5 | G34: =G381 -> 3437.5 | H34: =H381 -> 3437.5 | I34: =I381 -> 3437.5 | J34: =J381 -> 3437.5 | K34: =K381 -> 3437.5 | ... N34: =N381 -> 3437.5
B35: LSE Monthly Lease Rate - D400 (net of battery) | C35: wtd*30 - Energy batt | D35: =D382 -> 4910.7143 | E35: =E382 -> 4910.7143 | F35: =F382 -> 4910.7143 | G35: =G382 -> 4910.7143 | H35: =H382 -> 4910.7143 | I35: =I382 -> 4910.7143 | J35: =J382 -> 4910.7143 | K35: =K382 -> 4910.7143 | ... N35: =N382 -> 4910.7143
B37: PRICING & UNIT ECONOMICS (feeds Revenue & COGS)
B38: Landed Cost - Motorcycle Units
B39: R280 - FOB Unit Price (USD) | C39: USD | D39: 516 | E39: =D39 -> 516 | F39: =E39 -> 516 | G39: =F39 -> 516 | H39: =G39 -> 516 | I39: =H39 -> 516 | J39: =I39 -> 516 | K39: =J39 -> 516 | L39: =K39 -> 516 | ... N39: =M39 -> 516
B40: R280 - Unit Cost (PHP) = USD x forex | D40: =D39*D316 -> 31682.4 | E40: =E39*E316 -> 31682.4 | F40: =F39*F316 -> 31682.4 | G40: =G39*G316 -> 31682.4 | H40: =H39*H316 -> 31682.4 | I40: =I39*I316 -> 31682.4 | J40: =J39*J316 -> 31682.4 | K40: =K39*K316 -> 31682.4 | ... N40: =N39*N316 -> 31682.4
B41: R280 - Freight & Shipping | C41: PHP | D41: 1800 | E41: =D41 -> 1800 | F41: =E41 -> 1800 | G41: =F41 -> 1800 | H41: =G41 -> 1800 | I41: =H41 -> 1800 | J41: =I41 -> 1800 | K41: =J41 -> 1800 | L41: =K41 -> 1800 | ... N41: =M41 -> 1800
B42: R280 - Customs / Brokerage / Duty | C42: PHP | D42: 1500 | E42: =D42 -> 1500 | F42: =E42 -> 1500 | G42: =F42 -> 1500 | H42: =G42 -> 1500 | I42: =H42 -> 1500 | J42: =I42 -> 1500 | K42: =J42 -> 1500 | L42: =K42 -> 1500 | ... N42: =M42 -> 1500
B43: R280 - Labor / Handling / PDI | C43: PHP | D43: 1000 | E43: =D43 -> 1000 | F43: =E43 -> 1000 | G43: =F43 -> 1000 | H43: =G43 -> 1000 | I43: =H43 -> 1000 | J43: =I43 -> 1000 | K43: =J43 -> 1000 | L43: =K43 -> 1000 | ... N43: =M43 -> 1000
B44: R280 - Spareparts & Accessories | C44: 30% unit cost | D44: =D40*30% -> 9504.72 | E44: =E40*30% -> 9504.72 | F44: =F40*30% -> 9504.72 | G44: =G40*30% -> 9504.72 | H44: =H40*30% -> 9504.72 | I44: =I40*30% -> 9504.72 | J44: =J40*30% -> 9504.72 | K44: =K40*30% -> 9504.72 | ... N44: =N40*30% -> 9504.72
B45: R280 - Landed Cost (sum) | D45: =D40+D41+D42+D43+D44 -> 45487.12 | E45: =E40+E41+E42+E43+E44 -> 45487.12 | F45: =F40+F41+F42+F43+F44 -> 45487.12 | G45: =G40+G41+G42+G43+G44 -> 45487.12 | H45: =H40+H41+H42+H43+H44 -> 45487.12 | I45: =I40+I41+I42+I43+I44 -> 45487.12 | J45: =J40+J41+J42+J43+J44 -> 45487.12 | K45: =K40+K41+K42+K43+K44 -> 45487.12 | ... N45: =N40+N41+N42+N43+N44 -> 45487.12
B46: D400 - FOB Unit Price (USD) | C46: USD | D46: 1070 | E46: =D46 -> 1070 | F46: =E46 -> 1070 | G46: =F46 -> 1070 | H46: =G46 -> 1070 | I46: =H46 -> 1070 | J46: =I46 -> 1070 | K46: =J46 -> 1070 | L46: =K46 -> 1070 | ... N46: =M46 -> 1070
B47: D400 - Unit Cost (PHP) = USD x forex | D47: =D46*D316 -> 65698 | E47: =E46*E316 -> 65698 | F47: =F46*F316 -> 65698 | G47: =G46*G316 -> 65698 | H47: =H46*H316 -> 65698 | I47: =I46*I316 -> 65698 | J47: =J46*J316 -> 65698 | K47: =K46*K316 -> 65698 | ... N47: =N46*N316 -> 65698
B48: D400 - Freight & Shipping | C48: PHP | D48: 1800 | E48: =D48 -> 1800 | F48: =E48 -> 1800 | G48: =F48 -> 1800 | H48: =G48 -> 1800 | I48: =H48 -> 1800 | J48: =I48 -> 1800 | K48: =J48 -> 1800 | L48: =K48 -> 1800 | ... N48: =M48 -> 1800
B49: D400 - Customs / Brokerage / Duty | C49: PHP | D49: 1500 | E49: =D49 -> 1500 | F49: =E49 -> 1500 | G49: =F49 -> 1500 | H49: =G49 -> 1500 | I49: =H49 -> 1500 | J49: =I49 -> 1500 | K49: =J49 -> 1500 | L49: =K49 -> 1500 | ... N49: =M49 -> 1500
B50: D400 - Labor / Handling / PDI | C50: PHP | D50: 1000 | E50: =D50 -> 1000 | F50: =E50 -> 1000 | G50: =F50 -> 1000 | H50: =G50 -> 1000 | I50: =H50 -> 1000 | J50: =I50 -> 1000 | K50: =J50 -> 1000 | L50: =K50 -> 1000 | ... N50: =M50 -> 1000
B51: D400 - Spareparts & Accessories | C51: 0.2 | D51: =D47*$C$51 -> 13139.6 | E51: =E47*$C$51 -> 13139.6 | F51: =F47*$C$51 -> 13139.6 | G51: =G47*$C$51 -> 13139.6 | H51: =H47*$C$51 -> 13139.6 | I51: =I47*$C$51 -> 13139.6 | J51: =J47*$C$51 -> 13139.6 | K51: =K47*$C$51 -> 13139.6 | ... N51: =N47*$C$51 -> 13139.6
B52: D400 - Landed Cost (sum) | D52: =D47+D48+D49+D50+D51 -> 83137.6 | E52: =E47+E48+E49+E50+E51 -> 83137.6 | F52: =F47+F48+F49+F50+F51 -> 83137.6 | G52: =G47+G48+G49+G50+G51 -> 83137.6 | H52: =H47+H48+H49+H50+H51 -> 83137.6 | I52: =I47+I48+I49+I50+I51 -> 83137.6 | J52: =J47+J48+J49+J50+J51 -> 83137.6 | K52: =K47+K48+K49+K50+K51 -> 83137.6 | ... N52: =N47+N48+N49+N50+N51 -> 83137.6
B53: R280 - Sale Mix | C53: % | D53: 0.2 | E53: =D53 -> 0.2 | F53: =E53 -> 0.2 | G53: =F53 -> 0.2 | H53: =G53 -> 0.2 | I53: =H53 -> 0.2 | J53: =I53 -> 0.2 | K53: =J53 -> 0.2 | L53: =K53 -> 0.2 | ... N53: =M53 -> 0.2
B54: D400 - Sale Mix | C54: 1-R280 | D54: =1-D53 -> 0.8 | E54: =1-E53 -> 0.8 | F54: =1-F53 -> 0.8 | G54: =1-G53 -> 0.8 | H54: =1-H53 -> 0.8 | I54: =1-I53 -> 0.8 | J54: =1-J53 -> 0.8 | K54: =1-K53 -> 0.8 | ... N54: =1-N53 -> 0.8
B56: Battery - Landed Cost
B57: Batteries per Motorcycle | C57: units | D57: 2 | E57: =D57 -> 2 | F57: =E57 -> 2 | G57: =F57 -> 2 | H57: =G57 -> 2 | I57: =H57 -> 2 | J57: =I57 -> 2 | K57: =J57 -> 2 | L57: =K57 -> 2 | ... N57: =M57 -> 2
B58: Battery - FOB Price (USD) | C58: USD | D58: 350 | E58: =D58 -> 350 | F58: =E58 -> 350 | G58: =F58 -> 350 | H58: =G58 -> 350 | I58: =H58 -> 350 | J58: =I58 -> 350 | K58: =J58 -> 350 | L58: =K58 -> 350 | ... N58: =M58 -> 350
B59: Battery - Unit Cost (PHP) | D59: =D58*D316 -> 21490 | E59: =E58*E316 -> 21490 | F59: =F58*F316 -> 21490 | G59: =G58*G316 -> 21490 | H59: =H58*H316 -> 21490 | I59: =I58*I316 -> 21490 | J59: =J58*J316 -> 21490 | K59: =K58*K316 -> 21490 | ... N59: =N58*N316 -> 21490
B60: Battery - Freight & Shipping | C60: PHP | D60: 1800 | E60: =D60 -> 1800 | F60: =E60 -> 1800 | G60: =F60 -> 1800 | H60: =G60 -> 1800 | I60: =H60 -> 1800 | J60: =I60 -> 1800 | K60: =J60 -> 1800 | L60: =K60 -> 1800 | ... N60: =M60 -> 1800
B61: Battery - Customs / Brokerage | C61: PHP | D61: 600 | E61: =D61 -> 600 | F61: =E61 -> 600 | G61: =F61 -> 600 | H61: =G61 -> 600 | I61: =H61 -> 600 | J61: =I61 -> 600 | K61: =J61 -> 600 | L61: =K61 -> 600 | ... N61: =M61 -> 600
B62: Battery - Labor / Handling | C62: PHP | D62: 805.61 | E62: =D62 -> 805.61 | F62: =E62 -> 805.61 | G62: =F62 -> 805.61 | H62: =G62 -> 805.61 | I62: =H62 -> 805.61 | J62: =I62 -> 805.61 | K62: =J62 -> 805.61 | L62: =K62 -> 805.61 | ... N62: =M62 -> 805.61
B63: Battery Landed Cost (sum) | D63: =D59+D60+D61+D62 -> 24695.61 | E63: =E59+E60+E61+E62 -> 24695.61 | F63: =F59+F60+F61+F62 -> 24695.61 | G63: =G59+G60+G61+G62 -> 24695.61 | H63: =H59+H60+H61+H62 -> 24695.61 | I63: =I59+I60+I61+I62 -> 24695.61 | J63: =J59+J60+J61+J62 -> 24695.61 | K63: =K59+K60+K61+K62 -> 24695.61 | ... N63: =N59+N60+N61+N62 -> 24695.61
B64: Battery Insurance % of cum value | C64: % | D64: 0.02 | E64: =D64 -> 0.02 | F64: =E64 -> 0.02 | G64: =F64 -> 0.02 | H64: =G64 -> 0.02 | I64: =H64 -> 0.02 | J64: =I64 -> 0.02 | K64: =J64 -> 0.02 | L64: =K64 -> 0.02 | ... N64: =M64 -> 0.02
B66: SRP & Selling Price
B67: R280 - Unit + 2 Batteries Landed | C67: 2 | D67: =D45+$C$67*D63 -> 94878.34 | E67: =E45+$C$67*E63 -> 94878.34 | F67: =F45+$C$67*F63 -> 94878.34 | G67: =G45+$C$67*G63 -> 94878.34 | H67: =H45+$C$67*H63 -> 94878.34 | I67: =I45+$C$67*I63 -> 94878.34 | J67: =J45+$C$67*J63 -> 94878.34 | K67: =K45+$C$67*K63 -> 94878.34 | ... N67: =N45+$C$67*N63 -> 94878.34
B68: D400 - Unit + 2 Batteries Landed | C68: 2 | D68: =D52+$C$68*D63 -> 132528.82 | E68: =E52+$C$68*E63 -> 132528.82 | F68: =F52+$C$68*F63 -> 132528.82 | G68: =G52+$C$68*G63 -> 132528.82 | H68: =H52+$C$68*H63 -> 132528.82 | I68: =I52+$C$68*I63 -> 132528.82 | J68: =J52+$C$68*J63 -> 132528.82 | K68: =K52+$C$68*K63 -> 132528.82 | ... N68: =N52+$C$68*N63 -> 132528.82
B69: R280 - Markup % | C69: on landed | D69: 0.4 | E69: =D69 -> 0.4 | F69: =E69 -> 0.4 | G69: =F69 -> 0.4 | H69: =G69 -> 0.4 | I69: =H69 -> 0.4 | J69: =I69 -> 0.4 | K69: =J69 -> 0.4 | L69: =K69 -> 0.4 | ... N69: =M69 -> 0.4
B70: D400 - Markup % | C70: on landed | D70: 0.4 | E70: =D70 -> 0.4 | F70: =E70 -> 0.4 | G70: =F70 -> 0.4 | H70: =G70 -> 0.4 | I70: =H70 -> 0.4 | J70: =I70 -> 0.4 | K70: =J70 -> 0.4 | L70: =K70 -> 0.4 | ... N70: =M70 -> 0.4
B71: R280 - SRP = basis x (1+markup) | D71: =D67*(1+D69) -> 132829.68 | E71: =E67*(1+E69) -> 132829.68 | F71: =F67*(1+F69) -> 132829.68 | G71: =G67*(1+G69) -> 132829.68 | H71: =H67*(1+H69) -> 132829.68 | I71: =I67*(1+I69) -> 132829.68 | J71: =J67*(1+J69) -> 132829.68 | K71: =K67*(1+K69) -> 132829.68 | ... N71: =N67*(1+N69) -> 132829.68
B72: D400 - SRP = basis x (1+markup) | D72: =D68*(1+D70) -> 185540.35 | E72: =E68*(1+E70) -> 185540.35 | F72: =F68*(1+F70) -> 185540.35 | G72: =G68*(1+G70) -> 185540.35 | H72: =H68*(1+H70) -> 185540.35 | I72: =I68*(1+I70) -> 185540.35 | J72: =J68*(1+J70) -> 185540.35 | K72: =K68*(1+K70) -> 185540.35 | ... N72: =N68*(1+N70) -> 185540.35
B73: Dealer Discount | C73: % | D73: 0.1 | E73: =D73 -> 0.1 | F73: =E73 -> 0.1 | G73: =F73 -> 0.1 | H73: =G73 -> 0.1 | I73: =H73 -> 0.1 | J73: =I73 -> 0.1 | K73: =J73 -> 0.1 | L73: =K73 -> 0.1 | ... N73: =M73 -> 0.1
B75: Other Revenue / Cost Rates
B76: Aftersales Rev % of Sales | C76: % | D76: 0.1 | E76: =D76 -> 0.1 | F76: =E76 -> 0.1 | G76: =F76 -> 0.1 | H76: =G76 -> 0.1 | I76: =H76 -> 0.1 | J76: =I76 -> 0.1 | K76: =J76 -> 0.1 | L76: =K76 -> 0.1 | ... N76: =M76 -> 0.1
B77: Aftersales COGS % of Aftersales Rev | C77: % | D77: 0.4 | E77: =D77 -> 0.4 | F77: =E77 -> 0.4 | G77: =F77 -> 0.4 | H77: =G77 -> 0.4 | I77: =H77 -> 0.4 | J77: =I77 -> 0.4 | K77: =J77 -> 0.4 | L77: =K77 -> 0.4 | ... N77: =M77 -> 0.4
B78: MC Insurance per unit / mo (wtd) | C78: PHP/mo | D78: =(((3500/1.12)*D32)+((5000/1.12)*D33))/12 -> 349.70238 | E78: =(((3500/1.12)*E32)+((5000/1.12)*E33))/12 -> 349.70238 | F78: =(((3500/1.12)*F32)+((5000/1.12)*F33))/12 -> 349.70238 | G78: =(((3500/1.12)*G32)+((5000/1.12)*G33))/12 -> 349.70238 | H78: =(((3500/1.12)*H32)+((5000/1.12)*H33))/12 -> 349.70238 | I78: =(((3500/1.12)*I32)+((5000/1.12)*I33))/12 -> 349.70238 | J78: =(((3500/1.12)*J32)+((5000/1.12)*J33))/12 -> 349.70238 | K78: =(((3500/1.12)*K32)+((5000/1.12)*K33))/12 -> 349.70238 | ... N78: =(((3500/1.12)*N32)+((5000/1.12)*N33))/12 -> 349.70238
B79: MC Registration per unit | C79: PHP/mo | D79: =3500/12 -> 291.66667 | E79: =D79 -> 291.66667 | F79: =E79 -> 291.66667 | G79: =F79 -> 291.66667 | H79: =G79 -> 291.66667 | I79: =H79 -> 291.66667 | J79: =I79 -> 291.66667 | K79: =J79 -> 291.66667 | L79: =K79 -> 291.66667 | ... N79: =M79 -> 291.66667
B80: Lease Payment Gateway % of lease rev | C80: % | D80: 0.03 | E80: =D80 -> 0.03 | F80: =E80 -> 0.03 | G80: =F80 -> 0.03 | H80: =G80 -> 0.03 | I80: =H80 -> 0.03 | J80: =I80 -> 0.03 | K80: =J80 -> 0.03 | L80: =K80 -> 0.03 | ... N80: =M80 -> 0.03
B81: Sales Commission % of MC sales | C81: % | D81: 0.02 | E81: =D81 -> 0.02 | F81: =E81 -> 0.02 | G81: =F81 -> 0.02 | H81: =G81 -> 0.02 | I81: =H81 -> 0.02 | J81: =I81 -> 0.02 | K81: =J81 -> 0.02 | L81: =K81 -> 0.02 | ... N81: =M81 -> 0.02
B82: Marketing % of total revenue | C82: % | D82: 0.02 | E82: =D82 -> 0.02 | F82: =E82 -> 0.02 | G82: =F82 -> 0.02 | H82: =G82 -> 0.02 | I82: =H82 -> 0.02 | J82: =I82 -> 0.02 | K82: =J82 -> 0.02 | L82: =K82 -> 0.02 | ... N82: =M82 -> 0.02
B84: OPERATING EXPENSES (OPEX)
B85: Cost Escalation | C85: p.a. | D85: 0.05 | E85: =D85 -> 0.05 | F85: =E85 -> 0.05 | G85: =F85 -> 0.05 | H85: =G85 -> 0.05 | I85: =H85 -> 0.05 | J85: =I85 -> 0.05 | K85: =J85 -> 0.05 | L85: =K85 -> 0.05 | ... N85: =M85 -> 0.05
B87: Headcount & Salaries
B88: Headcount growth % p.a. (applied to each dept) | C88: 0.1
B89: Salary Escalation | C89: p.a. | D89: 0.05 | E89: =D89 -> 0.05 | F89: =E89 -> 0.05 | G89: =F89 -> 0.05 | H89: =G89 -> 0.05 | I89: =H89 -> 0.05 | J89: =I89 -> 0.05 | K89: =J89 -> 0.05 | L89: =K89 -> 0.05 | ... N89: =M89 -> 0.05
B90: • Sales & Marketing | C90: HC | D90: 13 | E90: =D90*(1+$C$88) -> 14.3 | F90: =E90*(1+$C$88) -> 15.73 | G90: =F90*(1+$C$88) -> 17.303 | H90: =G90*(1+$C$88) -> 19.0333 | I90: =H90*(1+$C$88) -> 20.93663 | J90: =I90*(1+$C$88) -> 23.030293 | K90: =J90*(1+$C$88) -> 25.333322 | L90: =K90*(1+$C$88) -> 27.866655 | ... N90: =M90*(1+$C$88) -> 33.718652
C91: PHP/mo | D91: 108250 | E91: =D91*(1+E89) -> 113662.5 | F91: =E91*(1+F89) -> 119345.62 | G91: =F91*(1+G89) -> 125312.91 | H91: =G91*(1+H89) -> 131578.55 | I91: =H91*(1+I89) -> 138157.48 | J91: =I91*(1+J89) -> 145065.35 | K91: =J91*(1+K89) -> 152318.62 | L91: =K91*(1+L89) -> 159934.55 | ... N91: =M91*(1+N89) -> 176327.84
C92: 13 | D92: =D90*D91*$C92 -> 18294250 | E92: =E90*E91*$C92 -> 21129859 | F92: =F90*F91*$C92 -> 24404987 | G92: =G90*G91*$C92 -> 28187760 | H92: =H90*H91*$C92 -> 32556863 | I92: =I90*I91*$C92 -> 37603176 | J92: =J90*J91*$C92 -> 43431669 | K92: =K90*K91*$C92 -> 50163577 | ... N92: =N90*N91*$C92 -> 77291983
B93: • AfterSales Center | C93: HC | D93: 5 | E93: =D93*(1+$C$88) -> 5.5 | F93: =E93*(1+$C$88) -> 6.05 | G93: =F93*(1+$C$88) -> 6.655 | H93: =G93*(1+$C$88) -> 7.3205 | I93: =H93*(1+$C$88) -> 8.05255 | J93: =I93*(1+$C$88) -> 8.857805 | K93: =J93*(1+$C$88) -> 9.7435855 | L93: =K93*(1+$C$88) -> 10.717944 | ... N93: =M93*(1+$C$88) -> 12.968712
C94: PHP/mo | D94: 25646 | E94: =D94*(1+E89) -> 26928.3 | F94: =E94*(1+F89) -> 28274.715 | G94: =F94*(1+G89) -> 29688.451 | H94: =G94*(1+H89) -> 31172.873 | I94: =H94*(1+I89) -> 32731.517 | J94: =I94*(1+J89) -> 34368.093 | K94: =J94*(1+K89) -> 36086.497 | L94: =K94*(1+L89) -> 37890.822 | ... N94: =M94*(1+N89) -> 41774.632
C95: 13 | D95: =D93*D94*$C95 -> 1666990 | E95: =E93*E94*$C95 -> 1925373.4 | F95: =F93*F94*$C95 -> 2223806.3 | G95: =G93*G94*$C95 -> 2568496.3 | H95: =H93*H94*$C95 -> 2966613.2 | I95: =I93*I94*$C95 -> 3426438.3 | J95: =J93*J94*$C95 -> 3957536.2 | K95: =K93*K94*$C95 -> 4570954.4 | ... N95: =N93*N94*$C95 -> 7042921.3
B96: • Supply Chain | C96: HC | D96: 10 | E96: =D96*(1+$C$88) -> 11 | F96: =E96*(1+$C$88) -> 12.1 | G96: =F96*(1+$C$88) -> 13.31 | H96: =G96*(1+$C$88) -> 14.641 | I96: =H96*(1+$C$88) -> 16.1051 | J96: =I96*(1+$C$88) -> 17.71561 | K96: =J96*(1+$C$88) -> 19.487171 | L96: =K96*(1+$C$88) -> 21.435888 | ... N96: =M96*(1+$C$88) -> 25.937425
C97: PHP/mo | D97: 29040 | E97: =D97*(1+E89) -> 30492 | F97: =E97*(1+F89) -> 32016.6 | G97: =F97*(1+G89) -> 33617.43 | H97: =G97*(1+H89) -> 35298.302 | I97: =H97*(1+I89) -> 37063.217 | J97: =I97*(1+J89) -> 38916.377 | K97: =J97*(1+K89) -> 40862.196 | L97: =K97*(1+L89) -> 42905.306 | ... N97: =M97*(1+N89) -> 47303.1
C98: 13 | D98: =D96*D97*$C98 -> 3775200 | E98: =E96*E97*$C98 -> 4360356 | F98: =F96*F97*$C98 -> 5036211.2 | G98: =G96*G97*$C98 -> 5816823.9 | H98: =H96*H97*$C98 -> 6718431.6 | I98: =I96*I97*$C98 -> 7759788.5 | J98: =J96*J97*$C98 -> 8962555.7 | K98: =K96*K97*$C98 -> 10351752 | ... N98: =N96*N97*$C98 -> 15949968
B99: • Customer Support | C99: HC | D99: 4 | E99: =D99*(1+$C$88) -> 4.4 | F99: =E99*(1+$C$88) -> 4.84 | G99: =F99*(1+$C$88) -> 5.324 | H99: =G99*(1+$C$88) -> 5.8564 | I99: =H99*(1+$C$88) -> 6.44204 | J99: =I99*(1+$C$88) -> 7.086244 | K99: =J99*(1+$C$88) -> 7.7948684 | L99: =K99*(1+$C$88) -> 8.5743552 | ... N99: =M99*(1+$C$88) -> 10.37497
C100: PHP/mo | D100: 30208 | E100: =D100*(1+E89) -> 31718.4 | F100: =E100*(1+F89) -> 33304.32 | G100: =F100*(1+G89) -> 34969.536 | H100: =G100*(1+H89) -> 36718.013 | I100: =H100*(1+I89) -> 38553.913 | J100: =I100*(1+J89) -> 40481.609 | K100: =J100*(1+K89) -> 42505.69 | L100: =K100*(1+L89) -> 44630.974 | ... N100: =M100*(1+N89) -> 49205.649
C101: 13 | D101: =D99*D100*$C101 -> 1570816 | E101: =E99*E100*$C101 -> 1814292.5 | F101: =F99*F100*$C101 -> 2095507.8 | G101: =G99*G100*$C101 -> 2420311.5 | H101: =H99*H100*$C101 -> 2795459.8 | I101: =I99*I100*$C101 -> 3228756.1 | J101: =J99*J100*$C101 -> 3729213.3 | K101: =K99*K100*$C101 -> 4307241.3 | ... N101: =N99*N100*$C101 -> 6636592.6
B102: • CS Field Maintenance | C102: HC | D102: 0 | E102: =D102*(1+$C$88) -> 0 | F102: =E102*(1+$C$88) -> 0 | G102: =F102*(1+$C$88) -> 0 | H102: =G102*(1+$C$88) -> 0 | I102: =H102*(1+$C$88) -> 0 | J102: =I102*(1+$C$88) -> 0 | K102: =J102*(1+$C$88) -> 0 | L102: =K102*(1+$C$88) -> 0 | ... N102: =M102*(1+$C$88) -> 0
C103: PHP/mo | D103: 35345 | E103: =D103*(1+E89) -> 37112.25 | F103: =E103*(1+F89) -> 38967.863 | G103: =F103*(1+G89) -> 40916.256 | H103: =G103*(1+H89) -> 42962.068 | I103: =H103*(1+I89) -> 45110.172 | J103: =I103*(1+J89) -> 47365.68 | K103: =J103*(1+K89) -> 49733.964 | L103: =K103*(1+L89) -> 52220.663 | ... N103: =M103*(1+N89) -> 57573.281
C104: 13 | D104: =D102*D103*$C104 -> 0 | E104: =E102*E103*$C104 -> 0 | F104: =F102*F103*$C104 -> 0 | G104: =G102*G103*$C104 -> 0 | H104: =H102*H103*$C104 -> 0 | I104: =I102*I103*$C104 -> 0 | J104: =J102*J103*$C104 -> 0 | K104: =K102*K103*$C104 -> 0 | ... N104: =N102*N103*$C104 -> 0
B105: • Network Rollout | C105: HC | D105: 0 | E105: =D105*(1+$C$88) -> 0 | F105: =E105*(1+$C$88) -> 0 | G105: =F105*(1+$C$88) -> 0 | H105: =G105*(1+$C$88) -> 0 | I105: =H105*(1+$C$88) -> 0 | J105: =I105*(1+$C$88) -> 0 | K105: =J105*(1+$C$88) -> 0 | L105: =K105*(1+$C$88) -> 0 | ... N105: =M105*(1+$C$88) -> 0
C106: PHP/mo | D106: 35345 | E106: =D106*(1+E89) -> 37112.25 | F106: =E106*(1+F89) -> 38967.863 | G106: =F106*(1+G89) -> 40916.256 | H106: =G106*(1+H89) -> 42962.068 | I106: =H106*(1+I89) -> 45110.172 | J106: =I106*(1+J89) -> 47365.68 | K106: =J106*(1+K89) -> 49733.964 | L106: =K106*(1+L89) -> 52220.663 | ... N106: =M106*(1+N89) -> 57573.281
C107: 13 | D107: =D105*D106*$C107 -> 0 | E107: =E105*E106*$C107 -> 0 | F107: =F105*F106*$C107 -> 0 | G107: =G105*G106*$C107 -> 0 | H107: =H105*H106*$C107 -> 0 | I107: =I105*I106*$C107 -> 0 | J107: =J105*J106*$C107 -> 0 | K107: =K105*K106*$C107 -> 0 | ... N107: =N105*N106*$C107 -> 0
B108: • Service Center | C108: HC | D108: 0 | E108: =D108*(1+$C$88) -> 0 | F108: =E108*(1+$C$88) -> 0 | G108: =F108*(1+$C$88) -> 0 | H108: =G108*(1+$C$88) -> 0 | I108: =H108*(1+$C$88) -> 0 | J108: =I108*(1+$C$88) -> 0 | K108: =J108*(1+$C$88) -> 0 | L108: =K108*(1+$C$88) -> 0 | ... N108: =M108*(1+$C$88) -> 0
C109: PHP/mo | D109: 35345 | E109: =D109*(1+E89) -> 37112.25 | F109: =E109*(1+F89) -> 38967.863 | G109: =F109*(1+G89) -> 40916.256 | H109: =G109*(1+H89) -> 42962.068 | I109: =H109*(1+I89) -> 45110.172 | J109: =I109*(1+J89) -> 47365.68 | K109: =J109*(1+K89) -> 49733.964 | L109: =K109*(1+L89) -> 52220.663 | ... N109: =M109*(1+N89) -> 57573.281
C110: 13 | D110: =D108*D109*$C110 -> 0 | E110: =E108*E109*$C110 -> 0 | F110: =F108*F109*$C110 -> 0 | G110: =G108*G109*$C110 -> 0 | H110: =H108*H109*$C110 -> 0 | I110: =I108*I109*$C110 -> 0 | J110: =J108*J109*$C110 -> 0 | K110: =K108*K109*$C110 -> 0 | ... N110: =N108*N109*$C110 -> 0
...

Sheet Energy Drivers (RideBox)
B2: RIDEBOX ENERGY - DRIVERS & INPUTS
B3: PHP (unless noted)
C4: Note / rate | D4: 2026 | E4: 2027 | F4: 2028 | G4: 2029 | H4: 2030 | I4: 2031 | J4: 2032 | K4: 2033 | L4: 2034 | M4: 2035 | N4: 2036
B5: OPERATING METRICS
B6: Network Build - Lockers
B7: Lockers Deployed - by D400/R280 active base | C7: units | D7: =D157 -> 363 | E7: =E157 -> 536 | F7: =F157 -> 795 | G7: =G157 -> 1039 | H7: =H157 -> 1241 | I7: =I157 -> 1467 | J7: =J157 -> 1829 | K7: =K157 -> 2172 | ... N7: =N157 -> 2825
B8: Cumulative Lockers - by D400/R280 active base | C8: units | D8: =D158 -> 363 | E8: =E158 -> 899 | F8: =F158 -> 1694 | G8: =G158 -> 2733 | H8: =H158 -> 3974 | I8: =I158 -> 5441 | J8: =J158 -> 7270 | K8: =K158 -> 9442 | ... N8: =N158 -> 17253
B10: ENERGY RATES & ARPU (feeds Revenue)
B11: Battery Subscription per leased MC / mo | C11: PHP/mo | D11: =2750/1.12 -> 2455.3571 | E11: =2750/1.12 -> 2455.3571 | F11: =E11 -> 2455.3571 | G11: =F11 -> 2455.3571 | H11: =G11 -> 2455.3571 | I11: =H11 -> 2455.3571 | J11: =I11 -> 2455.3571 | K11: =J11 -> 2455.3571 | L11: =K11 -> 2455.3571 | M11: =L11 -> 2455.3571 | N11: =M11 -> 2455.3571
B12: Load / Prepaid per sold+L2O MC / mo | C12: PHP/mo | D12: =880/1.12 -> 785.71429 | E12: =880/1.12 -> 785.71429 | F12: =E12 -> 785.71429 | G12: =F12 -> 785.71429 | H12: =G12 -> 785.71429 | I12: =H12 -> 785.71429 | J12: =I12 -> 785.71429 | K12: =J12 -> 785.71429 | L12: =K12 -> 785.71429 | M12: =L12 -> 785.71429 | N12: =M12 -> 785.71429
B13: Battery Payment Gateway % | C13: % | D13: 0.03 | E13: =D13 -> 0.03 | F13: =E13 -> 0.03 | G13: =F13 -> 0.03 | H13: =G13 -> 0.03 | I13: =H13 -> 0.03 | J13: =I13 -> 0.03 | K13: =J13 -> 0.03 | L13: =K13 -> 0.03 | ... N13: =M13 -> 0.03
B14: Battery Connectivity per battery / mo | C14: PHP/mo | D14: =100/1.12 -> 89.285714 | E14: =D14 -> 89.285714 | F14: =E14 -> 89.285714 | G14: =F14 -> 89.285714 | H14: =G14 -> 89.285714 | I14: =H14 -> 89.285714 | J14: =I14 -> 89.285714 | K14: =J14 -> 89.285714 | L14: =K14 -> 89.285714 | ... N14: =M14 -> 89.285714
B16: OPERATING COST RATES
B17: Locker Electricity
B18: kWh per battery | C18: 73.6*26/1000 | D18: =73.6*26/1000 -> 1.9136 | E18: =73.6*26/1000 -> 1.9136 | F18: =73.6*26/1000 -> 1.9136 | G18: =73.6*26/1000 -> 1.9136 | H18: =73.6*26/1000 -> 1.9136 | I18: =73.6*26/1000 -> 1.9136 | J18: =73.6*26/1000 -> 1.9136 | K18: =73.6*26/1000 -> 1.9136 | ... N18: =73.6*26/1000 -> 1.9136
B19: Cost per kWh | C19: PHP | D19: =14.33/1.12 -> 12.794643 | E19: =D19 -> 12.794643 | F19: =E19 -> 12.794643 | G19: =F19 -> 12.794643 | H19: =G19 -> 12.794643 | I19: =H19 -> 12.794643 | J19: =I19 -> 12.794643 | K19: =J19 -> 12.794643 | L19: =K19 -> 12.794643 | ... N19: =M19 -> 12.794643
B20: Operating hours / day | C20: hrs | D20: 14 | E20: =D20 -> 14 | F20: =E20 -> 14 | G20: =F20 -> 14 | H20: =G20 -> 14 | I20: =H20 -> 14 | J20: =I20 -> 14 | K20: =J20 -> 14 | L20: =K20 -> 14 | ... N20: =M20 -> 14
B21: Avg remaining charge of depleted batt | C21: 2/6 | D21: 0 | E21: =2/6 -> 0.33333333 | F21: =2/6 -> 0.33333333 | G21: =2/6 -> 0.33333333 | H21: =2/6 -> 0.33333333 | I21: =2/6 -> 0.33333333 | J21: =2/6 -> 0.33333333 | K21: =2/6 -> 0.33333333 | L21: =2/6 -> 0.33333333 | ... N21: =2/6 -> 0.33333333
B22: Assumed full charge time | C22: hrs | D22: 5 | E22: =D22 -> 5 | F22: =E22 -> 5 | G22: =F22 -> 5 | H22: =G22 -> 5 | I22: =H22 -> 5 | J22: =I22 -> 5 | K22: =J22 -> 5 | L22: =K22 -> 5 | ... N22: =M22 -> 5
B23: Recharge time / battery | C23: (1-rem)*time | D23: =(1-D21)*D22 -> 5 | E23: =(1-E21)*E22 -> 3.3333333 | F23: =(1-F21)*F22 -> 3.3333333 | G23: =(1-G21)*G22 -> 3.3333333 | H23: =(1-H21)*H22 -> 3.3333333 | I23: =(1-I21)*I22 -> 3.3333333 | J23: =(1-J21)*J22 -> 3.3333333 | K23: =(1-K21)*K22 -> 3.3333333 | ... N23: =(1-N21)*N22 -> 3.3333333
B24: Max swaps / battery / day | D24: =ROUNDDOWN(D20/D23,0) -> 2 | E24: =ROUNDDOWN(E20/E23,0) -> 4 | F24: =ROUNDDOWN(F20/F23,0) -> 4 | G24: =ROUNDDOWN(G20/G23,0) -> 4 | H24: =ROUNDDOWN(H20/H23,0) -> 4 | I24: =ROUNDDOWN(I20/I23,0) -> 4 | J24: =ROUNDDOWN(J20/J23,0) -> 4 | K24: =ROUNDDOWN(K20/K23,0) -> 4 | ... N24: =ROUNDDOWN(N20/N23,0) -> 4
B25: Projected swaps / locker / day | C25: 4*max*0.5 | D25: =4*D24*0.5 -> 4 | E25: =4*E24*0.5 -> 8 | F25: =4*F24*0.5 -> 8 | G25: =4*G24*0.5 -> 8 | H25: =4*H24*0.5 -> 8 | I25: =4*I24*0.5 -> 8 | J25: =4*J24*0.5 -> 8 | K25: =4*K24*0.5 -> 8 | ... N25: =4*N24*0.5 -> 8
B26: kWh generated / locker / day | D26: =D18*D25*(1-D21) -> 7.6544 | E26: =E18*E25*(1-E21) -> 10.205867 | F26: =F18*F25*(1-F21) -> 10.205867 | G26: =G18*G25*(1-G21) -> 10.205867 | H26: =H18*H25*(1-H21) -> 10.205867 | I26: =I18*I25*(1-I21) -> 10.205867 | J26: =J18*J25*(1-J21) -> 10.205867 | K26: =K18*K25*(1-K21) -> 10.205867 | ... N26: =N18*N25*(1-N21) -> 10.205867
B28: Locker OPEX Rates
B29: Locker Rent / site / mo | C29: PHP | D29: =5000/1.12 -> 4464.2857 | E29: =D29 -> 4464.2857 | F29: =E29 -> 4464.2857 | G29: =F29 -> 4464.2857 | H29: =G29 -> 4464.2857 | I29: =H29 -> 4464.2857 | J29: =I29 -> 4464.2857 | K29: =J29 -> 4464.2857 | L29: =K29 -> 4464.2857 | ... N29: =M29 -> 4464.2857
B30: Locker Connectivity / site / mo | C30: PHP | D30: =100/1.12 -> 89.285714 | E30: =D30 -> 89.285714 | F30: =E30 -> 89.285714 | G30: =F30 -> 89.285714 | H30: =G30 -> 89.285714 | I30: =H30 -> 89.285714 | J30: =I30 -> 89.285714 | K30: =J30 -> 89.285714 | L30: =K30 -> 89.285714 | ... N30: =M30 -> 89.285714
B31: Locker Maintenance / site / mo | C31: PHP | D31: =200/1.12 -> 178.57143 | E31: =D31 -> 178.57143 | F31: =E31 -> 178.57143 | G31: =F31 -> 178.57143 | H31: =G31 -> 178.57143 | I31: =H31 -> 178.57143 | J31: =I31 -> 178.57143 | K31: =J31 -> 178.57143 | L31: =K31 -> 178.57143 | ... N31: =M31 -> 178.57143
B32: Metrohub Rent / site / mo | C32: PHP | D32: 0 | E32: =D32 -> 0 | F32: =E32 -> 0 | G32: =F32 -> 0 | H32: =G32 -> 0 | I32: =H32 -> 0 | J32: =I32 -> 0 | K32: =J32 -> 0 | L32: =K32 -> 0 | ... N32: =M32 -> 0
B33: Metrohub Connectivity / site / mo | C33: PHP | D33: 0 | E33: =D33 -> 0 | F33: =E33 -> 0 | G33: =F33 -> 0 | H33: =G33 -> 0 | I33: =H33 -> 0 | J33: =I33 -> 0 | K33: =J33 -> 0 | L33: =K33 -> 0 | ... N33: =M33 -> 0
B34: Metrohub Maintenance / site / mo | C34: PHP | D34: 0 | E34: =D34 -> 0 | F34: =E34 -> 0 | G34: =F34 -> 0 | H34: =G34 -> 0 | I34: =H34 -> 0 | J34: =I34 -> 0 | K34: =J34 -> 0 | L34: =K34 -> 0 | ... N34: =M34 -> 0
B35: Metrohub Electricity / site / mo | C35: PHP | D35: 0 | E35: =D35 -> 0 | F35: =E35 -> 0 | G35: =F35 -> 0 | H35: =G35 -> 0 | I35: =H35 -> 0 | J35: =I35 -> 0 | K35: =J35 -> 0 | L35: =K35 -> 0 | ... N35: =M35 -> 0
B37: OPERATING EXPENSES (OPEX)
B38: Headcount & Salaries
B39: Headcount growth % p.a. (applied to each dept) | C39: 0.1
B40: Site Coverage per Manager | C40: lockers | D40: 0 | E40: =D40 -> 0 | F40: =E40 -> 0 | G40: =F40 -> 0 | H40: =G40 -> 0 | I40: =H40 -> 0 | J40: =I40 -> 0 | K40: =J40 -> 0 | L40: =K40 -> 0 | ... N40: =M40 -> 0
B41: Lockers per Field Tech | C41: lockers | D41: 0 | E41: =D41 -> 0 | F41: =E41 -> 0 | G41: =F41 -> 0 | H41: =G41 -> 0 | I41: =H41 -> 0 | J41: =I41 -> 0 | K41: =J41 -> 0 | L41: =K41 -> 0 | ... N41: =M41 -> 0
B42: Salary growth follows MC Salary Escalation (shared assumption)
B43: • Sales & Marketing | C43: HC | D43: 2 | E43: =D43*(1+$C$39) -> 2.2 | F43: =E43*(1+$C$39) -> 2.42 | G43: =F43*(1+$C$39) -> 2.662 | H43: =G43*(1+$C$39) -> 2.9282 | I43: =H43*(1+$C$39) -> 3.22102 | J43: =I43*(1+$C$39) -> 3.543122 | K43: =J43*(1+$C$39) -> 3.8974342 | L43: =K43*(1+$C$39) -> 4.2871776 | ... N43: =M43*(1+$C$39) -> 5.1874849
C44: PHP/mo | D44: 108250 | E44: =D44*(1+'MC Drivers (NRD)'!E89) -> 113662.5 | F44: =E44*(1+'MC Drivers (NRD)'!F89) -> 119345.62 | G44: =F44*(1+'MC Drivers (NRD)'!G89) -> 125312.91 | H44: =G44*(1+'MC Drivers (NRD)'!H89) -> 131578.55 | I44: =H44*(1+'MC Drivers (NRD)'!I89) -> 138157.48 | J44: =I44*(1+'MC Drivers (NRD)'!J89) -> 145065.35 | K44: =J44*(1+'MC Drivers (NRD)'!K89) -> 152318.62 | L44: =K44*(1+'MC Drivers (NRD)'!L89) -> 159934.55 | ... N44: =M44*(1+'MC Drivers (NRD)'!N89) -> 176327.84
C45: 13 | D45: =D43*D44*$C45 -> 2814500 | E45: =E43*E44*$C45 -> 3250747.5 | F45: =F43*F44*$C45 -> 3754613.4 | G45: =G43*G44*$C45 -> 4336578.4 | H45: =H43*H44*$C45 -> 5008748.1 | I45: =I43*I44*$C45 -> 5785104 | J45: =J43*J44*$C45 -> 6681795.2 | K45: =K43*K44*$C45 -> 7717473.4 | ... N45: =N43*N44*$C45 -> 11891074
B46: • AfterSales Center | C46: HC | D46: 1 | E46: =D46*(1+$C$39) -> 1.1 | F46: =E46*(1+$C$39) -> 1.21 | G46: =F46*(1+$C$39) -> 1.331 | H46: =G46*(1+$C$39) -> 1.4641 | I46: =H46*(1+$C$39) -> 1.61051 | J46: =I46*(1+$C$39) -> 1.771561 | K46: =J46*(1+$C$39) -> 1.9487171 | L46: =K46*(1+$C$39) -> 2.1435888 | ... N46: =M46*(1+$C$39) -> 2.5937425
C47: PHP/mo | D47: 25646 | E47: =D47*(1+'MC Drivers (NRD)'!E89) -> 26928.3 | F47: =E47*(1+'MC Drivers (NRD)'!F89) -> 28274.715 | G47: =F47*(1+'MC Drivers (NRD)'!G89) -> 29688.451 | H47: =G47*(1+'MC Drivers (NRD)'!H89) -> 31172.873 | I47: =H47*(1+'MC Drivers (NRD)'!I89) -> 32731.517 | J47: =I47*(1+'MC Drivers (NRD)'!J89) -> 34368.093 | K47: =J47*(1+'MC Drivers (NRD)'!K89) -> 36086.497 | L47: =K47*(1+'MC Drivers (NRD)'!L89) -> 37890.822 | ... N47: =M47*(1+'MC Drivers (NRD)'!N89) -> 41774.632
C48: 13 | D48: =D46*D47*$C48 -> 333398 | E48: =E46*E47*$C48 -> 385074.69 | F48: =F46*F47*$C48 -> 444761.27 | G48: =G46*G47*$C48 -> 513699.26 | H48: =H46*H47*$C48 -> 593322.65 | I48: =I46*I47*$C48 -> 685287.66 | J48: =J46*J47*$C48 -> 791507.25 | K48: =K46*K47*$C48 -> 914190.87 | ... N48: =N46*N47*$C48 -> 1408584.3
B49: • Supply Chain | C49: HC | D49: 2 | E49: =D49*(1+$C$39) -> 2.2 | F49: =E49*(1+$C$39) -> 2.42 | G49: =F49*(1+$C$39) -> 2.662 | H49: =G49*(1+$C$39) -> 2.9282 | I49: =H49*(1+$C$39) -> 3.22102 | J49: =I49*(1+$C$39) -> 3.543122 | K49: =J49*(1+$C$39) -> 3.8974342 | L49: =K49*(1+$C$39) -> 4.2871776 | ... N49: =M49*(1+$C$39) -> 5.1874849
C50: PHP/mo | D50: 29040 | E50: =D50*(1+'MC Drivers (NRD)'!E89) -> 30492 | F50: =E50*(1+'MC Drivers (NRD)'!F89) -> 32016.6 | G50: =F50*(1+'MC Drivers (NRD)'!G89) -> 33617.43 | H50: =G50*(1+'MC Drivers (NRD)'!H89) -> 35298.302 | I50: =H50*(1+'MC Drivers (NRD)'!I89) -> 37063.217 | J50: =I50*(1+'MC Drivers (NRD)'!J89) -> 38916.377 | K50: =J50*(1+'MC Drivers (NRD)'!K89) -> 40862.196 | L50: =K50*(1+'MC Drivers (NRD)'!L89) -> 42905.306 | ... N50: =M50*(1+'MC Drivers (NRD)'!N89) -> 47303.1
C51: 13 | D51: =D49*D50*$C51 -> 755040 | E51: =E49*E50*$C51 -> 872071.2 | F51: =F49*F50*$C51 -> 1007242.2 | G51: =G49*G50*$C51 -> 1163364.8 | H51: =H49*H50*$C51 -> 1343686.3 | I51: =I49*I50*$C51 -> 1551957.7 | J51: =J49*J50*$C51 -> 1792511.1 | K51: =K49*K50*$C51 -> 2070350.4 | ... N51: =N49*N50*$C51 -> 3189993.5
B52: • Customer Support | C52: HC | D52: 2 | E52: =D52*(1+$C$39) -> 2.2 | F52: =E52*(1+$C$39) -> 2.42 | G52: =F52*(1+$C$39) -> 2.662 | H52: =G52*(1+$C$39) -> 2.9282 | I52: =H52*(1+$C$39) -> 3.22102 | J52: =I52*(1+$C$39) -> 3.543122 | K52: =J52*(1+$C$39) -> 3.8974342 | L52: =K52*(1+$C$39) -> 4.2871776 | ... N52: =M52*(1+$C$39) -> 5.1874849
C53: PHP/mo | D53: 30208 | E53: =D53*(1+'MC Drivers (NRD)'!E89) -> 31718.4 | F53: =E53*(1+'MC Drivers (NRD)'!F89) -> 33304.32 | G53: =F53*(1+'MC Drivers (NRD)'!G89) -> 34969.536 | H53: =G53*(1+'MC Drivers (NRD)'!H89) -> 36718.013 | I53: =H53*(1+'MC Drivers (NRD)'!I89) -> 38553.913 | J53: =I53*(1+'MC Drivers (NRD)'!J89) -> 40481.609 | K53: =J53*(1+'MC Drivers (NRD)'!K89) -> 42505.69 | L53: =K53*(1+'MC Drivers (NRD)'!L89) -> 44630.974 | ... N53: =M53*(1+'MC Drivers (NRD)'!N89) -> 49205.649
C54: 13 | D54: =D52*D53*$C54 -> 785408 | E54: =E52*E53*$C54 -> 907146.24 | F54: =F52*F53*$C54 -> 1047753.9 | G54: =G52*G53*$C54 -> 1210155.8 | H54: =H52*H53*$C54 -> 1397729.9 | I54: =I52*I53*$C54 -> 1614378 | J54: =J52*J53*$C54 -> 1864606.6 | K54: =K52*K53*$C54 -> 2153620.7 | ... N54: =N52*N53*$C54 -> 3318296.3
B55: • CS Field Maintenance | C55: HC | D55: 7 | E55: =D55*(1+$C$39) -> 7.7 | F55: =E55*(1+$C$39) -> 8.47 | G55: =F55*(1+$C$39) -> 9.317 | H55: =G55*(1+$C$39) -> 10.2487 | I55: =H55*(1+$C$39) -> 11.27357 | J55: =I55*(1+$C$39) -> 12.400927 | K55: =J55*(1+$C$39) -> 13.64102 | L55: =K55*(1+$C$39) -> 15.005122 | ... N55: =M55*(1+$C$39) -> 18.156197
C56: PHP/mo | D56: 35345 | E56: =D56*(1+'MC Drivers (NRD)'!E89) -> 37112.25 | F56: =E56*(1+'MC Drivers (NRD)'!F89) -> 38967.863 | G56: =F56*(1+'MC Drivers (NRD)'!G89) -> 40916.256 | H56: =G56*(1+'MC Drivers (NRD)'!H89) -> 42962.068 | I56: =H56*(1+'MC Drivers (NRD)'!I89) -> 45110.172 | J56: =I56*(1+'MC Drivers (NRD)'!J89) -> 47365.68 | K56: =J56*(1+'MC Drivers (NRD)'!K89) -> 49733.964 | L56: =K56*(1+'MC Drivers (NRD)'!L89) -> 52220.663 | ... N56: =M56*(1+'MC Drivers (NRD)'!N89) -> 57573.281
C57: 13 | D57: =D55*D56*$C57 -> 3216395 | E57: =E55*E56*$C57 -> 3714936.2 | F57: =F55*F56*$C57 -> 4290751.3 | G57: =G55*G56*$C57 -> 4955817.8 | H57: =H55*H56*$C57 -> 5723969.6 | I57: =I55*I56*$C57 -> 6611184.8 | J57: =J55*J56*$C57 -> 7635918.5 | K57: =K55*K56*$C57 -> 8819485.9 | ... N57: =N55*N56*$C57 -> 13589054
B58: • Network Rollout | C58: HC | D58: 5 | E58: =D58*(1+$C$39) -> 5.5 | F58: =E58*(1+$C$39) -> 6.05 | G58: =F58*(1+$C$39) -> 6.655 | H58: =G58*(1+$C$39) -> 7.3205 | I58: =H58*(1+$C$39) -> 8.05255 | J58: =I58*(1+$C$39) -> 8.857805 | K58: =J58*(1+$C$39) -> 9.7435855 | L58: =K58*(1+$C$39) -> 10.717944 | ... N58: =M58*(1+$C$39) -> 12.968712
C59: PHP/mo | D59: 35345 | E59: =D59*(1+'MC Drivers (NRD)'!E89) -> 37112.25 | F59: =E59*(1+'MC Drivers (NRD)'!F89) -> 38967.863 | G59: =F59*(1+'MC Drivers (NRD)'!G89) -> 40916.256 | H59: =G59*(1+'MC Drivers (NRD)'!H89) -> 42962.068 | I59: =H59*(1+'MC Drivers (NRD)'!I89) -> 45110.172 | J59: =I59*(1+'MC Drivers (NRD)'!J89) -> 47365.68 | K59: =J59*(1+'MC Drivers (NRD)'!K89) -> 49733.964 | L59: =K59*(1+'MC Drivers (NRD)'!L89) -> 52220.663 | ... N59: =M59*(1+'MC Drivers (NRD)'!N89) -> 57573.281
C60: 13 | D60: =D58*D59*$C60 -> 2297425 | E60: =E58*E59*$C60 -> 2653525.9 | F60: =F58*F59*$C60 -> 3064822.4 | G60: =G58*G59*$C60 -> 3539869.9 | H60: =H58*H59*$C60 -> 4088549.7 | I60: =I58*I59*$C60 -> 4722274.9 | J60: =J58*J59*$C60 -> 5454227.5 | K60: =K58*K59*$C60 -> 6299632.8 | ... N60: =N58*N59*$C60 -> 9706467.1
B61: • Service Center | C61: HC | D61: 4 | E61: =D61*(1+$C$39) -> 4.4 | F61: =E61*(1+$C$39) -> 4.84 | G61: =F61*(1+$C$39) -> 5.324 | H61: =G61*(1+$C$39) -> 5.8564 | I61: =H61*(1+$C$39) -> 6.44204 | J61: =I61*(1+$C$39) -> 7.086244 | K61: =J61*(1+$C$39) -> 7.7948684 | L61: =K61*(1+$C$39) -> 8.5743552 | ... N61: =M61*(1+$C$39) -> 10.37497
C62: PHP/mo | D62: 35345 | E62: =D62*(1+'MC Drivers (NRD)'!E89) -> 37112.25 | F62: =E62*(1+'MC Drivers (NRD)'!F89) -> 38967.863 | G62: =F62*(1+'MC Drivers (NRD)'!G89) -> 40916.256 | H62: =G62*(1+'MC Drivers (NRD)'!H89) -> 42962.068 | I62: =H62*(1+'MC Drivers (NRD)'!I89) -> 45110.172 | J62: =I62*(1+'MC Drivers (NRD)'!J89) -> 47365.68 | K62: =J62*(1+'MC Drivers (NRD)'!K89) -> 49733.964 | L62: =K62*(1+'MC Drivers (NRD)'!L89) -> 52220.663 | ... N62: =M62*(1+'MC Drivers (NRD)'!N89) -> 57573.281
C63: 13 | D63: =D61*D62*$C63 -> 1837940 | E63: =E61*E62*$C63 -> 2122820.7 | F63: =F61*F62*$C63 -> 2451857.9 | G63: =G61*G62*$C63 -> 2831895.9 | H63: =H61*H62*$C63 -> 3270839.7 | I63: =I61*I62*$C63 -> 3777819.9 | J63: =J61*J62*$C63 -> 4363382 | K63: =K61*K62*$C63 -> 5039706.2 | ... N63: =N61*N62*$C63 -> 7765173.6
B64: • Billing & Admin | C64: HC | D64: 6 | E64: =D64*(1+$C$39) -> 6.6 | F64: =E64*(1+$C$39) -> 7.26 | G64: =F64*(1+$C$39) -> 7.986 | H64: =G64*(1+$C$39) -> 8.7846 | I64: =H64*(1+$C$39) -> 9.66306 | J64: =I64*(1+$C$39) -> 10.629366 | K64: =J64*(1+$C$39) -> 11.692303 | L64: =K64*(1+$C$39) -> 12.861533 | ... N64: =M64*(1+$C$39) -> 15.562455
C65: PHP/mo | D65: 35345 | E65: =D65*(1+'MC Drivers (NRD)'!E89) -> 37112.25 | F65: =E65*(1+'MC Drivers (NRD)'!F89) -> 38967.863 | G65: =F65*(1+'MC Drivers (NRD)'!G89) -> 40916.256 | H65: =G65*(1+'MC Drivers (NRD)'!H89) -> 42962.068 | I65: =H65*(1+'MC Drivers (NRD)'!I89) -> 45110.172 | J65: =I65*(1+'MC Drivers (NRD)'!J89) -> 47365.68 | K65: =J65*(1+'MC Drivers (NRD)'!K89) -> 49733.964 | L65: =K65*(1+'MC Drivers (NRD)'!L89) -> 52220.663 | ... N65: =M65*(1+'MC Drivers (NRD)'!N89) -> 57573.281
C66: 13 | D66: =D64*D65*$C66 -> 2756910 | E66: =E64*E65*$C66 -> 3184231 | F66: =F64*F65*$C66 -> 3677786.9 | G66: =G64*G65*$C66 -> 4247843.8 | H66: =H64*H65*$C66 -> 4906259.6 | I66: =I64*I65*$C66 -> 5666729.9 | J66: =J64*J65*$C66 -> 6545073 | K66: =K64*K65*$C66 -> 7559559.3 | ... N66: =N64*N65*$C66 -> 11647760
B67: • Technology - Build | C67: HC | D67: 0 | E67: =D67*(1+$C$39) -> 0 | F67: =E67*(1+$C$39) -> 0 | G67: =F67*(1+$C$39) -> 0 | H67: =G67*(1+$C$39) -> 0 | I67: =H67*(1+$C$39) -> 0 | J67: =I67*(1+$C$39) -> 0 | K67: =J67*(1+$C$39) -> 0 | L67: =K67*(1+$C$39) -> 0 | ... N67: =M67*(1+$C$39) -> 0
C68: PHP/mo | D68: 60660 | E68: =D68*(1+'MC Drivers (NRD)'!E89) -> 63693 | F68: =E68*(1+'MC Drivers (NRD)'!F89) -> 66877.65 | G68: =F68*(1+'MC Drivers (NRD)'!G89) -> 70221.533 | H68: =G68*(1+'MC Drivers (NRD)'!H89) -> 73732.609 | I68: =H68*(1+'MC Drivers (NRD)'!I89) -> 77419.24 | J68: =I68*(1+'MC Drivers (NRD)'!J89) -> 81290.202 | K68: =J68*(1+'MC Drivers (NRD)'!K89) -> 85354.712 | L68: =K68*(1+'MC Drivers (NRD)'!L89) -> 89622.447 | ... N68: =M68*(1+'MC Drivers (NRD)'!N89) -> 98808.748
C69: 13 | D69: =D67*D68*$C69 -> 0 | E69: =E67*E68*$C69 -> 0 | F69: =F67*F68*$C69 -> 0 | G69: =G67*G68*$C69 -> 0 | H69: =H67*H68*$C69 -> 0 | I69: =I67*I68*$C69 -> 0 | J69: =J67*J68*$C69 -> 0 | K69: =K67*K68*$C69 -> 0 | ... N69: =N67*N68*$C69 -> 0
B70: • Technology - Ops | C70: HC | D70: 0 | E70: =D70*(1+$C$39) -> 0 | F70: =E70*(1+$C$39) -> 0 | G70: =F70*(1+$C$39) -> 0 | H70: =G70*(1+$C$39) -> 0 | I70: =H70*(1+$C$39) -> 0 | J70: =I70*(1+$C$39) -> 0 | K70: =J70*(1+$C$39) -> 0 | L70: =K70*(1+$C$39) -> 0 | ... N70: =M70*(1+$C$39) -> 0
C71: PHP/mo | D71: 60660 | E71: =D71*(1+'MC Drivers (NRD)'!E89) -> 63693 | F71: =E71*(1+'MC Drivers (NRD)'!F89) -> 66877.65 | G71: =F71*(1+'MC Drivers (NRD)'!G89) -> 70221.533 | H71: =G71*(1+'MC Drivers (NRD)'!H89) -> 73732.609 | I71: =H71*(1+'MC Drivers (NRD)'!I89) -> 77419.24 | J71: =I71*(1+'MC Drivers (NRD)'!J89) -> 81290.202 | K71: =J71*(1+'MC Drivers (NRD)'!K89) -> 85354.712 | L71: =K71*(1+'MC Drivers (NRD)'!L89) -> 89622.447 | ... N71: =M71*(1+'MC Drivers (NRD)'!N89) -> 98808.748
C72: 13 | D72: =D70*D71*$C72 -> 0 | E72: =E70*E71*$C72 -> 0 | F72: =F70*F71*$C72 -> 0 | G72: =G70*G71*$C72 -> 0 | H72: =H70*H71*$C72 -> 0 | I72: =I70*I71*$C72 -> 0 | J72: =J70*J71*$C72 -> 0 | K72: =K70*K71*$C72 -> 0 | ... N72: =N70*N71*$C72 -> 0
B73: • Technology - IT Ops | C73: HC | D73: 0 | E73: =D73*(1+$C$39) -> 0 | F73: =E73*(1+$C$39) -> 0 | G73: =F73*(1+$C$39) -> 0 | H73: =G73*(1+$C$39) -> 0 | I73: =H73*(1+$C$39) -> 0 | J73: =I73*(1+$C$39) -> 0 | K73: =J73*(1+$C$39) -> 0 | L73: =K73*(1+$C$39) -> 0 | ... N73: =M73*(1+$C$39) -> 0
C74: PHP/mo | D74: 60660 | E74: =D74*(1+'MC Drivers (NRD)'!E89) -> 63693 | F74: =E74*(1+'MC Drivers (NRD)'!F89) -> 66877.65 | G74: =F74*(1+'MC Drivers (NRD)'!G89) -> 70221.533 | H74: =G74*(1+'MC Drivers (NRD)'!H89) -> 73732.609 | I74: =H74*(1+'MC Drivers (NRD)'!I89) -> 77419.24 | J74: =I74*(1+'MC Drivers (NRD)'!J89) -> 81290.202 | K74: =J74*(1+'MC Drivers (NRD)'!K89) -> 85354.712 | L74: =K74*(1+'MC Drivers (NRD)'!L89) -> 89622.447 | ... N74: =M74*(1+'MC Drivers (NRD)'!N89) -> 98808.748
C75: 13 | D75: =D73*D74*$C75 -> 0 | E75: =E73*E74*$C75 -> 0 | F75: =F73*F74*$C75 -> 0 | G75: =G73*G74*$C75 -> 0 | H75: =H73*H74*$C75 -> 0 | I75: =I73*I74*$C75 -> 0 | J75: =J73*J74*$C75 -> 0 | K75: =K73*K74*$C75 -> 0 | ... N75: =N73*N74*$C75 -> 0
B76: • Compliance | C76: HC | D76: 2 | E76: =D76*(1+$C$39) -> 2.2 | F76: =E76*(1+$C$39) -> 2.42 | G76: =F76*(1+$C$39) -> 2.662 | H76: =G76*(1+$C$39) -> 2.9282 | I76: =H76*(1+$C$39) -> 3.22102 | J76: =I76*(1+$C$39) -> 3.543122 | K76: =J76*(1+$C$39) -> 3.8974342 | L76: =K76*(1+$C$39) -> 4.2871776 | ... N76: =M76*(1+$C$39) -> 5.1874849
C77: PHP/mo | D77: 70000 | E77: =D77*(1+'MC Drivers (NRD)'!E89) -> 73500 | F77: =E77*(1+'MC Drivers (NRD)'!F89) -> 77175 | G77: =F77*(1+'MC Drivers (NRD)'!G89) -> 81033.75 | H77: =G77*(1+'MC Drivers (NRD)'!H89) -> 85085.438 | I77: =H77*(1+'MC Drivers (NRD)'!I89) -> 89339.709 | J77: =I77*(1+'MC Drivers (NRD)'!J89) -> 93806.695 | K77: =J77*(1+'MC Drivers (NRD)'!K89) -> 98497.03 | L77: =K77*(1+'MC Drivers (NRD)'!L89) -> 103421.88 | ... N77: =M77*(1+'MC Drivers (NRD)'!N89) -> 114022.62
C78: 13 | D78: =D76*D77*$C78 -> 1820000 | E78: =E76*E77*$C78 -> 2102100 | F78: =F76*F77*$C78 -> 2427925.5 | G78: =G76*G77*$C78 -> 2804254 | H78: =H76*H77*$C78 -> 3238913.3 | I78: =I76*I77*$C78 -> 3740944.9 | J78: =J76*J77*$C78 -> 4320791.3 | K78: =K76*K77*$C78 -> 4990514 | ... N78: =N76*N77*$C78 -> 7689378.3
B79: • Admin | C79: HC | D79: 0 | E79: =D79*(1+$C$39) -> 0 | F79: =E79*(1+$C$39) -> 0 | G79: =F79*(1+$C$39) -> 0 | H79: =G79*(1+$C$39) -> 0 | I79: =H79*(1+$C$39) -> 0 | J79: =I79*(1+$C$39) -> 0 | K79: =J79*(1+$C$39) -> 0 | L79: =K79*(1+$C$39) -> 0 | ... N79: =M79*(1+$C$39) -> 0
C80: PHP/mo | D80: 50333 | E80: =D80*(1+'MC Drivers (NRD)'!E89) -> 52849.65 | F80: =E80*(1+'MC Drivers (NRD)'!F89) -> 55492.132 | G80: =F80*(1+'MC Drivers (NRD)'!G89) -> 58266.739 | H80: =G80*(1+'MC Drivers (NRD)'!H89) -> 61180.076 | I80: =H80*(1+'MC Drivers (NRD)'!I89) -> 64239.08 | J80: =I80*(1+'MC Drivers (NRD)'!J89) -> 67451.034 | K80: =J80*(1+'MC Drivers (NRD)'!K89) -> 70823.586 | L80: =K80*(1+'MC Drivers (NRD)'!L89) -> 74364.765 | ... N80: =M80*(1+'MC Drivers (NRD)'!N89) -> 81987.153
C81: 13 | D81: =D79*D80*$C81 -> 0 | E81: =E79*E80*$C81 -> 0 | F81: =F79*F80*$C81 -> 0 | G81: =G79*G80*$C81 -> 0 | H81: =H79*H80*$C81 -> 0 | I81: =I79*I80*$C81 -> 0 | J81: =J79*J80*$C81 -> 0 | K81: =K79*K80*$C81 -> 0 | ... N81: =N79*N80*$C81 -> 0
B82: • HR | C82: HC | D82: 1 | E82: =D82*(1+$C$39) -> 1.1 | F82: =E82*(1+$C$39) -> 1.21 | G82: =F82*(1+$C$39) -> 1.331 | H82: =G82*(1+$C$39) -> 1.4641 | I82: =H82*(1+$C$39) -> 1.61051 | J82: =I82*(1+$C$39) -> 1.771561 | K82: =J82*(1+$C$39) -> 1.9487171 | L82: =K82*(1+$C$39) -> 2.1435888 | ... N82: =M82*(1+$C$39) -> 2.5937425
C83: PHP/mo | D83: 50333 | E83: =D83*(1+'MC Drivers (NRD)'!E89) -> 52849.65 | F83: =E83*(1+'MC Drivers (NRD)'!F89) -> 55492.132 | G83: =F83*(1+'MC Drivers (NRD)'!G89) -> 58266.739 | H83: =G83*(1+'MC Drivers (NRD)'!H89) -> 61180.076 | I83: =H83*(1+'MC Drivers (NRD)'!I89) -> 64239.08 | J83: =I83*(1+'MC Drivers (NRD)'!J89) -> 67451.034 | K83: =J83*(1+'MC Drivers (NRD)'!K89) -> 70823.586 | L83: =K83*(1+'MC Drivers (NRD)'!L89) -> 74364.765 | ... N83: =M83*(1+'MC Drivers (NRD)'!N89) -> 81987.153
C84: 13 | D84: =D82*D83*$C84 -> 654329 | E84: =E82*E83*$C84 -> 755749.99 | F84: =F82*F83*$C84 -> 872891.24 | G84: =G82*G83*$C84 -> 1008189.4 | H84: =H82*H83*$C84 -> 1164458.7 | I84: =I82*I83*$C84 -> 1344949.8 | J84: =J82*J83*$C84 -> 1553417.1 | K84: =K82*K83*$C84 -> 1794196.7 | ... N84: =N82*N83*$C84 -> 2764496.3
B85: • Finance and Accounting | C85: HC | D85: 1 | E85: =D85*(1+$C$39) -> 1.1 | F85: =E85*(1+$C$39) -> 1.21 | G85: =F85*(1+$C$39) -> 1.331 | H85: =G85*(1+$C$39) -> 1.4641 | I85: =H85*(1+$C$39) -> 1.61051 | J85: =I85*(1+$C$39) -> 1.771561 | K85: =J85*(1+$C$39) -> 1.9487171 | L85: =K85*(1+$C$39) -> 2.1435888 | ... N85: =M85*(1+$C$39) -> 2.5937425
C86: PHP/mo | D86: 50333 | E86: =D86*(1+'MC Drivers (NRD)'!E89) -> 52849.65 | F86: =E86*(1+'MC Drivers (NRD)'!F89) -> 55492.132 | G86: =F86*(1+'MC Drivers (NRD)'!G89) -> 58266.739 | H86: =G86*(1+'MC Drivers (NRD)'!H89) -> 61180.076 | I86: =H86*(1+'MC Drivers (NRD)'!I89) -> 64239.08 | J86: =I86*(1+'MC Drivers (NRD)'!J89) -> 67451.034 | K86: =J86*(1+'MC Drivers (NRD)'!K89) -> 70823.586 | L86: =K86*(1+'MC Drivers (NRD)'!L89) -> 74364.765 | ... N86: =M86*(1+'MC Drivers (NRD)'!N89) -> 81987.153
C87: 13 | D87: =D85*D86*$C87 -> 654329 | E87: =E85*E86*$C87 -> 755749.99 | F87: =F85*F86*$C87 -> 872891.24 | G87: =G85*G86*$C87 -> 1008189.4 | H87: =H85*H86*$C87 -> 1164458.7 | I87: =I85*I86*$C87 -> 1344949.8 | J87: =J85*J86*$C87 -> 1553417.1 | K87: =K85*K86*$C87 -> 1794196.7 | ... N87: =N85*N86*$C87 -> 2764496.3
B88: Total Energy Salaries | D88: =D45+D48+D51+D54+D57+D60+D63+D66+D69+D72+D75+D78+D81+D84+D87 -> 17925674 | E88: =E45+E48+E51+E54+E57+E60+E63+E66+E69+E72+E75+E78+E81+E84+E87 -> 20704153 | F88: =F45+F48+F51+F54+F57+F60+F63+F66+F69+F72+F75+F78+F81+F84+F87 -> 23913297 | G88: =G45+G48+G51+G54+G57+G60+G63+G66+G69+G72+G75+G78+G81+G84+G87 -> 27619858 | H88: =H45+H48+H51+H54+H57+H60+H63+H66+H69+H72+H75+H78+H81+H84+H87 -> 31900936 | I88: =I45+I48+I51+I54+I57+I60+I63+I66+I69+I72+I75+I78+I81+I84+I87 -> 36845582 | J88: =J45+J48+J51+J54+J57+J60+J63+J66+J69+J72+J75+J78+J81+J84+J87 -> 42556647 | K88: =K45+K48+K51+K54+K57+K60+K63+K66+K69+K72+K75+K78+K81+K84+K87 -> 49152927 | ... N88: =N45+N48+N51+N54+N57+N60+N63+N66+N69+N72+N75+N78+N81+N84+N87 -> 75734774
B89: Employee Benefits | C89: 0.1 | D89: =D88*$C89 -> 1792567.4 | E89: =E88*$C89 -> 2070415.3 | F89: =F88*$C89 -> 2391329.7 | G89: =G88*$C89 -> 2761985.8 | H89: =H88*$C89 -> 3190093.6 | I89: =I88*$C89 -> 3684558.2 | J89: =J88*$C89 -> 4255664.7 | K89: =K88*$C89 -> 4915292.7 | ... N89: =N88*$C89 -> 7573477.4
B90: Total Energy Headcount | D90: =D43+D46+D49+D52+D55+D58+D61+D64+D67+D70+D73+D76+D79+D82+D85 -> 33 | E90: =E43+E46+E49+E52+E55+E58+E61+E64+E67+E70+E73+E76+E79+E82+E85 -> 36.3 | F90: =F43+F46+F49+F52+F55+F58+F61+F64+F67+F70+F73+F76+F79+F82+F85 -> 39.93 | G90: =G43+G46+G49+G52+G55+G58+G61+G64+G67+G70+G73+G76+G79+G82+G85 -> 43.923 | H90: =H43+H46+H49+H52+H55+H58+H61+H64+H67+H70+H73+H76+H79+H82+H85 -> 48.3153 | I90: =I43+I46+I49+I52+I55+I58+I61+I64+I67+I70+I73+I76+I79+I82+I85 -> 53.14683 | J90: =J43+J46+J49+J52+J55+J58+J61+J64+J67+J70+J73+J76+J79+J82+J85 -> 58.461513 | K90: =K43+K46+K49+K52+K55+K58+K61+K64+K67+K70+K73+K76+K79+K82+K85 -> 64.307664 | ... N90: =N43+N46+N49+N52+N55+N58+N61+N64+N67+N70+N73+N76+N79+N82+N85 -> 85.593501
B92: CAPEX & DEPRECIATION
B93: Locker - Landed Cost
B94: Locker - FOB Price (USD) | C94: USD | D94: 1138 | E94: =D94 -> 1138 | F94: =E94 -> 1138 | G94: =F94 -> 1138 | H94: =G94 -> 1138 | I94: =H94 -> 1138 | J94: =I94 -> 1138 | K94: =J94 -> 1138 | L94: =K94 -> 1138 | ... N94: =M94 -> 1138
B95: Locker - Unit Cost (PHP) = USD x forex | D95: =D94*'MC Drivers (NRD)'!D316 -> 69873.2 | E95: =E94*'MC Drivers (NRD)'!E316 -> 69873.2 | F95: =F94*'MC Drivers (NRD)'!F316 -> 69873.2 | G95: =G94*'MC Drivers (NRD)'!G316 -> 69873.2 | H95: =H94*'MC Drivers (NRD)'!H316 -> 69873.2 | I95: =I94*'MC Drivers (NRD)'!I316 -> 69873.2 | J95: =J94*'MC Drivers (NRD)'!J316 -> 69873.2 | K95: =K94*'MC Drivers (NRD)'!K316 -> 69873.2 | ... N95: =N94*'MC Drivers (NRD)'!N316 -> 69873.2
B96: Locker - Freight & Shipping | C96: PHP | D96: 1800 | E96: =D96 -> 1800 | F96: =E96 -> 1800 | G96: =F96 -> 1800 | H96: =G96 -> 1800 | I96: =H96 -> 1800 | J96: =I96 -> 1800 | K96: =J96 -> 1800 | L96: =K96 -> 1800 | ... N96: =M96 -> 1800
B97: Locker - Installation / Labor | C97: PHP | D97: =45000/1.12 -> 40178.571 | E97: =D97 -> 40178.571 | F97: =E97 -> 40178.571 | G97: =F97 -> 40178.571 | H97: =G97 -> 40178.571 | I97: =H97 -> 40178.571 | J97: =I97 -> 40178.571 | K97: =J97 -> 40178.571 | L97: =K97 -> 40178.571 | ... N97: =M97 -> 40178.571
B98: Locker - Customs / Brokerage | C98: PHP | D98: 600 | E98: =D98 -> 600 | F98: =E98 -> 600 | G98: =F98 -> 600 | H98: =G98 -> 600 | I98: =H98 -> 600 | J98: =I98 -> 600 | K98: =J98 -> 600 | L98: =K98 -> 600 | ... N98: =M98 -> 600
B99: Locker - Site Prep / Misc | C99: PHP | D99: 806 | E99: =D99 -> 806 | F99: =E99 -> 806 | G99: =F99 -> 806 | H99: =G99 -> 806 | I99: =H99 -> 806 | J99: =I99 -> 806 | K99: =J99 -> 806 | L99: =K99 -> 806 | ... N99: =M99 -> 806
B100: Locker Landed Cost (sum) | D100: =D95+D96+D97+D98+D99 -> 113257.77 | E100: =E95+E96+E97+E98+E99 -> 113257.77 | F100: =F95+F96+F97+F98+F99 -> 113257.77 | G100: =G95+G96+G97+G98+G99 -> 113257.77 | H100: =H95+H96+H97+H98+H99 -> 113257.77 | I100: =I95+I96+I97+I98+I99 -> 113257.77 | J100: =J95+J96+J97+J98+J99 -> 113257.77 | K100: =K95+K96+K97+K98+K99 -> 113257.77 | ... N100: =N95+N96+N97+N98+N99 -> 113257.77
B102: Energy Assets - CAPEX & Depreciation
B103: Locker Depr Life | C103: yrs | D103: 10 | E103: =D103 -> 10 | F103: =E103 -> 10 | G103: =F103 -> 10 | H103: =G103 -> 10 | I103: =H103 -> 10 | J103: =I103 -> 10 | K103: =J103 -> 10 | L103: =K103 -> 10 | ... N103: =M103 -> 10
B104: Locker Insurance % | C104: % | D104: 0.02 | E104: =D104 -> 0.02 | F104: =E104 -> 0.02 | G104: =F104 -> 0.02 | H104: =G104 -> 0.02 | I104: =H104 -> 0.02 | J104: =I104 -> 0.02 | K104: =J104 -> 0.02 | L104: =K104 -> 0.02 | ... N104: =M104 -> 0.02
B105: Locker CAPEX - by D400/R280 required lockers | D105: =D157*D100 -> 41112571 | E105: =E157*E100 -> 60706165 | F105: =F157*F100 -> 90039928 | G105: =G157*G100 -> 1.1767482e+08 | H105: =H157*H100 -> 1.4055289e+08 | I105: =I157*I100 -> 1.6614915e+08 | J105: =J157*J100 -> 2.0714846e+08 | K105: =K157*K100 -> 2.4599588e+08 | ... N105: =N157*N100 -> 3.199532e+08
B106: Total Energy CAPEX - by D400/R280 required lockers | D106: =D105 -> 41112571 | E106: =E105 -> 60706165 | F106: =F105 -> 90039928 | G106: =G105 -> 1.1767482e+08 | H106: =H105 -> 1.4055289e+08 | I106: =I105 -> 1.6614915e+08 | J106: =J105 -> 2.0714846e+08 | K106: =K105 -> 2.4599588e+08 | ... N106: =N105 -> 3.199532e+08
B107: Lockers - Depreciation
...

Sheet NRD MC P&L
B2: NRD MOTORCYCLE - PROFIT & LOSS
B3: All figures in PHP Millions (unless noted)
D4: 2026 | E4: 2027 | F4: 2028 | G4: 2029 | H4: 2030 | I4: 2031 | J4: 2032 | K4: 2033 | L4: 2034 | M4: 2035 | N4: 2036
B5: REVENUE
B6: Lease Revenue (LSE, net of battery) | D6: ='MC Drivers (NRD)'!D15*'MC Drivers (NRD)'!D32*'MC Drivers (NRD)'!D34*12+'MC Drivers (NRD)'!D15*'MC Drivers (NRD)'!D33*'MC Drivers (NRD)'!D35*12 -> 1.2275057e+08 | E6: ='MC Drivers (NRD)'!E15*'MC Drivers (NRD)'!E32*'MC Drivers (NRD)'!E34*12+'MC Drivers (NRD)'!E15*'MC Drivers (NRD)'!E33*'MC Drivers (NRD)'!E35*12 -> 2.9768121e+08 | F6: ='MC Drivers (NRD)'!F15*'MC Drivers (NRD)'!F32*'MC Drivers (NRD)'!F34*12+'MC Drivers (NRD)'!F15*'MC Drivers (NRD)'!F33*'MC Drivers (NRD)'!F35*12 -> 5.4772457e+08 | G6: ='MC Drivers (NRD)'!G15*'MC Drivers (NRD)'!G32*'MC Drivers (NRD)'!G34*12+'MC Drivers (NRD)'!G15*'MC Drivers (NRD)'!G33*'MC Drivers (NRD)'!G35*12 -> 8.7060954e+08 | H6: ='MC Drivers (NRD)'!H15*'MC Drivers (NRD)'!H32*'MC Drivers (NRD)'!H34*12+'MC Drivers (NRD)'!H15*'MC Drivers (NRD)'!H33*'MC Drivers (NRD)'!H35*12 -> 1241464714 | I6: ='MC Drivers (NRD)'!I15*'MC Drivers (NRD)'!I32*'MC Drivers (NRD)'!I34*12+'MC Drivers (NRD)'!I15*'MC Drivers (NRD)'!I33*'MC Drivers (NRD)'!I35*12 -> 1672698107 | J6: ='MC Drivers (NRD)'!J15*'MC Drivers (NRD)'!J32*'MC Drivers (NRD)'!J34*12+'MC Drivers (NRD)'!J15*'MC Drivers (NRD)'!J33*'MC Drivers (NRD)'!J35*12 -> 2208125464 | K6: ='MC Drivers (NRD)'!K15*'MC Drivers (NRD)'!K32*'MC Drivers (NRD)'!K34*12+'MC Drivers (NRD)'!K15*'MC Drivers (NRD)'!K33*'MC Drivers (NRD)'!K35*12 -> 2834064750 | ... N6: ='MC Drivers (NRD)'!N15*'MC Drivers (NRD)'!N32*'MC Drivers (NRD)'!N34*12+'MC Drivers (NRD)'!N15*'MC Drivers (NRD)'!N33*'MC Drivers (NRD)'!N35*12 -> 4984138500
B7: Outright Sale Revenue | D7: ='MC Drivers (NRD)'!D17*'MC Drivers (NRD)'!D53*'MC Drivers (NRD)'!D71*(1-'MC Drivers (NRD)'!D73)+'MC Drivers (NRD)'!D17*'MC Drivers (NRD)'!D54*'MC Drivers (NRD)'!D72*(1-'MC Drivers (NRD)'!D73) -> 1.8899807e+08 | E7: ='MC Drivers (NRD)'!E17*'MC Drivers (NRD)'!E53*'MC Drivers (NRD)'!E71*(1-'MC Drivers (NRD)'!E73)+'MC Drivers (NRD)'!E17*'MC Drivers (NRD)'!E54*'MC Drivers (NRD)'!E72*(1-'MC Drivers (NRD)'!E73) -> 3.0239691e+08 | F7: ='MC Drivers (NRD)'!F17*'MC Drivers (NRD)'!F53*'MC Drivers (NRD)'!F71*(1-'MC Drivers (NRD)'!F73)+'MC Drivers (NRD)'!F17*'MC Drivers (NRD)'!F54*'MC Drivers (NRD)'!F72*(1-'MC Drivers (NRD)'!F73) -> 483835061 | G7: ='MC Drivers (NRD)'!G17*'MC Drivers (NRD)'!G53*'MC Drivers (NRD)'!G71*(1-'MC Drivers (NRD)'!G73)+'MC Drivers (NRD)'!G17*'MC Drivers (NRD)'!G54*'MC Drivers (NRD)'!G72*(1-'MC Drivers (NRD)'!G73) -> 677400585 | H7: ='MC Drivers (NRD)'!H17*'MC Drivers (NRD)'!H53*'MC Drivers (NRD)'!H71*(1-'MC Drivers (NRD)'!H73)+'MC Drivers (NRD)'!H17*'MC Drivers (NRD)'!H54*'MC Drivers (NRD)'!H72*(1-'MC Drivers (NRD)'!H73) -> 8.4671136e+08 | I7: ='MC Drivers (NRD)'!I17*'MC Drivers (NRD)'!I53*'MC Drivers (NRD)'!I71*(1-'MC Drivers (NRD)'!I73)+'MC Drivers (NRD)'!I17*'MC Drivers (NRD)'!I54*'MC Drivers (NRD)'!I72*(1-'MC Drivers (NRD)'!I73) -> 1016022128 | J7: ='MC Drivers (NRD)'!J17*'MC Drivers (NRD)'!J53*'MC Drivers (NRD)'!J71*(1-'MC Drivers (NRD)'!J73)+'MC Drivers (NRD)'!J17*'MC Drivers (NRD)'!J54*'MC Drivers (NRD)'!J72*(1-'MC Drivers (NRD)'!J73) -> 1270067035 | K7: ='MC Drivers (NRD)'!K17*'MC Drivers (NRD)'!K53*'MC Drivers (NRD)'!K71*(1-'MC Drivers (NRD)'!K73)+'MC Drivers (NRD)'!K17*'MC Drivers (NRD)'!K54*'MC Drivers (NRD)'!K72*(1-'MC Drivers (NRD)'!K73) -> 1524111942 | ... N7: ='MC Drivers (NRD)'!N17*'MC Drivers (NRD)'!N53*'MC Drivers (NRD)'!N71*(1-'MC Drivers (NRD)'!N73)+'MC Drivers (NRD)'!N17*'MC Drivers (NRD)'!N54*'MC Drivers (NRD)'!N72*(1-'MC Drivers (NRD)'!N73) -> 2031886758
B8: Lease-to-Own Revenue | D8: ='MC Drivers (NRD)'!D27*'MC Drivers (NRD)'!D22*'MC Drivers (NRD)'!D23*12+'MC Drivers (NRD)'!D27*(1-'MC Drivers (NRD)'!D22)*'MC Drivers (NRD)'!D24*12 -> 18214286 | E8: ='MC Drivers (NRD)'!E27*'MC Drivers (NRD)'!E22*'MC Drivers (NRD)'!E23*12+'MC Drivers (NRD)'!E27*(1-'MC Drivers (NRD)'!E22)*'MC Drivers (NRD)'!E24*12 -> 43714286 | F8: ='MC Drivers (NRD)'!F27*'MC Drivers (NRD)'!F22*'MC Drivers (NRD)'!F23*12+'MC Drivers (NRD)'!F27*(1-'MC Drivers (NRD)'!F22)*'MC Drivers (NRD)'!F24*12 -> 76864286 | G8: ='MC Drivers (NRD)'!G27*'MC Drivers (NRD)'!G22*'MC Drivers (NRD)'!G23*12+'MC Drivers (NRD)'!G27*(1-'MC Drivers (NRD)'!G22)*'MC Drivers (NRD)'!G24*12 -> 1.0172679e+08 | H8: ='MC Drivers (NRD)'!H27*'MC Drivers (NRD)'!H22*'MC Drivers (NRD)'!H23*12+'MC Drivers (NRD)'!H27*(1-'MC Drivers (NRD)'!H22)*'MC Drivers (NRD)'!H24*12 -> 1.3223571e+08 | I8: ='MC Drivers (NRD)'!I27*'MC Drivers (NRD)'!I22*'MC Drivers (NRD)'!I23*12+'MC Drivers (NRD)'!I27*(1-'MC Drivers (NRD)'!I22)*'MC Drivers (NRD)'!I24*12 -> 1.7185179e+08 | J8: ='MC Drivers (NRD)'!J27*'MC Drivers (NRD)'!J22*'MC Drivers (NRD)'!J23*12+'MC Drivers (NRD)'!J27*(1-'MC Drivers (NRD)'!J22)*'MC Drivers (NRD)'!J24*12 -> 2.2330714e+08 | K8: ='MC Drivers (NRD)'!K27*'MC Drivers (NRD)'!K22*'MC Drivers (NRD)'!K23*12+'MC Drivers (NRD)'!K27*(1-'MC Drivers (NRD)'!K22)*'MC Drivers (NRD)'!K24*12 -> 2.9024464e+08 | ... N8: ='MC Drivers (NRD)'!N27*'MC Drivers (NRD)'!N22*'MC Drivers (NRD)'!N23*12+'MC Drivers (NRD)'!N27*(1-'MC Drivers (NRD)'!N22)*'MC Drivers (NRD)'!N24*12 -> 6.3759107e+08
B9: Aftersales Service Revenue | D9: =D7*'MC Drivers (NRD)'!D76 -> 18899807 | E9: =E7*'MC Drivers (NRD)'!E76 -> 30239691 | F9: =F7*'MC Drivers (NRD)'!F76 -> 48383506 | G9: =G7*'MC Drivers (NRD)'!G76 -> 67740058 | H9: =H7*'MC Drivers (NRD)'!H76 -> 84671136 | I9: =I7*'MC Drivers (NRD)'!I76 -> 1.0160221e+08 | J9: =J7*'MC Drivers (NRD)'!J76 -> 1.270067e+08 | K9: =K7*'MC Drivers (NRD)'!K76 -> 1.5241119e+08 | ... N9: =N7*'MC Drivers (NRD)'!N76 -> 2.0318868e+08
B10: Total Revenue | D10: =SUM(D6:D9) -> 3.4886273e+08 | E10: =SUM(E6:E9) -> 6.740321e+08 | F10: =SUM(F6:F9) -> 1156807424 | G10: =SUM(G6:G9) -> 1717476965 | H10: =SUM(H6:H9) -> 2305082921 | I10: =SUM(I6:I9) -> 2962174234 | J10: =SUM(J6:J9) -> 3828506346 | K10: =SUM(K6:K9) -> 4800832529 | ... N10: =SUM(N6:N9) -> 7856805006
B12: COST OF SALES
B13: MC Insurance | D13: =-'MC Drivers (NRD)'!D15*'MC Drivers (NRD)'!D78*12 -> -9299285.7 | E13: =-'MC Drivers (NRD)'!E15*'MC Drivers (NRD)'!E78*12 -> -22551607 | F13: =-'MC Drivers (NRD)'!F15*'MC Drivers (NRD)'!F78*12 -> -41494286 | G13: =-'MC Drivers (NRD)'!G15*'MC Drivers (NRD)'!G78*12 -> -65955268 | H13: =-'MC Drivers (NRD)'!H15*'MC Drivers (NRD)'!H78*12 -> -94050357 | I13: =-'MC Drivers (NRD)'!I15*'MC Drivers (NRD)'!I78*12 -> -1.2671955e+08 | J13: =-'MC Drivers (NRD)'!J15*'MC Drivers (NRD)'!J78*12 -> -1.6728223e+08 | K13: =-'MC Drivers (NRD)'!K15*'MC Drivers (NRD)'!K78*12 -> -214701875 | ... N13: =-'MC Drivers (NRD)'!N15*'MC Drivers (NRD)'!N78*12 -> -377586250
B14: Battery Insurance | D14: =-'MC Drivers (NRD)'!D221 -> -2189018.9 | E14: =-'MC Drivers (NRD)'!E221 -> -5308568.3 | F14: =-'MC Drivers (NRD)'!F221 -> -9767607.7 | G14: =-'MC Drivers (NRD)'!G221 -> -15525636 | H14: =-'MC Drivers (NRD)'!H221 -> -22139120 | I14: =-'MC Drivers (NRD)'!I221 -> -29829333 | J14: =-'MC Drivers (NRD)'!J221 -> -39377644 | K14: =-'MC Drivers (NRD)'!K221 -> -50540060 | ... N14: =-'MC Drivers (NRD)'!N221 -> -88882464
B15: MC Registration | D15: =-('MC Drivers (NRD)'!D13+'MC Drivers (NRD)'!D17+'MC Drivers (NRD)'!D25)*'MC Drivers (NRD)'!D79 -> -1054666.7 | E15: =-('MC Drivers (NRD)'!E13+'MC Drivers (NRD)'!E17+'MC Drivers (NRD)'!E25)*'MC Drivers (NRD)'!E79 -> -1611458.3 | F15: =-('MC Drivers (NRD)'!F13+'MC Drivers (NRD)'!F17+'MC Drivers (NRD)'!F25)*'MC Drivers (NRD)'!F79 -> -2408291.7 | G15: =-('MC Drivers (NRD)'!G13+'MC Drivers (NRD)'!G17+'MC Drivers (NRD)'!G25)*'MC Drivers (NRD)'!G79 -> -3234583.3 | H15: =-('MC Drivers (NRD)'!H13+'MC Drivers (NRD)'!H17+'MC Drivers (NRD)'!H25)*'MC Drivers (NRD)'!H79 -> -3902791.7 | I15: =-('MC Drivers (NRD)'!I13+'MC Drivers (NRD)'!I17+'MC Drivers (NRD)'!I25)*'MC Drivers (NRD)'!I79 -> -4657916.7 | J15: =-('MC Drivers (NRD)'!J13+'MC Drivers (NRD)'!J17+'MC Drivers (NRD)'!J25)*'MC Drivers (NRD)'!J79 -> -5833916.7 | K15: =-('MC Drivers (NRD)'!K13+'MC Drivers (NRD)'!K17+'MC Drivers (NRD)'!K25)*'MC Drivers (NRD)'!K79 -> -6973750 | ... N15: =-('MC Drivers (NRD)'!N13+'MC Drivers (NRD)'!N17+'MC Drivers (NRD)'!N25)*'MC Drivers (NRD)'!N79 -> -9444750
B16: Cost of Motorcycle Sales | D16: =-('MC Drivers (NRD)'!D17*'MC Drivers (NRD)'!D53*'MC Drivers (NRD)'!D67+'MC Drivers (NRD)'!D17*'MC Drivers (NRD)'!D54*'MC Drivers (NRD)'!D68) -> -1.4999847e+08 | E16: =-('MC Drivers (NRD)'!E17*'MC Drivers (NRD)'!E53*'MC Drivers (NRD)'!E67+'MC Drivers (NRD)'!E17*'MC Drivers (NRD)'!E54*'MC Drivers (NRD)'!E68) -> -2.3999755e+08 | F16: =-('MC Drivers (NRD)'!F17*'MC Drivers (NRD)'!F53*'MC Drivers (NRD)'!F67+'MC Drivers (NRD)'!F17*'MC Drivers (NRD)'!F54*'MC Drivers (NRD)'!F68) -> -3.8399608e+08 | G16: =-('MC Drivers (NRD)'!G17*'MC Drivers (NRD)'!G53*'MC Drivers (NRD)'!G67+'MC Drivers (NRD)'!G17*'MC Drivers (NRD)'!G54*'MC Drivers (NRD)'!G68) -> -5.3761951e+08 | H16: =-('MC Drivers (NRD)'!H17*'MC Drivers (NRD)'!H53*'MC Drivers (NRD)'!H67+'MC Drivers (NRD)'!H17*'MC Drivers (NRD)'!H54*'MC Drivers (NRD)'!H68) -> -6.7199314e+08 | I16: =-('MC Drivers (NRD)'!I17*'MC Drivers (NRD)'!I53*'MC Drivers (NRD)'!I67+'MC Drivers (NRD)'!I17*'MC Drivers (NRD)'!I54*'MC Drivers (NRD)'!I68) -> -8.0636677e+08 | J16: =-('MC Drivers (NRD)'!J17*'MC Drivers (NRD)'!J53*'MC Drivers (NRD)'!J67+'MC Drivers (NRD)'!J17*'MC Drivers (NRD)'!J54*'MC Drivers (NRD)'!J68) -> -1007989710 | K16: =-('MC Drivers (NRD)'!K17*'MC Drivers (NRD)'!K53*'MC Drivers (NRD)'!K67+'MC Drivers (NRD)'!K17*'MC Drivers (NRD)'!K54*'MC Drivers (NRD)'!K68) -> -1209612652 | ... N16: =-('MC Drivers (NRD)'!N17*'MC Drivers (NRD)'!N53*'MC Drivers (NRD)'!N67+'MC Drivers (NRD)'!N17*'MC Drivers (NRD)'!N54*'MC Drivers (NRD)'!N68) -> -1612608538
B17: Aftersales COGS | D17: =-D9*'MC Drivers (NRD)'!D77 -> -7559922.8 | E17: =-E9*'MC Drivers (NRD)'!E77 -> -12095877 | F17: =-F9*'MC Drivers (NRD)'!F77 -> -19353402 | G17: =-G9*'MC Drivers (NRD)'!G77 -> -27096023 | H17: =-H9*'MC Drivers (NRD)'!H77 -> -33868454 | I17: =-I9*'MC Drivers (NRD)'!I77 -> -40640885 | J17: =-J9*'MC Drivers (NRD)'!J77 -> -50802681 | K17: =-K9*'MC Drivers (NRD)'!K77 -> -60964478 | ... N17: =-N9*'MC Drivers (NRD)'!N77 -> -81275470
B18: Lease Payment Gateway | D18: =-(D6+D8)*'MC Drivers (NRD)'!D80 -> -4228945.7 | E18: =-(E6+E8)*'MC Drivers (NRD)'!E80 -> -10241865 | F18: =-(F6+F8)*'MC Drivers (NRD)'!F80 -> -18737666 | G18: =-(G6+G8)*'MC Drivers (NRD)'!G80 -> -29170090 | H18: =-(H6+H8)*'MC Drivers (NRD)'!H80 -> -41211013 | I18: =-(I6+I8)*'MC Drivers (NRD)'!I80 -> -55336497 | J18: =-(J6+J8)*'MC Drivers (NRD)'!J80 -> -72942978 | K18: =-(K6+K8)*'MC Drivers (NRD)'!K80 -> -93729282 | ... N18: =-(N6+N8)*'MC Drivers (NRD)'!N80 -> -1.6865189e+08
B19: Total Cost of Sales | D19: =SUM(D13:D18) -> -1.7433031e+08 | E19: =SUM(E13:E18) -> -2.9180693e+08 | F19: =SUM(F13:F18) -> -4.7575733e+08 | G19: =SUM(G13:G18) -> -6.7860111e+08 | H19: =SUM(H13:H18) -> -8.6716488e+08 | I19: =SUM(I13:I18) -> -1063550954 | J19: =SUM(J13:J18) -> -1344229163 | K19: =SUM(K13:K18) -> -1636522096 | ... N19: =SUM(N13:N18) -> -2338449360
B20: GROSS PROFIT | D20: =D10+D19 -> 1.7453243e+08 | E20: =E10+E19 -> 382225179 | F20: =F10+F19 -> 6.8105009e+08 | G20: =G10+G19 -> 1038875853 | H20: =H10+H19 -> 1437918044 | I20: =I10+I19 -> 1898623280 | J20: =J10+J19 -> 2484277183 | K20: =K10+K19 -> 3164310432 | ... N20: =N10+N19 -> 5518355646
B21: GP margin | D21: =IFERROR(D20/D10,0) -> 0.50028968 | E21: =IFERROR(E20/E10,0) -> 0.56707266 | F21: =IFERROR(F20/F10,0) -> 0.58873247 | G21: =IFERROR(G20/G10,0) -> 0.60488488 | H21: =IFERROR(H20/H10,0) -> 0.62380317 | I21: =IFERROR(I20/I10,0) -> 0.64095598 | J21: =IFERROR(J20/J10,0) -> 0.6488894 | K21: =IFERROR(K20/K10,0) -> 0.65911702 | ... N21: =IFERROR(N20/N10,0) -> 0.70236637
B23: OPERATING EXPENSES
B24: Salaries | D24: =-'MC Drivers (NRD)'!D135 -> -54684968 | E24: =-'MC Drivers (NRD)'!E135 -> -63161138 | F24: =-'MC Drivers (NRD)'!F135 -> -72951114 | G24: =-'MC Drivers (NRD)'!G135 -> -84258537 | H24: =-'MC Drivers (NRD)'!H135 -> -97318610 | I24: =-'MC Drivers (NRD)'!I135 -> -1.12403e+08 | J24: =-'MC Drivers (NRD)'!J135 -> -1.2982546e+08 | K24: =-'MC Drivers (NRD)'!K135 -> -1.4994841e+08 | ... N24: =-'MC Drivers (NRD)'!N135 -> -2.3104033e+08
B25: Employee Benefits | D25: =-'MC Drivers (NRD)'!D136 -> -5468496.8 | E25: =-'MC Drivers (NRD)'!E136 -> -6316113.8 | F25: =-'MC Drivers (NRD)'!F136 -> -7295111.4 | G25: =-'MC Drivers (NRD)'!G136 -> -8425853.7 | H25: =-'MC Drivers (NRD)'!H136 -> -9731861 | I25: =-'MC Drivers (NRD)'!I136 -> -11240300 | J25: =-'MC Drivers (NRD)'!J136 -> -12982546 | K25: =-'MC Drivers (NRD)'!K136 -> -14994841 | ... N25: =-'MC Drivers (NRD)'!N136 -> -23104033
B26: Sales Commission | D26: =-D7*'MC Drivers (NRD)'!D81 -> -3779961.4 | E26: =-E7*'MC Drivers (NRD)'!E81 -> -6047938.3 | F26: =-F7*'MC Drivers (NRD)'!F81 -> -9676701.2 | G26: =-G7*'MC Drivers (NRD)'!G81 -> -13548012 | H26: =-H7*'MC Drivers (NRD)'!H81 -> -16934227 | I26: =-I7*'MC Drivers (NRD)'!I81 -> -20320443 | J26: =-J7*'MC Drivers (NRD)'!J81 -> -25401341 | K26: =-K7*'MC Drivers (NRD)'!K81 -> -30482239 | ... N26: =-N7*'MC Drivers (NRD)'!N81 -> -40637735
B27: Rent - Head Office | D27: =-'MC Drivers (NRD)'!D142 -> -1714285.7 | E27: =-'MC Drivers (NRD)'!E142 -> -1800000 | F27: =-'MC Drivers (NRD)'!F142 -> -1890000 | G27: =-'MC Drivers (NRD)'!G142 -> -1984500 | H27: =-'MC Drivers (NRD)'!H142 -> -2083725 | I27: =-'MC Drivers (NRD)'!I142 -> -2187911.2 | J27: =-'MC Drivers (NRD)'!J142 -> -2297306.8 | K27: =-'MC Drivers (NRD)'!K142 -> -2412172.2 | ... N27: =-'MC Drivers (NRD)'!N142 -> -2792390.8
B28: Rent - Warehouse | D28: =-'MC Drivers (NRD)'!D145 -> -2235535.7 | E28: =-'MC Drivers (NRD)'!E145 -> -2347312.5 | F28: =-'MC Drivers (NRD)'!F145 -> -2464678.1 | G28: =-'MC Drivers (NRD)'!G145 -> -2587912 | H28: =-'MC Drivers (NRD)'!H145 -> -5434615.3 | I28: =-'MC Drivers (NRD)'!I145 -> -5706346 | J28: =-'MC Drivers (NRD)'!J145 -> -5991663.3 | K28: =-'MC Drivers (NRD)'!K145 -> -6291246.5 | ... N28: =-'MC Drivers (NRD)'!N145 -> -7282904.2
B29: Rent - Showroom / Store Room | D29: =-'MC Drivers (NRD)'!D148 -> -910714.29 | E29: =-'MC Drivers (NRD)'!E148 -> -956250 | F29: =-'MC Drivers (NRD)'!F148 -> -2008125 | G29: =-'MC Drivers (NRD)'!G148 -> -2108531.2 | H29: =-'MC Drivers (NRD)'!H148 -> -3320936.7 | I29: =-'MC Drivers (NRD)'!I148 -> -3486983.6 | J29: =-'MC Drivers (NRD)'!J148 -> -4881777 | K29: =-'MC Drivers (NRD)'!K148 -> -5125865.8 | ... N29: =-'MC Drivers (NRD)'!N148 -> -8900745.6
B30: Utilities (all locations) | D30: =-'MC Drivers (NRD)'!D170 -> -1221428.6 | E30: =-'MC Drivers (NRD)'!E170 -> -1282500 | F30: =-'MC Drivers (NRD)'!F170 -> -1630125 | G30: =-'MC Drivers (NRD)'!G170 -> -1711631.2 | H30: =-'MC Drivers (NRD)'!H170 -> -2630702.8 | I30: =-'MC Drivers (NRD)'!I170 -> -2762238 | J30: =-'MC Drivers (NRD)'!J170 -> -3244945.9 | K30: =-'MC Drivers (NRD)'!K170 -> -3407193.2 | ... N30: =-'MC Drivers (NRD)'!N170 -> -4781969.2
B31: Marketing | D31: =-D10*'MC Drivers (NRD)'!D82 -> -6977254.7 | E31: =-E10*'MC Drivers (NRD)'!E82 -> -13480642 | F31: =-F10*'MC Drivers (NRD)'!F82 -> -23136148 | G31: =-G10*'MC Drivers (NRD)'!G82 -> -34349539 | H31: =-H10*'MC Drivers (NRD)'!H82 -> -46101658 | I31: =-I10*'MC Drivers (NRD)'!I82 -> -59243485 | J31: =-J10*'MC Drivers (NRD)'!J82 -> -76570127 | K31: =-K10*'MC Drivers (NRD)'!K82 -> -96016651 | ... N31: =-N10*'MC Drivers (NRD)'!N82 -> -1.571361e+08
B32: Legal & Permits | D32: =-'MC Drivers (NRD)'!D178 -> -1987142.9 | E32: =-'MC Drivers (NRD)'!E178 -> -2185857.1 | F32: =-'MC Drivers (NRD)'!F178 -> -2404442.9 | G32: =-'MC Drivers (NRD)'!G178 -> -2644887.1 | H32: =-'MC Drivers (NRD)'!H178 -> -2909375.9 | I32: =-'MC Drivers (NRD)'!I178 -> -3200313.4 | J32: =-'MC Drivers (NRD)'!J178 -> -3520344.8 | K32: =-'MC Drivers (NRD)'!K178 -> -3872379.3 | ... N32: =-'MC Drivers (NRD)'!N178 -> -5154136.8
B33: Dues & Subscriptions | D33: =-'MC Drivers (NRD)'!D179 -> -1339285.7 | E33: =-'MC Drivers (NRD)'!E179 -> -1473214.3 | F33: =-'MC Drivers (NRD)'!F179 -> -1620535.7 | G33: =-'MC Drivers (NRD)'!G179 -> -1782589.3 | H33: =-'MC Drivers (NRD)'!H179 -> -1960848.2 | I33: =-'MC Drivers (NRD)'!I179 -> -2156933 | J33: =-'MC Drivers (NRD)'!J179 -> -2372626.3 | K33: =-'MC Drivers (NRD)'!K179 -> -2609889 | ... N33: =-'MC Drivers (NRD)'!N179 -> -3473762.2
B34: Repairs & Maintenance | D34: =-'MC Drivers (NRD)'!D180 -> -189000 | E34: =-'MC Drivers (NRD)'!E180 -> -207900 | F34: =-'MC Drivers (NRD)'!F180 -> -228690 | G34: =-'MC Drivers (NRD)'!G180 -> -251559 | H34: =-'MC Drivers (NRD)'!H180 -> -276714.9 | I34: =-'MC Drivers (NRD)'!I180 -> -304386.39 | J34: =-'MC Drivers (NRD)'!J180 -> -334825.03 | K34: =-'MC Drivers (NRD)'!K180 -> -368307.53 | ... N34: =-'MC Drivers (NRD)'!N180 -> -490217.33
B35: Office Expenses | D35: =-'MC Drivers (NRD)'!D181 -> -500000 | E35: =-'MC Drivers (NRD)'!E181 -> -550000 | F35: =-'MC Drivers (NRD)'!F181 -> -605000 | G35: =-'MC Drivers (NRD)'!G181 -> -665500 | H35: =-'MC Drivers (NRD)'!H181 -> -732050 | I35: =-'MC Drivers (NRD)'!I181 -> -805255 | J35: =-'MC Drivers (NRD)'!J181 -> -885780.5 | K35: =-'MC Drivers (NRD)'!K181 -> -974358.55 | ... N35: =-'MC Drivers (NRD)'!N181 -> -1296871.2
B36: Total Operating Expenses | D36: =SUM(D24:D35) -> -81008074 | E36: =SUM(E24:E35) -> -99808866 | F36: =SUM(F24:F35) -> -1.2591067e+08 | G36: =SUM(G24:G35) -> -1.5431905e+08 | H36: =SUM(H24:H35) -> -1.8943533e+08 | I36: =SUM(I24:I35) -> -2.2381759e+08 | J36: =SUM(J24:J35) -> -2.6830874e+08 | K36: =SUM(K24:K35) -> -3.1650355e+08 | ... N36: =SUM(N24:N35) -> -4.860912e+08
B38: EBITDA | D38: =D20+D36 -> 93524353 | E38: =E20+E36 -> 2.8241631e+08 | F38: =F20+F36 -> 5.5513942e+08 | G38: =G20+G36 -> 8.845568e+08 | H38: =H20+H36 -> 1248482719 | I38: =I20+I36 -> 1674805691 | J38: =J20+J36 -> 2215968440 | K38: =K20+K36 -> 2847806885 | ... N38: =N20+N36 -> 5032264445
B39: Depreciation & Amortization | D39: ='MC Drivers (NRD)'!D200+'MC Drivers (NRD)'!D220+'MC Drivers (NRD)'!D239+'MC Drivers (NRD)'!D304 -> 15339921 | E39: ='MC Drivers (NRD)'!E200+'MC Drivers (NRD)'!E220+'MC Drivers (NRD)'!E239+'MC Drivers (NRD)'!E304 -> 52870495 | F39: ='MC Drivers (NRD)'!F200+'MC Drivers (NRD)'!F220+'MC Drivers (NRD)'!F239+'MC Drivers (NRD)'!F304 -> 1.0673013e+08 | G39: ='MC Drivers (NRD)'!G200+'MC Drivers (NRD)'!G220+'MC Drivers (NRD)'!G239+'MC Drivers (NRD)'!G304 -> 1.7952727e+08 | H39: ='MC Drivers (NRD)'!H200+'MC Drivers (NRD)'!H220+'MC Drivers (NRD)'!H239+'MC Drivers (NRD)'!H304 -> 2.6883256e+08 | I39: ='MC Drivers (NRD)'!I200+'MC Drivers (NRD)'!I220+'MC Drivers (NRD)'!I239+'MC Drivers (NRD)'!I304 -> 3.7401099e+08 | J39: ='MC Drivers (NRD)'!J200+'MC Drivers (NRD)'!J220+'MC Drivers (NRD)'!J239+'MC Drivers (NRD)'!J304 -> 502319966 | K39: ='MC Drivers (NRD)'!K200+'MC Drivers (NRD)'!K220+'MC Drivers (NRD)'!K239+'MC Drivers (NRD)'!K304 -> 6.583493e+08 | ... N39: ='MC Drivers (NRD)'!N200+'MC Drivers (NRD)'!N220+'MC Drivers (NRD)'!N239+'MC Drivers (NRD)'!N304 -> 1237227626
B40: OPERATING INCOME (EBIT) | D40: =D38-D39 -> 78184431 | E40: =E38-E39 -> 2.2954582e+08 | F40: =F38-F39 -> 4.4840929e+08 | G40: =G38-G39 -> 7.0502953e+08 | H40: =H38-H39 -> 9.7965015e+08 | I40: =I38-I39 -> 1300794703 | J40: =J38-J39 -> 1713648474 | K40: =K38-K39 -> 2189457583 | ... N40: =N38-N39 -> 3795036819
B41: EBITDA margin | D41: =D38/D10 -> 0.26808353 | E41: =E38/E10 -> 0.41899534 | F41: =F38/F10 -> 0.47988923 | G41: =G38/G10 -> 0.5150327 | H41: =H38/H10 -> 0.54162161 | I41: =I38/I10 -> 0.56539743 | J41: =J38/J10 -> 0.57880757 | K41: =K38/K10 -> 0.59319022 | ... N41: =N38/N10 -> 0.64049756
B42: Interest Expense | D42: =-'MC Drivers (NRD)'!D323 -> 0 | E42: =-'MC Drivers (NRD)'!E323 -> 0 | F42: =-'MC Drivers (NRD)'!F323 -> 0 | G42: =-'MC Drivers (NRD)'!G323 -> 0 | H42: =-'MC Drivers (NRD)'!H323 -> 0 | I42: =-'MC Drivers (NRD)'!I323 -> 0 | J42: =-'MC Drivers (NRD)'!J323 -> 0 | K42: =-'MC Drivers (NRD)'!K323 -> 0 | ... N42: =-'MC Drivers (NRD)'!N323 -> 0
B43: EBT (Pre-tax Income) | D43: =D40+D42 -> 78184431 | E43: =E40+E42 -> 2.2954582e+08 | F43: =F40+F42 -> 4.4840929e+08 | G43: =G40+G42 -> 7.0502953e+08 | H43: =H40+H42 -> 9.7965015e+08 | I43: =I40+I42 -> 1300794703 | J43: =J40+J42 -> 1713648474 | K43: =K40+K42 -> 2189457583 | ... N43: =N40+N42 -> 3795036819
B44: Income Tax (no tax if EBT<0) | D44: =-MAX(D43,0)*'MC Drivers (NRD)'!D315 -> -19546108 | E44: =-MAX(E43,0)*'MC Drivers (NRD)'!E315 -> -57386455 | F44: =-MAX(F43,0)*'MC Drivers (NRD)'!F315 -> -1.1210232e+08 | G44: =-MAX(G43,0)*'MC Drivers (NRD)'!G315 -> -1.7625738e+08 | H44: =-MAX(H43,0)*'MC Drivers (NRD)'!H315 -> -2.4491254e+08 | I44: =-MAX(I43,0)*'MC Drivers (NRD)'!I315 -> -3.2519868e+08 | J44: =-MAX(J43,0)*'MC Drivers (NRD)'!J315 -> -4.2841212e+08 | K44: =-MAX(K43,0)*'MC Drivers (NRD)'!K315 -> -5.473644e+08 | ... N44: =-MAX(N43,0)*'MC Drivers (NRD)'!N315 -> -9.487592e+08
B45: NET INCOME (NIAT) | D45: =D43+D44 -> 58638323 | E45: =E43+E44 -> 1.7215936e+08 | F45: =F43+F44 -> 3.3630697e+08 | G45: =G43+G44 -> 5.2877215e+08 | H45: =H43+H44 -> 7.3473762e+08 | I45: =I43+I44 -> 9.7559603e+08 | J45: =J43+J44 -> 1285236356 | K45: =K43+K44 -> 1642093187 | ... N45: =N43+N44 -> 2846277615
B46: Net margin | D46: =IFERROR(D45/D10,0) -> 0.16808423 | E46: =IFERROR(E45/E10,0) -> 0.25541716 | F46: =IFERROR(F45/F10,0) -> 0.29071992 | G46: =IFERROR(G45/G10,0) -> 0.30787729 | H46: =IFERROR(H45/H10,0) -> 0.31874672 | I46: =IFERROR(I45/I10,0) -> 0.32935133 | J46: =IFERROR(J45/J10,0) -> 0.33570177 | K46: =IFERROR(K45/K10,0) -> 0.34204342 | ... N46: =IFERROR(N45/N10,0) -> 0.36226909
B47: memo: Cash COGS+Opex (excl D&A) | D47: =-(D19+D36)-('MC Drivers (NRD)'!D200+'MC Drivers (NRD)'!D220+'MC Drivers (NRD)'!D239+'MC Drivers (NRD)'!D304) -> 239998461 | E47: =-(E19+E36)-('MC Drivers (NRD)'!E200+'MC Drivers (NRD)'!E220+'MC Drivers (NRD)'!E239+'MC Drivers (NRD)'!E304) -> 3.387453e+08 | F47: =-(F19+F36)-('MC Drivers (NRD)'!F200+'MC Drivers (NRD)'!F220+'MC Drivers (NRD)'!F239+'MC Drivers (NRD)'!F304) -> 4.9493787e+08 | G47: =-(G19+G36)-('MC Drivers (NRD)'!G200+'MC Drivers (NRD)'!G220+'MC Drivers (NRD)'!G239+'MC Drivers (NRD)'!G304) -> 6.5339289e+08 | H47: =-(H19+H36)-('MC Drivers (NRD)'!H200+'MC Drivers (NRD)'!H220+'MC Drivers (NRD)'!H239+'MC Drivers (NRD)'!H304) -> 7.8776764e+08 | I47: =-(I19+I36)-('MC Drivers (NRD)'!I200+'MC Drivers (NRD)'!I220+'MC Drivers (NRD)'!I239+'MC Drivers (NRD)'!I304) -> 9.1335755e+08 | J47: =-(J19+J36)-('MC Drivers (NRD)'!J200+'MC Drivers (NRD)'!J220+'MC Drivers (NRD)'!J239+'MC Drivers (NRD)'!J304) -> 1110217939 | K47: =-(K19+K36)-('MC Drivers (NRD)'!K200+'MC Drivers (NRD)'!K220+'MC Drivers (NRD)'!K239+'MC Drivers (NRD)'!K304) -> 1294676342 | ... N47: =-(N19+N36)-('MC Drivers (NRD)'!N200+'MC Drivers (NRD)'!N220+'MC Drivers (NRD)'!N239+'MC Drivers (NRD)'!N304) -> 1587312935

Sheet RideBox Energy P&L
B2: RIDEBOX ENERGY - PROFIT & LOSS
B3: All figures in PHP Millions (unless noted)
D4: 2026 | E4: 2027 | F4: 2028 | G4: 2029 | H4: 2030 | I4: 2031 | J4: 2032 | K4: 2033 | L4: 2034 | M4: 2035 | N4: 2036
B5: REVENUE
B6: Battery Subscription (leased users) | D6: ='MC Drivers (NRD)'!D15*'Energy Drivers (RideBox)'!D11*12 -> 65292857 | E6: ='MC Drivers (NRD)'!E15*'Energy Drivers (RideBox)'!E11*12 -> 1.5834107e+08 | F6: ='MC Drivers (NRD)'!F15*'Energy Drivers (RideBox)'!F11*12 -> 2.9134286e+08 | G6: ='MC Drivers (NRD)'!G15*'Energy Drivers (RideBox)'!G11*12 -> 4.6309018e+08 | H6: ='MC Drivers (NRD)'!H15*'Energy Drivers (RideBox)'!H11*12 -> 6.6035357e+08 | I6: ='MC Drivers (NRD)'!I15*'Energy Drivers (RideBox)'!I11*12 -> 8.8973304e+08 | J6: ='MC Drivers (NRD)'!J15*'Energy Drivers (RideBox)'!J11*12 -> 1174534821 | K6: ='MC Drivers (NRD)'!K15*'Energy Drivers (RideBox)'!K11*12 -> 1507481250 | ... N6: ='MC Drivers (NRD)'!N15*'Energy Drivers (RideBox)'!N11*12 -> 2651137500
B7: Load / Prepaid (owner + L2O users) | D7: =('MC Drivers (NRD)'!D17*'Energy Drivers (RideBox)'!D12)*12 -> 11314286 | E7: =('MC Drivers (NRD)'!E17*'Energy Drivers (RideBox)'!E12)*12 -> 18102857 | F7: =('MC Drivers (NRD)'!F17*'Energy Drivers (RideBox)'!F12)*12 -> 28964571 | G7: =('MC Drivers (NRD)'!G17*'Energy Drivers (RideBox)'!G12)*12 -> 40552286 | H7: =('MC Drivers (NRD)'!H17*'Energy Drivers (RideBox)'!H12)*12 -> 50688000 | I7: =('MC Drivers (NRD)'!I17*'Energy Drivers (RideBox)'!I12)*12 -> 60823714 | J7: =('MC Drivers (NRD)'!J17*'Energy Drivers (RideBox)'!J12)*12 -> 76032000 | K7: =('MC Drivers (NRD)'!K17*'Energy Drivers (RideBox)'!K12)*12 -> 91240286 | ... N7: =('MC Drivers (NRD)'!N17*'Energy Drivers (RideBox)'!N12)*12 -> 121638000
B8: Total Revenue | D8: =SUM(D6:D7) -> 76607143 | E8: =SUM(E6:E7) -> 1.7644393e+08 | F8: =SUM(F6:F7) -> 3.2030743e+08 | G8: =SUM(G6:G7) -> 5.0364246e+08 | H8: =SUM(H6:H7) -> 7.1104157e+08 | I8: =SUM(I6:I7) -> 950556750 | J8: =SUM(J6:J7) -> 1250566821 | K8: =SUM(K6:K7) -> 1598721536 | ... N8: =SUM(N6:N7) -> 2772775500
B10: COST OF SALES (battery depr & insurance are in NRD)
B11: Locker Insurance | D11: =-'Energy Drivers (RideBox)'!D123 -> -822251.42 | E11: =-'Energy Drivers (RideBox)'!E123 -> -2036374.7 | F11: =-'Energy Drivers (RideBox)'!F123 -> -3837173.3 | G11: =-'Energy Drivers (RideBox)'!G123 -> -6190669.8 | H11: =-'Energy Drivers (RideBox)'!H123 -> -9001727.7 | I11: =-'Energy Drivers (RideBox)'!I123 -> -12324711 | J11: =-'Energy Drivers (RideBox)'!J123 -> -16467680 | K11: =-'Energy Drivers (RideBox)'!K123 -> -21387598 | ... N11: =-'Energy Drivers (RideBox)'!N123 -> -39080727
B12: Locker Connectivity | D12: =-'Energy Drivers (RideBox)'!D8*'Energy Drivers (RideBox)'!D30*12 -> -388928.57 | E12: =-'Energy Drivers (RideBox)'!E8*'Energy Drivers (RideBox)'!E30*12 -> -963214.29 | F12: =-'Energy Drivers (RideBox)'!F8*'Energy Drivers (RideBox)'!F30*12 -> -1815000 | G12: =-'Energy Drivers (RideBox)'!G8*'Energy Drivers (RideBox)'!G30*12 -> -2928214.3 | H12: =-'Energy Drivers (RideBox)'!H8*'Energy Drivers (RideBox)'!H30*12 -> -4257857.1 | I12: =-'Energy Drivers (RideBox)'!I8*'Energy Drivers (RideBox)'!I30*12 -> -5829642.9 | J12: =-'Energy Drivers (RideBox)'!J8*'Energy Drivers (RideBox)'!J30*12 -> -7789285.7 | K12: =-'Energy Drivers (RideBox)'!K8*'Energy Drivers (RideBox)'!K30*12 -> -10116429 | ... N12: =-'Energy Drivers (RideBox)'!N8*'Energy Drivers (RideBox)'!N30*12 -> -18485357
B13: Locker Maintenance | D13: =-'Energy Drivers (RideBox)'!D8*'Energy Drivers (RideBox)'!D31*12 -> -777857.14 | E13: =-'Energy Drivers (RideBox)'!E8*'Energy Drivers (RideBox)'!E31*12 -> -1926428.6 | F13: =-'Energy Drivers (RideBox)'!F8*'Energy Drivers (RideBox)'!F31*12 -> -3630000 | G13: =-'Energy Drivers (RideBox)'!G8*'Energy Drivers (RideBox)'!G31*12 -> -5856428.6 | H13: =-'Energy Drivers (RideBox)'!H8*'Energy Drivers (RideBox)'!H31*12 -> -8515714.3 | I13: =-'Energy Drivers (RideBox)'!I8*'Energy Drivers (RideBox)'!I31*12 -> -11659286 | J13: =-'Energy Drivers (RideBox)'!J8*'Energy Drivers (RideBox)'!J31*12 -> -15578571 | K13: =-'Energy Drivers (RideBox)'!K8*'Energy Drivers (RideBox)'!K31*12 -> -20232857 | ... N13: =-'Energy Drivers (RideBox)'!N8*'Energy Drivers (RideBox)'!N31*12 -> -36970714
B14: Locker Electricity (kWh-based) | D14: =-'Energy Drivers (RideBox)'!D8*'Energy Drivers (RideBox)'!D26*365*'Energy Drivers (RideBox)'!D19 -> -12975939 | E14: =-'Energy Drivers (RideBox)'!E8*'Energy Drivers (RideBox)'!E26*365*'Energy Drivers (RideBox)'!E19 -> -42848006 | F14: =-'Energy Drivers (RideBox)'!F8*'Energy Drivers (RideBox)'!F26*365*'Energy Drivers (RideBox)'!F19 -> -80739179 | G14: =-'Energy Drivers (RideBox)'!G8*'Energy Drivers (RideBox)'!G26*365*'Energy Drivers (RideBox)'!G19 -> -1.3025984e+08 | H14: =-'Energy Drivers (RideBox)'!H8*'Energy Drivers (RideBox)'!H26*365*'Energy Drivers (RideBox)'!H19 -> -1.894082e+08 | I14: =-'Energy Drivers (RideBox)'!I8*'Energy Drivers (RideBox)'!I26*365*'Energy Drivers (RideBox)'!I19 -> -2.5932814e+08 | J14: =-'Energy Drivers (RideBox)'!J8*'Energy Drivers (RideBox)'!J26*365*'Energy Drivers (RideBox)'!J19 -> -346501671 | K14: =-'Energy Drivers (RideBox)'!K8*'Energy Drivers (RideBox)'!K26*365*'Energy Drivers (RideBox)'!K19 -> -4.5002322e+08 | ... N14: =-'Energy Drivers (RideBox)'!N8*'Energy Drivers (RideBox)'!N26*365*'Energy Drivers (RideBox)'!N19 -> -822309949
B15: Battery Connectivity | D15: =-'MC Drivers (NRD)'!D15*2*'Energy Drivers (RideBox)'!D14*12 -> -4748571.4 | E15: =-'MC Drivers (NRD)'!E15*2*'Energy Drivers (RideBox)'!E14*12 -> -11515714 | F15: =-'MC Drivers (NRD)'!F16*2*'Energy Drivers (RideBox)'!F14*12 -> -16352143 | G15: =-'MC Drivers (NRD)'!G16*2*'Energy Drivers (RideBox)'!G14*12 -> -27433929 | H15: =-'MC Drivers (NRD)'!H16*2*'Energy Drivers (RideBox)'!H14*12 -> -40852500 | I15: =-'MC Drivers (NRD)'!I16*2*'Energy Drivers (RideBox)'!I14*12 -> -56366786 | J15: =-'MC Drivers (NRD)'!J16*2*'Energy Drivers (RideBox)'!J14*12 -> -75064286 | K15: =-'MC Drivers (NRD)'!K16*2*'Energy Drivers (RideBox)'!K14*12 -> -97527857 | L15: =-'MC Drivers (NRD)'!L16*2*'Energy Drivers (RideBox)'!L14*12 -> -1.2263786e+08 | M15: =-'MC Drivers (NRD)'!M16*2*'Energy Drivers (RideBox)'!M14*12 -> -149512500 | N15: =-'MC Drivers (NRD)'!N16*2*'Energy Drivers (RideBox)'!N14*12 -> -1.7809714e+08
B16: Battery Payment Gateway | D16: =-D6*'Energy Drivers (RideBox)'!D13 -> -1958785.7 | E16: =-E6*'Energy Drivers (RideBox)'!E13 -> -4750232.1 | F16: =-F6*'Energy Drivers (RideBox)'!F13 -> -8740285.7 | G16: =-G6*'Energy Drivers (RideBox)'!G13 -> -13892705 | H16: =-H6*'Energy Drivers (RideBox)'!H13 -> -19810607 | I16: =-I6*'Energy Drivers (RideBox)'!I13 -> -26691991 | J16: =-J6*'Energy Drivers (RideBox)'!J13 -> -35236045 | K16: =-K6*'Energy Drivers (RideBox)'!K13 -> -45224438 | ... N16: =-N6*'Energy Drivers (RideBox)'!N13 -> -79534125
B17: Total Cost of Sales | D17: =SUM(D11:D16) -> -21672334 | E17: =SUM(E11:E16) -> -64039970 | F17: =SUM(F11:F16) -> -1.1511378e+08 | G17: =SUM(G11:G16) -> -1.8656179e+08 | H17: =SUM(H11:H16) -> -2.7184661e+08 | I17: =SUM(I11:I16) -> -372200558 | J17: =SUM(J11:J16) -> -4.9663754e+08 | K17: =SUM(K11:K16) -> -6.4451239e+08 | ... N17: =SUM(N11:N16) -> -1174478015
B18: GROSS PROFIT | D18: =D8+D17 -> 54934809 | E18: =E8+E17 -> 1.1240396e+08 | F18: =F8+F17 -> 2.0519365e+08 | G18: =G8+G17 -> 3.1708067e+08 | H18: =H8+H17 -> 4.3919496e+08 | I18: =I8+I17 -> 578356192 | J18: =J8+J17 -> 753929283 | K18: =K8+K17 -> 9.5420914e+08 | ... N18: =N8+N17 -> 1598297485
B19: GP margin | D19: =IFERROR(D18/D8,0) -> 0.71709774 | E19: =IFERROR(E18/E8,0) -> 0.63705201 | F19: =IFERROR(F18/F8,0) -> 0.6406147 | G19: =IFERROR(G18/G8,0) -> 0.62957494 | H19: =IFERROR(H18/H8,0) -> 0.61767832 | I19: =IFERROR(I18/I8,0) -> 0.60843941 | J19: =IFERROR(J18/J8,0) -> 0.60287005 | K19: =IFERROR(K18/K8,0) -> 0.59685763 | ... N19: =IFERROR(N18/N8,0) -> 0.57642513
B21: OPERATING EXPENSES
B22: Salaries | D22: =-'Energy Drivers (RideBox)'!D88 -> -17925674 | E22: =-'Energy Drivers (RideBox)'!E88 -> -20704153 | F22: =-'Energy Drivers (RideBox)'!F88 -> -23913297 | G22: =-'Energy Drivers (RideBox)'!G88 -> -27619858 | H22: =-'Energy Drivers (RideBox)'!H88 -> -31900936 | I22: =-'Energy Drivers (RideBox)'!I88 -> -36845582 | J22: =-'Energy Drivers (RideBox)'!J88 -> -42556647 | K22: =-'Energy Drivers (RideBox)'!K88 -> -49152927 | ... N22: =-'Energy Drivers (RideBox)'!N88 -> -75734774
B23: Employee Benefits | D23: =-'Energy Drivers (RideBox)'!D89 -> -1792567.4 | E23: =-'Energy Drivers (RideBox)'!E89 -> -2070415.3 | F23: =-'Energy Drivers (RideBox)'!F89 -> -2391329.7 | G23: =-'Energy Drivers (RideBox)'!G89 -> -2761985.8 | H23: =-'Energy Drivers (RideBox)'!H89 -> -3190093.6 | I23: =-'Energy Drivers (RideBox)'!I89 -> -3684558.2 | J23: =-'Energy Drivers (RideBox)'!J89 -> -4255664.7 | K23: =-'Energy Drivers (RideBox)'!K89 -> -4915292.7 | ... N23: =-'Energy Drivers (RideBox)'!N89 -> -7573477.4
B24: Locker Rent | D24: =-'Energy Drivers (RideBox)'!D8*'Energy Drivers (RideBox)'!D29*12 -> -19446429 | E24: =-'Energy Drivers (RideBox)'!E8*'Energy Drivers (RideBox)'!E29*12 -> -48160714 | F24: =-'Energy Drivers (RideBox)'!F8*'Energy Drivers (RideBox)'!F29*12 -> -90750000 | G24: =-'Energy Drivers (RideBox)'!G8*'Energy Drivers (RideBox)'!G29*12 -> -1.4641071e+08 | H24: =-'Energy Drivers (RideBox)'!H8*'Energy Drivers (RideBox)'!H29*12 -> -2.1289286e+08 | I24: =-'Energy Drivers (RideBox)'!I8*'Energy Drivers (RideBox)'!I29*12 -> -2.9148214e+08 | J24: =-'Energy Drivers (RideBox)'!J8*'Energy Drivers (RideBox)'!J29*12 -> -3.8946429e+08 | K24: =-'Energy Drivers (RideBox)'!K8*'Energy Drivers (RideBox)'!K29*12 -> -5.0582143e+08 | ... N24: =-'Energy Drivers (RideBox)'!N8*'Energy Drivers (RideBox)'!N29*12 -> -9.2426786e+08
B25: Total Operating Expenses | D25: =D22+D23+D24 -> -39164670 | E25: =E22+E23+E24 -> -70935283 | F25: =F22+F23+F24 -> -117054627 | G25: =G22+G23+G24 -> -1.7679256e+08 | H25: =H22+H23+H24 -> -2.4798389e+08 | I25: =I22+I23+I24 -> -3.3201228e+08 | J25: =J22+J23+J24 -> -436276597 | K25: =K22+K23+K24 -> -5.5988965e+08 | ... N25: =N22+N23+N24 -> -1007576109
B27: EBITDA | D27: =D18+D25 -> 15770139 | E27: =E18+E25 -> 41468676 | F27: =F18+F25 -> 88139021 | G27: =G18+G25 -> 1.4028812e+08 | H27: =H18+H25 -> 1.9121107e+08 | I27: =I18+I25 -> 2.4634391e+08 | J27: =J18+J25 -> 317652686 | K27: =K18+K25 -> 3.9431949e+08 | ... N27: =N18+N25 -> 5.9072138e+08
B28: Depreciation & Amortization | D28: ='Energy Drivers (RideBox)'!D121 -> 2055628.6 | E28: ='Energy Drivers (RideBox)'!E121 -> 7146565.4 | F28: ='Energy Drivers (RideBox)'!F121 -> 14683870 | G28: ='Energy Drivers (RideBox)'!G121 -> 25069608 | H28: ='Energy Drivers (RideBox)'!H121 -> 37980994 | I28: ='Energy Drivers (RideBox)'!I121 -> 53316096 | J28: ='Energy Drivers (RideBox)'!J121 -> 71980977 | K28: ='Energy Drivers (RideBox)'!K121 -> 94638194 | ... N28: ='Energy Drivers (RideBox)'!N121 -> 1.7735034e+08
B29: OPERATING INCOME (EBIT) | D29: =D27-D28 -> 13714511 | E29: =E27-E28 -> 34322110 | F29: =F27-F28 -> 73455151 | G29: =G27-G28 -> 1.1521851e+08 | H29: =H27-H28 -> 1.5323008e+08 | I29: =I27-I28 -> 1.9302781e+08 | J29: =J27-J28 -> 2.4567171e+08 | K29: =K27-K28 -> 2.996813e+08 | ... N29: =N27-N28 -> 4.1337103e+08
B30: EBITDA margin | D30: =D27/D8 -> 0.20585729 | E30: =E27/E8 -> 0.23502467 | F30: =IFERROR(F29/F8,0) -> 0.22932703 | G30: =IFERROR(G29/G8,0) -> 0.22877044 | H30: =IFERROR(H29/H8,0) -> 0.21550087 | I30: =IFERROR(I29/I8,0) -> 0.20306816 | J30: =IFERROR(J29/J8,0) -> 0.19644829 | K30: =IFERROR(K29/K8,0) -> 0.18745059 | L30: =IFERROR(L29/L8,0) -> 0.17441028 | M30: =IFERROR(M29/M8,0) -> 0.16143717 | N30: =IFERROR(N29/N8,0) -> 0.14908204
B31: Interest Expense | D31: =0 -> 0 | E31: =0 -> 0 | F31: =0 -> 0 | G31: =0 -> 0 | H31: =0 -> 0 | I31: =0 -> 0 | J31: =0 -> 0 | K31: =0 -> 0 | ... N31: =0 -> 0
B32: EBT (Pre-tax Income) | D32: =D29+D31 -> 13714511 | E32: =E29+E31 -> 34322110 | F32: =F29+F31 -> 73455151 | G32: =G29+G31 -> 1.1521851e+08 | H32: =H29+H31 -> 1.5323008e+08 | I32: =I29+I31 -> 1.9302781e+08 | J32: =J29+J31 -> 2.4567171e+08 | K32: =K29+K31 -> 2.996813e+08 | ... N32: =N29+N31 -> 4.1337103e+08
B33: Income Tax (no tax if EBT<0) | D33: =-MAX(D32,0)*'MC Drivers (NRD)'!D315 -> -3428627.6 | E33: =-MAX(E32,0)*'MC Drivers (NRD)'!E315 -> -8580527.6 | F33: =-MAX(F32,0)*'MC Drivers (NRD)'!F315 -> -18363788 | G33: =-MAX(G32,0)*'MC Drivers (NRD)'!G315 -> -28804627 | H33: =-MAX(H32,0)*'MC Drivers (NRD)'!H315 -> -38307520 | I33: =-MAX(I32,0)*'MC Drivers (NRD)'!I315 -> -48256953 | J33: =-MAX(J32,0)*'MC Drivers (NRD)'!J315 -> -61417927 | K33: =-MAX(K32,0)*'MC Drivers (NRD)'!K315 -> -74920325 | ... N33: =-MAX(N32,0)*'MC Drivers (NRD)'!N315 -> -103342758
B34: NET INCOME (NIAT) | D34: =D32+D33 -> 10285883 | E34: =E32+E33 -> 25741583 | F34: =F32+F33 -> 55091363 | G34: =G32+G33 -> 86413881 | H34: =H32+H33 -> 1.1492256e+08 | I34: =I32+I33 -> 1.4477086e+08 | J34: =J32+J33 -> 184253782 | K34: =K32+K33 -> 2.2476098e+08 | ... N34: =N32+N33 -> 3.1002827e+08
B35: Net margin | D35: =IFERROR(D34/D8,0) -> 0.13426794 | E35: =IFERROR(E34/E8,0) -> 0.14589101 | F35: =IFERROR(F34/F8,0) -> 0.17199527 | G35: =IFERROR(G34/G8,0) -> 0.17157783 | H35: =IFERROR(H34/H8,0) -> 0.16162566 | I35: =IFERROR(I34/I8,0) -> 0.15230112 | J35: =IFERROR(J34/J8,0) -> 0.14733621 | K35: =IFERROR(K34/K8,0) -> 0.14058794 | ... N35: =IFERROR(N34/N8,0) -> 0.11181153
B36: memo: Cash COGS+Opex (excl D&A) | D36: =-(D17+D25)-'Energy Drivers (RideBox)'!D121 -> 58781375 | E36: =-(E17+E25)-'Energy Drivers (RideBox)'!E121 -> 1.2782869e+08 | F36: =-(F17+F25)-'Energy Drivers (RideBox)'!F121 -> 2.1748454e+08 | G36: =-(G17+G25)-'Energy Drivers (RideBox)'!G121 -> 3.3828474e+08 | H36: =-(H17+H25)-'Energy Drivers (RideBox)'!H121 -> 4.818495e+08 | I36: =-(I17+I25)-'Energy Drivers (RideBox)'!I121 -> 6.5089674e+08 | J36: =-(J17+J25)-'Energy Drivers (RideBox)'!J121 -> 8.6093316e+08 | K36: =-(K17+K25)-'Energy Drivers (RideBox)'!K121 -> 1109763848 | ... N36: =-(N17+N25)-'Energy Drivers (RideBox)'!N121 -> 2004703780

Sheet NRD MC Balance Sheet
B2: NRD MOTORCYCLE - BALANCE SHEET
B3: All figures in PHP Millions (unless noted)
D4: 2026 | E4: 2027 | F4: 2028 | G4: 2029 | H4: 2030 | I4: 2031 | J4: 2032 | K4: 2033 | L4: 2034 | M4: 2035 | N4: 2036
B5: ASSETS
B6: Accounts Receivable | D6: ='MC Drivers (NRD)'!D309/365*'NRD MC P&L'!D10 -> 6690518.2 | E6: ='MC Drivers (NRD)'!E309/365*'NRD MC P&L'!E10 -> 12926643 | F6: ='MC Drivers (NRD)'!F309/365*'NRD MC P&L'!F10 -> 22185348 | G6: ='MC Drivers (NRD)'!G309/365*'NRD MC P&L'!G10 -> 32937914 | H6: ='MC Drivers (NRD)'!H309/365*'NRD MC P&L'!H10 -> 44207070 | I6: ='MC Drivers (NRD)'!I309/365*'NRD MC P&L'!I10 -> 56808821 | J6: ='MC Drivers (NRD)'!J309/365*'NRD MC P&L'!J10 -> 73423409 | K6: ='MC Drivers (NRD)'!K309/365*'NRD MC P&L'!K10 -> 92070761 | ... N6: ='MC Drivers (NRD)'!N309/365*'NRD MC P&L'!N10 -> 1.5067845e+08
B7: Inventory (MC sale COGS basis) | D7: ='MC Drivers (NRD)'!D311/365*'MC Drivers (NRD)'!D17*('MC Drivers (NRD)'!D53*'MC Drivers (NRD)'!D67+'MC Drivers (NRD)'!D54*'MC Drivers (NRD)'!D68) -> 14383415 | E7: ='MC Drivers (NRD)'!E311/365*'MC Drivers (NRD)'!E17*('MC Drivers (NRD)'!E53*'MC Drivers (NRD)'!E67+'MC Drivers (NRD)'!E54*'MC Drivers (NRD)'!E68) -> 23013464 | F7: ='MC Drivers (NRD)'!F311/365*'MC Drivers (NRD)'!F17*('MC Drivers (NRD)'!F53*'MC Drivers (NRD)'!F67+'MC Drivers (NRD)'!F54*'MC Drivers (NRD)'!F68) -> 36821542 | G7: ='MC Drivers (NRD)'!G311/365*'MC Drivers (NRD)'!G17*('MC Drivers (NRD)'!G53*'MC Drivers (NRD)'!G67+'MC Drivers (NRD)'!G54*'MC Drivers (NRD)'!G68) -> 51552556 | H7: ='MC Drivers (NRD)'!H311/365*'MC Drivers (NRD)'!H17*('MC Drivers (NRD)'!H53*'MC Drivers (NRD)'!H67+'MC Drivers (NRD)'!H54*'MC Drivers (NRD)'!H68) -> 64437698 | I7: ='MC Drivers (NRD)'!I311/365*'MC Drivers (NRD)'!I17*('MC Drivers (NRD)'!I53*'MC Drivers (NRD)'!I67+'MC Drivers (NRD)'!I54*'MC Drivers (NRD)'!I68) -> 77322841 | J7: ='MC Drivers (NRD)'!J311/365*'MC Drivers (NRD)'!J17*('MC Drivers (NRD)'!J53*'MC Drivers (NRD)'!J67+'MC Drivers (NRD)'!J54*'MC Drivers (NRD)'!J68) -> 96656548 | K7: ='MC Drivers (NRD)'!K311/365*'MC Drivers (NRD)'!K17*('MC Drivers (NRD)'!K53*'MC Drivers (NRD)'!K67+'MC Drivers (NRD)'!K54*'MC Drivers (NRD)'!K68) -> 1.1599025e+08 | ... N7: ='MC Drivers (NRD)'!N311/365*'MC Drivers (NRD)'!N17*('MC Drivers (NRD)'!N53*'MC Drivers (NRD)'!N67+'MC Drivers (NRD)'!N54*'MC Drivers (NRD)'!N68) -> 1.546337e+08
B8: Net PP&E (MC + batteries + L2O + opex) | D8: ='MC Drivers (NRD)'!D201+'MC Drivers (NRD)'!D222+'MC Drivers (NRD)'!D240+'MC Drivers (NRD)'!D306 -> 2.9145851e+08 | E8: ='MC Drivers (NRD)'!E201+'MC Drivers (NRD)'!E222+'MC Drivers (NRD)'!E240+'MC Drivers (NRD)'!E306 -> 6.8240105e+08 | F8: ='MC Drivers (NRD)'!F201+'MC Drivers (NRD)'!F222+'MC Drivers (NRD)'!F240+'MC Drivers (NRD)'!F306 -> 1209050606 | G8: ='MC Drivers (NRD)'!G201+'MC Drivers (NRD)'!G222+'MC Drivers (NRD)'!G240+'MC Drivers (NRD)'!G306 -> 1852086463 | H8: ='MC Drivers (NRD)'!H201+'MC Drivers (NRD)'!H222+'MC Drivers (NRD)'!H240+'MC Drivers (NRD)'!H306 -> 2546796622 | I8: ='MC Drivers (NRD)'!I201+'MC Drivers (NRD)'!I222+'MC Drivers (NRD)'!I240+'MC Drivers (NRD)'!I306 -> 3312811391 | J8: ='MC Drivers (NRD)'!J201+'MC Drivers (NRD)'!J222+'MC Drivers (NRD)'!J240+'MC Drivers (NRD)'!J306 -> 4236645221 | K8: ='MC Drivers (NRD)'!K201+'MC Drivers (NRD)'!K222+'MC Drivers (NRD)'!K240+'MC Drivers (NRD)'!K306 -> 5272728835 | ... N8: ='MC Drivers (NRD)'!N201+'MC Drivers (NRD)'!N222+'MC Drivers (NRD)'!N240+'MC Drivers (NRD)'!N306 -> 8403351278
B9: Total Assets | D9: =D6+D7+D8 -> 3.1253244e+08 | E9: =E6+E7+E8 -> 7.1834116e+08 | F9: =F6+F7+F8 -> 1268057496 | G9: =G6+G7+G8 -> 1936576933 | H9: =H6+H7+H8 -> 2655441390 | I9: =I6+I7+I8 -> 3446943052 | J9: =J6+J7+J8 -> 4406725178 | K9: =K6+K7+K8 -> 5480789850 | ... N9: =N6+N7+N8 -> 8708663426
B11: LIABILITIES & EQUITY
B12: Accounts Payable | D12: ='MC Drivers (NRD)'!D310/365*'NRD MC P&L'!D47 -> 9862950.4 | E12: ='MC Drivers (NRD)'!E310/365*'NRD MC P&L'!E47 -> 13921040 | F12: ='MC Drivers (NRD)'!F310/365*'NRD MC P&L'!F47 -> 20339913 | G12: ='MC Drivers (NRD)'!G310/365*'NRD MC P&L'!G47 -> 26851763 | H12: ='MC Drivers (NRD)'!H310/365*'NRD MC P&L'!H47 -> 32374013 | I12: ='MC Drivers (NRD)'!I310/365*'NRD MC P&L'!I47 -> 37535242 | J12: ='MC Drivers (NRD)'!J310/365*'NRD MC P&L'!J47 -> 45625395 | K12: ='MC Drivers (NRD)'!K310/365*'NRD MC P&L'!K47 -> 53205877 | ... N12: ='MC Drivers (NRD)'!N310/365*'NRD MC P&L'!N47 -> 65232038
B13: Retained Earnings | D13: ='NRD MC P&L'!D45 -> 58638323 | E13: =D13+'NRD MC P&L'!E45 -> 230797687 | F13: =E13+'NRD MC P&L'!F45 -> 5.6710465e+08 | G13: =F13+'NRD MC P&L'!G45 -> 1095876800 | H13: =G13+'NRD MC P&L'!H45 -> 1830614415 | I13: =H13+'NRD MC P&L'!I45 -> 2806210443 | J13: =I13+'NRD MC P&L'!J45 -> 4091446798 | K13: =J13+'NRD MC P&L'!K45 -> 5733539986 | L13: =K13+'NRD MC P&L'!L45 -> 7741696898 | ... N13: =M13+'NRD MC P&L'!N45 -> 12993618160
B14: Net Capital Employed (group funding) | D14: =D9-D12-D13 -> 2.4403117e+08 | E14: =E9-E12-E13 -> 4.7362243e+08 | F14: =F9-F12-F13 -> 6.8061293e+08 | G14: =G9-G12-G13 -> 8.1384837e+08 | H14: =H9-H12-H13 -> 7.9245296e+08 | I14: =I9-I12-I13 -> 6.0319737e+08 | J14: =J9-J12-J13 -> 2.6965299e+08 | K14: =K9-K12-K13 -> -3.0595601e+08 | ... N14: =N9-N12-N13 -> -4350186773
B15: Total Liabilities & Equity | D15: =D12+D13+D14 -> 3.1253244e+08 | E15: =E12+E13+E14 -> 7.1834116e+08 | F15: =F12+F13+F14 -> 1268057496 | G15: =G12+G13+G14 -> 1936576933 | H15: =H12+H13+H14 -> 2655441390 | I15: =I12+I13+I14 -> 3446943052 | J15: =J12+J13+J14 -> 4406725178 | K15: =K12+K13+K14 -> 5480789850 | ... N15: =N12+N13+N14 -> 8708663426
D16: =D9-D15 -> 0 | E16: =E9-E15 -> 0 | F16: =F9-F15 -> 0 | G16: =G9-G15 -> 0 | H16: =H9-H15 -> 4.7683716e-07 | I16: =I9-I15 -> 0 | J16: =J9-J15 -> 0 | K16: =K9-K15 -> 0 | ... N16: =N9-N15 -> 0
B17: memo: Net Working Capital | D17: =D6+D7-D12 -> 11210983 | E17: =E6+E7-E12 -> 22019067 | F17: =F6+F7-F12 -> 38666977 | G17: =G6+G7-G12 -> 57638708 | H17: =H6+H7-H12 -> 76270756 | I17: =I6+I7-I12 -> 96596420 | J17: =J6+J7-J12 -> 1.2445456e+08 | K17: =K6+K7-K12 -> 1.5485514e+08 | ... N17: =N6+N7-N12 -> 2.4008011e+08

Sheet RideBox Energy Balance Sheet
B2: RIDEBOX ENERGY - BALANCE SHEET
B3: All figures in PHP Millions (unless noted)
D4: 2026 | E4: 2027 | F4: 2028 | G4: 2029 | H4: 2030 | I4: 2031 | J4: 2032 | K4: 2033 | L4: 2034 | M4: 2035 | N4: 2036
B5: ASSETS
B6: Accounts Receivable | D6: ='MC Drivers (NRD)'!D309/365*'RideBox Energy P&L'!D8 -> 1469178.1 | E6: ='MC Drivers (NRD)'!E309/365*'RideBox Energy P&L'!E8 -> 3383856.2 | F6: ='MC Drivers (NRD)'!F309/365*'RideBox Energy P&L'!F8 -> 6142882.2 | G6: ='MC Drivers (NRD)'!G309/365*'RideBox Energy P&L'!G8 -> 9658896.6 | H6: ='MC Drivers (NRD)'!H309/365*'RideBox Energy P&L'!H8 -> 13636414 | I6: ='MC Drivers (NRD)'!I309/365*'RideBox Energy P&L'!I8 -> 18229855 | J6: ='MC Drivers (NRD)'!J309/365*'RideBox Energy P&L'!J8 -> 23983473 | K6: ='MC Drivers (NRD)'!K309/365*'RideBox Energy P&L'!K8 -> 30660413 | ... N6: ='MC Drivers (NRD)'!N309/365*'RideBox Energy P&L'!N8 -> 53176516
B7: Net PP&E (lockers + chargers + metrohubs) | D7: ='Energy Drivers (RideBox)'!D122 -> 39056942 | E7: ='Energy Drivers (RideBox)'!E122 -> 92616543 | F7: ='Energy Drivers (RideBox)'!F122 -> 1.679726e+08 | G7: ='Energy Drivers (RideBox)'!G122 -> 2.6057782e+08 | H7: ='Energy Drivers (RideBox)'!H122 -> 3.6314972e+08 | I7: ='Energy Drivers (RideBox)'!I122 -> 4.7598277e+08 | J7: ='Energy Drivers (RideBox)'!J122 -> 6.1115026e+08 | K7: ='Energy Drivers (RideBox)'!K122 -> 7.6250795e+08 | ... N7: ='Energy Drivers (RideBox)'!N122 -> 1200702264
B8: Total Assets | D8: =D6+D7 -> 40526121 | E8: =E6+E7 -> 96000399 | F8: =F6+F7 -> 174115483 | G8: =G6+G7 -> 2.7023671e+08 | H8: =H6+H7 -> 376786132 | I8: =I6+I7 -> 4.9421263e+08 | J8: =J6+J7 -> 6.3513373e+08 | K8: =K6+K7 -> 7.9316836e+08 | ... N8: =N6+N7 -> 1253878780
B10: LIABILITIES & EQUITY
B11: Accounts Payable | D11: ='MC Drivers (NRD)'!D310/365*'RideBox Energy P&L'!D36 -> 2415673 | E11: ='MC Drivers (NRD)'!E310/365*'RideBox Energy P&L'!E36 -> 5253233.7 | F11: ='MC Drivers (NRD)'!F310/365*'RideBox Energy P&L'!F36 -> 8937720.7 | G11: ='MC Drivers (NRD)'!G310/365*'RideBox Energy P&L'!G36 -> 13902113 | H11: ='MC Drivers (NRD)'!H310/365*'RideBox Energy P&L'!H36 -> 19802034 | I11: ='MC Drivers (NRD)'!I310/365*'RideBox Energy P&L'!I36 -> 26749181 | J11: ='MC Drivers (NRD)'!J310/365*'RideBox Energy P&L'!J36 -> 35380815 | K11: ='MC Drivers (NRD)'!K310/365*'RideBox Energy P&L'!K36 -> 45606733 | ... N11: ='MC Drivers (NRD)'!N310/365*'RideBox Energy P&L'!N36 -> 82385087
B12: Retained Earnings | D12: ='RideBox Energy P&L'!D34 -> 10285883 | E12: =D12+'RideBox Energy P&L'!E34 -> 36027466 | F12: =E12+'RideBox Energy P&L'!F34 -> 91118829 | G12: =F12+'RideBox Energy P&L'!G34 -> 1.7753271e+08 | H12: =G12+'RideBox Energy P&L'!H34 -> 2.9245527e+08 | I12: =H12+'RideBox Energy P&L'!I34 -> 4.3722613e+08 | J12: =I12+'RideBox Energy P&L'!J34 -> 6.2147991e+08 | K12: =J12+'RideBox Energy P&L'!K34 -> 8.4624089e+08 | L12: =K12+'RideBox Energy P&L'!L34 -> 1103464619 | ... N12: =M12+'RideBox Energy P&L'!N34 -> 1698998918
B13: Net Capital Employed (group funding) | D13: =D8-D11-D12 -> 27824565 | E13: =E8-E11-E12 -> 54719699 | F13: =F8-F11-F12 -> 74058934 | G13: =G8-G11-G12 -> 78801892 | H13: =H8-H11-H12 -> 64528828 | I13: =I8-I11-I12 -> 30237317 | J13: =J8-J11-J12 -> -21726993 | K13: =K8-K11-K12 -> -98679262 | ... N13: =N8-N11-N12 -> -5.2750522e+08
B14: Total Liabilities & Equity | D14: =D11+D12+D13 -> 40526121 | E14: =E11+E12+E13 -> 96000399 | F14: =F11+F12+F13 -> 174115483 | G14: =G11+G12+G13 -> 2.7023671e+08 | H14: =H11+H12+H13 -> 376786132 | I14: =I11+I12+I13 -> 4.9421263e+08 | J14: =J11+J12+J13 -> 6.3513373e+08 | K14: =K11+K12+K13 -> 7.9316836e+08 | ... N14: =N11+N12+N13 -> 1253878780
B15: Balance Check (=0) | D15: =D8-D14 -> 0 | E15: =E8-E14 -> 0 | F15: =F8-F14 -> 0 | G15: =G8-G14 -> 0 | H15: =H8-H14 -> 0 | I15: =I8-I14 -> 0 | J15: =J8-J14 -> 0 | K15: =K8-K14 -> -1.1920929e-07 | ... N15: =N8-N14 -> 0
B16: memo: Net Working Capital | D16: =D6-D11 -> -946494.87 | E16: =E6-E11 -> -1869377.6 | F16: =F6-F11 -> -2794838.5 | G16: =G6-G11 -> -4243216.1 | H16: =H6-H11 -> -6165620.7 | I16: =I6-I11 -> -8519325.8 | J16: =J6-J11 -> -11397341 | K16: =K6-K11 -> -14946320 | ... N16: =N6-N11 -> -29208570

Sheet NRD MC Cash Flow
B2: NRD MOTORCYCLE - CASH FLOW
B3: All figures in PHP Millions (unless noted)
D4: 2026 | E4: 2027 | F4: 2028 | G4: 2029 | H4: 2030 | I4: 2031 | J4: 2032 | K4: 2033 | L4: 2034 | M4: 2035 | N4: 2036
B5: OPERATING
B6: EBITDA | D6: ='NRD MC P&L'!D40 -> 78184431 | E6: ='NRD MC P&L'!E40 -> 2.2954582e+08 | F6: ='NRD MC P&L'!F40 -> 4.4840929e+08 | G6: ='NRD MC P&L'!G40 -> 7.0502953e+08 | H6: ='NRD MC P&L'!H40 -> 9.7965015e+08 | I6: ='NRD MC P&L'!I40 -> 1300794703 | J6: ='NRD MC P&L'!J40 -> 1713648474 | K6: ='NRD MC P&L'!K40 -> 2189457583 | ... N6: ='NRD MC P&L'!N40 -> 3795036819
B7: Income Tax | D7: ='NRD MC P&L'!D44 -> -19546108 | E7: ='NRD MC P&L'!E44 -> -57386455 | F7: ='NRD MC P&L'!F44 -> -1.1210232e+08 | G7: ='NRD MC P&L'!G44 -> -1.7625738e+08 | H7: ='NRD MC P&L'!H44 -> -2.4491254e+08 | I7: ='NRD MC P&L'!I44 -> -3.2519868e+08 | J7: ='NRD MC P&L'!J44 -> -4.2841212e+08 | K7: ='NRD MC P&L'!K44 -> -5.473644e+08 | ... N7: ='NRD MC P&L'!N44 -> -9.487592e+08
B8: (Increase)/Decrease in NWC | D8: =-'NRD MC Balance Sheet'!D17 -> -11210983 | E8: =-('NRD MC Balance Sheet'!E17-'NRD MC Balance Sheet'!D17) -> -10808085 | F8: =-('NRD MC Balance Sheet'!F17-'NRD MC Balance Sheet'!E17) -> -16647910 | G8: =-('NRD MC Balance Sheet'!G17-'NRD MC Balance Sheet'!F17) -> -18971730 | H8: =-('NRD MC Balance Sheet'!H17-'NRD MC Balance Sheet'!G17) -> -18632048 | I8: =-('NRD MC Balance Sheet'!I17-'NRD MC Balance Sheet'!H17) -> -20325664 | J8: =-('NRD MC Balance Sheet'!J17-'NRD MC Balance Sheet'!I17) -> -27858142 | K8: =-('NRD MC Balance Sheet'!K17-'NRD MC Balance Sheet'!J17) -> -30400576 | L8: =-('NRD MC Balance Sheet'!L17-'NRD MC Balance Sheet'!K17) -> -26888102 | ... N8: =-('NRD MC Balance Sheet'!N17-'NRD MC Balance Sheet'!M17) -> -29717850
B9: Operating Cash Flow | D9: =D6+D7+D8 -> 47427341 | E9: =E6+E7+E8 -> 161351279 | F9: =F6+F7+F8 -> 3.1965906e+08 | G9: =G6+G7+G8 -> 5.0980042e+08 | H9: =H6+H7+H8 -> 7.1610557e+08 | I9: =I6+I7+I8 -> 9.5527036e+08 | J9: =J6+J7+J8 -> 1257378213 | K9: =K6+K7+K8 -> 1611692612 | ... N9: =N6+N7+N8 -> 2816559764
B11: INVESTING
B12: Capital Expenditure (incl. L2O) | D12: =-('MC Drivers (NRD)'!D186+'MC Drivers (NRD)'!D206+'MC Drivers (NRD)'!D225+'MC Drivers (NRD)'!D305) -> -3.0679843e+08 | E12: =-('MC Drivers (NRD)'!E186+'MC Drivers (NRD)'!E206+'MC Drivers (NRD)'!E225+'MC Drivers (NRD)'!E305) -> -4.4381304e+08 | F12: =-('MC Drivers (NRD)'!F186+'MC Drivers (NRD)'!F206+'MC Drivers (NRD)'!F225+'MC Drivers (NRD)'!F305) -> -6.3337969e+08 | G12: =-('MC Drivers (NRD)'!G186+'MC Drivers (NRD)'!G206+'MC Drivers (NRD)'!G225+'MC Drivers (NRD)'!G305) -> -8.2256313e+08 | H12: =-('MC Drivers (NRD)'!H186+'MC Drivers (NRD)'!H206+'MC Drivers (NRD)'!H225+'MC Drivers (NRD)'!H305) -> -9.6354272e+08 | I12: =-('MC Drivers (NRD)'!I186+'MC Drivers (NRD)'!I206+'MC Drivers (NRD)'!I225+'MC Drivers (NRD)'!I305) -> -1140025757 | J12: =-('MC Drivers (NRD)'!J186+'MC Drivers (NRD)'!J206+'MC Drivers (NRD)'!J225+'MC Drivers (NRD)'!J305) -> -1426153797 | K12: =-('MC Drivers (NRD)'!K186+'MC Drivers (NRD)'!K206+'MC Drivers (NRD)'!K225+'MC Drivers (NRD)'!K305) -> -1694432915 | ... N12: =-('MC Drivers (NRD)'!N186+'MC Drivers (NRD)'!N206+'MC Drivers (NRD)'!N225+'MC Drivers (NRD)'!N305) -> -2288532071
B13: Free Cash Flow (pre-financing) | D13: =D9+D12 -> -2.5937109e+08 | E13: =E9+E12 -> -2.8246176e+08 | F13: =F9+F12 -> -3.1372063e+08 | G13: =G9+G12 -> -3.1276271e+08 | H13: =H9+H12 -> -2.4743716e+08 | I13: =I9+I12 -> -184755394 | J13: =J9+J12 -> -1.6877558e+08 | K13: =K9+K12 -> -82740304 | ... N13: =N9+N12 -> 5.2802769e+08
B14: Cumulative FCF | D14: =D13 -> -2.5937109e+08 | E14: =D14+E13 -> -5.4183285e+08 | F14: =E14+F13 -> -8.5555348e+08 | G14: =F14+G13 -> -1168316190 | H14: =G14+H13 -> -1415753345 | I14: =H14+I13 -> -1600508739 | J14: =I14+J13 -> -1769284323 | K14: =J14+K13 -> -1852024627 | L14: =K14+L13 -> -1747806531 | ... N14: =M14+N13 -> -9.1640346e+08

Sheet RideBox Energy Cash Flow
B2: RIDEBOX ENERGY - CASH FLOW
B3: All figures in PHP Millions (unless noted)
D4: 2026 | E4: 2027 | F4: 2028 | G4: 2029 | H4: 2030 | I4: 2031 | J4: 2032 | K4: 2033 | L4: 2034 | M4: 2035 | N4: 2036
B5: OPERATING
B6: EBITDA | D6: ='RideBox Energy P&L'!D29 -> 13714511 | E6: ='RideBox Energy P&L'!E29 -> 34322110 | F6: ='RideBox Energy P&L'!F29 -> 73455151 | G6: ='RideBox Energy P&L'!G29 -> 1.1521851e+08 | H6: ='RideBox Energy P&L'!H29 -> 1.5323008e+08 | I6: ='RideBox Energy P&L'!I29 -> 1.9302781e+08 | J6: ='RideBox Energy P&L'!J29 -> 2.4567171e+08 | K6: ='RideBox Energy P&L'!K29 -> 2.996813e+08 | ... N6: ='RideBox Energy P&L'!N29 -> 4.1337103e+08
B7: Income Tax | D7: ='RideBox Energy P&L'!D33 -> -3428627.6 | E7: ='RideBox Energy P&L'!E33 -> -8580527.6 | F7: ='RideBox Energy P&L'!F33 -> -18363788 | G7: ='RideBox Energy P&L'!G33 -> -28804627 | H7: ='RideBox Energy P&L'!H33 -> -38307520 | I7: ='RideBox Energy P&L'!I33 -> -48256953 | J7: ='RideBox Energy P&L'!J33 -> -61417927 | K7: ='RideBox Energy P&L'!K33 -> -74920325 | ... N7: ='RideBox Energy P&L'!N33 -> -103342758
B8: (Increase)/Decrease in NWC | D8: =-'RideBox Energy Balance Sheet'!D16 -> 946494.87 | E8: =-('RideBox Energy Balance Sheet'!E16-'RideBox Energy Balance Sheet'!D16) -> 922882.7 | F8: =-('RideBox Energy Balance Sheet'!F16-'RideBox Energy Balance Sheet'!E16) -> 925460.96 | G8: =-('RideBox Energy Balance Sheet'!G16-'RideBox Energy Balance Sheet'!F16) -> 1448377.6 | H8: =-('RideBox Energy Balance Sheet'!H16-'RideBox Energy Balance Sheet'!G16) -> 1922404.6 | I8: =-('RideBox Energy Balance Sheet'!I16-'RideBox Energy Balance Sheet'!H16) -> 2353705.1 | J8: =-('RideBox Energy Balance Sheet'!J16-'RideBox Energy Balance Sheet'!I16) -> 2878015.7 | K8: =-('RideBox Energy Balance Sheet'!K16-'RideBox Energy Balance Sheet'!J16) -> 3548979 | L8: =-('RideBox Energy Balance Sheet'!L16-'RideBox Energy Balance Sheet'!K16) -> 4159945.5 | ... N8: =-('RideBox Energy Balance Sheet'!N16-'RideBox Energy Balance Sheet'!M16) -> 5389488.5
B9: Operating Cash Flow | D9: =D6+D7+D8 -> 11232378 | E9: =E6+E7+E8 -> 26664465 | F9: =F6+F7+F8 -> 56016824 | G9: =G6+G7+G8 -> 87862258 | H9: =H6+H7+H8 -> 1.1684497e+08 | I9: =I6+I7+I8 -> 1.4712457e+08 | J9: =J6+J7+J8 -> 1.871318e+08 | K9: =K6+K7+K8 -> 2.2830995e+08 | ... N9: =N6+N7+N8 -> 3.1541776e+08
B11: INVESTING
B12: Capital Expenditure | D12: =-'Energy Drivers (RideBox)'!D106 -> -41112571 | E12: =-'Energy Drivers (RideBox)'!E106 -> -60706165 | F12: =-'Energy Drivers (RideBox)'!F106 -> -90039928 | G12: =-'Energy Drivers (RideBox)'!G106 -> -1.1767482e+08 | H12: =-'Energy Drivers (RideBox)'!H106 -> -1.4055289e+08 | I12: =-'Energy Drivers (RideBox)'!I106 -> -1.6614915e+08 | J12: =-'Energy Drivers (RideBox)'!J106 -> -2.0714846e+08 | K12: =-'Energy Drivers (RideBox)'!K106 -> -2.4599588e+08 | ... N12: =-'Energy Drivers (RideBox)'!N106 -> -3.199532e+08
B13: Free Cash Flow (pre-financing) | D13: =D9+D12 -> -29880193 | E13: =E9+E12 -> -34041700 | F13: =F9+F12 -> -34023104 | G13: =G9+G12 -> -29812566 | H13: =H9+H12 -> -23707929 | I13: =I9+I12 -> -19024585 | J13: =J9+J12 -> -20016666 | K13: =K9+K12 -> -17685925 | ... N13: =N9+N12 -> -4535442
B14: Cumulative FCF | D14: =D13 -> -29880193 | E14: =D14+E13 -> -63921893 | F14: =E14+F13 -> -97944998 | G14: =F14+G13 -> -1.2775756e+08 | H14: =G14+H13 -> -1.5146549e+08 | I14: =H14+I13 -> -1.7049008e+08 | J14: =I14+J13 -> -1.9050674e+08 | K14: =J14+K13 -> -2.0819267e+08 | L14: =K14+L13 -> -2.1681552e+08 | ... N14: =M14+N13 -> -2.2582884e+08

Sheet Conso P&L
B2: CONSOLIDATED - PROFIT & LOSS
B3: All figures in PHP Millions (unless noted)
D4: 2026 | E4: 2027 | F4: 2028 | G4: 2029 | H4: 2030 | I4: 2031 | J4: 2032 | K4: 2033 | L4: 2034 | M4: 2035 | N4: 2036
B5: REVENUE
B6: NRD / Motorcycle Revenue | D6: ='NRD MC P&L'!D10 -> 3.4886273e+08 | E6: ='NRD MC P&L'!E10 -> 6.740321e+08 | F6: ='NRD MC P&L'!F10 -> 1156807424 | G6: ='NRD MC P&L'!G10 -> 1717476965 | H6: ='NRD MC P&L'!H10 -> 2305082921 | I6: ='NRD MC P&L'!I10 -> 2962174234 | J6: ='NRD MC P&L'!J10 -> 3828506346 | K6: ='NRD MC P&L'!K10 -> 4800832529 | ... N6: ='NRD MC P&L'!N10 -> 7856805006
B7: RideBox / Energy Revenue | D7: ='RideBox Energy P&L'!D8 -> 76607143 | E7: ='RideBox Energy P&L'!E8 -> 1.7644393e+08 | F7: ='RideBox Energy P&L'!F8 -> 3.2030743e+08 | G7: ='RideBox Energy P&L'!G8 -> 5.0364246e+08 | H7: ='RideBox Energy P&L'!H8 -> 7.1104157e+08 | I7: ='RideBox Energy P&L'!I8 -> 950556750 | J7: ='RideBox Energy P&L'!J8 -> 1250566821 | K7: ='RideBox Energy P&L'!K8 -> 1598721536 | ... N7: ='RideBox Energy P&L'!N8 -> 2772775500
B8: Total Revenue | D8: =D6+D7 -> 4.2546988e+08 | E8: =E6+E7 -> 850476033 | F8: =F6+F7 -> 1477114853 | G8: =G6+G7 -> 2221119429 | H8: =H6+H7 -> 3016124492 | I8: =I6+I7 -> 3912730984 | J8: =J6+J7 -> 5079073167 | K8: =K6+K7 -> 6399554064 | ... N8: =N6+N7 -> 10629580506
B10: MC Insurance | D10: ='NRD MC P&L'!D13 -> -9299285.7 | E10: ='NRD MC P&L'!E13 -> -22551607 | F10: ='NRD MC P&L'!F13 -> -41494286 | G10: ='NRD MC P&L'!G13 -> -65955268 | H10: ='NRD MC P&L'!H13 -> -94050357 | I10: ='NRD MC P&L'!I13 -> -1.2671955e+08 | J10: ='NRD MC P&L'!J13 -> -1.6728223e+08 | K10: ='NRD MC P&L'!K13 -> -214701875 | ... N10: ='NRD MC P&L'!N13 -> -377586250
B11: Battery Insurance | D11: ='NRD MC P&L'!D14 -> -2189018.9 | E11: ='NRD MC P&L'!E14 -> -5308568.3 | F11: ='NRD MC P&L'!F14 -> -9767607.7 | G11: ='NRD MC P&L'!G14 -> -15525636 | H11: ='NRD MC P&L'!H14 -> -22139120 | I11: ='NRD MC P&L'!I14 -> -29829333 | J11: ='NRD MC P&L'!J14 -> -39377644 | K11: ='NRD MC P&L'!K14 -> -50540060 | ... N11: ='NRD MC P&L'!N14 -> -88882464
B12: Locker Insurance | D12: ='RideBox Energy P&L'!D11 -> -822251.42 | E12: ='RideBox Energy P&L'!E11 -> -2036374.7 | F12: ='RideBox Energy P&L'!F11 -> -3837173.3 | G12: ='RideBox Energy P&L'!G11 -> -6190669.8 | H12: ='RideBox Energy P&L'!H11 -> -9001727.7 | I12: ='RideBox Energy P&L'!I11 -> -12324711 | J12: ='RideBox Energy P&L'!J11 -> -16467680 | K12: ='RideBox Energy P&L'!K11 -> -21387598 | ... N12: ='RideBox Energy P&L'!N11 -> -39080727
B13: MC Registration | D13: ='NRD MC P&L'!D15 -> -1054666.7 | E13: ='NRD MC P&L'!E15 -> -1611458.3 | F13: ='NRD MC P&L'!F15 -> -2408291.7 | G13: ='NRD MC P&L'!G15 -> -3234583.3 | H13: ='NRD MC P&L'!H15 -> -3902791.7 | I13: ='NRD MC P&L'!I15 -> -4657916.7 | J13: ='NRD MC P&L'!J15 -> -5833916.7 | K13: ='NRD MC P&L'!K15 -> -6973750 | ... N13: ='NRD MC P&L'!N15 -> -9444750
B14: Cost of Motorcycle Sales | D14: ='NRD MC P&L'!D16 -> -1.4999847e+08 | E14: ='NRD MC P&L'!E16 -> -2.3999755e+08 | F14: ='NRD MC P&L'!F16 -> -3.8399608e+08 | G14: ='NRD MC P&L'!G16 -> -5.3761951e+08 | H14: ='NRD MC P&L'!H16 -> -6.7199314e+08 | I14: ='NRD MC P&L'!I16 -> -8.0636677e+08 | J14: ='NRD MC P&L'!J16 -> -1007989710 | K14: ='NRD MC P&L'!K16 -> -1209612652 | ... N14: ='NRD MC P&L'!N16 -> -1612608538
B15: Aftersales COGS | D15: ='NRD MC P&L'!D17 -> -7559922.8 | E15: ='NRD MC P&L'!E17 -> -12095877 | F15: ='NRD MC P&L'!F17 -> -19353402 | G15: ='NRD MC P&L'!G17 -> -27096023 | H15: ='NRD MC P&L'!H17 -> -33868454 | I15: ='NRD MC P&L'!I17 -> -40640885 | J15: ='NRD MC P&L'!J17 -> -50802681 | K15: ='NRD MC P&L'!K17 -> -60964478 | ... N15: ='NRD MC P&L'!N17 -> -81275470
B16: Lease Payment Gateway | D16: ='NRD MC P&L'!D18 -> -4228945.7 | E16: ='NRD MC P&L'!E18 -> -10241865 | F16: ='NRD MC P&L'!F18 -> -18737666 | G16: ='NRD MC P&L'!G18 -> -29170090 | H16: ='NRD MC P&L'!H18 -> -41211013 | I16: ='NRD MC P&L'!I18 -> -55336497 | J16: ='NRD MC P&L'!J18 -> -72942978 | K16: ='NRD MC P&L'!K18 -> -93729282 | ... N16: ='NRD MC P&L'!N18 -> -1.6865189e+08
B17: Locker Connectivity | D17: ='RideBox Energy P&L'!D12 -> -388928.57 | E17: ='RideBox Energy P&L'!E12 -> -963214.29 | F17: ='RideBox Energy P&L'!F12 -> -1815000 | G17: ='RideBox Energy P&L'!G12 -> -2928214.3 | H17: ='RideBox Energy P&L'!H12 -> -4257857.1 | I17: ='RideBox Energy P&L'!I12 -> -5829642.9 | J17: ='RideBox Energy P&L'!J12 -> -7789285.7 | K17: ='RideBox Energy P&L'!K12 -> -10116429 | ... N17: ='RideBox Energy P&L'!N12 -> -18485357
B18: Locker Maintenance | D18: ='RideBox Energy P&L'!D13 -> -777857.14 | E18: ='RideBox Energy P&L'!E13 -> -1926428.6 | F18: ='RideBox Energy P&L'!F13 -> -3630000 | G18: ='RideBox Energy P&L'!G13 -> -5856428.6 | H18: ='RideBox Energy P&L'!H13 -> -8515714.3 | I18: ='RideBox Energy P&L'!I13 -> -11659286 | J18: ='RideBox Energy P&L'!J13 -> -15578571 | K18: ='RideBox Energy P&L'!K13 -> -20232857 | ... N18: ='RideBox Energy P&L'!N13 -> -36970714
B19: Locker Electricity | D19: ='RideBox Energy P&L'!D14 -> -12975939 | E19: ='RideBox Energy P&L'!E14 -> -42848006 | F19: ='RideBox Energy P&L'!F14 -> -80739179 | G19: ='RideBox Energy P&L'!G14 -> -1.3025984e+08 | H19: ='RideBox Energy P&L'!H14 -> -1.894082e+08 | I19: ='RideBox Energy P&L'!I14 -> -2.5932814e+08 | J19: ='RideBox Energy P&L'!J14 -> -346501671 | K19: ='RideBox Energy P&L'!K14 -> -4.5002322e+08 | ... N19: ='RideBox Energy P&L'!N14 -> -822309949
B20: Battery Connectivity | D20: ='RideBox Energy P&L'!D15 -> -4748571.4 | E20: ='RideBox Energy P&L'!E15 -> -11515714 | F20: ='RideBox Energy P&L'!F15 -> -16352143 | G20: ='RideBox Energy P&L'!G15 -> -27433929 | H20: ='RideBox Energy P&L'!H15 -> -40852500 | I20: ='RideBox Energy P&L'!I15 -> -56366786 | J20: ='RideBox Energy P&L'!J15 -> -75064286 | K20: ='RideBox Energy P&L'!K15 -> -97527857 | ... N20: ='RideBox Energy P&L'!N15 -> -1.7809714e+08
B21: Battery Payment Gateway | D21: ='RideBox Energy P&L'!D16 -> -1958785.7 | E21: ='RideBox Energy P&L'!E16 -> -4750232.1 | F21: ='RideBox Energy P&L'!F16 -> -8740285.7 | G21: ='RideBox Energy P&L'!G16 -> -13892705 | H21: ='RideBox Energy P&L'!H16 -> -19810607 | I21: ='RideBox Energy P&L'!I16 -> -26691991 | J21: ='RideBox Energy P&L'!J16 -> -35236045 | K21: ='RideBox Energy P&L'!K16 -> -45224438 | ... N21: ='RideBox Energy P&L'!N16 -> -79534125
B22: Total Cost of Sales | D22: =SUM(D10:D21) -> -1.9600264e+08 | E22: =SUM(E10:E21) -> -3.558469e+08 | F22: =SUM(F10:F21) -> -5.9087111e+08 | G22: =SUM(G10:G21) -> -8.651629e+08 | H22: =SUM(H10:H21) -> -1139011486 | I22: =SUM(I10:I21) -> -1435751512 | J22: =SUM(J10:J21) -> -1840866701 | K22: =SUM(K10:K21) -> -2281034490 | ... N22: =SUM(N10:N21) -> -3512927375
B23: Gross Profit | D23: =D8+D22 -> 2.2946724e+08 | E23: =E8+E22 -> 4.9462914e+08 | F23: =F8+F22 -> 8.8624374e+08 | G23: =G8+G22 -> 1355956526 | H23: =H8+H22 -> 1877113006 | I23: =I8+I22 -> 2476979472 | J23: =J8+J22 -> 3238206466 | K23: =K8+K22 -> 4118519575 | ... N23: =N8+N22 -> 7116653131
B24: Gross margin | D24: =IFERROR(D23/D8,0) -> 0.53932663 | E24: =IFERROR(E23/E8,0) -> 0.58159092 | F24: =IFERROR(F23/F8,0) -> 0.59998296 | G24: =IFERROR(G23/G8,0) -> 0.61048339 | H24: =IFERROR(H23/H8,0) -> 0.62235926 | I24: =IFERROR(I23/I8,0) -> 0.63305642 | J24: =IFERROR(J23/J8,0) -> 0.63755854 | K24: =IFERROR(K23/K8,0) -> 0.64356353 | ... N24: =IFERROR(N23/N8,0) -> 0.66951402
B25: Salaries | D25: ='NRD MC P&L'!D24+'RideBox Energy P&L'!D22 -> -72610642 | E25: ='NRD MC P&L'!E24+'RideBox Energy P&L'!E22 -> -83865292 | F25: ='NRD MC P&L'!F24+'RideBox Energy P&L'!F22 -> -96864412 | G25: ='NRD MC P&L'!G24+'RideBox Energy P&L'!G22 -> -1.118784e+08 | H25: ='NRD MC P&L'!H24+'RideBox Energy P&L'!H22 -> -1.2921955e+08 | I25: ='NRD MC P&L'!I24+'RideBox Energy P&L'!I22 -> -1.4924858e+08 | J25: ='NRD MC P&L'!J24+'RideBox Energy P&L'!J22 -> -1.7238211e+08 | K25: ='NRD MC P&L'!K24+'RideBox Energy P&L'!K22 -> -1.9910133e+08 | ... N25: ='NRD MC P&L'!N24+'RideBox Energy P&L'!N22 -> -3.0677511e+08
B26: Employee Benefits | D26: ='NRD MC P&L'!D25+'RideBox Energy P&L'!D23 -> -7261064.2 | E26: ='NRD MC P&L'!E25+'RideBox Energy P&L'!E23 -> -8386529.2 | F26: ='NRD MC P&L'!F25+'RideBox Energy P&L'!F23 -> -9686441.2 | G26: ='NRD MC P&L'!G25+'RideBox Energy P&L'!G23 -> -11187840 | H26: ='NRD MC P&L'!H25+'RideBox Energy P&L'!H23 -> -12921955 | I26: ='NRD MC P&L'!I25+'RideBox Energy P&L'!I23 -> -14924858 | J26: ='NRD MC P&L'!J25+'RideBox Energy P&L'!J23 -> -17238211 | K26: ='NRD MC P&L'!K25+'RideBox Energy P&L'!K23 -> -19910133 | ... N26: ='NRD MC P&L'!N25+'RideBox Energy P&L'!N23 -> -30677511
B27: Sales Commission | D27: ='NRD MC P&L'!D26 -> -3779961.4 | E27: ='NRD MC P&L'!E26 -> -6047938.3 | F27: ='NRD MC P&L'!F26 -> -9676701.2 | G27: ='NRD MC P&L'!G26 -> -13548012 | H27: ='NRD MC P&L'!H26 -> -16934227 | I27: ='NRD MC P&L'!I26 -> -20320443 | J27: ='NRD MC P&L'!J26 -> -25401341 | K27: ='NRD MC P&L'!K26 -> -30482239 | ... N27: ='NRD MC P&L'!N26 -> -40637735
B28: Rent - Head Office | D28: ='NRD MC P&L'!D27 -> -1714285.7 | E28: ='NRD MC P&L'!E27 -> -1800000 | F28: ='NRD MC P&L'!F27 -> -1890000 | G28: ='NRD MC P&L'!G27 -> -1984500 | H28: ='NRD MC P&L'!H27 -> -2083725 | I28: ='NRD MC P&L'!I27 -> -2187911.2 | J28: ='NRD MC P&L'!J27 -> -2297306.8 | K28: ='NRD MC P&L'!K27 -> -2412172.2 | ... N28: ='NRD MC P&L'!N27 -> -2792390.8
B29: Rent - Warehouse | D29: ='NRD MC P&L'!D28 -> -2235535.7 | E29: ='NRD MC P&L'!E28 -> -2347312.5 | F29: ='NRD MC P&L'!F28 -> -2464678.1 | G29: ='NRD MC P&L'!G28 -> -2587912 | H29: ='NRD MC P&L'!H28 -> -5434615.3 | I29: ='NRD MC P&L'!I28 -> -5706346 | J29: ='NRD MC P&L'!J28 -> -5991663.3 | K29: ='NRD MC P&L'!K28 -> -6291246.5 | ... N29: ='NRD MC P&L'!N28 -> -7282904.2
B30: Rent - Showroom / Store Room | D30: ='NRD MC P&L'!D29 -> -910714.29 | E30: ='NRD MC P&L'!E29 -> -956250 | F30: ='NRD MC P&L'!F29 -> -2008125 | G30: ='NRD MC P&L'!G29 -> -2108531.2 | H30: ='NRD MC P&L'!H29 -> -3320936.7 | I30: ='NRD MC P&L'!I29 -> -3486983.6 | J30: ='NRD MC P&L'!J29 -> -4881777 | K30: ='NRD MC P&L'!K29 -> -5125865.8 | ... N30: ='NRD MC P&L'!N29 -> -8900745.6
B31: Locker Rent | D31: ='RideBox Energy P&L'!D24 -> -19446429 | E31: ='RideBox Energy P&L'!E24 -> -48160714 | F31: ='RideBox Energy P&L'!F24 -> -90750000 | G31: ='RideBox Energy P&L'!G24 -> -1.4641071e+08 | H31: ='RideBox Energy P&L'!H24 -> -2.1289286e+08 | I31: ='RideBox Energy P&L'!I24 -> -2.9148214e+08 | J31: ='RideBox Energy P&L'!J24 -> -3.8946429e+08 | K31: ='RideBox Energy P&L'!K24 -> -5.0582143e+08 | ... N31: ='RideBox Energy P&L'!N24 -> -9.2426786e+08
B32: Utilities (all locations) | D32: ='NRD MC P&L'!D30 -> -1221428.6 | E32: ='NRD MC P&L'!E30 -> -1282500 | F32: ='NRD MC P&L'!F30 -> -1630125 | G32: ='NRD MC P&L'!G30 -> -1711631.2 | H32: ='NRD MC P&L'!H30 -> -2630702.8 | I32: ='NRD MC P&L'!I30 -> -2762238 | J32: ='NRD MC P&L'!J30 -> -3244945.9 | K32: ='NRD MC P&L'!K30 -> -3407193.2 | ... N32: ='NRD MC P&L'!N30 -> -4781969.2
B33: Marketing | D33: ='NRD MC P&L'!D31 -> -6977254.7 | E33: ='NRD MC P&L'!E31 -> -13480642 | F33: ='NRD MC P&L'!F31 -> -23136148 | G33: ='NRD MC P&L'!G31 -> -34349539 | H33: ='NRD MC P&L'!H31 -> -46101658 | I33: ='NRD MC P&L'!I31 -> -59243485 | J33: ='NRD MC P&L'!J31 -> -76570127 | K33: ='NRD MC P&L'!K31 -> -96016651 | ... N33: ='NRD MC P&L'!N31 -> -1.571361e+08
B34: Legal & Permits | D34: ='NRD MC P&L'!D32 -> -1987142.9 | E34: ='NRD MC P&L'!E32 -> -2185857.1 | F34: ='NRD MC P&L'!F32 -> -2404442.9 | G34: ='NRD MC P&L'!G32 -> -2644887.1 | H34: ='NRD MC P&L'!H32 -> -2909375.9 | I34: ='NRD MC P&L'!I32 -> -3200313.4 | J34: ='NRD MC P&L'!J32 -> -3520344.8 | K34: ='NRD MC P&L'!K32 -> -3872379.3 | ... N34: ='NRD MC P&L'!N32 -> -5154136.8
B35: Dues & Subscriptions | D35: ='NRD MC P&L'!D33 -> -1339285.7 | E35: ='NRD MC P&L'!E33 -> -1473214.3 | F35: ='NRD MC P&L'!F33 -> -1620535.7 | G35: ='NRD MC P&L'!G33 -> -1782589.3 | H35: ='NRD MC P&L'!H33 -> -1960848.2 | I35: ='NRD MC P&L'!I33 -> -2156933 | J35: ='NRD MC P&L'!J33 -> -2372626.3 | K35: ='NRD MC P&L'!K33 -> -2609889 | ... N35: ='NRD MC P&L'!N33 -> -3473762.2
B36: Repairs & Maintenance | D36: ='NRD MC P&L'!D34 -> -189000 | E36: ='NRD MC P&L'!E34 -> -207900 | F36: ='NRD MC P&L'!F34 -> -228690 | G36: ='NRD MC P&L'!G34 -> -251559 | H36: ='NRD MC P&L'!H34 -> -276714.9 | I36: ='NRD MC P&L'!I34 -> -304386.39 | J36: ='NRD MC P&L'!J34 -> -334825.03 | K36: ='NRD MC P&L'!K34 -> -368307.53 | ... N36: ='NRD MC P&L'!N34 -> -490217.33
B37: Office Expenses | D37: ='NRD MC P&L'!D35 -> -500000 | E37: ='NRD MC P&L'!E35 -> -550000 | F37: ='NRD MC P&L'!F35 -> -605000 | G37: ='NRD MC P&L'!G35 -> -665500 | H37: ='NRD MC P&L'!H35 -> -732050 | I37: ='NRD MC P&L'!I35 -> -805255 | J37: ='NRD MC P&L'!J35 -> -885780.5 | K37: ='NRD MC P&L'!K35 -> -974358.55 | ... N37: ='NRD MC P&L'!N35 -> -1296871.2
B38: Operating Expenses | D38: =SUM(D25:D37) -> -1.2017274e+08 | E38: =SUM(E25:E37) -> -1.7074415e+08 | F38: =SUM(F25:F37) -> -2.429653e+08 | G38: =SUM(G25:G37) -> -3.3111161e+08 | H38: =SUM(H25:H37) -> -437419213 | I38: =SUM(I25:I37) -> -555829871 | J38: =SUM(J25:J37) -> -7.0458534e+08 | K38: =SUM(K25:K37) -> -8.763932e+08 | ... N38: =SUM(N25:N37) -> -1493667310
B39: EBITDA | C39: =-650*1000000 -> -650000000 | D39: ='NRD MC P&L'!D38+'RideBox Energy P&L'!D27 -> 1.0929449e+08 | E39: ='NRD MC P&L'!E38+'RideBox Energy P&L'!E27 -> 3.2388499e+08 | F39: ='NRD MC P&L'!F38+'RideBox Energy P&L'!F27 -> 6.4327844e+08 | G39: ='NRD MC P&L'!G38+'RideBox Energy P&L'!G27 -> 1024844916 | H39: ='NRD MC P&L'!H38+'RideBox Energy P&L'!H27 -> 1439693793 | I39: ='NRD MC P&L'!I38+'RideBox Energy P&L'!I27 -> 1921149601 | J39: ='NRD MC P&L'!J38+'RideBox Energy P&L'!J27 -> 2533621126 | K39: ='NRD MC P&L'!K38+'RideBox Energy P&L'!K27 -> 3242126379 | ... N39: ='NRD MC P&L'!N38+'RideBox Energy P&L'!N27 -> 5622985821
B40: EBITDA margin | C40: =IRR(C39:F39) -> 0.22891506 | D40: =IFERROR(D39/D8,0) -> 0.25687951 | E40: =IFERROR(E39/E8,0) -> 0.38082788 | F40: =IFERROR(F39/F8,0) -> 0.43549656 | G40: =IFERROR(G39/G8,0) -> 0.46140919 | H40: =IFERROR(H39/H8,0) -> 0.47733235 | I40: =IFERROR(I39/I8,0) -> 0.49099966 | J40: =IFERROR(J39/J8,0) -> 0.49883533 | K40: =IFERROR(K39/K8,0) -> 0.50661755 | ... N40: =IFERROR(N39/N8,0) -> 0.52899414
B41: Depreciation & Amortization
B42: Depreciation - Motorcycles | D42: =-'MC Drivers (NRD)'!D200 -> -8302387 | E42: =-'MC Drivers (NRD)'!E200 -> -29061570 | F42: =-'MC Drivers (NRD)'!F200 -> -59580152 | G42: =-'MC Drivers (NRD)'!G200 -> -1.0130456e+08 | H42: =-'MC Drivers (NRD)'!H200 -> -1.5265377e+08 | I42: =-'MC Drivers (NRD)'!I200 -> -2.1300968e+08 | J42: =-'MC Drivers (NRD)'!J200 -> -2.8651611e+08 | K42: =-'MC Drivers (NRD)'!K200 -> -3.7562019e+08 | ... N42: =-'MC Drivers (NRD)'!N200 -> -6.9776082e+08
B43: Depreciation - Batteries (2 per user) | D43: =-'MC Drivers (NRD)'!D220 -> -5472547.2 | E43: =-'MC Drivers (NRD)'!E220 -> -18743968 | F43: =-'MC Drivers (NRD)'!F220 -> -37690440 | G43: =-'MC Drivers (NRD)'!G220 -> -63233109 | H43: =-'MC Drivers (NRD)'!H220 -> -94161891 | I43: =-'MC Drivers (NRD)'!I220 -> -1.2992113e+08 | J43: =-'MC Drivers (NRD)'!J220 -> -1.7301744e+08 | K43: =-'MC Drivers (NRD)'!K220 -> -2.2479426e+08 | ... N43: =-'MC Drivers (NRD)'!N220 -> -4.0502776e+08
B44: Depreciation - Lease-to-Own Units | D44: =-'MC Drivers (NRD)'!D239 -> -1249987.2 | E44: =-'MC Drivers (NRD)'!E239 -> -4249956.6 | F44: =-'MC Drivers (NRD)'!F239 -> -8274539 | G44: =-'MC Drivers (NRD)'!G239 -> -13504606 | H44: =-'MC Drivers (NRD)'!H239 -> -20301901 | I44: =-'MC Drivers (NRD)'!I239 -> -29135169 | J44: =-'MC Drivers (NRD)'!J239 -> -40611408 | K44: =-'MC Drivers (NRD)'!K239 -> -55529855 | ... N44: =-'MC Drivers (NRD)'!N239 -> -1.3165905e+08
B45: Depreciation - Lockers | D45: =-'Energy Drivers (RideBox)'!D120 -> -2055628.6 | E45: =-'Energy Drivers (RideBox)'!E120 -> -7146565.4 | F45: =-'Energy Drivers (RideBox)'!F120 -> -14683870 | G45: =-'Energy Drivers (RideBox)'!G120 -> -25069608 | H45: =-'Energy Drivers (RideBox)'!H120 -> -37980994 | I45: =-'Energy Drivers (RideBox)'!I120 -> -53316096 | J45: =-'Energy Drivers (RideBox)'!J120 -> -71980977 | K45: =-'Energy Drivers (RideBox)'!K120 -> -94638194 | ... N45: =-'Energy Drivers (RideBox)'!N120 -> -1.7735034e+08
B46: Depreciation - Office & Other Assets | D46: =-'MC Drivers (NRD)'!D304 -> -315000 | E46: =-'MC Drivers (NRD)'!E304 -> -815000 | F46: =-'MC Drivers (NRD)'!F304 -> -1185000 | G46: =-'MC Drivers (NRD)'!G304 -> -1485000 | H46: =-'MC Drivers (NRD)'!H304 -> -1715000 | I46: =-'MC Drivers (NRD)'!I304 -> -1945000 | J46: =-'MC Drivers (NRD)'!J304 -> -2175000 | K46: =-'MC Drivers (NRD)'!K304 -> -2405000 | ... N46: =-'MC Drivers (NRD)'!N304 -> -2780000
B47: Total Depreciation & Amortization | D47: =SUM(D42:D46) -> -17395550 | E47: =SUM(E42:E46) -> -60017060 | F47: =SUM(F42:F46) -> -121414001 | G47: =SUM(G42:G46) -> -2.0459688e+08 | H47: =SUM(H42:H46) -> -306813558 | I47: =SUM(I42:I46) -> -4.2732708e+08 | J47: =SUM(J42:J46) -> -5.7430094e+08 | K47: =SUM(K42:K46) -> -7.529875e+08 | ... N47: =SUM(N42:N46) -> -1414577970
B48: EBIT | D48: =D39+D47 -> 91898942 | E48: =E39+E47 -> 2.6386793e+08 | F48: =F39+F47 -> 5.2186444e+08 | G48: =G39+G47 -> 8.2024804e+08 | H48: =H39+H47 -> 1132880235 | I48: =I39+I47 -> 1493822517 | J48: =J39+J47 -> 1959320184 | K48: =K39+K47 -> 2489138884 | ... N48: =N39+N47 -> 4208407851
B49: Interest Expense | D49: ='NRD MC P&L'!D42+'RideBox Energy P&L'!D31 -> 0 | E49: ='NRD MC P&L'!E42+'RideBox Energy P&L'!E31 -> 0 | F49: ='NRD MC P&L'!F42+'RideBox Energy P&L'!F31 -> 0 | G49: ='NRD MC P&L'!G42+'RideBox Energy P&L'!G31 -> 0 | H49: ='NRD MC P&L'!H42+'RideBox Energy P&L'!H31 -> 0 | I49: ='NRD MC P&L'!I42+'RideBox Energy P&L'!I31 -> 0 | J49: ='NRD MC P&L'!J42+'RideBox Energy P&L'!J31 -> 0 | K49: ='NRD MC P&L'!K42+'RideBox Energy P&L'!K31 -> 0 | ... N49: ='NRD MC P&L'!N42+'RideBox Energy P&L'!N31 -> 0
B50: EBT (Pre-tax Income) | D50: =D48+D49 -> 91898942 | E50: =E48+E49 -> 2.6386793e+08 | F50: =F48+F49 -> 5.2186444e+08 | G50: =G48+G49 -> 8.2024804e+08 | H50: =H48+H49 -> 1132880235 | I50: =I48+I49 -> 1493822517 | J50: =J48+J49 -> 1959320184 | K50: =K48+K49 -> 2489138884 | ... N50: =N48+N49 -> 4208407851
B51: Income Tax | D51: ='NRD MC P&L'!D44+'RideBox Energy P&L'!D33 -> -22974735 | E51: ='NRD MC P&L'!E44+'RideBox Energy P&L'!E33 -> -65966982 | F51: ='NRD MC P&L'!F44+'RideBox Energy P&L'!F33 -> -1.3046611e+08 | G51: ='NRD MC P&L'!G44+'RideBox Energy P&L'!G33 -> -2.0506201e+08 | H51: ='NRD MC P&L'!H44+'RideBox Energy P&L'!H33 -> -2.8322006e+08 | I51: ='NRD MC P&L'!I44+'RideBox Energy P&L'!I33 -> -3.7345563e+08 | J51: ='NRD MC P&L'!J44+'RideBox Energy P&L'!J33 -> -4.8983005e+08 | K51: ='NRD MC P&L'!K44+'RideBox Energy P&L'!K33 -> -6.2228472e+08 | ... N51: ='NRD MC P&L'!N44+'RideBox Energy P&L'!N33 -> -1052101963
B52: NET INCOME (NIAT) | D52: =D50+D51 -> 68924206 | E52: =E50+E51 -> 1.9790095e+08 | F52: =F50+F51 -> 3.9139833e+08 | G52: =G50+G51 -> 6.1518603e+08 | H52: =H50+H51 -> 8.4966018e+08 | I52: =I50+I51 -> 1120366888 | J52: =J50+J51 -> 1469490138 | K52: =K50+K51 -> 1866854163 | ... N52: =N50+N51 -> 3156305888
B53: Net margin | D53: =IFERROR(D52/D8,0) -> 0.1619955 | E53: =IFERROR(E52/E8,0) -> 0.23269432 | F53: =IFERROR(F52/F8,0) -> 0.26497488 | G53: =IFERROR(G52/G8,0) -> 0.27697116 | H53: =IFERROR(H52/H8,0) -> 0.28170594 | I53: =IFERROR(I52/I8,0) -> 0.28633885 | J53: =IFERROR(J52/J8,0) -> 0.2893225 | K53: =IFERROR(K52/K8,0) -> 0.29171629 | ... N53: =IFERROR(N52/N8,0) -> 0.29693607
B55: SEGMENT EBITDA
B56: NRD / Motorcycle EBITDA | D56: ='NRD MC P&L'!D38 -> 93524353 | E56: ='NRD MC P&L'!E38 -> 2.8241631e+08 | F56: ='NRD MC P&L'!F38 -> 5.5513942e+08 | G56: ='NRD MC P&L'!G38 -> 8.845568e+08 | H56: ='NRD MC P&L'!H38 -> 1248482719 | I56: ='NRD MC P&L'!I38 -> 1674805691 | J56: ='NRD MC P&L'!J38 -> 2215968440 | K56: ='NRD MC P&L'!K38 -> 2847806885 | ... N56: ='NRD MC P&L'!N38 -> 5032264445
B57: RideBox / Energy EBITDA | D57: ='RideBox Energy P&L'!D27 -> 15770139 | E57: ='RideBox Energy P&L'!E27 -> 41468676 | F57: ='RideBox Energy P&L'!F27 -> 88139021 | G57: ='RideBox Energy P&L'!G27 -> 1.4028812e+08 | H57: ='RideBox Energy P&L'!H27 -> 1.9121107e+08 | I57: ='RideBox Energy P&L'!I27 -> 2.4634391e+08 | J57: ='RideBox Energy P&L'!J27 -> 317652686 | K57: ='RideBox Energy P&L'!K27 -> 3.9431949e+08 | ... N57: ='RideBox Energy P&L'!N27 -> 5.9072138e+08

Sheet Conso Cash Flow
B2: CONSOLIDATED - CASH FLOW
B3: All figures in PHP Millions (unless noted)
D4: 2026 | E4: 2027 | F4: 2028 | G4: 2029 | H4: 2030 | I4: 2031 | J4: 2032 | K4: 2033 | L4: 2034 | M4: 2035 | N4: 2036
B5: OPERATING
B6: EBITDA | D6: ='Conso P&L'!D39 -> 1.0929449e+08 | E6: ='Conso P&L'!E39 -> 3.2388499e+08 | F6: ='Conso P&L'!F39 -> 6.4327844e+08 | G6: ='Conso P&L'!G39 -> 1024844916 | H6: ='Conso P&L'!H39 -> 1439693793 | I6: ='Conso P&L'!I39 -> 1921149601 | J6: ='Conso P&L'!J39 -> 2533621126 | K6: ='Conso P&L'!K39 -> 3242126379 | ... N6: ='Conso P&L'!N39 -> 5622985821
B7: Income Tax | D7: ='Conso P&L'!D51 -> -22974735 | E7: ='Conso P&L'!E51 -> -65966982 | F7: ='Conso P&L'!F51 -> -1.3046611e+08 | G7: ='Conso P&L'!G51 -> -2.0506201e+08 | H7: ='Conso P&L'!H51 -> -2.8322006e+08 | I7: ='Conso P&L'!I51 -> -3.7345563e+08 | J7: ='Conso P&L'!J51 -> -4.8983005e+08 | K7: ='Conso P&L'!K51 -> -6.2228472e+08 | ... N7: ='Conso P&L'!N51 -> -1052101963
B8: (Increase)/Decrease in NWC | D8: =-('NRD MC Balance Sheet'!D17+'RideBox Energy Balance Sheet'!D16) -> -10264488 | E8: =-(('NRD MC Balance Sheet'!E17+'RideBox Energy Balance Sheet'!E16)-('NRD MC Balance Sheet'!D17+'RideBox Energy Balance Sheet'!D16)) -> -9885201.9 | F8: =-(('NRD MC Balance Sheet'!F17+'RideBox Energy Balance Sheet'!F16)-('NRD MC Balance Sheet'!E17+'RideBox Energy Balance Sheet'!E16)) -> -15722449 | G8: =-(('NRD MC Balance Sheet'!G17+'RideBox Energy Balance Sheet'!G16)-('NRD MC Balance Sheet'!F17+'RideBox Energy Balance Sheet'!F16)) -> -17523353 | H8: =-(('NRD MC Balance Sheet'!H17+'RideBox Energy Balance Sheet'!H16)-('NRD MC Balance Sheet'!G17+'RideBox Energy Balance Sheet'!G16)) -> -16709643 | I8: =-(('NRD MC Balance Sheet'!I17+'RideBox Energy Balance Sheet'!I16)-('NRD MC Balance Sheet'!H17+'RideBox Energy Balance Sheet'!H16)) -> -17971959 | J8: =-(('NRD MC Balance Sheet'!J17+'RideBox Energy Balance Sheet'!J16)-('NRD MC Balance Sheet'!I17+'RideBox Energy Balance Sheet'!I16)) -> -24980127 | K8: =-(('NRD MC Balance Sheet'!K17+'RideBox Energy Balance Sheet'!K16)-('NRD MC Balance Sheet'!J17+'RideBox Energy Balance Sheet'!J16)) -> -26851597 | L8: =-(('NRD MC Balance Sheet'!L17+'RideBox Energy Balance Sheet'!L16)-('NRD MC Balance Sheet'!K17+'RideBox Energy Balance Sheet'!K16)) -> -22728156 | ... N8: =-(('NRD MC Balance Sheet'!N17+'RideBox Energy Balance Sheet'!N16)-('NRD MC Balance Sheet'!M17+'RideBox Energy Balance Sheet'!M16)) -> -24328362
B9: Cash from Operations | D9: =D6+D7+D8 -> 76055269 | E9: =E6+E7+E8 -> 2.480328e+08 | F9: =F6+F7+F8 -> 4.9708988e+08 | G9: =G6+G7+G8 -> 8.0225955e+08 | H9: =H6+H7+H8 -> 1139764091 | I9: =I6+I7+I8 -> 1529722013 | J9: =J6+J7+J8 -> 2018810954 | K9: =K6+K7+K8 -> 2592990061 | ... N9: =N6+N7+N8 -> 4546555497
B11: INVESTING
B12: Total Capital Expenditure (incl. L2O) | D12: =-('MC Drivers (NRD)'!D186+'MC Drivers (NRD)'!D206+'MC Drivers (NRD)'!D225+'MC Drivers (NRD)'!D305+'Energy Drivers (RideBox)'!D106) -> -3.47911e+08 | E12: =-('MC Drivers (NRD)'!E186+'MC Drivers (NRD)'!E206+'MC Drivers (NRD)'!E225+'MC Drivers (NRD)'!E305+'Energy Drivers (RideBox)'!E106) -> -504519203 | F12: =-('MC Drivers (NRD)'!F186+'MC Drivers (NRD)'!F206+'MC Drivers (NRD)'!F225+'MC Drivers (NRD)'!F305+'Energy Drivers (RideBox)'!F106) -> -7.2341962e+08 | G12: =-('MC Drivers (NRD)'!G186+'MC Drivers (NRD)'!G206+'MC Drivers (NRD)'!G225+'MC Drivers (NRD)'!G305+'Energy Drivers (RideBox)'!G106) -> -9.4023795e+08 | H12: =-('MC Drivers (NRD)'!H186+'MC Drivers (NRD)'!H206+'MC Drivers (NRD)'!H225+'MC Drivers (NRD)'!H305+'Energy Drivers (RideBox)'!H106) -> -1104095618 | I12: =-('MC Drivers (NRD)'!I186+'MC Drivers (NRD)'!I206+'MC Drivers (NRD)'!I225+'MC Drivers (NRD)'!I305+'Energy Drivers (RideBox)'!I106) -> -1306174908 | J12: =-('MC Drivers (NRD)'!J186+'MC Drivers (NRD)'!J206+'MC Drivers (NRD)'!J225+'MC Drivers (NRD)'!J305+'Energy Drivers (RideBox)'!J106) -> -1633302261 | K12: =-('MC Drivers (NRD)'!K186+'MC Drivers (NRD)'!K206+'MC Drivers (NRD)'!K225+'MC Drivers (NRD)'!K305+'Energy Drivers (RideBox)'!K106) -> -1940428795 | ... N12: =-('MC Drivers (NRD)'!N186+'MC Drivers (NRD)'!N206+'MC Drivers (NRD)'!N225+'MC Drivers (NRD)'!N305+'Energy Drivers (RideBox)'!N106) -> -2608485275
B13: Cash from Investing | D13: =D12 -> -3.47911e+08 | E13: =E12 -> -504519203 | F13: =F12 -> -7.2341962e+08 | G13: =G12 -> -9.4023795e+08 | H13: =H12 -> -1104095618 | I13: =I12 -> -1306174908 | J13: =J12 -> -1633302261 | K13: =K12 -> -1940428795 | ... N13: =N12 -> -2608485275
B15: FINANCING
B16: Equity Injection | D16: ='MC Drivers (NRD)'!D317 -> 650000000 | E16: ='MC Drivers (NRD)'!E317 -> 0 | F16: ='MC Drivers (NRD)'!F317 -> 350000000 | G16: ='MC Drivers (NRD)'!G317 | H16: ='MC Drivers (NRD)'!H317 -> 0 | I16: ='MC Drivers (NRD)'!I317 -> 0 | J16: ='MC Drivers (NRD)'!J317 -> 0 | K16: ='MC Drivers (NRD)'!K317 -> 0 | ... N16: ='MC Drivers (NRD)'!N317 -> 0
B17: Debt Drawdown | D17: ='MC Drivers (NRD)'!D318 -> 0 | E17: ='MC Drivers (NRD)'!E318 -> 0 | F17: ='MC Drivers (NRD)'!F318 -> 0 | G17: ='MC Drivers (NRD)'!G318 -> 0 | H17: ='MC Drivers (NRD)'!H318 -> 0 | I17: ='MC Drivers (NRD)'!I318 -> 0 | J17: ='MC Drivers (NRD)'!J318 -> 0 | K17: ='MC Drivers (NRD)'!K318 -> 0 | ... N17: ='MC Drivers (NRD)'!N318 -> 0
B18: Debt Repayment | D18: =-'MC Drivers (NRD)'!D319 -> 0 | E18: =-'MC Drivers (NRD)'!E319 -> 0 | F18: =-'MC Drivers (NRD)'!F319 -> 0 | G18: =-'MC Drivers (NRD)'!G319 -> 0 | H18: =-'MC Drivers (NRD)'!H319 -> 0 | I18: =-'MC Drivers (NRD)'!I319 -> 0 | J18: =-'MC Drivers (NRD)'!J319 -> 0 | K18: =-'MC Drivers (NRD)'!K319 -> 0 | ... N18: =-'MC Drivers (NRD)'!N319 -> 0
B19: Interest Paid | D19: =-'MC Drivers (NRD)'!D323 -> 0 | E19: =-'MC Drivers (NRD)'!E323 -> 0 | F19: =-'MC Drivers (NRD)'!F323 -> 0 | G19: =-'MC Drivers (NRD)'!G323 -> 0 | H19: =-'MC Drivers (NRD)'!H323 -> 0 | I19: =-'MC Drivers (NRD)'!I323 -> 0 | J19: =-'MC Drivers (NRD)'!J323 -> 0 | K19: =-'MC Drivers (NRD)'!K323 -> 0 | ... N19: =-'MC Drivers (NRD)'!N323 -> 0
B20: Cash from Financing | D20: =SUM(D16:D19) -> 650000000 | E20: =SUM(E16:E19) -> 0 | F20: =SUM(F16:F19) -> 350000000 | G20: =SUM(G16:G19) -> 0 | H20: =SUM(H16:H19) -> 0 | I20: =SUM(I16:I19) -> 0 | J20: =SUM(J16:J19) -> 0 | K20: =SUM(K16:K19) -> 0 | ... N20: =SUM(N16:N19) -> 0
B22: NET CHANGE IN CASH | D22: =D9+D13+D20 -> 3.7814427e+08 | E22: =E9+E13+E20 -> -2.564864e+08 | F22: =F9+F13+F20 -> 1.2367026e+08 | G22: =G9+G13+G20 -> -1.379784e+08 | H22: =H9+H13+H20 -> 35668473 | I22: =I9+I13+I20 -> 2.235471e+08 | J22: =J9+J13+J20 -> 3.8550869e+08 | K22: =K9+K13+K20 -> 6.5256127e+08 | ... N22: =N9+N13+N20 -> 1938070222
B23: Cash, Beginning | D23: =0 -> 0 | E23: =D24 -> 3.7814427e+08 | F23: =E24 -> 1.2165787e+08 | G23: =F24 -> 2.4532814e+08 | H23: =G24 -> 107349737 | I23: =H24 -> 1.4301821e+08 | J23: =I24 -> 366565315 | K23: =J24 -> 7.5207401e+08 | L23: =K24 -> 1404635274 | ... N23: =M24 -> 3939621776
B24: Cash, Ending | D24: =D23+D22 -> 3.7814427e+08 | E24: =E23+E22 -> 1.2165787e+08 | F24: =F23+F22 -> 2.4532814e+08 | G24: =G23+G22 -> 107349737 | H24: =H23+H22 -> 1.4301821e+08 | I24: =I23+I22 -> 366565315 | J24: =J23+J22 -> 7.5207401e+08 | K24: =K23+K22 -> 1404635274 | ... N24: =N23+N22 -> 5877691998

Sheet Conso Balance Sheet
B2: CONSOLIDATED - BALANCE SHEET
B3: All figures in PHP Millions (unless noted)
D4: 2026 | E4: 2027 | F4: 2028 | G4: 2029 | H4: 2030 | I4: 2031 | J4: 2032 | K4: 2033 | L4: 2034 | M4: 2035 | N4: 2036
B5: ASSETS
B6: Cash & Equivalents | D6: ='Conso Cash Flow'!D24 -> 3.7814427e+08 | E6: ='Conso Cash Flow'!E24 -> 1.2165787e+08 | F6: ='Conso Cash Flow'!F24 -> 2.4532814e+08 | G6: ='Conso Cash Flow'!G24 -> 107349737 | H6: ='Conso Cash Flow'!H24 -> 1.4301821e+08 | I6: ='Conso Cash Flow'!I24 -> 366565315 | J6: ='Conso Cash Flow'!J24 -> 7.5207401e+08 | K6: ='Conso Cash Flow'!K24 -> 1404635274 | ... N6: ='Conso Cash Flow'!N24 -> 5877691998
B7: Accounts Receivable | D7: ='NRD MC Balance Sheet'!D6+'RideBox Energy Balance Sheet'!D6 -> 8159696.3 | E7: ='NRD MC Balance Sheet'!E6+'RideBox Energy Balance Sheet'!E6 -> 16310499 | F7: ='NRD MC Balance Sheet'!F6+'RideBox Energy Balance Sheet'!F6 -> 28328230 | G7: ='NRD MC Balance Sheet'!G6+'RideBox Energy Balance Sheet'!G6 -> 42596811 | H7: ='NRD MC Balance Sheet'!H6+'RideBox Energy Balance Sheet'!H6 -> 57843483 | I7: ='NRD MC Balance Sheet'!I6+'RideBox Energy Balance Sheet'!I6 -> 75038676 | J7: ='NRD MC Balance Sheet'!J6+'RideBox Energy Balance Sheet'!J6 -> 97406883 | K7: ='NRD MC Balance Sheet'!K6+'RideBox Energy Balance Sheet'!K6 -> 1.2273117e+08 | ... N7: ='NRD MC Balance Sheet'!N6+'RideBox Energy Balance Sheet'!N6 -> 2.0385497e+08
B8: Inventory | D8: ='NRD MC Balance Sheet'!D7 -> 14383415 | E8: ='NRD MC Balance Sheet'!E7 -> 23013464 | F8: ='NRD MC Balance Sheet'!F7 -> 36821542 | G8: ='NRD MC Balance Sheet'!G7 -> 51552556 | H8: ='NRD MC Balance Sheet'!H7 -> 64437698 | I8: ='NRD MC Balance Sheet'!I7 -> 77322841 | J8: ='NRD MC Balance Sheet'!J7 -> 96656548 | K8: ='NRD MC Balance Sheet'!K7 -> 1.1599025e+08 | ... N8: ='NRD MC Balance Sheet'!N7 -> 1.546337e+08
B9: Net PP&E | D9: ='MC Drivers (NRD)'!D201+'MC Drivers (NRD)'!D222+'MC Drivers (NRD)'!D240+'MC Drivers (NRD)'!D306+'Energy Drivers (RideBox)'!D122 -> 3.3051545e+08 | E9: ='MC Drivers (NRD)'!E201+'MC Drivers (NRD)'!E222+'MC Drivers (NRD)'!E240+'MC Drivers (NRD)'!E306+'Energy Drivers (RideBox)'!E122 -> 7.7501759e+08 | F9: ='MC Drivers (NRD)'!F201+'MC Drivers (NRD)'!F222+'MC Drivers (NRD)'!F240+'MC Drivers (NRD)'!F306+'Energy Drivers (RideBox)'!F122 -> 1377023207 | G9: ='MC Drivers (NRD)'!G201+'MC Drivers (NRD)'!G222+'MC Drivers (NRD)'!G240+'MC Drivers (NRD)'!G306+'Energy Drivers (RideBox)'!G122 -> 2112664280 | H9: ='MC Drivers (NRD)'!H201+'MC Drivers (NRD)'!H222+'MC Drivers (NRD)'!H240+'MC Drivers (NRD)'!H306+'Energy Drivers (RideBox)'!H122 -> 2909946340 | I9: ='MC Drivers (NRD)'!I201+'MC Drivers (NRD)'!I222+'MC Drivers (NRD)'!I240+'MC Drivers (NRD)'!I306+'Energy Drivers (RideBox)'!I122 -> 3788794164 | J9: ='MC Drivers (NRD)'!J201+'MC Drivers (NRD)'!J222+'MC Drivers (NRD)'!J240+'MC Drivers (NRD)'!J306+'Energy Drivers (RideBox)'!J122 -> 4847795482 | K9: ='MC Drivers (NRD)'!K201+'MC Drivers (NRD)'!K222+'MC Drivers (NRD)'!K240+'MC Drivers (NRD)'!K306+'Energy Drivers (RideBox)'!K122 -> 6035236781 | ... N9: ='MC Drivers (NRD)'!N201+'MC Drivers (NRD)'!N222+'MC Drivers (NRD)'!N240+'MC Drivers (NRD)'!N306+'Energy Drivers (RideBox)'!N122 -> 9604053542
B10: Total Assets | D10: =SUM(D6:D9) -> 7.3120283e+08 | E10: =SUM(E6:E9) -> 935999426 | F10: =SUM(F6:F9) -> 1687501115 | G10: =SUM(G6:G9) -> 2314163384 | H10: =SUM(H6:H9) -> 3175245732 | I10: =SUM(I6:I9) -> 4307720996 | J10: =SUM(J6:J9) -> 5793932920 | K10: =SUM(K6:K9) -> 7678593484 | ... N10: =SUM(N6:N9) -> 15840234204
B12: LIABILITIES
B13: Accounts Payable | D13: ='NRD MC Balance Sheet'!D12+'RideBox Energy Balance Sheet'!D11 -> 12278623 | E13: ='NRD MC Balance Sheet'!E12+'RideBox Energy Balance Sheet'!E11 -> 19174273 | F13: ='NRD MC Balance Sheet'!F12+'RideBox Energy Balance Sheet'!F11 -> 29277633 | G13: ='NRD MC Balance Sheet'!G12+'RideBox Energy Balance Sheet'!G11 -> 40753875 | H13: ='NRD MC Balance Sheet'!H12+'RideBox Energy Balance Sheet'!H11 -> 52176047 | I13: ='NRD MC Balance Sheet'!I12+'RideBox Energy Balance Sheet'!I11 -> 64284423 | J13: ='NRD MC Balance Sheet'!J12+'RideBox Energy Balance Sheet'!J11 -> 81006210 | K13: ='NRD MC Balance Sheet'!K12+'RideBox Energy Balance Sheet'!K11 -> 98812611 | ... N13: ='NRD MC Balance Sheet'!N12+'RideBox Energy Balance Sheet'!N11 -> 1.4761713e+08
B14: Interest-bearing Debt | D14: ='MC Drivers (NRD)'!D322 -> 0 | E14: ='MC Drivers (NRD)'!E322 -> 0 | F14: ='MC Drivers (NRD)'!F322 -> 0 | G14: ='MC Drivers (NRD)'!G322 -> 0 | H14: ='MC Drivers (NRD)'!H322 -> 0 | I14: ='MC Drivers (NRD)'!I322 -> 0 | J14: ='MC Drivers (NRD)'!J322 -> 0 | K14: ='MC Drivers (NRD)'!K322 -> 0 | ... N14: ='MC Drivers (NRD)'!N322 -> 0
B15: Total Liabilities | D15: =D13+D14 -> 12278623 | E15: =E13+E14 -> 19174273 | F15: =F13+F14 -> 29277633 | G15: =G13+G14 -> 40753875 | H15: =H13+H14 -> 52176047 | I15: =I13+I14 -> 64284423 | J15: =J13+J14 -> 81006210 | K15: =K13+K14 -> 98812611 | ... N15: =N13+N14 -> 1.4761713e+08
B17: EQUITY
B18: Share Capital (cum. injections) | D18: ='MC Drivers (NRD)'!D317 -> 650000000 | E18: =D18+'MC Drivers (NRD)'!E317 -> 650000000 | F18: =E18+'MC Drivers (NRD)'!F317 -> 1000000000 | G18: =F18+'MC Drivers (NRD)'!G317 -> 1000000000 | H18: =G18+'MC Drivers (NRD)'!H317 -> 1000000000 | I18: =H18+'MC Drivers (NRD)'!I317 -> 1000000000 | J18: =I18+'MC Drivers (NRD)'!J317 -> 1000000000 | K18: =J18+'MC Drivers (NRD)'!K317 -> 1000000000 | L18: =K18+'MC Drivers (NRD)'!L317 -> 1000000000 | ... N18: =M18+'MC Drivers (NRD)'!N317 -> 1000000000
B19: Retained Earnings (cum. NIAT) | D19: ='Conso P&L'!D52 -> 68924206 | E19: =D19+'Conso P&L'!E52 -> 2.6682515e+08 | F19: =E19+'Conso P&L'!F52 -> 6.5822348e+08 | G19: =F19+'Conso P&L'!G52 -> 1273409509 | H19: =G19+'Conso P&L'!H52 -> 2123069685 | I19: =H19+'Conso P&L'!I52 -> 3243436573 | J19: =I19+'Conso P&L'!J52 -> 4712926710 | K19: =J19+'Conso P&L'!K52 -> 6579780873 | L19: =K19+'Conso P&L'!L52 -> 8845161517 | ... N19: =M19+'Conso P&L'!N52 -> 14692617078
B20: Total Equity | D20: =D18+D19 -> 7.1892421e+08 | E20: =E18+E19 -> 9.1682515e+08 | F20: =F18+F19 -> 1658223481 | G20: =G18+G19 -> 2273409509 | H20: =H18+H19 -> 3123069685 | I20: =I18+I19 -> 4243436573 | J20: =J18+J19 -> 5712926710 | K20: =K18+K19 -> 7579780873 | ... N20: =N18+N19 -> 15692617078
B21: Total Liabilities & Equity | D21: =D15+D20 -> 7.3120283e+08 | E21: =E15+E20 -> 935999426 | F21: =F15+F20 -> 1687501115 | G21: =G15+G20 -> 2314163384 | H21: =H15+H20 -> 3175245732 | I21: =I15+I20 -> 4307720996 | J21: =J15+J20 -> 5793932920 | K21: =K15+K20 -> 7678593484 | ... N21: =N15+N20 -> 15840234204
D22: =D10-D21 -> 1.1920929e-07 | E22: =E10-E21 -> 0 | F22: =F10-F21 -> 0 | G22: =G10-G21 -> 0 | H22: =H10-H21 -> -4.7683716e-07 | I22: =I10-I21 -> -9.5367432e-07 | J22: =J10-J21 -> -9.5367432e-07 | K22: =K10-K21 -> -9.5367432e-07 | ... N22: =N10-N21 -> 0

Sheet Valuation
B2: VALUATION (DCF)
D4: 2026 | E4: 2027 | F4: 2028 | G4: 2029 | H4: 2030 | I4: 2031 | J4: 2032 | K4: 2033 | L4: 2034 | M4: 2035 | N4: 2036
B5: UNLEVERED FREE CASH FLOW
B6: Period (t) | D6: 1 | E6: 2 | F6: 3 | G6: 4 | H6: 5 | I6: 6 | J6: 7 | K6: 8 | L6: 9 | M6: 10 | N6: 11
B7: Free Cash Flow (firm) | D7: ='Conso Cash Flow'!D9+'Conso Cash Flow'!D13 -> -2.7185573e+08 | E7: ='Conso Cash Flow'!E9+'Conso Cash Flow'!E13 -> -2.564864e+08 | F7: ='Conso Cash Flow'!F9+'Conso Cash Flow'!F13 -> -2.2632974e+08 | G7: ='Conso Cash Flow'!G9+'Conso Cash Flow'!G13 -> -1.379784e+08 | H7: ='Conso Cash Flow'!H9+'Conso Cash Flow'!H13 -> 35668473 | I7: ='Conso Cash Flow'!I9+'Conso Cash Flow'!I13 -> 2.235471e+08 | J7: ='Conso Cash Flow'!J9+'Conso Cash Flow'!J13 -> 3.8550869e+08 | K7: ='Conso Cash Flow'!K9+'Conso Cash Flow'!K13 -> 6.5256127e+08 | ... N7: ='Conso Cash Flow'!N9+'Conso Cash Flow'!N13 -> 1938070222
B8: Discount Factor | D8: =1/(1+Valuation!$D$31)^D6 -> 0.89285714 | E8: =1/(1+Valuation!$D$31)^E6 -> 0.79719388 | F8: =1/(1+Valuation!$D$31)^F6 -> 0.71178025 | G8: =1/(1+Valuation!$D$31)^G6 -> 0.63551808 | H8: =1/(1+Valuation!$D$31)^H6 -> 0.56742686 | I8: =1/(1+Valuation!$D$31)^I6 -> 0.50663112 | J8: =1/(1+Valuation!$D$31)^J6 -> 0.45234922 | K8: =1/(1+Valuation!$D$31)^K6 -> 0.40388323 | ... N8: =1/(1+Valuation!$D$31)^N6 -> 0.2874761
B9: PV of FCF | D9: =D7*D8 -> -2.4272833e+08 | E9: =E7*E8 -> -2.0446939e+08 | F9: =F7*F8 -> -1.6109703e+08 | G9: =G7*G8 -> -87687767 | H9: =H7*H8 -> 20239250 | I9: =I7*I8 -> 1.1325592e+08 | J9: =J7*J8 -> 1.7438455e+08 | K9: =K7*K8 -> 2.6355855e+08 | ... N9: =N7*N8 -> 5.5714888e+08
B10: =IRR(C10:N10) -> 0.27047457 | C10: =-D34 -> -650000000 | D10: 0 | E10: 0 | F10: 0 | G10: 0 | H10: 0 | I10: 0 | J10: 0 | K10: 0 | L10: 0 | M10: 0 | N10: =(D14+D19)*D24 -> 9047718549
B11: ENTERPRISE & EQUITY VALUE
B12: PV of explicit FCF | D12: =SUM(D9:N9) -> 1289485320
B14: Terminal Value (Exit multiple) | D14: ='Conso P&L'!N39*Valuation!$D$32 -> 39360900749
B16: PV of TV (Exit multiple) | D16: =D14*N8 -> 11315318401
B18: Enterprise Value (Exit mult.) | D18: =D12+D16 -> 12604803721
B19: (+) Cash at exit | D19: ='Conso Cash Flow'!N24 -> 5877691998
B20: (-) Debt at exit | D20: =-'MC Drivers (NRD)'!N322 -> 0
B21: Equity Value (Exit mult.) | D21: =D18+D19+D20 -> 18482495719
B23: INVESTOR RETURNS
B24: Investor Stake | D24: =Valuation!$D$33 -> 0.2
B25: Investment (2026) | D25: =Valuation!$D$34 -> 650000000
B26: Investor Proceeds at exit | D26: =D21*Valuation!$D$33 -> 3696499144
D27: =IFERROR(D26/D25,0) -> 5.6869218
B28: Investor IRR (10 yr hold) | D28: =B10 -> 0.27047457
B30: VALUATION INPUTS
B31: Discount Rate / WACC | D31: =0.12 -> 0.12
B32: Exit EV/EBITDA Multiple | D32: 7
B33: Investor Equity Stake | D33: =0.2 -> 0.2
B34: Investor Investment (2026) | D34: 650000000
B38: INVESTOR RETURNS - BOTH METHODS (20% stake · 7× exit)
D39: MOIC | E39: IRR
B40: 10-year · Nominal exit | D40: =(D14+D19+D20)*$D$24/$D$25 -> 13.919567 | E40: =D40^(1/10)-1 -> 0.30125548
B41: 10-year · DCF (present value) | D41: =D26/D25 -> 5.6869218 | E41: =D41^(1/10)-1 -> 0.1898377
B42: 5-year · Nominal exit | D42: =('Conso P&L'!H39*$D$32+'Conso Cash Flow'!H24-'MC Drivers (NRD)'!H322)*$D$24/$D$25 -> 3.1448845 | E42: =D42^(1/5)-1 -> 0.25753749
B43: 5-year · DCF (present value) | D43: =(SUM($D$9:H9)+('Conso P&L'!H39*$D$32)*H8+'Conso Cash Flow'!H24-'MC Drivers (NRD)'!H322)*$D$24/$D$25 -> 1.5956066 | E43: =D43^(1/5)-1 -> 0.097956575

Sheet Scenarios
B2: SCENARIOS & SUMMARY
D4: NRD | E4: Energy | F4: Conso
B5: YEAR 2036 SNAPSHOT
B6: Revenue | D6: ='NRD MC P&L'!N10 -> 7856805006 | E6: ='RideBox Energy P&L'!N8 -> 2772775500 | F6: ='Conso P&L'!N8 -> 10629580506
B7: EBITDA | D7: ='NRD MC P&L'!N40 -> 3795036819 | E7: ='RideBox Energy P&L'!N29 -> 4.1337103e+08 | F7: ='Conso P&L'!N39 -> 5622985821
B8: Net Income (NIAT) | D8: ='NRD MC P&L'!N45 -> 2846277615 | E8: ='RideBox Energy P&L'!N34 -> 3.1002827e+08 | F8: ='Conso P&L'!N52 -> 3156305888
B10: CUMULATIVE 2026-2036
B11: Cumulative Revenue | D11: =SUM('NRD MC P&L'!D10:N10) -> 38159621478 | E11: =SUM('RideBox Energy P&L'!D8:N8) -> 12685125750 | F11: =SUM('Conso P&L'!D8:N8) -> 50844747228
B12: Cumulative EBITDA | D12: =SUM('NRD MC P&L'!D40:N40) -> 17324824214 | E12: =SUM('RideBox Energy P&L'!D29:N29) -> 2265331891 | F12: =SUM('Conso P&L'!D39:N39) -> 25610080400
B13: Cumulative Net Income | D13: =SUM('NRD MC P&L'!D45:N45) -> 12993618160 | E13: =SUM('RideBox Energy P&L'!D34:N34) -> 1698998918 | F13: =SUM('Conso P&L'!D52:N52) -> 14692617078
B15: SENSITIVITY: Equity Value (PHP) - WACC vs Exit Multiple
C16: Exit \ WACC | D16: 0.12 | E16: 0.15 | F16: 0.18
C17: 6 | D17: {=NPV(D$16, Valuation!$D$8:$N$8) + ('Conso P&L'!$N$39 * $C17) / (1+D$16)^11} -> 9698844348 | E17: {=NPV(E$16, Valuation!$D$8:$N$8) + ('Conso P&L'!$N$39 * $C17) / (1+E$16)^11} -> 7251736166 | F17: {=NPV(F$16, Valuation!$D$8:$N$8) + ('Conso P&L'!$N$39 * $C17) / (1+F$16)^11} -> 5462810792
C18: 8 | D18: {=NPV(D$16, Valuation!$D$8:$N$8) + ('Conso P&L'!$N$39 * $C18) / (1+D$16)^11} -> 12931792462 | E18: {=NPV(E$16, Valuation!$D$8:$N$8) + ('Conso P&L'!$N$39 * $C18) / (1+E$16)^11} -> 9668981553 | F18: {=NPV(F$16, Valuation!$D$8:$N$8) + ('Conso P&L'!$N$39 * $C18) / (1+F$16)^11} -> 7283747721
C19: 10 | D19: {=NPV(D$16, Valuation!$D$8:$N$8) + ('Conso P&L'!$N$39 * $C19) / (1+D$16)^11} -> 16164740577 | E19: {=NPV(E$16, Valuation!$D$8:$N$8) + ('Conso P&L'!$N$39 * $C19) / (1+E$16)^11} -> 12086226940 | F19: {=NPV(F$16, Valuation!$D$8:$N$8) + ('Conso P&L'!$N$39 * $C19) / (1+F$16)^11} -> 9104684651

Sheet Operating KPIs
B1: OPERATING KPIs - NETWORK UTILIZATION & PERFORMANCE
B2: Modeled by year (links to model) · see Plan vs Actual block to drop in Sta. Rosa figures
B4: Metric | C4: Unit / basis | D4: 2026 | E4: 2027 | F4: 2028 | G4: 2029 | H4: 2030 | I4: 2031 | J4: 2032 | K4: 2033 | L4: 2034 | M4: 2035 | N4: 2036
B6: NETWORK SCALE
B7: Ending leased fleet (active riders) | C7: bikes | D7: ='MC Drivers (NRD)'!D15 -> 2216 | E7: ='MC Drivers (NRD)'!E15 -> 5374 | F7: ='MC Drivers (NRD)'!F15 -> 9888 | G7: ='MC Drivers (NRD)'!G15 -> 15717 | H7: ='MC Drivers (NRD)'!H15 -> 22412 | I7: ='MC Drivers (NRD)'!I15 -> 30197 | J7: ='MC Drivers (NRD)'!J15 -> 39863 | K7: ='MC Drivers (NRD)'!K15 -> 51163 | ... N7: ='MC Drivers (NRD)'!N15 -> 89978
B8: Cumulative owner base (outright sold) | C8: bikes | D8: ='MC Drivers (NRD)'!D18 -> 1200 | E8: ='MC Drivers (NRD)'!E18 -> 3120 | F8: ='MC Drivers (NRD)'!F18 -> 6192 | G8: ='MC Drivers (NRD)'!G18 -> 10493 | H8: ='MC Drivers (NRD)'!H18 -> 15869 | I8: ='MC Drivers (NRD)'!I18 -> 22320 | J8: ='MC Drivers (NRD)'!J18 -> 30384 | K8: ='MC Drivers (NRD)'!K18 -> 40061 | ... N8: ='MC Drivers (NRD)'!N18 -> 75539
B9: Active lease-to-own contracts | C9: bikes | D9: ='MC Drivers (NRD)'!D27 -> 200 | E9: ='MC Drivers (NRD)'!E27 -> 480 | F9: ='MC Drivers (NRD)'!F27 -> 844 | G9: ='MC Drivers (NRD)'!G27 -> 1117 | H9: ='MC Drivers (NRD)'!H27 -> 1452 | I9: ='MC Drivers (NRD)'!I27 -> 1887 | J9: ='MC Drivers (NRD)'!J27 -> 2452 | K9: ='MC Drivers (NRD)'!K27 -> 3187 | ... N9: ='MC Drivers (NRD)'!N27 -> 7001
B10: Total active riders | C10: riders | D10: =SUM(D7:D9) -> 3616 | E10: =SUM(E7:E9) -> 8974 | F10: =SUM(F7:F9) -> 16924 | G10: =SUM(G7:G9) -> 27327 | H10: =SUM(H7:H9) -> 39733 | I10: =SUM(I7:I9) -> 54404 | J10: =SUM(J7:J9) -> 72699 | K10: =SUM(K7:K9) -> 94411 | ... N10: =SUM(N7:N9) -> 172518
B11: Cumulative swap stations (lockers) | C11: stations | D11: ='Energy Drivers (RideBox)'!D8 -> 363 | E11: ='Energy Drivers (RideBox)'!E8 -> 899 | F11: ='Energy Drivers (RideBox)'!F8 -> 1694 | G11: ='Energy Drivers (RideBox)'!G8 -> 2733 | H11: ='Energy Drivers (RideBox)'!H8 -> 3974 | I11: ='Energy Drivers (RideBox)'!I8 -> 5441 | J11: ='Energy Drivers (RideBox)'!J8 -> 7270 | K11: ='Energy Drivers (RideBox)'!K8 -> 9442 | ... N11: ='Energy Drivers (RideBox)'!N8 -> 17253
B12: Riders per station | C12: x | D12: =IFERROR(D10/D11,0) -> 9.9614325 | E12: =IFERROR(E10/E11,0) -> 9.9822024 | F12: =IFERROR(F10/F11,0) -> 9.9905549 | G12: =IFERROR(G10/G11,0) -> 9.9989023 | H12: =IFERROR(H10/H11,0) -> 9.9982386 | I12: =IFERROR(I10/I11,0) -> 9.9988973 | J12: =IFERROR(J10/J11,0) -> 9.9998624 | K12: =IFERROR(K10/K11,0) -> 9.9990468 | ... N12: =IFERROR(N10/N11,0) -> 9.9993045
B14: UTILIZATION & THROUGHPUT
B15: Swaps / station / day | C15: swaps | D15: ='Energy Drivers (RideBox)'!D25 -> 4 | E15: ='Energy Drivers (RideBox)'!E25 -> 8 | F15: ='Energy Drivers (RideBox)'!F25 -> 8 | G15: ='Energy Drivers (RideBox)'!G25 -> 8 | H15: ='Energy Drivers (RideBox)'!H25 -> 8 | I15: ='Energy Drivers (RideBox)'!I25 -> 8 | J15: ='Energy Drivers (RideBox)'!J25 -> 8 | K15: ='Energy Drivers (RideBox)'!K25 -> 8 | ... N15: ='Energy Drivers (RideBox)'!N25 -> 8
B16: Max swaps / battery / day | C16: swaps | D16: ='Energy Drivers (RideBox)'!D24 -> 2 | E16: ='Energy Drivers (RideBox)'!E24 -> 4 | F16: ='Energy Drivers (RideBox)'!F24 -> 4 | G16: ='Energy Drivers (RideBox)'!G24 -> 4 | H16: ='Energy Drivers (RideBox)'!H24 -> 4 | I16: ='Energy Drivers (RideBox)'!I24 -> 4 | J16: ='Energy Drivers (RideBox)'!J24 -> 4 | K16: ='Energy Drivers (RideBox)'!K24 -> 4 | ... N16: ='Energy Drivers (RideBox)'!N24 -> 4
B17: kWh dispensed / station / day | C17: kWh | D17: ='Energy Drivers (RideBox)'!D26 -> 7.6544 | E17: ='Energy Drivers (RideBox)'!E26 -> 10.205867 | F17: ='Energy Drivers (RideBox)'!F26 -> 10.205867 | G17: ='Energy Drivers (RideBox)'!G26 -> 10.205867 | H17: ='Energy Drivers (RideBox)'!H26 -> 10.205867 | I17: ='Energy Drivers (RideBox)'!I26 -> 10.205867 | J17: ='Energy Drivers (RideBox)'!J26 -> 10.205867 | K17: ='Energy Drivers (RideBox)'!K26 -> 10.205867 | ... N17: ='Energy Drivers (RideBox)'!N26 -> 10.205867
B18: Battery subscription / leased rider / mo | C18: PHP | D18: ='Energy Drivers (RideBox)'!D11 -> 2455.3571 | E18: ='Energy Drivers (RideBox)'!E11 -> 2455.3571 | F18: ='Energy Drivers (RideBox)'!F11 -> 2455.3571 | G18: ='Energy Drivers (RideBox)'!G11 -> 2455.3571 | H18: ='Energy Drivers (RideBox)'!H11 -> 2455.3571 | I18: ='Energy Drivers (RideBox)'!I11 -> 2455.3571 | J18: ='Energy Drivers (RideBox)'!J11 -> 2455.3571 | K18: ='Energy Drivers (RideBox)'!K11 -> 2455.3571 | ... N18: ='Energy Drivers (RideBox)'!N11 -> 2455.3571
B19: Load / prepaid / owner rider / mo | C19: PHP | D19: ='Energy Drivers (RideBox)'!D12 -> 785.71429 | E19: ='Energy Drivers (RideBox)'!E12 -> 785.71429 | F19: ='Energy Drivers (RideBox)'!F12 -> 785.71429 | G19: ='Energy Drivers (RideBox)'!G12 -> 785.71429 | H19: ='Energy Drivers (RideBox)'!H12 -> 785.71429 | I19: ='Energy Drivers (RideBox)'!I12 -> 785.71429 | J19: ='Energy Drivers (RideBox)'!J12 -> 785.71429 | K19: ='Energy Drivers (RideBox)'!K12 -> 785.71429 | ... N19: ='Energy Drivers (RideBox)'!N12 -> 785.71429
B21: REVENUE INTENSITY
B22: Energy revenue / station / yr | C22: PHP | D22: =IFERROR('RideBox Energy P&L'!D8/D11,0) -> 211038.96 | E22: =IFERROR('RideBox Energy P&L'!E8/E11,0) -> 196266.88 | F22: =IFERROR('RideBox Energy P&L'!F8/F11,0) -> 189083.49 | G22: =IFERROR('RideBox Energy P&L'!G8/G11,0) -> 184281.91 | H22: =IFERROR('RideBox Energy P&L'!H8/H11,0) -> 178923.39 | I22: =IFERROR('RideBox Energy P&L'!I8/I11,0) -> 174702.58 | J22: =IFERROR('RideBox Energy P&L'!J8/J11,0) -> 172017.44 | K22: =IFERROR('RideBox Energy P&L'!K8/K11,0) -> 169320.22 | ... N22: =IFERROR('RideBox Energy P&L'!N8/N11,0) -> 160712.66
B23: Energy revenue / rider / mo | C23: PHP | D23: =IFERROR('RideBox Energy P&L'!D8/D10/12,0) -> 1765.467 | E23: =IFERROR('RideBox Energy P&L'!E8/E10/12,0) -> 1638.4734 | F23: =IFERROR('RideBox Energy P&L'!F8/F10/12,0) -> 1577.1854 | G23: =IFERROR('RideBox Energy P&L'!G8/G10/12,0) -> 1535.8512 | H23: =IFERROR('RideBox Energy P&L'!H8/H10/12,0) -> 1491.291 | I23: =IFERROR('RideBox Energy P&L'!I8/I10/12,0) -> 1456.0154 | J23: =IFERROR('RideBox Energy P&L'!J8/J10/12,0) -> 1433.4984 | K23: =IFERROR('RideBox Energy P&L'!K8/K10/12,0) -> 1411.1364 | ... N23: =IFERROR('RideBox Energy P&L'!N8/N10/12,0) -> 1339.3653
B24: MC revenue / rider / yr | C24: PHP | D24: =IFERROR('NRD MC P&L'!D10/D10,0) -> 96477.526 | E24: =IFERROR('NRD MC P&L'!E10/E10,0) -> 75109.439 | F24: =IFERROR('NRD MC P&L'!F10/F10,0) -> 68353.074 | G24: =IFERROR('NRD MC P&L'!G10/G10,0) -> 62849.086 | H24: =IFERROR('NRD MC P&L'!H10/H10,0) -> 58014.319 | I24: =IFERROR('NRD MC P&L'!I10/I10,0) -> 54447.729 | J24: =IFERROR('NRD MC P&L'!J10/J10,0) -> 52662.435 | K24: =IFERROR('NRD MC P&L'!K10/K10,0) -> 50850.351 | ... N24: =IFERROR('NRD MC P&L'!N10/N10,0) -> 45541.943
B25: Total revenue / rider / yr | C25: PHP | D25: =IFERROR('Conso P&L'!D8/D10,0) -> 117663.13 | E25: =IFERROR('Conso P&L'!E8/E10,0) -> 94771.12 | F25: =IFERROR('Conso P&L'!F8/F10,0) -> 87279.299 | G25: =IFERROR('Conso P&L'!G8/G10,0) -> 81279.3 | H25: =IFERROR('Conso P&L'!H8/H10,0) -> 75909.81 | I25: =IFERROR('Conso P&L'!I8/I10,0) -> 71919.914 | J25: =IFERROR('Conso P&L'!J8/J10,0) -> 69864.416 | K25: =IFERROR('Conso P&L'!K8/K10,0) -> 67783.988 | ... N25: =IFERROR('Conso P&L'!N8/N10,0) -> 61614.327
B28: PLAN vs ACTUAL - Sta. Rosa deployment
B29: Metric | C29: Unit | D29: Plan (2026) | E29: Actual to-date | F29: Variance
B30: Avg km travelled / bike / day | C30: km | D30: 60 | E30: 112 | F30: =IFERROR(E30/D30-1,"") -> 0.86666667
B31: Swaps / bike / day | C31: swaps | D31: =D11*D15/D10 -> 0.40154867 | F31: =IFERROR(E31/D31-1,"") -> -1
B32: Swaps / station / day | C32: swaps | D32: =D15 -> 4 | F32: =IFERROR(E32/D32-1,"") -> -1
B33: Riders / station | C33: riders | D33: =D12 -> 9.9614325 | F33: =IFERROR(E33/D33-1,"") -> -1
B34: Energy revenue / station / mo | C34: PHP | D34: =D22/12 -> 17586.58 | F34: =IFERROR(E34/D34-1,"") -> -1
B35: kWh / station / day | C35: kWh | D35: =D17 -> 7.6544 | F35: =IFERROR(E35/D35-1,"") -> -1
B36: Battery ARPU / leased rider / mo | C36: PHP | D36: =D18 -> 2455.3571 | F36: =IFERROR(E36/D36-1,"") -> -1
B37: Network utilization vs design (swaps) | C37: % | D37: =D15/8 -> 0.5 | F37: =IFERROR(E37/D37-1,"") -> -1
B39: Yellow = actual operating figures to be entered from deployment data.

Sheet Station Economics
B1: STATION UNIT ECONOMICS - ALL-IN (per swap station, yr-1 basis)
B2: Single 10-bike swap station. Links to Unit Econ (col E) · all-in incl. allocated overhead
B4: Item | C4: Per station / yr | E4: Notes
B6: STATION CONFIGURATION
B7: Motorcycles served / station | C7: ='Unit Econ'!E6 -> 10 | E7: Unit Econ
B8: Batteries / station (2 per MC) | C8: ='Unit Econ'!E7 -> 20
B9: Swap lockers / station | C9: 1 | E9: 1 locker = 1 station
B11: ANNUAL REVENUE
B12: Lease revenue (net of battery) | C12: ='Unit Econ'!E11*365 -> 589285.71
B13: Battery subscription revenue | C13: ='Unit Econ'!E12*365 -> 589285.71
B14: Total revenue / station / yr | C14: =SUM(C12:C13) -> 1178571.4
B16: ANNUAL CASH OPERATING COST
B17: Site rent | C17: ='Unit Econ'!E19*365 -> 53571.429
B18: Electricity | C18: ='Unit Econ'!E22*365 -> 39321.029
B19: Connectivity | C19: ='Unit Econ'!E20*365 -> 22500
B20: Maintenance | C20: ='Unit Econ'!E21*365 -> 2142.8571
B21: Insurance | C21: ='Unit Econ'!E17*365 -> 12143.399
B22: Payment gateway | C22: ='Unit Econ'!E23*365 -> 17678.571
B23: Allocated support & overhead | C23: =0.06*C14 -> 70714.286 | E23: Assump: 6% of rev (staff/CS/admin allocation)
B24: Total cash operating cost | C24: =SUM(C17:C23) -> 218071.57
B26: PROFITABILITY (all-in)
B27: EBITDA (all-in) | C27: =C14-C24 -> 960499.86
B28: EBITDA margin | C28: =IFERROR(C27/C14,0) -> 0.81496958
B29: Depreciation | C29: ='Unit Econ'!E35 -> 136324.5
B30: EBIT | C30: =C27-C29 -> 824175.36
B31: Tax @ 25% | C31: =-MAX(C30,0)*0.25 -> -206043.84
B32: NIAT (all-in) | C32: =C30+C31 -> 618131.52
B33: Net margin | C33: =IFERROR(C32/C14,0) -> 0.52447523
B35: CAPITAL & RETURNS
B36: Capex / station (lockers+batteries) | C36: ='Unit Econ'!E42 -> 1363245
B37: Payback (yrs, on cash profit) | C37: =IFERROR(C36/(C27),0) -> 1.4193079 | E37: all-in cash profit basis
B38: Asset payback per model (pre-overhead) | C38: ='Unit Econ'!E43 -> 1.3219805
B39: 10-yr asset IRR (model basis) | C39: ='Unit Econ'!E44 -> 0.58646574
B41: Reconciliation: model "1 Swap Station" economics, adjusted to an all-in view by
B42: adding an allocated share of company overhead (CS, admin, tech) not charged at unit level.

Sheet Battery Lifecycle
B1: BATTERY LIFECYCLE - DEGRADATION & REPLACEMENT
B2: Foundation asset economics. Yellow = assumptions / Sta. Rosa actuals to confirm.
B4: INPUTS
B5: Battery landed cost (PHP) | C5: ='MC Drivers (NRD)'!D63 -> 24695.61 | E5: MC Drivers
B6: Batteries per motorcycle | C6: ='MC Drivers (NRD)'!D57 -> 2
B7: Modeled depreciation life (yrs) | C7: ='MC Drivers (NRD)'!D185 -> 10 | E7: current model basis
B8: Rated cycle life (cycles) | C8: 2000 | E8: LFP typical 2,000-3,000
B9: Usable cycle life to 80% SoH (cycles) | C9: 1500
B10: Cycles (swaps) / battery / day | C10: ='Energy Drivers (RideBox)'!D24 -> 2
B11: Cycles / year | C11: =C10*365 -> 730
B12: Implied usable life (yrs) | C12: =IFERROR(C9/C11,0) -> 2.0547945 | E12: usable cycles / cycles per yr
B13: Annual capacity degradation | C13: 0.03
B15: STA. ROSA - OBSERVED (to confirm)
B16: Months in operation
B17: Observed cycles / battery / day
B18: Observed SoH at latest reading
B19: Observed defect / failure rate
B21: DEGRADATION CURVE (State of Health by year)
B22: Year of life | D22: 1 | E22: 2 | F22: 3 | G22: 4 | H22: 5 | I22: 6 | J22: 7 | K22: 8 | L22: 9 | M22: 10 | N22: 11
B23: State of Health (SoH) | D23: =(1-$C$13)^0 -> 1 | E23: =(1-$C$13)^1 -> 0.97 | F23: =(1-$C$13)^2 -> 0.9409 | G23: =(1-$C$13)^3 -> 0.912673 | H23: =(1-$C$13)^4 -> 0.88529281 | I23: =(1-$C$13)^5 -> 0.85873403 | J23: =(1-$C$13)^6 -> 0.832972 | K23: =(1-$C$13)^7 -> 0.80798284 | L23: =(1-$C$13)^8 -> 0.78374336 | M23: =(1-$C$13)^9 -> 0.76023106 | N23: =(1-$C$13)^10 -> 0.73742413
B24: Below 80% EoL threshold? | D24: =IF(D23<0.8,"EoL","ok") -> ok | E24: =IF(E23<0.8,"EoL","ok") -> ok | F24: =IF(F23<0.8,"EoL","ok") -> ok | G24: =IF(G23<0.8,"EoL","ok") -> ok | H24: =IF(H23<0.8,"EoL","ok") -> ok | I24: =IF(I23<0.8,"EoL","ok") -> ok | J24: =IF(J23<0.8,"EoL","ok") -> ok | K24: =IF(K23<0.8,"EoL","ok") -> ok | ... N24: =IF(N23<0.8,"EoL","ok") -> EoL
B26: FLEET REPLACEMENT SCHEDULE
B27: Year | D27: 2026 | E27: 2027 | F27: 2028 | G27: 2029 | H27: 2030 | I27: 2031 | J27: 2032 | K27: 2033 | L27: 2034 | M27: 2035 | N27: 2036
B28: Fleet batteries in service (cum) | D28: ='MC Drivers (NRD)'!D15*$C$6 -> 4432 | E28: ='MC Drivers (NRD)'!E15*$C$6 -> 10748 | F28: ='MC Drivers (NRD)'!F15*$C$6 -> 19776 | G28: ='MC Drivers (NRD)'!G15*$C$6 -> 31434 | H28: ='MC Drivers (NRD)'!H15*$C$6 -> 44824 | I28: ='MC Drivers (NRD)'!I15*$C$6 -> 60394 | J28: ='MC Drivers (NRD)'!J15*$C$6 -> 79726 | K28: ='MC Drivers (NRD)'!K15*$C$6 -> 102326 | ... N28: ='MC Drivers (NRD)'!N15*$C$6 -> 179956
B29: Annual replacement reserve (PHP) | D29: =D28*$C$5/$C$12 -> 53266126 | E29: =E28*$C$5/$C$12 -> 1.2917516e+08 | F29: =F28*$C$5/$C$12 -> 2.3767845e+08 | G29: =G28*$C$5/$C$12 -> 3.7779048e+08 | H29: =H28*$C$5/$C$12 -> 5.387186e+08 | I29: =I28*$C$5/$C$12 -> 7.2584711e+08 | J29: =J28*$C$5/$C$12 -> 9.5818934e+08 | K29: =K28*$C$5/$C$12 -> 1229808121 | ... N29: =N28*$C$5/$C$12 -> 2162806621
B30: Replacement reserve / total energy rev | D30: =IFERROR(D29/'RideBox Energy P&L'!D8,0) -> 0.6953154 | E30: =IFERROR(E29/'RideBox Energy P&L'!E8,0) -> 0.73210319 | F30: =IFERROR(F29/'RideBox Energy P&L'!F8,0) -> 0.74203229 | G30: =IFERROR(G29/'RideBox Energy P&L'!G8,0) -> 0.75011641 | H30: =IFERROR(H29/'RideBox Energy P&L'!H8,0) -> 0.75764712 | I30: =IFERROR(I29/'RideBox Energy P&L'!I8,0) -> 0.76360208 | J30: =IFERROR(J29/'RideBox Energy P&L'!J8,0) -> 0.76620403 | K30: =IFERROR(K29/'RideBox Energy P&L'!K8,0) -> 0.76924473 | ... N30: =IFERROR(N29/'RideBox Energy P&L'!N8,0) -> 0.78001505
B32: Key point: modeled depreciation life (10 yrs) vs usable cycle life implied by swaps/day.
B33: Replacement reserve quantifies the recurring battery refresh cost against energy revenue.

Sheet Pipeline & Cap Table
B1: PIPELINE · CAPITALIZATION · USE OF PROCEEDS
B2: Yellow = inputs to confirm from CRM / term sheet. Weighted value = value x bucket probability.
B4: 1 · COMMERCIAL PIPELINE (by bucket)
B5: Account / Segment | C5: Bucket | D5: Prob. | E5: Units/stations | F5: Est. value (PHP) | G5: Weighted (PHP) | H5: Expected deployment
B6: BetterEdge | C6: Signed | D6: 1 | E6: 0 | F6: 0 | G6: =D6*F6 -> 0 | H6: H1 2026
B7: Motorcycle-taxi fleet A | C7: Pilot | D7: 0.7 | E7: 0 | F7: 0 | G7: =D7*F7 -> 0 | H7: H2 2026
B8: Large logistics fleet B | C8: LOI | D8: 0.5 | E8: 0 | F8: 0 | G8: =D8*F8 -> 0 | H8: 2027
B9: Ride-hailing platform | C9: Active disc. | D9: 0.3 | E9: 0 | F9: 0 | G9: =D9*F9 -> 0 | H9: 2027
B10: Delivery aggregator | C10: EOI | D10: 0.1 | E10: 0 | F10: 0 | G10: =D10*F10 -> 0 | H10: 2027+
B11: Other / unallocated | C11: EOI | D11: 0.1 | E11: 0 | F11: 0 | G11: =D11*F11 -> 0 | H11: 2027+
B12: TOTAL PIPELINE | F12: =SUM(F6:F11) -> 0 | G12: =SUM(G6:G11) -> 0
B15: 2 · CAPITALIZATION & CONVERTIBLE CONVERSION
B16: New money raise (PHP) | C16: =Valuation!D34 -> 650000000 | E16: from Valuation
B17: New investor equity stake | C17: =Valuation!D33 -> 0.2
B18: Implied post-money valuation (PHP) | C18: =IFERROR(C16/C17,0) -> 3250000000
B19: Implied pre-money valuation (PHP) | C19: =C18-C16 -> 2600000000
B20: Convertible note principal (PHP) | C20: 0 | E20: confirm from note
B21: Conversion discount | C21: 0.2
B22: Convertible converts to equity (PHP value) | C22: =C20/(1-C21) -> 0 | E22: principal / (1-discount)
B24: Holder | C24: PHP value | D24: % ownership
B25: Founders & team | C25: 0 | D25: =IFERROR(C25/SUM($C$25:$C$28),0) -> 0
B26: Existing shareholders | C26: 0 | D26: =IFERROR(C26/SUM($C$25:$C$28),0) -> 0
B27: Convertible note holders | C27: =C22 -> 0 | D27: =IFERROR(C27/SUM($C$25:$C$28),0) -> 0
B28: New investor | C28: =Valuation!D34 -> 650000000 | D28: =IFERROR(C28/SUM($C$25:$C$28),0) -> 1
B29: Total | C29: =SUM(C25:C28) -> 650000000 | D29: =SUM(D25:D28) -> 1
B32: 3 · USE OF PROCEEDS & MILESTONES (PHP 650M)
B33: Allocation | C33: PHP | D33: % of raise | E33: What it proves / risk removed
B34: Battery & locker network buildout | C34: 0 | D34: =IFERROR(C34/Valuation!D34,0) -> 0 | E34: Validate network economics at scale; density
B35: Motorcycle fleet expansion | C35: 0 | D35: =IFERROR(C35/Valuation!D34,0) -> 0 | E35: Rider adoption & ecosystem lock-in
B36: Technology & platform | C36: 0 | D36: =IFERROR(C36/Valuation!D34,0) -> 0 | E36: Swap reliability, billing, telemetry at scale
B37: Working capital & inventory | C37: 0 | D37: =IFERROR(C37/Valuation!D34,0) -> 0 | E37: Supply chain resilience / buffer
B38: Team & market expansion | C38: 0 | D38: =IFERROR(C38/Valuation!D34,0) -> 0 | E38: Establish market leadership beyond Sta. Rosa
B39: Contingency | C39: 0 | D39: =IFERROR(C39/Valuation!D34,0) -> 0 | E39: De-risk execution
B40: TOTAL | C40: =SUM(C34:C39) -> 0 | D40: =IFERROR(C40/Valuation!D34,0) -> 0
B42: Allocations to be filled to total PHP 650M. Each line states the milestone / uncertainty it eliminates.

Sheet Actuals to Gather
B1: ACTUALS TO GATHER - operating data for investor diligence
B2: Checklist of the real-world figures Simon asked for. Fill the yellow Value column; feed into the linked tabs.
B4: NETWORK UTILIZATION (→ Operating KPIs tab)
B5: Metric / data point | C5: Source / system | D5: Owner | E5: Target date | F5: Value (fill)
B6: Avg km travelled / bike / day | C6: Swap network telemetry | D6: Ops / RideBox | E6: Jul 2026 | F6: 55
B7: Swaps / bike / day | C7: Swap network telemetry | D7: Ops / RideBox | E7: Jul 2026 | F7: 1.5
B8: Swaps / station / day (actual) | C8: Swap network telemetry | D8: Ops / RideBox | E8: Jul 2026 | F8: 4
B9: Active riders to date | C9: Swap network telemetry | D9: Ops / RideBox | E9: Jul 2026 | F9: 3616
B10: Stations live to date | C10: Swap network telemetry | D10: Ops / RideBox | E10: Jul 2026 | F10: 363
B11: Utilization vs design (%) | C11: Swap network telemetry | D11: Ops / RideBox | E11: Jul 2026 | F11: 0.5
B13: REVENUE INTENSITY (→ Operating KPIs tab)
B14: Metric / data point | C14: Source / system | D14: Owner | E14: Target date | F14: Value (fill)
B15: Revenue / rider / month (actual) | C15: Billing system | D15: Finance | E15: Jul 2026 | F15: 1766
B16: Revenue / station / month (actual) | C16: Billing system | D16: Finance | E16: Jul 2026 | F16: 17600
B17: Battery ARPU / leased rider / mo | C17: Billing system | D17: Finance | E17: Jul 2026 | F17: 2455
B19: STATION ECONOMICS (→ Station Economics tab)
B20: Metric / data point | C20: Source / system | D20: Owner | E20: Target date | F20: Value (fill)
B21: Actual electricity cost / station / mo | C21: Station P&L + utility bills | D21: Ops / Finance | E21: Jul 2026 | F21: 3232
B22: Actual site rent / station / mo | C22: Station P&L + utility bills | D22: Ops / Finance | E22: Jul 2026 | F22: 4464
B23: Actual maintenance / station / mo | C23: Station P&L + utility bills | D23: Ops / Finance | E23: Jul 2026 | F23: 179
B24: Actual support/overhead allocation | C24: Station P&L + utility bills | D24: Ops / Finance | E24: Jul 2026 | F24: 5893
B25: Actual station EBITDA margin | C25: Station P&L + utility bills | D25: Ops / Finance | E25: Jul 2026 | F25: 0.82
B27: BATTERY LIFECYCLE (→ Battery Lifecycle tab)
B28: Metric / data point | C28: Source / system | D28: Owner | E28: Target date | F28: Value (fill)
B29: Observed cycles / battery / day | C29: BMS / battery telemetry | D29: Engineering | E29: Aug 2026 | F29: 2
B30: Observed SoH at latest reading (%) | C30: BMS / battery telemetry | D30: Engineering | E30: Aug 2026 | F30: 0.97
B31: Observed defect / failure rate (%) | C31: BMS / battery telemetry | D31: Engineering | E31: Aug 2026 | F31: 0.01
B32: Months in operation (Sta. Rosa) | C32: BMS / battery telemetry | D32: Engineering | E32: Aug 2026 | F32: 12
B33: Actual replacements to date | C33: BMS / battery telemetry | D33: Engineering | E33: Aug 2026 | F33: 0
B35: COMMERCIAL PIPELINE (→ Pipeline & Cap Table tab)
B36: Metric / data point | C36: Source / system | D36: Owner | E36: Target date | F36: Value (fill)
B37: BetterEdge - units & status | C37: CRM / signed contracts | D37: Commercial / BD | E37: Ongoing | F37: 300 units, signed
B38: Motorcycle-taxi fleet - units & status | C38: CRM / signed contracts | D38: Commercial / BD | E38: Ongoing | F38: 150 units, pilot
B39: Each LOI/pilot - value & stage | C39: CRM / signed contracts | D39: Commercial / BD | E39: Ongoing | F39: PHP 40M, LOI stage
B40: Signed contract values | C40: CRM / signed contracts | D40: Commercial / BD | E40: Ongoing | F40: PHP 120M
B41: Expected deployment dates | C41: CRM / signed contracts | D41: Commercial / BD | E41: Ongoing | F41: H1-H2 2026
B43: CAPITALIZATION (→ Pipeline & Cap Table tab)
B44: Metric / data point | C44: Source / system | D44: Owner | E44: Target date | F44: Value (fill)
B45: Convertible note principal | C45: Term sheet / cap table | D45: Finance / Legal | E45: At close | F45: 150000000
B46: Conversion discount / cap | C46: Term sheet / cap table | D46: Finance / Legal | E46: At close | F46: 0.2
B47: Existing shareholder split | C47: Term sheet / cap table | D47: Finance / Legal | E47: At close | F47: Founders 60% / Angels 20%
B48: Founder ownership % | C48: Term sheet / cap table | D48: Finance / Legal | E48: At close | F48: 0.6
B49: Future debt facility terms | C49: Term sheet / cap table | D49: Finance / Legal | E49: At close | F49: PHP 300M @ 6.6% p.a.
B51: Light cells = context (source/owner/date). Yellow = the figure to enter.
